Workbook
Name AcquisEligBasis: [1]Budget!$H$65
Name AddRevY1: #REF!
Name AddRevY1: '[2]Rent Schedule'!$K$34
Name AddRevY1: 'Rent Schedule'!$K$34
Name Admin: [1]OpEx!$C$22
Name AggBasis: [1]Bonds!$C$17
Name ApplFrac: Inputs!$F$8
Name AvgIncome: 'Income (2)'!$N$3
Name AvgIncome: Income!$N$3
Name BaseAnnRentIncome: '[3]Rent Schedule'!$O$29
Name BC_Equity: #REF!
Name BldgAcquis: [1]Input!$M$16
Name Closing: '[1]UW Draw'!$E$6
Name ClosingDevFee: '[1]UW Draw'!$C$127
Name CODraw: [1]Input!$Q$38
Name COI: [1]Bonds!$L$28
Name CommRent: [1]Input!$H$32
Name CommSqFt: [1]Input!$G$32
Name Completion: [1]Credits!$I$5
Name CompletionDevFee: '[1]UW Draw'!$C$128
Name CompletionDraw: [1]Input!$Q$37
Name CompletionOLB: [1]Financing!$C$19
Name ConstDur: Inputs!$C$56
Name ConstLoan: #REF!
Name ConstrInt: [1]Financing!$C$28
Name ConstrLoan: [1]Financing!$C$15
Name ConstrLoanFees: [1]Financing!$C$36
Name ConstrLoanLTC: [1]Financing!$B$17
Name ConstrLoanLTV: [1]Financing!$B$16
Name ConstrLoanTerm: [1]Financing!$C$31
Name ConstrPd: [1]Input!$B$6
Name ConstrPdInt: '[1]UW Draw'!$C$97
Name ConstrType: [1]Input!$M$2
Name Conting: [4]Inputs!$C$52
Name Conting: [2]Inputs!$C$52
Name Conting: Inputs!$C$52
Name CostCertDevFee: '[1]UW Draw'!$C$130
Name CostCertDraw: [1]Input!$Q$39
Name County: [1]Input!$H$2
Name CountyAMI: 'Income (2)'!$Q$22
Name CountyAMI: Income!$Q$22
Name CreditAlloc: [1]Budget!$O$18
Name CreditRate: [1]Budget!$O$14
Name DateModel: Inputs!$E$2
Name DDF: '[1]UW Draw'!$C$19
Name DebtService: [1]Financing!$G$24,[1]Financing!$K$24,[1]Financing!$O$24
Name Demo: [1]Input!$M$15
Name DEVCOSTS: 'Development Budget'!$A$1:$K$122
Name DEVCOSTS: #REF!
Name DeveloperFee: [1]Input!$M$18
Name DevFeeInt: Inputs!$C$54
Name DevFeeSchedule: Inputs!$E$42:$E$47
Name EGI: 'Income (2)'!$R$10
Name EGI: Income!$R$10
Name EligBasis: [1]Budget!$G$65:$H$65
Name EquitySchedule: Inputs!$D$42:$D$47
Name ExpenseEsc: [1]Input!$H$36
Name ExpInfl: Inputs!$C$36
Name ExpTotalY1: '[4]Operating Expense'!$E$19
Name ExpTotalY1: '[2]Operating Expense'!$E$20

Sheet Inputs
B1: Project | C1: Columbia at Independence Heights (NO QCT) | D1: Version | E1: Updated September 2023 - Structured Parking transaction | K1: =78/3.4 -> 22.941176 | L1: apex apartments with ext detention
B2: Number of Units | C2: ='Rent Schedule'!D26 -> 221 | D2: Date | E2: 45320
K3: =250*925 -> 231250 | L3: buildable NRSF per JHP
B4: Acres | C4: 5.26 | K4: ='Rent Schedule'!E26 -> 839.93213 | L4: avg unit SF
B5: Units/Acre | C5: =TotalUnitCount/C4 -> 42.015209 | K5: =K3/K4 -> 275.31987
B6: Acquisition Price | C6: =D6*TotalUnitCount -> 0 | E6: per unit
B8: Type of Allocation | D8: 0.04 | E8: Appl Frac | F8: 0.0324
B10: Max Credit Allocation | F10: GA: $950,000; TX: $1,500,000
B11: Max Dev. Fee Allowable | F11: GA: $1.8MM for 9%, $2.5MM for 4%
B13: Rents
C14: 2023 Houston LIHTC rents | F14: 0.03 | G14: 2023 FMR+10% | K14: 2023
C15: 30% LIHTC | D15: 50% LIHTC | E15: 60% LIHTC | F15: 30% PBV | G15: 50% PBV | H15: 80% LIHTC | I15: 811 | J15: Market | K15: FMR | L15: UA | N15: SF | O15: Mix | P15: Market Rate/SF
B16: 1 BR | C16: 499 | D16: 831 | E16: 1049 | F16: 1204 | G16: =F16 -> 1204 | H16: =E16/0.6*0.8 -> 1398.6667 | J16: 1250 | K16: 1014 | L16: =10+6+22+20+13+23+36 -> 130 | N16: 665 | O16: 0.47 | P16: =J16/N16 -> 1.8796992 | S16: 443 | T16: 739 | U16: 887
B17: 2 BR | C17: 599 | D17: 997 | E17: 1258 | F17: 1437 | G17: =F17 -> 1437 | H17: =E17/0.6*0.8 -> 1677.3333 | J17: 1600 | K17: 1208 | L17: =12+9+31+28+17+30+46 -> 173 | N17: 850 | O17: 0.41 | P17: =J17/N17 -> 1.8823529 | S17: 532 | T17: 887 | U17: 1065
B18: 3 BR | C18: 691 | D18: 1151 | E18: 1454 | F18: 1894 | G18: =F18 -> 1894 | H18: =E18/0.6*0.8 -> 1938.6667 | J18: 1875 | K18: 1603 | L18: =13+11+40+36+21+37+56 -> 214 | N18: 1200 | O18: 0.12 | P18: =J18/N18 -> 1.5625 | S18: 615 | T18: 1025 | U18: 1230
B19: 4 BR | O19: =1-SUM(O16:O18) -> 0
B20: UA's | C20: Y | D20: Y | E20: Y | F20: Y | G20: Y | H20: y | I20: Y | J20: N | N20: =SUMPRODUCT(SF,unitmix) -> 805.05 | P20: =SUMPRODUCT(P16:P19,unitmix) -> 1.8427234
L21: *asssume $20/unit savings
B22: Set Asides | C22: Income Limits | D22: Total Mix | F22: Of | G22: Less
B23: 30% PBV | C23: 0.3 | D23: 0.1 | E23: 0 | F23: of Total | H23: =IFERROR(INDEX($D$23:$D$31,MATCH(G23,$B$23:$B$31,0)),0) -> 0
B24: 50% PBV | C24: 0.5 | D24: 0.1 | E24: 0 | F24: of Total | H24: =IFERROR(INDEX($D$23:$D$31,MATCH(G24,$B$23:$B$31,0)),0) -> 0 | L24: Tax Abatement
B25: 60% LIHTC | C25: 0.6 | D25: =1-D23-D24-D26-D32 -> 0.8 | E25: 0 | F25: Plug | H25: =INDEX($D$23:$D$31,MATCH(G25,$B$23:$B$31,0)) -> 0 | L25: 1 | M25: 1 | T25: =995/625 -> 1.592
B26: 80% LIHTC | C26: 0.8 | D26: 0 | F26: of Total | H26: =IFERROR(INDEX($D$23:$D$31,MATCH(G26,$B$23:$B$31,0)),0) -> 0 | L26: =L25+1 -> 2 | M26: 1
D27: =IF(F27="of LIHTC",ofLIHTC,IF(F27="of total",ofTotal,Plug))-H27 -> 0 | E27: 0 | F27: of Total | H27: =IFERROR(INDEX($D$23:$D$31,MATCH(G27,$B$23:$B$31,0)),0) -> 0 | L27: =L26+1 -> 3 | M27: 1
D28: =IF(F28="of LIHTC",ofLIHTC,IF(F28="of total",ofTotal,Plug))-H28 -> 0 | E28: 0 | F28: of Total | G28: =B27 -> 0 | H28: =IFERROR(INDEX($D$23:$D$31,MATCH(G28,$B$23:$B$31,0)),0) -> 0 | L28: =L27+1 -> 4 | M28: 1
D29: =IF(F29="of LIHTC",ofLIHTC,IF(F29="of total",ofTotal,Plug))-H29 -> 0 | E29: 0 | F29: of Total | G29: =B28 | H29: =IFERROR(INDEX($D$23:$D$31,MATCH(G29,$B$23:$B$31,0)),0) -> 0 | L29: =L28+1 -> 5 | M29: 1
D30: =IF(F30="of LIHTC",ofLIHTC,IF(F30="of total",ofTotal,Plug))-H30 -> 0 | E30: 0 | F30: of Total | G30: =B29 | H30: =IFERROR(INDEX($D$23:$D$31,MATCH(G30,$B$23:$B$31,0)),0) -> 0 | L30: =L29+1 -> 6 | M30: 1
D31: =IF(F31="of LIHTC",ofLIHTC,IF(F31="of total",ofTotal,Plug))-H31 -> 0 | E31: 0 | F31: of Total | G31: =B30 | H31: =IFERROR(INDEX($D$23:$D$31,MATCH(G31,$B$23:$B$31,0)),0) -> 0 | L31: =L30+1 -> 7 | M31: 1
B32: Market | C32: None | D32: 0 | L32: =L31+1 -> 8 | M32: 1
D33: =SUM(D23:D32) -> 1 | E33: =SUMPRODUCT(C23:C26,D23:D26)/SUM(D23:D26) -> 0.56 | F33: income avg | L33: =L32+1 -> 9 | M33: 1
B34: Vacancy Rate | C34: 0.07 | L34: =L33+1 -> 10 | M34: 1
B35: Revenue Inflation | C35: 0.02 | L35: =L34+1 -> 11 | M35: 1 | O35: =1014*1.1 -> 1115.4
B36: Expense Inflation | C36: 0.03 | L36: =L35+1 -> 12 | M36: 1 | O36: =1208*1.1 -> 1328.8
B37: Replacement Reserve | C37: 300 | D37: per units | L37: =L36+1 -> 13 | M37: 1 | O37: =1603*1.1 -> 1763.3
L38: =L37+1 -> 14 | M38: 1
L39: =L38+1 -> 15 | M39: 1
B40: Start Year | C40: 2023 | L40: =L39+1 -> 16 | M40: 1
A41: Month | D41: Equity Schedule | E41: Fee Schedule | L41: =L40+1 -> 17 | M41: 1
B42: Start | L42: =L41+1 -> 18 | M42: 1
B43: Application | C43: 44743 | F43: =EOMONTH(C43,0) -> 44773 | L43: =L42+1 -> 19 | M43: 1
A44: 1 | B44: Closing | C44: 45000 | D44: 0.15 | E44: 0.2 | F44: =EOMONTH(C44,0) -> 45016 | G44: 12 | H44: months from app date | L44: =L43+1 -> 20 | M44: 1
A45: =12*(C45-C44)/365 -> 18.575342 | B45: Completion | C45: 45565 | D45: 0.67 | E45: 0.2 | F45: =EOMONTH(C45,0) -> 45565
A46: =A45+LeaseUpTime -> 33.575342 | B46: Stabilization | C46: =EDATE(C45,J46+3) -> 46111 | D46: 0.15 | E46: 0.15 | F46: =EOMONTH(C46,0) -> 46112 | G46: 15 | H46: Units/month | J46: =ROUNDUP(TotalUnitCount/G46,0) -> 15 | K46: months
A47: =A46+3 -> 36.575342 | B47: 8609's | C47: =EDATE(C46,3) -> 46203 | D47: 0.03 | E47: =1-E44-E45-E46-'Summary Sources-Uses'!Q20 -> 0.45 | F47: =EOMONTH(C47,0) -> 46203
D48: =SUM(D44:D47) -> 1 | E48: =SUM(E44:E47) -> 1
B51: Hard Cost Per Unit | C51: 115000 | D51: *Incl. comm SF | F51: =#REF! -> #REF! | G51: const contract per unit | I51: =F51/'Rent Schedule'!E26 -> #REF! | J51: per NRSF
B52: Contingency | C52: 0.05 | F52: =F51*TotalUnitCount -> #REF! | G52: total const contract
F53: 2000000 | G53: deferred fee target
B54: Developer Fee Interest | C54: 0.08 | F54: =F52-'Summary Sources-Uses'!E17+F53 -> #REF! | G54: target const contract | I54: =F54/TotalUnitCount -> #REF! | J54: target per unit cost
F55: =F52-F54 -> #REF! | G55: need to cut
B56: Construction Duration | C56: 15 | F56: =F55/TotalUnitCount -> #REF! | G56: need to cut per unit
E57: Rent
B58: Commercial SF | C58: 3000 | E58: 5 | F58: /sf/year | G58: =C58*E58 -> 15000
B59: Parking | C59: 5 | D59: per 1000
B60: spaces | C60: =C58/1000*C59 -> 15
B61: SF | C61: 275 | D61: average
B62: Total SF | C62: =C60*C61 -> 4125
B63: acres | C63: =C62/43560 -> 0.09469697
B64: Cost per SF | C64: 85
B65: total cost | C65: =C64*C58 -> 255000

Sheet Summary Sources-Uses
A1: SUMMARY SOURCES & USES | L1: 45960
A2: Project Name
A3: Units New (61 Affordable units, amenities, community space) | L3: =G5&" Family Units" -> 0 Family Units
L4: 95% affordable below 60% AMI, 5% Market
A5: SOURCES & USES - Total Project | G5: 0 | H5: units
B7: Sources: | F7: Per Unit | H7: Uses: | K7: Total | L7: Per Unit
B8: First Mortgage | D8: =E49 -> 1st Mortgage | E8: =K49 -> 0 | F8: =E8/G$5 -> #DIV/0! | G8: =E8/$E$23 -> 0.46441928 | H8: Acquisition Costs | K8: ='Development Budget'!H10 -> 0 | L8: =K8/G$5 -> #DIV/0! | M8: =K8/$K$23 -> 3.0453723e-06
B9: 2nd Mortgage | D9: =E51 -> 2nd Mortgage | E9: =K51 -> 0 | F9: =E9/G$5 -> #DIV/0! | G9: =E9/$E$23 -> 0.09136117 | H9: Construction Costs | K9: ='Development Budget'!H21 -> 0 | L9: =K9/G$5 -> #DIV/0! | M9: =K9/$K$23 -> 0.5850362 | P9: CHANGES to SOURCES
B10: 3rd Mortgage | D10: =E53 -> GAP Funding (TBD) | E10: =K53 -> 0 | F10: =E10/G$5 -> #DIV/0! | G10: =E10/$E$23 -> 0.73088936 | H10: Predevelopment Costs | K10: ='Development Budget'!H29 -> 0 | L10: =K10/G$5 -> #DIV/0! | M10: =K10/$K$23 -> 0.0027347444
B11: 4th Mortgage | D11: =E56 -> 0 | E11: 0 | F11: =E11/G$5 -> #DIV/0! | G11: =E11/$E$23 -> 0 | H11: Financing | K11: ='Development Budget'!H40 -> 2045006.5 | L11: =K11/G$5 -> 33524.697 | M11: =K11/$K$23 -> 0.062278063 | P11: 1 | R11: 28792745 | S11: QCT Credits
D12: =E59 -> n.a. | F12: =E12/G$5 -> #DIV/0! | G12: =E12/$E$23 -> 0 | H12: Professional Services | K12: ='Development Budget'!H54 -> 752400 | L12: =K12/G$5 -> #DIV/0! | M12: =K12/$K$23 -> 0.022913381 | R12: =E37*10 -> 9461781.2 | S12: noQCT
B13: Other Equity | D13: n/a | E13: =E45 -> 0 | F13: =E13/G$5 -> #DIV/0! | G13: =E13/$E$23 -> 0 | H13: Local Government Fees | K13: ='Development Budget'!H60 -> 371885.27 | L13: =K13/G$5 -> #DIV/0! | M13: =K13/$K$23 -> 0.011325291 | R13: =R12-R11 -> -19330963 | S13: Loss in credits
B14: Other grant/loan | D14: FHLB AHP | E14: 0 | F14: =E14/G$5 -> #DIV/0! | G14: =E14/$E$23 -> 0 | H14: Permanent Financing Fees | K14: ='Development Budget'!H67 -> 583875 | L14: =K14/G$5 -> #DIV/0! | M14: =K14/$K$23 -> 0.017781168
B15: LIHTC Equity (4%)-Fed | D15: investor | E15: =E39 -> 8230926.5 | F15: =E15/G$5 -> 134933.22 | G15: =E15/$E$23 -> 0.25066236 | H15: Tax Credit Costs | K15: ='Development Budget'!H75 -> 156675.25 | L15: =K15/G$5 -> 2568.4467 | M15: =K15/$K$23 -> 0.0047713447 | R15: 25047183 | S15: QCT Equity
B16: LIHTC Equity (4%)-State | D16: investor | E16: =E41 -> 0 | F16: =E16/G$5 -> 0 | G16: =E16/$E$23 -> 0 | H16: Equity Costs | K16: ='Development Budget'!H81 -> 115000 | L16: =K16/G$5 -> #DIV/0! | M16: =K16/$K$23 -> 0.0035021782 | R16: =E15 -> 8230926.5 | S16: noQCT
B17: Deferred Devel Fee | D17: developer | E17: =K23-SUM(E8:E16,E18) -> -18830917 | F17: =E17/G$5 -> -308703.55 | G17: =E17/$E$23 -> -0.57347153 | H17: Start Up and Reserves | K17: ='Development Budget'!H88 -> 2436302.8 | L17: =K17/G$5 -> 39939.391 | M17: =K17/$K$23 -> 0.074194492 | R17: =R16-R15 -> -16816256 | S17: Loss in Equity
B18: Earnings on GIC (set equal to interest exp) | E18: ='Development Budget'!G33 -> 1186697.6 | G18: =E18/$E$23 -> 0.036139361 | H18: Other Costs | K18: ='Development Budget'!H91 -> 75000 | L18: =K18/G$5 -> #DIV/0! | M18: =K18/$K$23 -> 0.0022840292
C20: percent of fee deferred | D20: =E17/K20 -> -2.690131 | H20: Developer Fee | K20: 7000000 | L20: =K20/G$5 -> #DIV/0! | M20: =K20/$K$23 -> 0.21317606
C21: Payback period | D21: ='20yr Proforma'!C54 -> 0
R22: Permanent Debt
B23: Total Sources: | E23: =SUM(E8:E18) -> 32836707 | F23: =E23/G$5 -> 538306.68 | H23: Total Uses: | K23: =SUM(K8:K21) -> 32836707 | L23: =K23/G$5 -> 538306.68 | R23: 17700000 | S23: QCT Perm Debt
R24: =E8+K51 -> 0 | S24: noQCT
Q25: =R25/R23 -> -1 | R25: =R24-R23 -> -17700000 | S25: Increase in debt
R27: Deferred Developer Fee
B28: LIHTC Equity | R28: 372056 | S28: QCT DDF
B29: Total Eligible Costs | E29: ='Development Budget'!J94 -> 24658652 | R29: =E17 -> -18830917 | S29: noQCT
B30: Percentage Low Income | D30: 1 | Q30: =R30/R28 -> -51.613125 | R30: =R29-R28 -> -19202973 | S30: Increase in DDF
B31: Eligible Basis Acquis. | D31: 1 | E31: 0
B32: Eligible Basis-Dev. Cost | D32: ='Rent Schedule'!D27 -> 0.95927602 | E32: =E29*D32 -> 23654453 | R32: FEMA Allocation
B33: Combined Basis | E33: =E31+E32 -> 23654453 | R33: =20000000 -> 20000000 | S33: QCT FEMA
B34: Boost | D34: 1 | R34: =E10 -> 0 | S34: noQCT
B35: Qualified Basis: | E35: =E33*D34 -> 23654453 | Q35: =R35/R33 -> -1 | R35: =R34-R33 -> -20000000 | S35: Increase in FEMA
B36: Eligible Annual Credit: | D36: 0.04 | E36: =E35*D36 -> 946178.12
B37: LIHTC allocation | E37: =E36 -> 946178.12
B38: Federal Equity Pricing ($/credit) | D38: 0.87 | E38: =E37*10*D38 -> 8231749.7
B39: Total Federal LIHTC Equity | E39: =E38*0.9999 -> 8230926.5 | F39: 99.99% to LP investor
B40: State Equity Pricing ($/credit) | E40: =E37*10*D40 -> 0
B41: Total State LIHTC Equity | E41: =E40*0.9999 -> 0
B43: Total Equity Yield | E43: =E39+E41 -> 8230926.5
B45: 45L Credits | D45: =D38 -> 0.87 | E45: 0
W46: Total Funds | Y46: 18250000
B47: Debt Sources: | H47: rate | I47: amortiz | J47: term | K47: principal | L47: annual DS | N47: annual DS/unit | Q47: DSCR Y1 | R47: DSCR Y15 | S47: DSCR Y20
B49: 1st Mortgage: | E49: 1st Mortgage | H49: =0.0405+0.0184+0.0025 -> 0.0614 | I49: =480/12 -> 40 | J49: =216/12 -> 18 | K49: 0 | L49: =PMT(H49/12,I49*12,K49)*-12 -> 0 | N49: =L49/G5 -> #DIV/0! | Q49: ='20yr Proforma'!F51 -> 1.2332214 | R49: ='20yr Proforma'!T51 -> 1.3152017 | S49: ='20yr Proforma'!Y51 -> 1.3172033 | W49: HHA Portion | Y49: 3000000
F50: *10yr (4.05%) + 184bp spread + 25bp cushion | W50: Wells Portion | Y50: =Y46-Y49 -> 15250000
B51: 2nd Mortgage | E51: 2nd Mortgage | H51: =H49 -> 0.0614 | I51: =I49 -> 40 | J51: =J49 -> 18 | K51: 0 | L51: =PMT(H51/12,I51*12,K51)*-12 -> 0 | N51: =L51/G5 -> #DIV/0!
B53: Soft Loan | E53: GAP Funding (TBD) | H53: 0.01 | I53: 40 | J53: 40 | K53: 0 | L53: =K53*H53 -> 0 | M53: cash flow-interest only | N53: =L53/G5 -> #DIV/0!
B55: Soft Loan B | L55: =K55*H55 -> 0 | N55: =L55/G5 -> #DIV/0!
B57: 4th Mortgage | E57: n.a.
B59: 5th Mortgage | E59: n.a.
B61: 6th Mortgage | E61: n. a.
D63: totals: | L63: =SUM(L49:L61) -> 0
B66: Debt Sources:
E67: Bond Allocation: | G67: (TBD) | K67: ='50% Test'!F5 -> 13562258
E68: Construction Loan (Taxable) | H68: =0.04+0.0245+0.0015 -> 0.066 | I68: * | K68: ='Flow of Funds'!AD134 -> -1762837.9
E69: 50% Test Calculation: | K69: ='50% Test'!D10 -> 0.55
F70: * rate is 30-day SOFR 4.00% + 245bp with 15 bps hedge

Sheet Development Budget
K1: 3/14/2025
A2: Development Costs & Tax Treatment | K2: ='[2]Summary Sources-Uses'!L2 -> Structured Parking Transaction
A3: =ProjName -> Columbia at Independence Heights | K3: ='Summary Sources-Uses'!L1 -> 45960
B5: MATCHES TDHCA CORE APP (4%) | J5: Construction:
G6: Total | I6: Per Unit | J6: Section 42 | K6: Notes
J7: Basis Eligible
B8: Acquisition Costs
C9: Land/Ground Lease Prepayment | G9: 0 | I9: =IF(G9>0,G9/TotalUnitCount,"") | K9: HHA Ground Lease- confirm not capitalized- $100/year for 75 years
H10: =SUM(G9:G9) -> 0
B11: Construction Costs | I11: =IF(G11>0,G11/TotalUnitCount,"")
C12: Hard Costs | G12: 0 | I12: =IF(G12>0,G12/TotalUnitCount,"") | J12: =G12-400000 -> -400000 | K12: $400K carved out of basis for commercial space
C13: Sitework & Related Fees | G13: 0 | I13: =IF(G13>0,G13/TotalUnitCount,"") | J13: =G13*0.9 -> 0 | K13: 90% for basis
C14: Structured Parking | G14: 0 | I14: =IF(G14>0,G14/TotalUnitCount,"") | J14: =G14 -> 0
C15: General Conditions | G15: 0 | I15: =IF(G15>0,G15/TotalUnitCount,"") | J15: =G15 -> 0
C16: GC Overhead | G16: 0 | I16: =IF(G16>0,G16/TotalUnitCount,"") | J16: =G16 -> 0
C17: GC Profit | G17: =(G12+G13+G14)*0.06 -> 0 | I17: =IF(G17>0,G17/TotalUnitCount,"") | J17: =G17 -> 0
C18: Builders Risk Insurance | G18: 0 | I18: =IF(G18>0,G18/TotalUnitCount,"") | J18: =G18 -> 0
C19: Payment and Performance Bond | G19: 0 | I19: =IF(G19>0,G19/TotalUnitCount,"") | J19: =G19 -> 0
C20: Construction Contingency (5%) | G20: =(G12+G13+G14+G15+G16+G17+G19)*0.05 -> 0 | I20: =IF(G20>0,G20/TotalUnitCount,"") | J20: =G20 -> 0
H21: =SUM(G12:G20) -> 0
B22: Predevelopment Costs | I22: =IF(G22>0,G22/TotalUnitCount,"")
C23: Property Appraisal | G23: 0 | I23: =IF(G23>0,G23/TotalUnitCount,"") | J23: =G23 -> 0
C24: Market Study | G24: 0 | I24: =IF(G24>0,G24/TotalUnitCount,"") | J24: =G24 -> 0
C25: Environmental Report(s) | G25: 0 | I25: =IF(G25>0,G25/TotalUnitCount,"") | J25: =G25 -> 0 | K25: Includes Part 58 costs, and phase 2
C26: Soil Borings | G26: 0 | I26: =IF(G26>0,G26/TotalUnitCount,"") | J26: =G26 -> 0
C27: Boundary and Topographical Survey | G27: 0 | I27: =IF(G27>0,G27/TotalUnitCount,"") | J27: =G27 -> 0
C28: Zoning/Site Plan Fees | G28: 0 | I28: =IF(G28>0,G28/TotalUnitCount,"") | J28: =G28 -> 0
H29: =SUM(G23:G28) -> 0
B30: Financing | I30: =IF(G30>0,G30/TotalUnitCount,"")
C31: Construction Financing and Placement Fees | G31: ='Summary Sources-Uses'!K68*1.3% -> -22916.893 | I31: =IF(G31>0,G31/TotalUnitCount,"") | J31: =G31*0.5 -> -11458.446 | K31: 1.3% of construction bonds- 50% in basis (confirming w/ CohnReznick)
C32: Construction Loan Interest | G32: ='Flow of Funds'!H159 -> 711225.82 | I32: =IF(G32>0,G32/TotalUnitCount,"") -> 3218.2164 | J32: ='Flow of Funds'!$H$160 -> 151470.82 | K32: Based on CIP Calc - Flow of funds
C33: Bond Interst (Fully Drawn) | G33: ='Flow of Funds'!H116 -> 1186697.6 | I33: =IF(G33>0,G33/TotalUnitCount,"") -> 5369.6724 | J33: ='Flow of Funds'!H117 -> 745924.21
C34: Bond issuer Fee (APV) | G34: 0 | I34: =IF(G34>0,G34/TotalUnitCount,"") | J34: =G34*0.1 -> 0 | K34: 1.0% of construction bonds- 10% in basis (confirming w/ CohnReznick)
C35: Lender's Legal Fees | G35: 50000 | I35: =IF(G35>0,G35/TotalUnitCount,"") -> 226.24434 | J35: 150000
C36: Construction Period Real Estate Tax | G36: 0 | I36: =IF(G36>0,G36/TotalUnitCount,"") | J36: =G36 -> 0
C37: GL Insurance & BR Security during construction | G37: 120000 | I37: =IF(G37>0,G37/TotalUnitCount,"") -> 542.98643 | J37: 320000
C38: Bond Issuer Legal-Bond Board and Trustee Fees | G38: 0 | I38: =IF(G38>0,G38/TotalUnitCount,"") | J38: =160000 -> 160000 | K38: Based on MIP and HUD loan amount
C39: Freddie TEL legal & Associated Fees | G39: 0 | J39: 0
H40: =SUM(G31:G39) -> 2045006.5
B41: Professional Services | I41: =IF(G41>0,G41/TotalUnitCount,"")
C42: Architectural Fee - Design | G42: =150000 -> 150000 | I42: =IF(G42>0,G42/TotalUnitCount,"") -> 678.73303 | J42: =G42 -> 150000
C43: Architectural Fee - Supervision | G43: 87400 | I43: =IF(G43>0,G43/TotalUnitCount,"") -> 395.47511 | J43: =G43 -> 87400
C44: Architectural Fee - Reimbursables | G44: 20000 | I44: =IF(G44>0,G44/TotalUnitCount,"") -> 90.497738 | J44: =G44 -> 20000
C45: Landscape Architect | G45: 35000 | I45: =IF(G45>0,G45/TotalUnitCount,"") -> 158.37104 | J45: =G45 -> 35000
C46: Engineering | G46: =150000 -> 150000 | I46: =IF(G46>0,G46/TotalUnitCount,"") -> 678.73303 | J46: =G46 -> 150000
C47: Real Estate Attorney | G47: 75000 | I47: =IF(G47>0,G47/TotalUnitCount,"") -> 339.36652 | J47: =G47*0.6 -> 45000
C48: HHA Legal (Coats Rose) | G48: 50000 | I48: =IF(G48>0,G48/TotalUnitCount,"") -> 226.24434 | J48: =G48*0.25 -> 12500
C49: Accounting | G49: 70000 | I49: =IF(G49>0,G49/TotalUnitCount,"") -> 316.74208 | J49: 70000
C50: Green Building Certification/Registration | G50: 0 | I50: =IF(G50>0,G50/TotalUnitCount,"") | J50: =G50 -> 0
C51: Construction Inspection Fees | G51: 40000 | I51: =IF(G51>0,G51/TotalUnitCount,"") -> 180.99548 | J51: =G51 -> 40000
C52: Accessibility Consulting | G52: 30000 | I52: =IF(G52>0,G52/TotalUnitCount,"") -> 135.74661 | J52: =G52 -> 30000
C53: Construction Materials Testing | G53: 45000 | I53: =IF(G53>0,G53/TotalUnitCount,"") -> 203.61991 | J53: =G53 -> 45000
H54: =SUM(G42:G53) -> 752400
B55: Local Government Fees | I55: =IF(G55>0,G55/TotalUnitCount,"")
C56: Building Permits | G56: =160000 -> 160000 | I56: =IF(G56>0,G56/TotalUnitCount,"") -> 723.9819 | J56: =G56 -> 160000 | K56: Building Permits & Park Open Spaces Fees- quotes from permit expeditor
C57: Impact Fees | G57: 186154.27 | I57: =IF(G57>0,G57/TotalUnitCount,"") -> 842.32701 | J57: =G57 -> 186154.27 | K57: Invoice amt. from City
C58: Plan review | G58: 25731 | I58: =IF(G58>0,G58/TotalUnitCount,"") -> 116.42986 | J58: =G58 -> 25731 | K58: Invoice amt. from City
C59: Other local fees | I59: =IF(G59>0,G59/TotalUnitCount,"") | J59: =G59 -> 0
H60: =SUM(G56:G59) -> 371885.27
B61: Permanent Financing Fees | I61: =IF(G61>0,G61/TotalUnitCount,"")
C62: Permanent Loan Fees | G62: =10000+160500+14250+64125+50000+10000 -> 308875 | I62: =IF(G62>0,G62/TotalUnitCount,"") -> 1397.6244 | K62: App. Fee, Origination Fee, Freddie Mac Fee, Standby Fee, Construction Monitoring Fee
C63: Permanent Loan Legal Fees | G63: 120000 | I63: =IF(G63>0,G63/TotalUnitCount,"") -> 542.98643
C64: Title and Recording Fees | G64: 115000 | I64: =IF(G64>0,G64/TotalUnitCount,"") -> 520.36199 | J64: =G64*0.75 -> 86250
C65: As-Built Survey | G65: 30000 | I65: =IF(G65>0,G65/TotalUnitCount,"") -> 135.74661
C66: Conversion Fee | G66: 10000 | I66: =IF(G66>0,G66/TotalUnitCount,"") -> 45.248869
H67: =SUM(G62:G66) -> 583875
B68: Tax Credit Costs | I68: =IF(G68>0,G68/TotalUnitCount,"")
C69: Application Fee | G69: =N69*'Summary Sources-Uses'!G5 -> 0 | I69: =IF(G69>0,G69/TotalUnitCount,"") | K69: Per TDHCA - $20/unit | N69: 41 | O69: per unit
C70: Pre-application Fee | G70: 0 | I70: =IF(G70>0,G70/TotalUnitCount,"") | K70: Per TDHCA - $10 per unit | N70: 10 | O70: per unit
C71: Commitment Fee | G71: =N71*'Summary Sources-Uses'!E37 -> 37847.125 | I71: =IF(G71>0,G71/TotalUnitCount,"") -> 171.25396 | K71: Per TDHCA - 4% of annual LIHTC allocation | N71: 0.04 | O71: of annual LIHTC
C72: Bond Development Determination Fee | G72: =N72*'Summary Sources-Uses'!E37 -> 37847.125 | I72: =IF(G72>0,G72/TotalUnitCount,"") -> 171.25396 | K72: Per TDHCA - 4% of annual LIHTC allocation | N72: 0.04 | O72: of annual LIHTC
C73: LIHTC Allocation Processing Fee | G73: 70000 | I73: =IF(G73>0,G73/TotalUnitCount,"") -> 316.74208 | K73: Per TDHCA
C74: LIHTC Compliance Monitoring Fee | G74: =N74*LIUnits -> 8480 | I74: =IF(G74>0,G74/TotalUnitCount,"") -> 38.371041 | K74: Per TDHCA | N74: 40 | O74: per tax credit unit
H75: =SUM(G69:G74) -> 156675.25
B76: Equity Costs | I76: =IF(G76>0,G76/TotalUnitCount,"")
C77: Partnership Organization Fees | G77: 35000 | I77: =IF(G77>0,G77/TotalUnitCount,"") -> 158.37104
C78: Tax Credit Legal Opinion | G78: 30000 | I78: =IF(G78>0,G78/TotalUnitCount,"") -> 135.74661
C79: Syndicator Legal Fees | G79: 30000 | I79: =IF(G79>0,G79/TotalUnitCount,"") -> 135.74661
C80: Syndicator Due Diligence Fee | G80: 20000 | I80: =IF(G80>0,G80/TotalUnitCount,"") -> 90.497738
H81: =SUM(G77:G80) -> 115000
B82: Start Up and Reserves | I82: =IF(G82>0,G82/TotalUnitCount,"")
C83: Marketing | G83: 50000 | I83: =IF(G83>0,G83/TotalUnitCount,"") -> 226.24434
C84: Rent-Up Reserves | G84: =ExpTotalY1/12*4 -> 600000 | I84: =IF(G84>0,G84/TotalUnitCount,"") -> 2714.9321 | K84: 4 months OpEx
C85: Operating Deficit Reserve | G85: =(('Operating Expense'!E20/12+'Summary Sources-Uses'!$L$49/12)*6) -> 1470002.8 | I85: =IF(G85>0,G85/TotalUnitCount,"") -> 6651.5965 | K85: Per TDHCA- 2-6 months opex + debt service
C86: Replacement Reserve | G86: ='Operating Expense'!E21 -> 66300 | I86: =IF(G86>0,G86/TotalUnitCount,"") -> 300
C87: Furniture, Fixtures and Equipment | G87: 250000 | I87: =IF(G87>0,G87/TotalUnitCount,"") -> 1131.2217 | J87: =G87 -> 250000
H88: =SUM(G83:G87) -> 2436302.8
B89: Other Costs | I89: =IF(G89>0,G89/TotalUnitCount,"")
C90: Soft Cost Contingency | G90: 75000 | I90: =IF(G90>0,G90/TotalUnitCount,"") -> 339.36652 | J90: =G90*0.5 -> 37500
H91: =G90 -> 75000
B92: Total, Excluding Developer Fee | G92: =SUM(G8:G90) -> 25836707 | H92: =SUM(H9:H91) -> 25836707 | I92: =IF(G92>0,G92/TotalUnitCount,"") -> 116908.18 | J92: =SUM(J9:J90) -> 21442306
C93: Developer Fee | G93: ='Summary Sources-Uses'!K20 -> 7000000 | I93: =IF(G93>0,G93/TotalUnitCount,"") -> 31674.208 | J93: =MIN(SUM(J9:J90)*0.15,G93) -> 3216345.9
B94: Total, With Developer Fee | G94: =G92+G93 -> 32836707 | I94: =IF(G94>0,G94/TotalUnitCount,"") -> 148582.39 | J94: =J92+J93 -> 24658652
K96: =ProjName -> Columbia at Independence Heights
K98: Page 3
H101: =H92-G92 -> 0

Sheet Rent Schedule
A1: =ProjName -> Columbia at Independence Heights (NO QCT)
A2: Maximum Eligible & Projected Rents | K2: ='Summary Sources-Uses'!L1 -> 45960 | N2: 1792 | T2: 42400 | U2: =T2+T3+T4 -> 210700
H3: PBV rents are 110% of 2025 FMR Rents | N3: =(N2*0.1)+N2 -> 1971.2 | T3: 129600 | U3: =U2*12 -> 2528400
A4: RENT ROLL | H4: LIHTC rents are 2025 rents per Novogradac | T4: 38700
H5: Utility Allowances (UA) are based on HHA 1/25 schedule
A6: Unit Type | B6: Set-Aside | C6: Income Limit | D6: Number of Units | E6: Avg NRSF | F6: Max Eligible Gross Rent | G6: UA | H6: Net Rent | I6: $/NRSF | K6: Annual Rent | N6: =F12*1.1 -> 1639 | O6: =F18*1.1 -> 1815 | P6: =F24*1.1 -> 2145 | U6: =U3*20 -> 50568000
A7: 1 BR | B7: =N28 -> 30% PBV | C7: =IFERROR(INDEX(IncomeLimits,MATCH($B7,SetAsides,0)),"") -> 0.3 | D7: 6 | E7: =IF(LEN($B7)>1,INDEX(UnitSFAvg,MATCH($A7,UnitTypes,0)),"") -> 665 | F7: =H7-G7 -> 1531 | G7: =-F70 -> -206 | H7: 1325 | I7: =IFERROR(H7/E7,"") -> 1.9924812 | K7: =IFERROR(H7*12*D7,"") -> 95400 | L7: PBV-LIHTC
A8: 1 BR | B8: =N29 -> 50% PBV | C8: =IFERROR(INDEX(IncomeLimits,MATCH($B8,SetAsides,0)),"") -> 0.5 | D8: 6 | E8: =IF(LEN($B8)>1,INDEX(UnitSFAvg,MATCH($A8,UnitTypes,0)),"") -> 665 | F8: =H8-G8 -> 1531 | G8: =-F70 -> -206 | H8: 1325 | I8: =IFERROR(H8/E8,"") -> 1.9924812 | K8: =IFERROR(H8*12*D8,"") -> 95400 | L8: PBV-LIHTC | N8: Total Required HAP Vouchers from HHA | R8: =D7+D8+D9+D13+D14+D15+D19+D20+D21 -> 131
A9: 1 BR | B9: 60% PBV | C9: 0.6 | D9: 20 | E9: =IF(LEN($B9)>1,INDEX(UnitSFAvg,MATCH($A9,UnitTypes,0)),"") -> 665 | F9: =N6-G9 -> 1845 | G9: =-F70 -> -206 | H9: 1325 | I9: =IFERROR(H9/E9,"") -> 1.9924812 | K9: =IFERROR(H9*12*D9,"") -> 318000 | L9: PBV-LIHTC | N9: HAP Voucher Payment Standard | R9: 1.1 | S9: of HUD FMR rent
A10: 1 BR | B10: =N30 -> 60% LIHTC | C10: =IFERROR(INDEX(IncomeLimits,MATCH($B10,SetAsides,0)),"") -> 0.6 | D10: 26 | E10: =IF(LEN($B10)>1,INDEX(UnitSFAvg,MATCH($A10,UnitTypes,0)),"") -> 665 | F10: 1137 | G10: =-F70 -> -206 | H10: =IF(SUM(F10:G10)>0,SUM(F10:G10),"") -> 931 | I10: =IFERROR(H10/E10,"") -> 1.4 | K10: =IFERROR(H10*12*D10,"") -> 290472 | L10: LIHTC only | N10: Total Affordable Units below 60% AMI | R10: =D26-D11-D12-D17-D18-D24 -> 212
A11: 1 BR | B11: =N31 -> 80% LIHTC | C11: =IFERROR(INDEX(IncomeLimits,MATCH($B11,SetAsides,0)),"") -> 0.8 | D11: 0 | E11: =IF(LEN($B11)>1,INDEX(UnitSFAvg,MATCH($A11,UnitTypes,0)),"") -> 665 | F11: 1517 | G11: =-F70 -> -206 | H11: =IF(SUM(F11:G11)>0,SUM(F11:G11),"") -> 1311 | I11: =IFERROR(H11/E11,"") -> 1.9714286 | K11: =IFERROR(H11*12*D11,"") -> 0 | L11: LIHTC only | W11: =1135*1.1 -> 1248.5
A12: 1 BR | B12: =N37 -> Market | C12: unrestricted | D12: 7 | E12: =IF(LEN($B12)>1,INDEX(UnitSFAvg,MATCH($A12,UnitTypes,0)),"") -> 665 | F12: 1490 | G12: =IFERROR(IF(INDEX(RentRange,MATCH("UA's",RentRow,0),MATCH($B12,RentColumn,0))="Y", IFERROR(-INDEX(RentRange,MATCH($A12,RentRow,0),MATCH(G$6,RentColumn,0)),""),""),"") | H12: =IF(SUM(F12:G12)>0,SUM(F12:G12),"") -> 1490 | I12: =IFERROR(H12/E12,"") -> 2.2406015 | K12: =IFERROR(H12*12*D12,"") -> 125160 | L12: market | W12: =1357*1.1 -> 1492.7
A13: 2 BR | B13: =B7 -> 30% PBV | C13: =IFERROR(INDEX(IncomeLimits,MATCH($B13,SetAsides,0)),"") -> 0.3 | D13: 12 | E13: =IF(LEN($B13)>1,INDEX(UnitSFAvg,MATCH($A13,UnitTypes,0)),"") -> 850 | F13: =H13-G13 -> 1869 | G13: =-G70 -> -269 | H13: 1600 | I13: =IFERROR(H13/E13,"") -> 1.8823529 | K13: =IFERROR(H13*12*D13,"") -> 230400 | L13: PBV-LIHTC | W13: =1792*1.1 -> 1971.2
A14: 2 BR | B14: =B8 -> 50% PBV | C14: =IFERROR(INDEX(IncomeLimits,MATCH($B14,SetAsides,0)),"") -> 0.5 | D14: 12 | E14: =IF(LEN($B14)>1,INDEX(UnitSFAvg,MATCH($A14,UnitTypes,0)),"") -> 850 | F14: =H14-G14 -> 1869 | G14: =-G70 -> -269 | H14: 1600 | I14: =IFERROR(H14/E14,"") -> 1.8823529 | K14: =IFERROR(H14*12*D14,"") -> 230400 | L14: PBV-LIHTC | P14: =D7+D13+D19 -> 20 | Q14: 30% PBV
A15: 2 BR | B15: =B9 -> 60% PBV | C15: 0.6 | D15: 57 | E15: =IF(LEN($B15)>1,INDEX(UnitSFAvg,MATCH($A15,UnitTypes,0)),"") -> 850 | F15: =H15-G15 -> 1869 | G15: =-G70 -> -269 | H15: 1600 | I15: =H14/E14 -> 1.8823529 | K15: =IFERROR(H15*12*D15,"") -> 1094400 | L15: PBV-LIHTC | P15: =D8+D14+D20 -> 20 | Q15: 50% PBV
A16: 2 BR | B16: =B10 -> 60% LIHTC | C16: =IFERROR(INDEX(IncomeLimits,MATCH($B16,SetAsides,0)),"") -> 0.6 | D16: 45 | E16: =IF(LEN($B16)>1,INDEX(UnitSFAvg,MATCH($A16,UnitTypes,0)),"") -> 850 | F16: 1365 | G16: =-G70 -> -269 | H16: =G16+F16 -> 1096 | I16: =IFERROR(H16/E16,"") -> 1.2894118 | K16: =IFERROR(H16*12*D16,"") -> 591840 | L16: LIHTC only | P16: =D9+D15+D21 -> 91 | Q16: 60% PBV
A17: 2 BR | B17: =B11 -> 80% LIHTC | C17: =IFERROR(INDEX(IncomeLimits,MATCH($B17,SetAsides,0)),"") -> 0.8 | D17: 0 | E17: =IF(LEN($B17)>1,INDEX(UnitSFAvg,MATCH($A17,UnitTypes,0)),"") -> 850 | F17: 1820 | G17: =-G70 -> -269 | H17: =G17+F17 -> 1551 | I17: =IFERROR(H17/E17,"") -> 1.8247059 | K17: =IFERROR(H17*12*D17,"") -> 0 | L17: LIHTC only | P17: =D10+D16+D22 -> 81 | Q17: 60% LIHTC
A18: 2 BR | B18: =B12 -> Market | C18: unrestricted | D18: 2 | E18: =IF(LEN($B18)>1,INDEX(UnitSFAvg,MATCH($A18,UnitTypes,0)),"") -> 850 | F18: 1650 | G18: =IFERROR(IF(INDEX(RentRange,MATCH("UA's",RentRow,0),MATCH($B18,RentColumn,0))="Y", IFERROR(-INDEX(RentRange,MATCH($A18,RentRow,0),MATCH(G$6,RentColumn,0)),""),""),"") | H18: =IF(SUM(F18:G18)>0,SUM(F18:G18),"") -> 1650 | I18: =IFERROR(H18/E18,"") -> 1.9411765 | K18: =IFERROR(H18*12*D18,"") -> 39600 | L18: market | P18: =D12+D18+D24 -> 9 | Q18: market
A19: 3 BR | B19: =B13 -> 30% PBV | C19: =IFERROR(INDEX(IncomeLimits,MATCH($B19,SetAsides,0)),"") -> 0.3 | D19: 2 | E19: =IF(LEN($B19)>1,INDEX(UnitSFAvg,MATCH($A19,UnitTypes,0)),"") -> 1200 | F19: =H19-G19 -> 2481 | G19: =-H70 -> -331 | H19: 2150 | I19: =IFERROR(H19/E19,"") -> 1.7916667 | K19: =IFERROR(H19*12*D19,"") -> 51600 | L19: PBV-LIHTC
A20: 3 BR | B20: =B14 -> 50% PBV | C20: =IFERROR(INDEX(IncomeLimits,MATCH($B20,SetAsides,0)),"") -> 0.5 | D20: 2 | E20: =IF(LEN($B20)>1,INDEX(UnitSFAvg,MATCH($A20,UnitTypes,0)),"") -> 1200 | F20: =H20-G20 -> 2481 | G20: =-H70 -> -331 | H20: 2150 | I20: =IFERROR(H20/E20,"") -> 1.7916667 | K20: =IFERROR(H20*12*D20,"") -> 51600 | L20: PBV-LIHTC
A21: 3 BR | B21: =B15 -> 60% PBV | C21: 0.6 | D21: 14 | E21: =IF(LEN($B21)>1,INDEX(UnitSFAvg,MATCH($A21,UnitTypes,0)),"") -> 1200 | F21: =H21-G21 -> 2481 | G21: =-H70 -> -331 | H21: 2150 | I21: =H20/E20 -> 1.7916667 | K21: =IFERROR(H21*12*D21,"") -> 361200 | L21: PBV-LIHTC
A22: 3 BR | B22: =B16 -> 60% LIHTC | C22: =IFERROR(INDEX(IncomeLimits,MATCH($B22,SetAsides,0)),"") -> 0.6 | D22: 10 | E22: =IF(LEN($B22)>1,INDEX(UnitSFAvg,MATCH($A22,UnitTypes,0)),"") -> 1200 | F22: 1577 | G22: =-H70 -> -331 | H22: =IF(SUM(F22:G22)>0,SUM(F22:G22),"") -> 1246 | I22: =IFERROR(H22/E22,"") -> 1.0383333 | K22: =IFERROR(H22*12*D22,"") -> 149520 | L22: LIHTC only
A23: 3 BR | B23: =B17 -> 80% LIHTC | C23: =IFERROR(INDEX(IncomeLimits,MATCH($B23,SetAsides,0)),"") -> 0.8 | D23: 0 | E23: =IF(LEN($B23)>1,INDEX(UnitSFAvg,MATCH($A23,UnitTypes,0)),"") -> 1200 | F23: 2103 | G23: =-H70 -> -331 | H23: =IF(SUM(F23:G23)>0,SUM(F23:G23),"") -> 1772 | I23: =IFERROR(H23/E23,"") -> 1.4766667 | K23: =IFERROR(H23*12*D23,"") -> 0 | L23: LIHTC only
A24: 3 BR | B24: =B18 -> Market | C24: unrestricted | D24: 0 | E24: =IF(LEN($B24)>1,INDEX(UnitSFAvg,MATCH($A24,UnitTypes,0)),"") -> 1200 | F24: 1950 | G24: =IFERROR(IF(INDEX(RentRange,MATCH("UA's",RentRow,0),MATCH($B24,RentColumn,0))="Y", IFERROR(-INDEX(RentRange,MATCH($A24,RentRow,0),MATCH(G$6,RentColumn,0)),""),""),"") | H24: =IF(SUM(F24:G24)>0,SUM(F24:G24),"") -> 1950 | I24: =IFERROR(H24/E24,"") -> 1.625 | K24: =IFERROR(H24*12*D24,"") -> 0 | L24: market
A26: TOTAL | D26: =SUM(D7:D25) -> 221 | E26: =SUMPRODUCT($E$7:$E$25,$D$7:$D$25)/D26 -> 839.93213 | H26: =SUMPRODUCT(K26/12/D26) -> 1404.5973 | K26: =SUM(K7:K25) -> 3724992 | L26: =GrossRentIncomeY1/D26 -> 16855.167 | P26: Target Total Distribution | U26: Actual Distribution by Unit Type
D27: =(D7+D8+D9+D10+D13+D14+D15+D16+D19+D20+D21+D22)/D26 -> 0.95927602 | N27: Distribution of Units | P27: 1 BR | Q27: 2 BR | R27: 3 BR | S27: Total | U27: 1 BR | V27: 2 BR | W27: 3 BR | X27: Total | Y27: Variance
A28: Other Income | F28: Per Unit/Mo. | H28: All Units/Mo. | K28: Annual Revenue | N28: {=IF(SetAsides>0,SetAsides,"")} -> 30% PBV | P28: =P$38*Inputs!$D23 -> 0.047 | Q28: =Q$38*Inputs!$D23 -> 0.041 | R28: =R$38*Inputs!$D23 -> 0.012 | S28: =SUM(P28:R28) -> 0.1 | U28: =C45/TotalUnitCount -> 0.027149321 | V28: =D45/TotalUnitCount -> 0.054298643 | W28: =E45/TotalUnitCount -> 0.0090497738 | X28: =SUM(U28:W28) -> 0.090497738 | Y28: =S28-X28 -> 0.0095022624
A29: Laundry Machine Collections | F29: 0.75 | H29: =F29*TotalUnitCount -> 165.75 | K29: =H29*12 -> 1989 | N29: 50% PBV | P29: =P$38*Inputs!$D24 -> 0.047 | Q29: =Q$38*Inputs!$D24 -> 0.041 | R29: =R$38*Inputs!$D24 -> 0.012 | S29: =SUM(P29:R29) -> 0.1 | U29: =C46/TotalUnitCount -> 0.027149321 | V29: =D46/TotalUnitCount -> 0.054298643 | W29: =E46/TotalUnitCount -> 0.0090497738 | X29: =SUM(U29:W29) -> 0.090497738 | Y29: =S29-X29 -> 0.0095022624
A30: Late Fees | F30: 0.75 | H30: =F30*TotalUnitCount -> 165.75 | K30: =H30*12 -> 1989 | N30: 60% LIHTC | P30: =P$38*Inputs!$D25 -> 0.376 | Q30: =Q$38*Inputs!$D25 -> 0.328 | R30: =R$38*Inputs!$D25 -> 0.096 | S30: =SUM(P30:R30) -> 0.8 | U30: =C48/TotalUnitCount -> 0.11764706 | V30: =D48/TotalUnitCount -> 0.20361991 | W30: =E48/TotalUnitCount -> 0.045248869 | X30: =SUM(U30:W30) -> 0.36651584 | Y30: =S30-X30 -> 0.43348416
A31: Application Fees | F31: 0.75 | H31: =F31*TotalUnitCount -> 165.75 | K31: =H31*12 -> 1989 | N31: 80% LIHTC | P31: =P$38*Inputs!$D26 -> 0 | Q31: =Q$38*Inputs!$D26 -> 0 | R31: =R$38*Inputs!$D26 -> 0 | S31: =SUM(P31:R31) -> 0 | U31: =C49/TotalUnitCount -> 0 | V31: =D49/TotalUnitCount -> 0 | W31: =E49/TotalUnitCount -> 0 | X31: =SUM(U31:W31) -> 0 | Y31: =S31-X31 -> 0
A32: Security Deposit Forfeitures | F32: 0.75 | H32: =F32*TotalUnitCount -> 165.75 | K32: =H32*12 -> 1989 | P32: =P$38*Inputs!$D27 -> 0 | Q32: =Q$38*Inputs!$D27 -> 0 | R32: =R$38*Inputs!$D27 -> 0 | S32: =SUM(P32:R32) -> 0 | U32: =#REF!/TotalUnitCount -> #REF! | V32: =#REF!/TotalUnitCount -> #REF! | W32: =#REF!/TotalUnitCount -> #REF! | X32: =SUM(U32:W32) -> #REF! | Y32: =S32-X32 -> #REF!
A33: Other | F33: 9 | H33: =F33*TotalUnitCount -> 1989 | K33: =H33*12 -> 23868 | M33: =18238/12649-1 -> 0.44185311 | P33: =P$38*Inputs!$D28 -> 0 | Q33: =Q$38*Inputs!$D28 -> 0 | R33: =R$38*Inputs!$D28 -> 0 | S33: =SUM(P33:R33) -> 0 | U33: =#REF!/TotalUnitCount -> #REF! | V33: =#REF!/TotalUnitCount -> #REF! | W33: =#REF!/TotalUnitCount -> #REF! | X33: =SUM(U33:W33) -> #REF! | Y33: =S33-X33 -> #REF!
F34: =SUM(F29:F33) -> 12 | H34: =SUM(H29:H33) -> 2652 | K34: =SUM(K29:K33) -> 31824 | P34: =P$38*Inputs!$D29 -> 0 | Q34: =Q$38*Inputs!$D29 -> 0 | R34: =R$38*Inputs!$D29 -> 0 | S34: =SUM(P34:R34) -> 0 | U34: =#REF!/TotalUnitCount -> #REF! | V34: =#REF!/TotalUnitCount -> #REF! | W34: =#REF!/TotalUnitCount -> #REF! | X34: =SUM(U34:W34) -> #REF! | Y34: =S34-X34 -> #REF!
A35: Commerical Space | E35: SF | H35: Monthly | I35: per SF/mo | J35: per year | K35: Annual Revenue | P35: =P$38*Inputs!$D30 -> 0 | Q35: =Q$38*Inputs!$D30 -> 0 | R35: =R$38*Inputs!$D30 -> 0 | S35: =SUM(P35:R35) -> 0 | U35: =#REF!/TotalUnitCount -> #REF! | V35: =#REF!/TotalUnitCount -> #REF! | W35: =#REF!/TotalUnitCount -> #REF! | X35: =SUM(U35:W35) -> #REF! | Y35: =S35-X35 -> #REF!
A36: Commercial Space | E36: 3000 | H36: 0 | I36: =H36/E36 -> 0 | J36: =I36*12 -> 0 | K36: 100 | P36: =P$38*Inputs!$D31 -> 0 | Q36: =Q$38*Inputs!$D31 -> 0 | R36: =R$38*Inputs!$D31 -> 0 | S36: =SUM(P36:R36) -> 0 | U36: =#REF!/TotalUnitCount -> #REF! | V36: =#REF!/TotalUnitCount -> #REF! | W36: =#REF!/TotalUnitCount -> #REF! | X36: =SUM(U36:W36) -> #REF! | Y36: =S36-X36 -> #REF!
N37: Market | P37: =P$38*Inputs!$D32 -> 0 | Q37: =Q$38*Inputs!$D32 -> 0 | R37: =R$38*Inputs!$D32 -> 0 | S37: =SUM(P37:R37) -> 0 | U37: =C50/TotalUnitCount -> 0.031674208 | V37: =D50/TotalUnitCount -> 0.0090497738 | W37: =E50/TotalUnitCount -> 0 | X37: =SUM(U37:W37) -> 0.040723982 | Y37: =S37-X37 -> -0.040723982
A38: Subsidy Type | C38: Units | D38: Share | H38: Gross Potential Income | K38: =K26 -> 3724992 | N38: Total | P38: =INDEX(unitmix,MATCH(P27,UnitTypes,0)) -> 0.47 | Q38: =INDEX(unitmix,MATCH(Q27,UnitTypes,0)) -> 0.41 | R38: =INDEX(unitmix,MATCH(R27,UnitTypes,0)) -> 0.12 | S38: =SUM(S28:S37) -> 1 | U38: =SUM(U28:U37) -> #REF! | V38: =SUM(V28:V37) -> #REF! | W38: =SUM(W28:W37) -> #REF! | X38: =SUM(X28:X37) -> #REF!
A39: PHA Sec 8 PBV-HAP | C39: =TotalUnitCount-SUM(C40:C41) -> 131 | D39: =C39/$C$42 -> 0.59276018 | H39: Other Income | K39: =AddRevY1 -> 31824
A40: LIHTC | C40: =SUMIF($B$7:$B$25,"*LIHTC",$D$7:$D$25) -> 81 | D40: =C40/$C$42 -> 0.36651584 | H40: Commercial Income per year | K40: =K36 -> 100 | U40: Total LI | X40: =1-X37 -> 0.95927602
A41: Market Rate | C41: =SUMIF($B$7:$B$25,"Market",$D$7:$D$25) -> 9 | D41: =C41/$C$42 -> 0.040723982 | H41: Vacancy | J41: ='20yr Proforma'!J5 -> 0.07 | K41: =SUM(K38:K40)*-J41 -> -262984.12
A42: Total | C42: =SUM(C39:C41) -> 221 | D42: =C42/$C$42 -> 1 | H42: Net Income | K42: =SUM(K38:K41) -> 3493931.9
A44: Unit Count | C44: 1 BR | D44: 2 BR | E44: 3 BR | F44: Total | H44: % of Total | I44: % of LI
A45: =N28 -> 30% PBV | C45: =D7 -> 6 | D45: =D13 -> 12 | E45: =D19 -> 2 | F45: =SUM(C45:E45) -> 20 | H45: =F45/$F$51 -> 0.090497738 | I45: =F45/($F$51-$F$50) -> 0.094339623
A46: =N29 -> 50% PBV | C46: =D8 -> 6 | D46: =D14 -> 12 | E46: =D20 -> 2 | F46: =SUM(C46:E46) -> 20 | H46: =F46/$F$51 -> 0.090497738 | I46: =F46/($F$51-$F$50) -> 0.094339623
A47: 60% PBV | C47: 20 | D47: 57 | E47: 14 | F47: 91 | H47: =F47/$F$51 -> 0.41176471 | I47: =F47/($F$51-$F$50) -> 0.42924528
A48: =N30 -> 60% LIHTC | C48: 26 | D48: 45 | E48: 10 | F48: =SUM(C48:E48) -> 81 | H48: =F48/$F$51 -> 0.36651584 | I48: =F48/($F$51-$F$50) -> 0.38207547
A49: =N31 -> 80% LIHTC | C49: =D11 -> 0 | D49: =D17 -> 0 | E49: =D11+D17+D23 -> 0 | F49: =SUM(C49:E49) -> 0 | H49: =F49/$F$51 -> 0 | I49: =F49/($F$51-$F$50) -> 0
A50: =N37 -> Market | C50: =D12 -> 7 | D50: =D18 -> 2 | E50: =D24 -> 0 | F50: =SUM(C50:E50) -> 9 | H50: =F50/$F$51 -> 0.040723982
A51: Total | C51: =SUM(C45:C50) -> 65 | D51: =SUM(D45:D50) -> 128 | E51: =SUM(E45:E50) -> 28 | F51: =SUM(F45:F50) -> 221 | H51: =SUM(H45:H50) -> 1 | I51: =SUM(I45:I50) -> 1
A52: Unit Mix | C52: =C51/$F$51 -> 0.29411765 | D52: =D51/$F$51 -> 0.57918552 | E52: =E51/$F$51 -> 0.12669683 | F52: =F51/$F$51 -> 1
C56: =SUM(C45:C50) -> 65 | D56: =SUM(D45:D50) -> 128 | E56: =SUM(E45:E50) -> 28 | F56: =SUM(F45:F50) -> 221
C57: =C56/$F$56 -> 0.29411765 | D57: =D56/$F$56 -> 0.57918552 | E57: =E56/$F$56 -> 0.12669683
A59: Utility | C59: Who Pays | D59: Energy Source | E59: 0-BR | F59: 1-BR | G59: 2-BR | H59: 3BR | I59: 4BR | K59: Source of Utility Allowance & Effective Date
A60: Heating | C60: Tenant | D60: Electric | F60: 14 | G60: 16 | H60: 19 | K60: HHA 1/1/2025
A61: Cooking | C61: Tenant | D61: Electric | F61: 8 | G61: 12 | H61: 16 | K61: HHA 1/1/2025
A62: Other Electric | C62: Tenant | F62: 31 | G62: 44 | H62: 56 | K62: HHA 1/1/2025
A63: Air Conditioning | C63: Tenant | D63: Electric | F63: 28 | G63: 39 | H63: 50 | K63: HHA 1/1/2025
A64: Water Heater | C64: Tenant | D64: Electric | F64: 18 | G64: 24 | H64: 29 | K64: HHA 1/1/2025
A65: Water | C65: Tenant | F65: 37 | G65: 48 | H65: 60 | K65: HHA 1/1/2025
A66: Sewer | C66: Tenant | F66: 55 | G66: 71 | H66: 86 | K66: HHA 1/1/2025
A67: Trash | C67: Landlord
A68: Flat Fee | C68: Tenant | F68: 15 | G68: 15 | H68: 15 | K68: HHA 1/1/2025
A69: Other | C69: Tenant
B70: Total Paid by Tenant | E70: $ - | F70: =SUM(F60:F69) -> 206 | G70: =SUM(G60:G69) -> 269 | H70: =SUM(H60:H69) -> 331 | I70: $ -

Sheet Operating Expense
A1: OPERATING BUDGET / EXPENSES | M1: ='Summary Sources-Uses'!L2 -> 0
A2: ='Summary Sources-Uses'!A2 -> Project Name | M2: ='Summary Sources-Uses'!L1 -> 45960
N3: NOTE: Expenses updated. Do not match TDHCA application
E5: Independence Heights | J5: Average of Comparable Properties
A6: EXPENSES | E6: ='Rent Schedule'!D26 -> 221 | F6: units | J6: =E6 -> 221 | K6: =F6 -> units
A8: OPERATING EXPENSES | E8: 2024 Baseline | F8: per unit | J8: bad debt | K8: =(H46+J46+L46+N46+P46+R46)/6 -> 193.56109
J9: other admin | K9: =(H47+J47+L47+N47+P47+R47)/6 -> 286.38269
A10: TOTAL ADMINISTRATIVE EXPENSES | E10: =E81 -> 115000 | F10: =E10/$E$6 -> 520.36199 | J10: =K10*E$6 -> 106067.57 | K10: =(H48+J48+L48+N48+P48+R48)/6 -> 479.94378
A11: TOTAL MARKETING EXPENSES | E11: =E86 -> 30000 | F11: =E11/$E$6 -> 135.74661 | J11: =K11*E$6 -> 11241.195 | K11: =(H49+J49+L49+N49+P49+R49)/6 -> 50.865135
A12: TOTAL PAYROLL EXPENSES | E12: =E96 -> 450000 | F12: =E12/$E$6 -> 2036.1991 | J12: =K12*E$6 -> 392076.17 | K12: =(H50+J50+L50+N50+P50+R50)/6 -> 1774.1003
A13: TOTAL MAINTENANCE EXPENSES | E13: =E106 -> 230000 | F13: =E13/$E$6 -> 1040.724 | J13: =K13*E$6 -> 186021.55 | K13: =(H51+J51+L51+N51+P51+R51)/6 -> 841.72646
A14: TOTAL CONTRACT EXPENSES | E14: =E114 -> 210000 | F14: =E14/$E$6 -> 950.22624 | G14: * adjusted for security expense | J14: =K14*E$6 -> 231155.53 | K14: =(H52+J52+L52+N52+P52+R52)/6 -> 1045.9526
A15: TOTAL UTILITY EXPENSES | E15: =E121 -> 215000 | F15: =E15/$E$6 -> 972.85068 | G15: *adjusted for tenant paid utilities | J15: =K15*E$6 -> 152399.68 | K15: =(H53+J53+L53+N53+P53+R53)/6 -> 689.59129
A16: TOTAL MANAGEMENT AND PROFESSIONAL EXPENSES | E16: =E130 -> 361635.91 | F16: =E16/$E$6 -> 1636.3616 | J16: =K16*E$6 -> 279410.3 | K16: =(H54+J54+L54+N54+P54+R54)/6 -> 1264.3
A17: TOTAL TAXES AND INSURANCE | E17: =E136 -> 290000 | F17: =E17/$E$6 -> 1312.2172 | G17: *adjusted for flood insurance where applicable | J17: =K17*E$6 -> 255743.64 | K17: =(H55+J55+L55+N55+P55+R55)/6 -> 1157.211
A18: Annual HHA Issuer Fee | E18: =E138 -> 13562.258 | F18: =E18/$E$6 -> 61.367685
B20: TOTAL EXPENSE | E20: =SUM(E10:E18) -> 1915198.2 | F20: =E20/$E$6 -> 8666.0551 | J20: =SUM(J10:J17) -> 1614115.6 | K20: =SUM(K10:K17) -> 7303.6907
B21: Replacement Reserves | E21: =300*E6 -> 66300 | F21: =E21/$E$6 -> 300
B22: TOTAL EXPENSE + Repl Res. | E22: =E20+E21 -> 1981498.2 | F22: =E22/E6 -> 8966.0551
A24: Property Taxes | E24: 0 | F24: 0 | G24: per unit
A25: W/o Property Taxes or replacement reserves | E25: =E20-E24 -> 1915198.2 | F25: =E25/E6 -> 8666.0551 | G25: per unit
A28: Net Revenue | E28: =NetIncomeY1 -> 3493931.9 | H28: =ExpTotalY1/12 -> 159599.85
A29: Expense Ratio | E29: =E20/E28 -> 0.54814983 | F29: <- may not exceed 65% per TDHCA
A30: NOI/Net Revenue | E30: =(E28-E20)/E28 -> 0.45185017
A33: Columbia Portfolio Family Comps:
A34: Columbia Parc, Renaissance Square, Pendana, Brookside
A37: OPERATING BUDGET / EXPENSES
A38: COMPARABLES in COLUMBIA PORTFOLIO
G40: 2023 Full Year | I40: 2023 Full Year | K40: 2023 Full Year | M40: 2023 Full Year | O40: 2023 Full Year | Q40: 2023 Full Year
G41: Pendana at W Lakes | I41: Columbia Sylvan Hills | K41: Columbia Brookside II-III | M41: Park Commons HFS, HFOP | O41: Renaissance Square | Q41: Columbia Parc @ Bayou Distr
A42: EXPENSES | G42: 200 | H42: units | I42: 191 | J42: units | K42: =132+138 -> 270 | L42: units | M42: =151+179 -> 330 | N42: units | O42: 140 | P42: units | Q42: 466 | R42: units
A44: OPERATING EXPENSES
B46: Bad Debt Expense | G46: 34857.09 | H46: =G46/G$42 -> 174.28545 | I46: 63638.06 | J46: =I46/I$42 -> 333.18356 | K46: =30841.05+17031.96 -> 47873.01 | L46: =K46/K$42 -> 177.30744 | M46: =8259.72+41005.28 -> 49265 | N46: =M46/M$42 -> 149.28788 | O46: 11517.23 | P46: =O46/O$42 -> 82.265929 | Q46: 114186.9 | R46: =Q46/Q$42 -> 245.03627
B47: All Other Admin Expense | G47: =96635.82-G46 -> 61778.73 | H47: =G47/G$42 -> 308.89365 | I47: =115284.62-I46 -> 51646.56 | J47: =I47/I$42 -> 270.40084 | K47: =79427.6-K46+47508.61 -> 79063.2 | L47: =K47/K$42 -> 292.82667 | M47: =50385.39-M46+70545.57 -> 71665.96 | N47: =M47/M$42 -> 217.16958 | O47: =46971.31-O46 -> 35454.08 | P47: =O47/O$42 -> 253.24343 | Q47: =289291.98-Q46 -> 175105.08 | R47: =Q47/Q$42 -> 375.76197
A48: TOTAL ADMINISTRATIVE EXPENSES | G48: =G46+G47 -> 96635.82 | H48: =G48/G$42 -> 483.1791 | I48: =I46+I47 -> 115284.62 | J48: =I48/I$42 -> 603.5844 | K48: =K46+K47 -> 126936.21 | L48: =K48/K$42 -> 470.13411 | M48: =M46+M47 -> 120930.96 | N48: =M48/M$42 -> 366.45745 | O48: =O46+O47 -> 46971.31 | P48: =O48/O$42 -> 335.50936 | Q48: =Q46+Q47 -> 289291.98 | R48: =Q48/Q$42 -> 620.79824
A49: TOTAL MARKETING EXPENSES | G49: 12789.35 | H49: =G49/G$42 -> 63.94675 | I49: 13318.35 | J49: =I49/I$42 -> 69.729581 | K49: =4079.38+3906.67 -> 7986.05 | L49: =K49/K$42 -> 29.577963 | M49: =6019.15+4933.34 -> 10952.49 | N49: =M49/M$42 -> 33.189364 | O49: 7102.73 | P49: =O49/O$42 -> 50.733786 | Q49: 27034.23 | R49: =Q49/Q$42 -> 58.013369
A50: TOTAL PAYROLL EXPENSES | G50: 489458.47 | H50: =G50/G$42 -> 2447.2923 | I50: 347193.89 | J50: =I50/I$42 -> 1817.7691 | K50: =183054.93+193045.46 -> 376100.39 | L50: =K50/K$42 -> 1392.9644 | M50: =285524.83+242835.05 -> 528359.88 | N50: =M50/M$42 -> 1601.0905 | O50: =154648.03+51953 -> 206601.03 | P50: =O50/O$42 -> 1475.7216 | Q50: 889949.97 | R50: =Q50/Q$42 -> 1909.7639
A51: TOTAL MAINTENANCE EXPENSES | G51: 195288.79 | H51: =G51/G$42 -> 976.44395 | I51: 170057.73 | J51: =I51/I$42 -> 890.35461 | K51: =96619.62+106586.17 -> 203205.79 | L51: =K51/K$42 -> 752.61404 | M51: =101093.71+104212.04 -> 205305.75 | N51: =M51/M$42 -> 622.13864 | O51: 121738.49 | P51: =O51/O$42 -> 869.56064 | Q51: 437689.05 | R51: =Q51/Q$42 -> 939.24689
A52: TOTAL CONTRACT EXPENSES | G52: 141629.56 | H52: =G52/G$42 -> 708.1478 | I52: 275639.61 | J52: =I52/I$42 -> 1443.1393 | K52: =158796.88+99845.3 -> 258642.18 | L52: =K52/K$42 -> 957.934 | M52: =197838.2+95082.78 -> 292920.98 | N52: =M52/M$42 -> 887.63933 | O52: =136716.73-51953 -> 84763.73 | P52: =O52/O$42 -> 605.45521 | Q52: 779804.48 | R52: =Q52/Q$42 -> 1673.4002
A53: TOTAL UTILITY EXPENSES | C53: net of water/sewer collection | G53: =210123.7-82110.95 -> 128012.75 | H53: =G53/G$42 -> 640.06375 | I53: =310145.67-168748.08 -> 141397.59 | J53: =I53/I$42 -> 740.30152 | K53: =143111.58-73181.92-77139.45+131485.39 -> 124275.6 | L53: =K53/K$42 -> 460.28 | M53: =362149.68+138733.19 -> 500882.87 | N53: =M53/M$42 -> 1517.8269 | O53: =66341.65-22450 -> 43891.65 | P53: =O53/O$42 -> 313.51179 | Q53: =216952.74 -> 216952.74 | R53: =Q53/Q$42 -> 465.56382
A54: TOTAL MANAGEMENT & PROFESSIONAL EXPENSES | G54: 260457.44 | H54: =G54/G$42 -> 1302.2872 | I54: 329211.4 | J54: =I54/I$42 -> 1723.6199 | K54: =163155.76+154941.25 -> 318097.01 | L54: =K54/K$42 -> 1178.1371 | M54: =230656.49+182780.11 -> 413436.6 | N54: =M54/M$42 -> 1252.8382 | O54: 148368.25 | P54: =O54/O$42 -> 1059.7732 | Q54: 498221.33 | R54: =Q54/Q$42 -> 1069.1445
A55: TOTAL TAX & INSURANCE EXPENSES* | G55: 387800.7 | H55: =G55/G$42 -> 1939.0035 | I55: 131393.04 | J55: =I55/I$42 -> 687.92168 | K55: =141805.78+43470+91891 -> 277166.78 | L55: =K55/K$42 -> 1026.5436 | M55: =-67824.02+80121.72-60443.94+72479.94 -> 24333.7 | N55: =M55/M$42 -> 73.738485 | O55: 204093.08 | P55: =O55/O$42 -> 1457.8077 | Q55: 819345.04 | R55: =Q55/Q$42 -> 1758.2512
A56: * includes anticipated tax abatement for RAD/PBV
B57: TOTAL EXPENSES: | G57: =SUM(G48:G55) -> 1712072.9 | H57: =G57/G$42 -> 8560.3644 | I57: =SUM(I48:I55) -> 1523496.2 | J57: =I57/I$42 -> 7976.4201 | K57: =SUM(K48:K55) -> 1692410 | L57: =K57/K$42 -> 6268.1852 | M57: =SUM(M48:M55) -> 2097123.2 | N57: =M57/M$42 -> 6354.9189 | O57: =SUM(O48:O55) -> 863530.27 | P57: =O57/O$42 -> 6168.0734 | Q57: =SUM(Q48:Q55) -> 3958288.8 | R57: =Q57/Q$42 -> 8494.182
A59: TOTAL OPERATING EXPENSES
G60: includes full property tax; regional mgr charges | I60: no property tax payment; social services costs ($95K/yr); high w&s cost; high security cost | K60: combined two phases in single office; high contract labor; short-staffed | M60: low taxation; water & sewer paid by property; operates as combined site; insurance seems incorrect | O60: Full taxation; contract leasing & maint added into payroll; some shared cost with Ren II | Q60: water/sewer indiv billed; very high contract expenses; lower turn costs; PILOT taxes; very high insurance
A68: OPERATING EXPENSES | E68: Annual
A70: ADMINISTRATIVE EXPENSES
A71: Office Supplies / Postage | E71: 15000
A72: Equipment Rental | E72: 5000
A73: Travel | E73: 5000
A74: Uniforms | E74: 5000
A75: Employee Education/Training | E75: 40000
A76: Cable/Internet Expense | E76: 15000
A77: Telephones | E77: 8000
A78: Computer Equipment | E78: 10000
A79: Reports / Screening | E79: 2000
A80: Social Entertainment | E80: 10000
A81: TOTAL ADMINISTRATIVE EXPENSES | E81: =SUM(E71:E80) -> 115000
A83: MARKETING EXPENSES
A84: Apartment Guide/Blue Book | E84: 25000
A85: Promotional/Other Marketing | E85: 5000
A86: TOTAL MARKETING EXPENSES | E86: =SUM(E84:E85) -> 30000
A88: PAYROLL EXPENSES
A89: Manager | E89: 90000
A90: Leasing Consultant | E90: 50000
A91: Assistant Manager | E91: 70000
A92: Resident Services | E92: 50000
A93: Maintenance | E93: 50000
A94: Grounds/Porter | E94: 50000
A95: Benefits/Taxes | E95: =SUM(E89:E94)*0.25 -> 90000
A96: TOTAL PAYROLL EXPENSES | E96: =SUM(E89:E95) -> 450000
A98: INTERIOR SUPPLIES & REPAIRS
A99: Cleaning/Painting | E99: 60000
A100: Fire Inspection/Repairs | E100: 20000
A101: Dryer Vent Cleaning | E101: 10000
A102: EXTERIOR SUPPLIES & REPAIRS
A103: Grounds Supplies | E103: 60000
A104: Landscape Supplies | E104: 30000
A105: Maintenance Equipment/Supplies | E105: 50000
A106: TOTAL MAINTENANCE EXPENSES | E106: =SUM(E99:E105) -> 230000
A108: CONTRACT EXPENSES
A109: Landscaping | E109: 30000
A110: Pest Control | E110: 20000
A111: Sanitation | E111: 20000
A112: Elevator | E112: 20000
A113: Security Services | E113: 120000
A114: TOTAL CONTRACT EXPENSES | E114: =SUM(E109:E113) -> 210000
A116: UTILITY EXPENSES
A117: Water / Sewer | E117: 80000
A118: Vacant Electricity | E118: 15000
A119: Common Electricity | E119: 80000
A120: Trash Collection | E120: 40000
A121: TOTAL UTILITY EXPENSES | E121: =SUM(E117:E120) -> 215000
A123: MANAGEMENT & PROFESSIONAL EXPENSES
A124: Management Fee | E124: ='20yr Proforma'!F19*0.06 -> 209635.91
A125: Computer Software/Network | E125: 60000
A126: Accounting Fees | E126: 10000
A127: Legal Fees | E127: 10000
A128: Resident Services | E128: 42000 | F128: update based on Apt Life quote
...

Sheet 20yr Proforma
A1: SUMMARY PROFORMA | D1: ='Summary Sources-Uses'!L1 -> 45960
A2: Development Name: | F2: ='Summary Sources-Uses'!A2 -> Project Name | K2: ='Summary Sources-Uses'!L1 -> 45960
C4: Year | F4: 1 | G4: 2 | H4: 3 | I4: 4 | J4: 5 | K4: 6 | L4: 7 | M4: 8 | N4: 9 | O4: 10 | P4: 11 | Q4: 12 | R4: 13 | S4: 14 | T4: 15
A5: Units: | C5: =TotalUnitCount -> 221 | F5: Annual Income Growth Rate: | H5: =RevInfl -> 0.02 | I5: Vacancy Loss | J5: 0.07 | K5: Annual Operating Expense/unit | M5: ='Operating Expense'!F20 -> 8666.0551 | N5: * on sqr. foot basis | O5: LP Investor Asset Mgmt Fee: | Q5: 8500 | R5: fee increases 3% per annum
A6: Total Rentable SF: | C6: ='Rent Schedule'!E26*'Rent Schedule'!D26 -> 185625 | F6: Annual Expense Growth Rate: | H6: 0.03 | K6: Annual Replacement Reserve/unit | M6: =ReplReserve -> 300 | O6: Other Asset Mgmt. Fee: | Q6: 7500 | R6: fee increases 3% per annum
A7: Stabilized Year 1 = | C7: 2028 | M7: =M5+M6 -> 8966.0551 | O7: SLP Asset Mgt fee | Q7: 7500 | R7: fee increases 3% per annum
E9: 2025 | F9: =$C$4&" "&F4 -> Year 1 | G9: =$C$4&" "&G4 -> Year 2 | H9: =$C$4&" "&H4 -> Year 3 | I9: =$C$4&" "&I4 -> Year 4 | J9: =$C$4&" "&J4 -> Year 5 | K9: =$C$4&" "&K4 -> Year 6 | L9: =$C$4&" "&L4 -> Year 7 | M9: =$C$4&" "&M4 -> Year 8 | ... T9: =$C$4&" "&T4 -> Year 15 | U9: Year 16 | V9: Year 17 | W9: Year 18 | X9: Year 19 | Y9: Year 20
E10: baseline | F10: 2028 | G10: =F10+1 -> 2029 | H10: =G10+1 -> 2030 | I10: =H10+1 -> 2031 | J10: =I10+1 -> 2032 | K10: =J10+1 -> 2033 | L10: =K10+1 -> 2034 | M10: =L10+1 -> 2035 | N10: =M10+1 -> 2036 | ... Y10: =X10+1 -> 2047
E11: * note that rents/expenses are trended from current levels | F11: 1 | G11: 2 | H11: 3 | I11: 4 | J11: 5 | K11: 6 | L11: 7 | M11: 8 | N11: 9 | O11: 10 | P11: 11 | Q11: 12 | R11: 13 | S11: 14 | T11: 15 | U11: 16 | V11: 17 | W11: 18 | X11: 19 | Y11: 20
A12: Total Potential Rent Income | E12: =GrossRentIncomeY1 -> 3724992 | F12: =E12 -> 3724992 | G12: =F12*(1+$H5) -> 3799491.8 | H12: =G12*(1+$H5) -> 3875481.7 | I12: =H12*(1+$H5) -> 3952991.3 | J12: =I12*(1+$H5) -> 4032051.1 | K12: =J12*(1+$H5) -> 4112692.2 | L12: =K12*(1+$H5) -> 4194946 | M12: =L12*(1+$H5) -> 4278844.9 | N12: =M12*(1+$H5) -> 4364421.8 | ... Y12: =X12*(1+$H5) -> 5426610
A13: ADD: | B13: Commercial + Other Income | E13: =AddRevY1+'Rent Schedule'!K36 -> 31924 | F13: =E13 -> 31924 | G13: =F13*(1+$H5) -> 32562.48 | H13: =G13*(1+$H5) -> 33213.73 | I13: =H13*(1+$H5) -> 33878.004 | J13: =I13*(1+$H5) -> 34555.564 | K13: =J13*(1+$H5) -> 35246.676 | L13: =K13*(1+$H5) -> 35951.609 | M13: =L13*(1+$H5) -> 36670.641 | N13: =M13*(1+$H5) -> 37404.054 | ... Y13: =X13*(1+$H5) -> 46507.24
A15: Gross Potential Income | E15: =E12+E13 -> 3756916 | F15: =F12+F13 -> 3756916 | G15: =G12+G13 -> 3832054.3 | H15: =H12+H13 -> 3908695.4 | I15: =I12+I13 -> 3986869.3 | J15: =J12+J13 -> 4066606.7 | K15: =K12+K13 -> 4147938.8 | L15: =L12+L13 -> 4230897.6 | ... Y15: =Y12+Y13 -> 5473117.2
A17: LESS: | B17: Vacancy Allowance/Bad Debts/Concessions | E17: =(E12+E13)*$J5 -> 262984.12 | F17: =(F12+F13)*$J5 -> 262984.12 | G17: =(G12+G13)*$J5 -> 268243.8 | H17: =(H12+H13)*$J5 -> 273608.68 | I17: =(I12+I13)*$J5 -> 279080.85 | J17: =(J12+J13)*$J5 -> 284662.47 | K17: =(K12+K13)*$J5 -> 290355.72 | L17: =(L12+L13)*$J5 -> 296162.83 | ... Y17: =(Y12+Y13)*$J5 -> 383118.2
A19: Stabilized Income | E19: =+E15-E17 -> 3493931.9 | F19: =+F15-F17 -> 3493931.9 | G19: =+G15-G17 -> 3563810.5 | H19: =+H15-H17 -> 3635086.7 | I19: =+I15-I17 -> 3707788.5 | J19: =+J15-J17 -> 3781944.2 | K19: =+K15-K17 -> 3857583.1 | L19: =+L15-L17 -> 3934734.8 | ... Y19: =+Y15-Y17 -> 5089999
A21: LESS: | B21: Operating Expenses | E21: =ExpTotalY1 -> 1915198.2 | F21: =E21 -> 1915198.2 | G21: =$F21*(1+$H6)^(G11-1) -> 1972654.1 | H21: =$F21*(1+$H6)^(H11-1) -> 2031833.7 | I21: =$F21*(1+$H6)^(I11-1) -> 2092788.8 | J21: =$F21*(1+$H6)^(J11-1) -> 2155572.4 | K21: =$F21*(1+$H6)^(K11-1) -> 2220239.6 | L21: =$F21*(1+$H6)^(L11-1) -> 2286846.8 | M21: =$F21*(1+$H6)^(M11-1) -> 2355452.2 | N21: =$F21*(1+$H6)^(N11-1) -> 2426115.7 | ... Y21: =$F21*(1+$H6)^(Y11-1) -> 3358311.6
A22: ADD: Property Tax Reduction | D22: =IF(Inputs!M25>0,"yes","no") -> yes | E22: =-'Operating Expense'!E24 -> 0 | F22: =$E$22*(1+$H$6)^F11*INDEX(Inputs!$M$25:$M$39,MATCH('20yr Proforma'!F11,Inputs!$L$25:$L$39,0)) -> 0 | G22: =$E$22*(1+$H$6)^G11*INDEX(Inputs!$M$25:$M$39,MATCH('20yr Proforma'!G11,Inputs!$L$25:$L$39,0)) -> 0 | H22: =$E$22*(1+$H$6)^H11*INDEX(Inputs!$M$25:$M$39,MATCH('20yr Proforma'!H11,Inputs!$L$25:$L$39,0)) -> 0 | I22: =$E$22*(1+$H$6)^I11*INDEX(Inputs!$M$25:$M$39,MATCH('20yr Proforma'!I11,Inputs!$L$25:$L$39,0)) -> 0 | J22: =$E$22*(1+$H$6)^J11*INDEX(Inputs!$M$25:$M$39,MATCH('20yr Proforma'!J11,Inputs!$L$25:$L$39,0)) -> 0 | K22: =$E$22*(1+$H$6)^K11*INDEX(Inputs!$M$25:$M$39,MATCH('20yr Proforma'!K11,Inputs!$L$25:$L$39,0)) -> 0 | L22: =$E$22*(1+$H$6)^L11*INDEX(Inputs!$M$25:$M$39,MATCH('20yr Proforma'!L11,Inputs!$L$25:$L$39,0)) -> 0 | M22: =$E$22*(1+$H$6)^M11*INDEX(Inputs!$M$25:$M$39,MATCH('20yr Proforma'!M11,Inputs!$L$25:$L$39,0)) -> 0 | ... T22: =$E$22*(1+$H$6)^T11*INDEX(Inputs!$M$25:$M$39,MATCH('20yr Proforma'!T11,Inputs!$L$25:$L$39,0)) -> 0 | U22: =$E$22*(1+$H$6)^U11*INDEX(Inputs!$M$25:$M$45,MATCH('20yr Proforma'!U11,Inputs!$L$25:$L$45,0)) -> 0 | V22: =$E$22*(1+$H$6)^V11*INDEX(Inputs!$M$25:$M$45,MATCH('20yr Proforma'!V11,Inputs!$L$25:$L$45,0)) -> 0 | W22: =$E$22*(1+$H$6)^W11*INDEX(Inputs!$M$25:$M$45,MATCH('20yr Proforma'!W11,Inputs!$L$25:$L$45,0)) -> 0 | X22: =$E$22*(1+$H$6)^X11*INDEX(Inputs!$M$25:$M$45,MATCH('20yr Proforma'!X11,Inputs!$L$25:$L$45,0)) -> 0 | Y22: =$E$22*(1+$H$6)^Y11*INDEX(Inputs!$M$25:$M$45,MATCH('20yr Proforma'!Y11,Inputs!$L$25:$L$45,0)) -> 0
A23: LESS: | B23: Replacement Reserves | E23: =F23 -> 66300 | F23: =M6*$C5 -> 66300 | G23: =F23*(1+$H6) -> 68289 | H23: =G23*(1+$H6) -> 70337.67 | I23: =H23*(1+$H6) -> 72447.8 | J23: =I23*(1+$H6) -> 74621.234 | K23: =J23*(1+$H6) -> 76859.871 | L23: =K23*(1+$H6) -> 79165.667 | M23: =L23*(1+$H6) -> 81540.637 | N23: =M23*(1+$H6) -> 83986.856 | ... Y23: =X23*(1+$H6) -> 116257.45
A24: Net Operating Income | E24: =E19-E21-E23-E22 -> 1512433.7 | F24: =F19-F21-F23-F22 -> 1512433.7 | G24: =G19-G21-G23-G22 -> 1522867.4 | H24: =H19-H21-H23-H22 -> 1532915.3 | I24: =I19-I21-I23-I22 -> 1542551.9 | J24: =J19-J21-J23-J22 -> 1551750.6 | K24: =K19-K21-K23-K22 -> 1560483.7 | L24: =L19-L21-L23-L22 -> 1568722.3 | ... Y24: =Y19-Y21-Y23-Y22 -> 1615430
B26: SCHEDULED DEBT SERVICE:
A27: LESS: | B27: Debt Service 1st | E27: ='[5]Summary Sources-Uses'!$D$8 -> 1st Mortgage | F27: ='Summary Sources-Uses'!L49 -> 0 | G27: =F27 -> 0 | H27: =G27 -> 0 | I27: =H27 -> 0 | J27: =I27 -> 0 | K27: =J27 -> 0 | L27: =K27 -> 0 | M27: =L27 -> 0 | N27: =M27 -> 0 | ... Y27: =X27 -> 0
B28: Debt Service 2nd | E28: ='Summary Sources-Uses'!E53 -> GAP Funding (TBD) | F28: ='Summary Sources-Uses'!L53 -> 0 | G28: =F28 -> 0 | H28: =G28 -> 0 | I28: =H28 -> 0 | J28: =I28 -> 0 | K28: =J28 -> 0 | L28: =K28 -> 0 | M28: =L28 -> 0 | N28: =M28 -> 0 | ... Y28: =X28 -> 0
B29: Debt Service 3rd | E29: ='Summary Sources-Uses'!E55 -> 0 | F29: ='Summary Sources-Uses'!L55 -> 0 | G29: =F29 -> 0 | H29: =G29 -> 0 | I29: =H29 -> 0 | J29: =I29 -> 0 | K29: =J29 -> 0 | L29: =K29 -> 0 | M29: =L29 -> 0 | N29: =M29 -> 0 | ... Y29: =X29 -> 0
B30: Debt Service 4th | F30: ='Summary Sources-Uses'!L57 -> 0 | G30: =F30 -> 0 | H30: =G30 -> 0 | I30: =H30 -> 0 | J30: =I30 -> 0 | K30: =J30 -> 0 | L30: =K30 -> 0 | M30: =L30 -> 0 | N30: =M30 -> 0 | ... Y30: =X30 -> 0
B31: Debt Service 5th
B32: Debt Service 6th
C33: deferred fee note | E33: 12 | F33: =MIN(F63,SUM(F39:F41)) -> -18830917 | G33: =MIN(G63,SUM(G39:G41)) -> 0 | H33: =MIN(H63,SUM(H39:H41)) -> 0 | I33: =MIN(I63,SUM(I39:I41)) -> 0 | J33: =MIN(J63,SUM(J39:J41)) -> 0 | K33: =MIN(K63,SUM(K39:K41)) -> 0 | L33: =MIN(L63,SUM(L39:L41)) -> 0 | M33: =MIN(M63,SUM(M39:M41)) -> 0 | ... T33: =MIN(T63,SUM(T39:T41)) -> 0
A35: Operating Cash Flow Waterfall:
B36: Net Operating Income: | F36: =F24 -> 1512433.7 | G36: =G24 -> 1522867.4 | H36: =H24 -> 1532915.3 | I36: =I24 -> 1542551.9 | J36: =J24 -> 1551750.6 | K36: =K24 -> 1560483.7 | L36: =L24 -> 1568722.3 | M36: =M24 -> 1576436.7 | ... Y36: =Y24 -> 1615430
B37: (less) First mortgage debt | E37: scheduled P&I | F37: =-F27 -> 0 | G37: =-G27 -> 0 | H37: =-H27 -> 0 | I37: =-I27 -> 0 | J37: =-J27 -> 0 | K37: =-K27 -> 0 | L37: =-L27 -> 0 | M37: =-M27 -> 0 | ... Y37: =-Y27 -> 0
B38: (less) Second mortgage debt_HHA | F38: =-'Summary Sources-Uses'!L51 -> 0 | G38: =F38 -> 0 | H38: =G38 -> 0 | I38: =H38 -> 0 | J38: =I38 -> 0 | K38: =J38 -> 0 | L38: =K38 -> 0 | M38: =L38 -> 0 | N38: =M38 -> 0 | ... Y38: =X38 -> 0
B39: Cash Flow after 1st Mortg Debt: | F39: =SUM(F36:F38) -> 286024.76 | G39: =SUM(G36:G38) -> 296458.45 | H39: =SUM(H36:H38) -> 306506.37 | I39: =SUM(I36:I38) -> 316142.96 | J39: =SUM(J36:J38) -> 325341.63 | K39: =SUM(K36:K38) -> 334074.71 | L39: =SUM(L36:L38) -> 342313.39 | M39: =SUM(M36:M38) -> 350027.71 | ... Y39: =SUM(Y36:Y38) -> 389021.01
B41: (less) Investor LP Asset Mgmt fee | E41: from cash flow | F41: =-$Q$5 -> -8500 | G41: =F41*(1+$H6) -> -8755 | H41: =G41*(1+$H6) -> -9017.65 | I41: =H41*(1+$H6) -> -9288.1795 | J41: =I41*(1+$H6) -> -9566.8249 | K41: =J41*(1+$H6) -> -9853.8296 | L41: =K41*(1+$H6) -> -10149.445 | M41: =L41*(1+$H6) -> -10453.928 | N41: =M41*(1+$H6) -> -10767.546 | ... Y41: =X41*(1+$H6) -> -14904.801
B42: (less) payment to DDF | E42: from cash flow -to P&I | F42: =-F33 -> 18830917 | G42: =-MIN(SUM(G39:G41),G63) -> 0 | H42: =-MIN(SUM(H39:H41),H63) -> 0 | I42: =-MIN(SUM(I39:I41),I63) -> 0 | J42: =-MIN(SUM(J39:J41),J63) -> 0 | K42: =-MIN(SUM(K39:K41),K63) -> 0 | L42: =-MIN(SUM(L39:L41),L63) -> 0 | M42: =-MIN(SUM(M39:M41),M63) -> 0 | N42: =-MIN(SUM(N39:N41),N63) -> 0 | ... T42: =-MIN(SUM(T39:T41),T63) -> 0 | U42: 0 | V42: 0 | W42: 0 | X42: 0 | Y42: 0
B43: (less) SLP Asset Mgmt fee-Columbia SLP | E43: from cash flow | F43: =IF(SUM(F39:F42)>F83, -F83,0) -> -8500 | G43: =IF(SUM(G39:G42)>G83, -G83,0) -> -8755 | H43: =IF(SUM(H39:H42)>H83, -H83,0) -> -9017.65 | I43: =IF(SUM(I39:I42)>I83, -I83,0) -> -9288.1795 | J43: =IF(SUM(J39:J42)>J83, -J83,0) -> -9566.8249 | K43: =IF(SUM(K39:K42)>K83, -K83,0) -> -9853.8296 | L43: =IF(SUM(L39:L42)>L83, -L83,0) -> -10149.445 | M43: =IF(SUM(M39:M42)>M83, -M83,0) -> -10453.928 | ... Y43: =IF(SUM(Y39:Y42)>Y83, -Y83,0) -> -14904.801
B44: (less) Cash Flow to Investor LP | D44: 0.1 | E44: from cash flow | F44: =IF(SUM(F39:F43)>0,-SUM(F39:F43)*$D$44,0) -> -1909994.1 | G44: =IF(SUM(G39:G43)>0,-SUM(G39:G43)*$D$44,0) -> -27894.845 | H44: =IF(SUM(H39:H43)>0,-SUM(H39:H43)*$D$44,0) -> -28847.107 | I44: =IF(SUM(I39:I43)>0,-SUM(I39:I43)*$D$44,0) -> -29756.66 | J44: =IF(SUM(J39:J43)>0,-SUM(J39:J43)*$D$44,0) -> -30620.798 | K44: =IF(SUM(K39:K43)>0,-SUM(K39:K43)*$D$44,0) -> -31436.705 | L44: =IF(SUM(L39:L43)>0,-SUM(L39:L43)*$D$44,0) -> -32201.45 | M44: =IF(SUM(M39:M43)>0,-SUM(M39:M43)*$D$44,0) -> -32911.985 | ... Y44: =IF(SUM(Y39:Y43)>0,-SUM(Y39:Y43)*$D$44,0) -> -35921.141
B45: (less) Cashflow to GP/SLP | D45: 0.0001 | E45: from cash flow | F45: =IF(SUM(F39:F43)>0,-SUM(F39:F43)*$D$45,0) -> -1909.9941 | G45: =IF(SUM(G39:G43)>0,-SUM(G39:G43)*$D$45,0) -> -27.894845 | H45: =IF(SUM(H39:H43)>0,-SUM(H39:H43)*$D$45,0) -> -28.847107 | I45: =IF(SUM(I39:I43)>0,-SUM(I39:I43)*$D$45,0) -> -29.75666 | J45: =IF(SUM(J39:J43)>0,-SUM(J39:J43)*$D$45,0) -> -30.620798 | K45: =IF(SUM(K39:K43)>0,-SUM(K39:K43)*$D$45,0) -> -31.436705 | L45: =IF(SUM(L39:L43)>0,-SUM(L39:L43)*$D$45,0) -> -32.20145 | M45: =IF(SUM(M39:M43)>0,-SUM(M39:M43)*$D$45,0) -> -32.911985 | ... Y45: =IF(SUM(Y39:Y43)>0,-SUM(Y39:Y43)*$D$45,0) -> -35.921141
B46: (less) Incentive Mgmt Fee to GP/SLP | D46: 0.9 | E46: from cash flow | F46: =-F89 -> -201135.91 | G46: =-G89 -> -205073.63 | H46: =-H89 -> -209087.55 | I46: =-I89 -> -213179.13 | J46: =-J89 -> -217349.83 | K46: =-K89 -> -221601.16 | L46: =-L89 -> -225934.64 | M46: =-M89 -> -230351.84 | ... Y46: =-Y89 -> -290495.14
B47: (less) 2nd mortgage debt-HHA | D47: 0.5 | E47: from cash flow -to P&I | F47: =IF(SUM(F39:F46)>0,-SUM(F39:F46)*$D$47,0) -> -8493450.7 | G47: =IF(SUM(G39:G46)>0,-SUM(G39:G46)*$D$47,0) -> -22976.04 | H47: =IF(SUM(H39:H46)>0,-SUM(H39:H46)*$D$47,0) -> -25253.781 | I47: =IF(SUM(I39:I46)>0,-SUM(I39:I46)*$D$47,0) -> -27300.529 | J47: =IF(SUM(J39:J46)>0,-SUM(J39:J46)*$D$47,0) -> -29103.368 | K47: =IF(SUM(K39:K46)>0,-SUM(K39:K46)*$D$47,0) -> -30648.875 | L47: =IF(SUM(L39:L46)>0,-SUM(L39:L46)*$D$47,0) -> -31923.103 | M47: =IF(SUM(M39:M46)>0,-SUM(M39:M46)*$D$47,0) -> -32911.558 | ... Y47: =IF(SUM(Y39:Y46)>0,-SUM(Y39:Y46)*$D$47,0) -> -16379.604
B48: (less) | D48: 0.5 | E48: from cash flow -to P&I | F48: =-IF(SUM(F$39:F47)>0,MIN(F29,SUM(F$39:F47)*$D$48),0) -> 0 | G48: =-IF(SUM(G$39:G47)>0,MIN(G29,SUM(G$39:G47)*$D$48),0) -> 0 | H48: =-IF(SUM(H$39:H47)>0,MIN(H29,SUM(H$39:H47)*$D$48),0) -> 0 | I48: =-IF(SUM(I$39:I47)>0,MIN(I29,SUM(I$39:I47)*$D$48),0) -> 0 | J48: =-IF(SUM(J$39:J47)>0,MIN(J29,SUM(J$39:J47)*$D$48),0) -> 0 | K48: =-IF(SUM(K$39:K47)>0,MIN(K29,SUM(K$39:K47)*$D$48),0) -> 0 | L48: =-IF(SUM(L$39:L47)>0,MIN(L29,SUM(L$39:L47)*$D$48),0) -> 0 | M48: =-IF(SUM(M$39:M47)>0,MIN(M29,SUM(M$39:M47)*$D$48),0) -> 0 | ... Y48: =-IF(SUM(Y$39:Y47)>0,MIN(Y29,SUM(Y$39:Y47)*$D$48),0) -> 0
B49: Net Cash Flow | F49: =SUM(F39:F48) -> 8493450.7 | G49: =SUM(G39:G48) -> 22976.04 | H49: =SUM(H39:H48) -> 25253.781 | I49: =SUM(I39:I48) -> 27300.529 | J49: =SUM(J39:J48) -> 29103.368 | K49: =SUM(K39:K48) -> 30648.875 | L49: =SUM(L39:L48) -> 31923.103 | M49: =SUM(M39:M48) -> 32911.558 | ... Y49: =SUM(Y39:Y48) -> 16379.604
B51: DSC - 1st & 2nd Mrgt | F51: =F36/-SUM(F37:F38) -> 1.2332214 | G51: =G36/-SUM(G37:G38) -> 1.2417289 | H51: =H36/-SUM(H37:H38) -> 1.2499218 | I51: =I36/-SUM(I37:I38) -> 1.2577794 | J51: =J36/-SUM(J37:J38) -> 1.2652799 | K51: =K36/-SUM(K37:K38) -> 1.2724007 | L51: =L36/-SUM(L37:L38) -> 1.2791185 | M51: =M36/-SUM(M37:M38) -> 1.2854086 | ... Y51: =Y36/-SUM(Y37:Y38) -> 1.3172033
B52: DSC 1st & subordinate mortgages+DDF | F52: =-F36/SUM(F37+F38+F42+F47+F48) -> -0.16599981 | G52: =-G36/SUM(G37+G38+G42+G47+G48) -> 1.2188936 | H52: =-H36/SUM(H37+H38+H42+H47+H48) -> 1.2247032 | I52: =-I36/SUM(I37+I38+I42+I47+I48) -> 1.2303902 | J52: =-J36/SUM(J37+J38+J42+J47+J48) -> 1.2359501 | K52: =-K36/SUM(K37+K38+K42+K47+K48) -> 1.2413778 | L52: =-L36/SUM(L37+L38+L42+L47+L48) -> 1.246668 | M52: =-M36/SUM(M37+M38+M42+M47+M48) -> 1.2518153 | ... Y52: =-Y36/SUM(Y37+Y38+Y42+Y47+Y48) -> 1.299843
C54: =SUM(F54:T54) -> 0 | F54: =IF(F63>0,1,0) -> 0 | G54: =IF(G63>0,1,0) -> 0 | H54: =IF(H63>0,1,0) -> 0 | I54: =IF(I63>0,1,0) -> 0 | J54: =IF(J63>0,1,0) -> 0 | K54: =IF(K63>0,1,0) -> 0 | L54: =IF(L63>0,1,0) -> 0 | M54: =IF(M63>0,1,0) -> 0 | ... T54: =IF(T63>0,1,0) -> 0
B55: Total Cash Flow to AHA (prior to residual CF split): | F55: =-(#REF!+#REF!+#REF!+F42*0.25)+(F49*0) -> #REF! | G55: =-(#REF!+#REF!+#REF!+G42*0.25)+(G49*0) -> #REF! | H55: =-(#REF!+#REF!+#REF!+H42*0.25)+(H49*0) -> #REF! | I55: =-(#REF!+#REF!+#REF!+I42*0.25)+(I49*0) -> #REF! | J55: =-(#REF!+#REF!+#REF!+J42*0.25)+(J49*0) -> #REF! | K55: =-(#REF!+#REF!+#REF!+K42*0.25)+(K49*0) -> #REF! | L55: =-(#REF!+#REF!+#REF!+L42*0.25)+(L49*0) -> #REF! | M55: =-(#REF!+#REF!+#REF!+M42*0.25)+(M49*0) -> #REF! | ... Y55: =-(#REF!+#REF!+#REF!+Y42*0.25)+(Y49*0) -> #REF!
B56: (incl A/M fee; share of DDF; cash flow loan) | F56: =SUM(F55:Y55) -> #REF!
B58: Total Cash Flow to ELHC (prior to residual CF split): | F58: =-(F47+#REF!+F42*0.375)+(F52*0) -> #REF! | G58: =-(G47+#REF!+G42*0.375)+(G52*0) -> #REF! | H58: =-(H47+#REF!+H42*0.375)+(H52*0) -> #REF! | I58: =-(I47+#REF!+I42*0.375)+(I52*0) -> #REF! | J58: =-(J47+#REF!+J42*0.375)+(J52*0) -> #REF! | K58: =-(K47+#REF!+K42*0.375)+(K52*0) -> #REF! | L58: =-(L47+#REF!+L42*0.375)+(L52*0) -> #REF! | M58: =-(M47+#REF!+M42*0.375)+(M52*0) -> #REF! | ... Y58: =-(Y47+#REF!+Y42*0.375)+(Y52*0) -> #REF!
B59: (incl A/M fee; share of DDF; cash flow loan) | F59: =SUM(F58:Y58) -> #REF!
B61: Total Cash Flow to AHA (prior to residual CF split): | F61: =-(#REF!+F42*0.375)+(F55*0) -> #REF! | G61: =-(#REF!+G42*0.375)+(G55*0) -> #REF! | H61: =-(#REF!+H42*0.375)+(H55*0) -> #REF! | I61: =-(#REF!+I42*0.375)+(I55*0) -> #REF! | J61: =-(#REF!+J42*0.375)+(J55*0) -> #REF! | K61: =-(#REF!+K42*0.375)+(K55*0) -> #REF! | L61: =-(#REF!+L42*0.375)+(L55*0) -> #REF! | M61: =-(#REF!+M42*0.375)+(M55*0) -> #REF! | ... Y61: =-(#REF!+Y42*0.375)+(Y55*0) -> #REF!
B62: (incl A/M fee; share of DDF; cash flow loan) | F62: =SUM(F61:Y61) -> #REF!
C63: DDF Balance & Payments | F63: ='Summary Sources-Uses'!E17 -> -18830917 | G63: =SUM(F63:F65) -> 0 | H63: =SUM(G63:G65) -> 0 | I63: =SUM(H63:H65) -> 0 | J63: =SUM(I63:I65) -> 0 | K63: =SUM(J63:J65) -> 0 | L63: =SUM(K63:K65) -> 0 | M63: =SUM(L63:L65) -> 0 | N63: =SUM(M63:M65) -> 0 | ... T63: =SUM(S63:S65) -> 0
C64: Interest | D64: 0 | F64: =F63*$D$64 -> 0 | G64: =G63*$D$64 -> 0 | H64: =H63*$D$64 -> 0 | I64: =I63*$D$64 -> 0 | J64: =J63*$D$64 -> 0 | K64: =K63*$D$64 -> 0 | L64: =L63*$D$64 -> 0 | M64: =M63*$D$64 -> 0 | ... T64: =T63*$D$64 -> 0
C65: Payments | E65: =SUM(F65:T65) -> 18830917 | F65: =-F33 -> 18830917 | G65: =-G33 -> 0 | H65: =-H33 -> 0 | I65: =-I33 -> 0 | J65: =-J33 -> 0 | K65: =-K33 -> 0 | L65: =-L33 -> 0 | M65: =-M33 -> 0 | ... T65: =-T33 -> 0
B68: HHA Share of Paid Devel Fee: | E68: =('Summary Sources-Uses'!K20-'Summary Sources-Uses'!E17)*0.4 -> 10332367
B69: HHA Share of Deferred Devel Fee: | E69: =SUM(F69:T69) -> -7532366.7 | F69: =-F65*0.4 -> -7532366.7 | G69: =-G65*0.4 -> 0 | H69: =-H65*0.4 -> 0 | I69: =-I65*0.3 -> 0 | J69: =-J65*0.3 -> 0 | K69: =-K65*0.3 -> 0 | L69: =-L65*0.3 -> 0 | M69: =-M65*0.3 -> 0 | N69: =-N65*0.3 -> 0 | O69: =-O65*0.3 -> 0 | P69: =-P65*0.3 -> 0 | ... T69: =-T65*0.3 -> 0
B70: HHA 2nd Mortgage Loan Pmts (HHA Soft): | E70: =SUM(F70:T70) -> 8924308.9 | F70: =-F47 -> 8493450.7 | G70: =-G47 -> 22976.04 | H70: =-H47 -> 25253.781 | I70: =-I47 -> 27300.529 | J70: =-J47 -> 29103.368 | K70: =-K47 -> 30648.875 | L70: =-L47 -> 31923.103 | M70: =-M47 -> 32911.558 | ... Y70: =-Y47 -> 16379.604 | Z70: =Y70*(1+$H6) -> 16870.993 | AA70: =Z70*(1+$H6) -> 17377.122 | AB70: =AA70*(1+$H6) -> 17898.436 | AC70: =AB70*(1+$H6) -> 18435.389 | AD70: =AC70*(1+$H6) -> 18988.451 | AE70: =AD70*(1+$H6) -> 19558.104 | AF70: =AE70*(1+$H6) -> 20144.847 | AG70: =AF70*(1+$H6) -> 20749.193 | ... AI70: =AH70*(1+$H6) -> 22012.819
B71: HHA 3rd Mortgage Loan Pmts (FEMA): | E71: =SUM(F71:T71) -> 0 | F71: =-F48 -> 0 | G71: =-G48 -> 0 | H71: =-H48 -> 0 | I71: =-I48 -> 0 | J71: =-J48 -> 0 | K71: =-K48 -> 0 | L71: =-L48 -> 0 | M71: =-M48 -> 0 | ... Y71: =-Y48 -> 0 | Z71: =Y71*(1+$H7) -> 0 | AA71: =Z71*(1+$H7) -> 0 | AB71: =AA71*(1+$H7) -> 0 | AC71: =AB71*(1+$H7) -> 0 | AD71: =AC71*(1+$H7) -> 0 | AE71: =AD71*(1+$H7) -> 0 | AF71: =AE71*(1+$H7) -> 0 | AG71: =AF71*(1+$H7) -> 0 | ... AI71: =AH71*(1+$H7) -> 0
B72: HHA Share of Net Cash Flow: | E72: =SUM(F72:T72) -> 3569723.6 | F72: =0.4*F49 -> 3397380.3 | G72: =0.4*G49 -> 9190.4162 | H72: =0.4*H49 -> 10101.512 | I72: =0.4*I49 -> 10920.211 | J72: =0.4*J49 -> 11641.347 | K72: =0.4*K49 -> 12259.55 | L72: =0.4*L49 -> 12769.241 | M72: =0.4*M49 -> 13164.623 | ... Y72: =0.4*Y49 -> 6551.8418 | Z72: =Y72*(1+$H8) -> 6551.8418 | AA72: =Z72*(1+$H8) -> 6551.8418 | AB72: =AA72*(1+$H8) -> 6551.8418 | AC72: =AB72*(1+$H8) -> 6551.8418 | AD72: =AC72*(1+$H8) -> 6551.8418 | AE72: =AD72*(1+$H8) -> 6551.8418 | AF72: =AE72*(1+$H8) -> 6551.8418 | AG72: =AF72*(1+$H8) -> 6551.8418 | ... AI72: =AH72*(1+$H8) -> 6551.8418
B73: 15 Year Total: | E73: =SUM(E68:E72) -> 15294032
C75: HHA Loan Info-2nd and 3rd Combined
D76: Principal | F76: ='Summary Sources-Uses'!K53+'Summary Sources-Uses'!K55 -> 0 | G76: =F79 -> 15746549 | H76: =G79 -> 15963573 | I76: =H79 -> 16178319 | J76: =I79 -> 16391019 | K76: =J79 -> 16601916 | L76: =K79 -> 16811267 | M76: =L79 -> 17019344 | N76: =M79 -> 17226432 | ... Y76: =X79 -> 19537192
D77: Interest | F77: ='Summary Sources-Uses'!$L$53+'Summary Sources-Uses'!$H$55 -> 0 | G77: ='Summary Sources-Uses'!$L$53+'Summary Sources-Uses'!$H$55 -> 0 | H77: ='Summary Sources-Uses'!$L$53+'Summary Sources-Uses'!$H$55 -> 0 | I77: ='Summary Sources-Uses'!$L$53+'Summary Sources-Uses'!$H$55 -> 0 | J77: ='Summary Sources-Uses'!$L$53+'Summary Sources-Uses'!$H$55 -> 0 | K77: ='Summary Sources-Uses'!$L$53+'Summary Sources-Uses'!$H$55 -> 0 | L77: ='Summary Sources-Uses'!$L$53+'Summary Sources-Uses'!$H$55 -> 0 | M77: ='Summary Sources-Uses'!$L$53+'Summary Sources-Uses'!$H$55 -> 0 | ... Y77: ='Summary Sources-Uses'!$L$53+'Summary Sources-Uses'!$H$55 -> 0
D78: Payments | F78: =F47+F48 -> -8493450.7 | G78: =G47+G48 -> -22976.04 | H78: =H47+H48 -> -25253.781 | I78: =I47+I48 -> -27300.529 | J78: =J47+J48 -> -29103.368 | K78: =K47+K48 -> -30648.875 | L78: =L47+L48 -> -31923.103 | M78: =M47+M48 -> -32911.558 | ... Y78: =Y47+Y48 -> -16379.604
D79: Cummulative Balance | F79: =SUM(F76:F78) -> 15746549 | G79: =SUM(G76:G78) -> 15963573 | H79: =SUM(H76:H78) -> 16178319 | I79: =SUM(I76:I78) -> 16391019 | J79: =SUM(J76:J78) -> 16601916 | K79: =SUM(K76:K78) -> 16811267 | L79: =SUM(L76:L78) -> 17019344 | M79: =SUM(M76:M78) -> 17226432 | ... Y79: =SUM(Y76:Y78) -> 19760812
B81: Asset Mgmt Fees projection;
C82: LP Investor Asset Mgmt Fee: | E82: 8500 | F82: =E82 -> 8500 | G82: =F82*(1+$H6) -> 8755 | H82: =G82*(1+$H6) -> 9017.65 | I82: =H82*(1+$H6) -> 9288.1795 | J82: =I82*(1+$H6) -> 9566.8249 | K82: =J82*(1+$H6) -> 9853.8296 | L82: =K82*(1+$H6) -> 10149.445 | M82: =L82*(1+$H6) -> 10453.928 | N82: =M82*(1+$H6) -> 10767.546 | ... T82: =S82*(1+$H6) -> 12857.013
C83: SLP Asset Mgt fee | E83: 8500 | F83: =E83 -> 8500 | G83: =F83*(1+$H$6) -> 8755 | H83: =G83*(1+$H$6) -> 9017.65 | I83: =H83*(1+$H$6) -> 9288.1795 | J83: =I83*(1+$H$6) -> 9566.8249 | K83: =J83*(1+$H$6) -> 9853.8296 | L83: =K83*(1+$H$6) -> 10149.445 | M83: =L83*(1+$H$6) -> 10453.928 | N83: =M83*(1+$H$6) -> 10767.546 | ... Y83: =X83*(1+$H$6) -> 14904.801
B86: Incentive Management Fee
B87: Potential Incentive Mgmt Fee | D87: 0.9 | F87: =IF(SUM(F39:F45)>0,-SUM(F39:F45)*$D$87,0)*-1 -> 15469234 | G87: =IF(SUM(G39:G45)>0,-SUM(G39:G45)*$D$87,0)*-1 -> 225923.14 | H87: =IF(SUM(H39:H45)>0,-SUM(H39:H45)*$D$87,0)*-1 -> 233635.6 | I87: =IF(SUM(I39:I45)>0,-SUM(I39:I45)*$D$87,0)*-1 -> 241002.17 | J87: =IF(SUM(J39:J45)>0,-SUM(J39:J45)*$D$87,0)*-1 -> 248000.91 | K87: =IF(SUM(K39:K45)>0,-SUM(K39:K45)*$D$87,0)*-1 -> 254609.02 | L87: =IF(SUM(L39:L45)>0,-SUM(L39:L45)*$D$87,0)*-1 -> 260802.76 | M87: =IF(SUM(M39:M45)>0,-SUM(M39:M45)*$D$87,0)*-1 -> 266557.46 | ... Y87: =IF(SUM(Y39:Y45)>0,-SUM(Y39:Y45)*$D$87,0)*-1 -> 290928.91
B88: Max Incentive Mgmt Fee* | F88: =F19*0.12 -> 419271.83 | G88: =G19*0.12 -> 427657.26 | H88: =H19*0.12 -> 436210.41 | I88: =I19*0.12 -> 444934.62 | J88: =J19*0.12 -> 453833.31 | K88: =K19*0.12 -> 462909.97 | L88: =L19*0.12 -> 472168.17 | M88: =M19*0.12 -> 481611.54 | ... Y88: =Y19*0.12 -> 610799.88
B89: Incentive Mgmt Fee Paid | F89: =IF(F95>0,F87,F87+F95) -> 201135.91 | G89: =IF(G95>0,G87,G87+G95) -> 205073.63 | H89: =IF(H95>0,H87,H87+H95) -> 209087.55 | I89: =IF(I95>0,I87,I87+I95) -> 213179.13 | J89: =IF(J95>0,J87,J87+J95) -> 217349.83 | K89: =IF(K95>0,K87,K87+K95) -> 221601.16 | L89: =IF(L95>0,L87,L87+L95) -> 225934.64 | M89: =IF(M95>0,M87,M87+M95) -> 230351.84 | ... Y89: =IF(Y95>0,Y87,Y87+Y95) -> 290495.14
C90: ***Sum of Incentive Management Fee, management fees (assumed 6%) and asset management fee may not exceed 12% of effective gross income.
D91: Mgmt Fee (6% of Stabilized Income): | F91: =F19*0.06 -> 209635.91 | G91: =G19*0.06 -> 213828.63 | H91: =H19*0.06 -> 218105.2 | I91: =I19*0.06 -> 222467.31 | J91: =J19*0.06 -> 226916.65 | K91: =K19*0.06 -> 231454.99 | L91: =L19*0.06 -> 236084.09 | M91: =M19*0.06 -> 240805.77 | ... Y91: =Y19*0.06 -> 305399.94
D92: Asset Mgmt Fee | F92: =F83 -> 8500 | G92: =G83 -> 8755 | H92: =H83 -> 9017.65 | I92: =I83 -> 9288.1795 | J92: =J83 -> 9566.8249 | K92: =K83 -> 9853.8296 | L92: =L83 -> 10149.445 | M92: =M83 -> 10453.928 | ... Y92: =Y83 -> 14904.801
D93: Incentive Mgmt Fee | F93: =F87 -> 15469234 | G93: =G87 -> 225923.14 | H93: =H87 -> 233635.6 | I93: =I87 -> 241002.17 | J93: =J87 -> 248000.91 | K93: =K87 -> 254609.02 | L93: =L87 -> 260802.76 | M93: =M87 -> 266557.46 | ... Y93: =Y87 -> 290928.91
D94: Total: | F94: =SUM(F91:F93) -> 15687370 | G94: =SUM(G91:G93) -> 448506.77 | H94: =SUM(H91:H93) -> 460758.46 | I94: =SUM(I91:I93) -> 472757.65 | J94: =SUM(J91:J93) -> 484484.39 | K94: =SUM(K91:K93) -> 495917.83 | L94: =SUM(L91:L93) -> 507036.29 | M94: =SUM(M91:M93) -> 517817.16 | ... Y94: =SUM(Y91:Y93) -> 611233.65
D95: Reduction in IMF (Max-Total): | F95: =F88-F94 -> -15268098 | G95: =G88-G94 -> -20849.51 | H95: =H88-H94 -> -24548.05 | I95: =I88-I94 -> -27823.039 | J95: =J88-J94 -> -30651.079 | K95: =K88-K94 -> -33007.86 | L95: =L88-L94 -> -34868.12 | M95: =M88-M94 -> -36205.621 | ... Y95: =Y88-Y94 -> -433.77413

Sheet Credit Delivery & Pay-Ins
B1: ='Summary Sources-Uses'!A2 -> Project Name | G1: ='Summary Sources-Uses'!L2 -> 0 | Q1: ='Summary Sources-Uses'!L1 -> 45960
C3: Credit Allocation (annual): | F3: ='Summary Sources-Uses'!E37 -> 946178.12 | J3: Annual Credits (allocation): | N3: =F3 -> 946178.12 | P3: Closing | Q3: ='Flow of Funds'!H3 -> 46447
C4: Total Units: | F4: =TotalUnitCount -> 221 | J4: Syndicator Percentage: | N4: 0.9999 | P4: Construction | Q4: 22
C5: LIHTC Units: | F5: 212 | J5: Equity Pricing (per credit): | N5: ='Summary Sources-Uses'!D38 -> 0.87 | P5: Completion | Q5: =EDATE(Q3,Q4) -> 47119
C6: Cred Factor | F6: =(F3/F5)/12*N4 -> 371.88817
K7: Total Equity Pay-In | N7: ='Summary Sources-Uses'!E39 -> 8230926.5 | P7: Absorbtion Rate | Q7: 25
B8: LEASE-UP / CREDIT DELIVERY SCHEDULE
C9: LIHTC Units Only
B10: Year | C10: Units Leased | D10: Cumulative | E10: Tax Credit | F10: Monthly | I10: EQUITY PAY-IN SCHEDULE
B11: =YEAR(Q5) -> 2029 | C11: In Month | D11: Leased | E11: Factor | F11: Credits | K11: Month | L11: Milestone | M11: % complete | N11: Federal | O11: State | P11: total | Q11: % of total
B12: January | C12: 0 | D12: =C12 -> 0 | E12: 0 | F12: =D12*E12 -> 0 | H12: =DATE(I12,1,1) -> 45658 | I12: 2025 | J12: January
B13: February | C13: 0 | D13: =D12+C13 -> 0 | E13: 0 | F13: =D13*E13 -> 0 | H13: =EDATE(H12,1) -> 45689 | J13: February
B14: March | C14: 0 | D14: =D13+C14 -> 0 | E14: 0 | F14: =D14*E14 -> 0 | H14: =EDATE(H13,1) -> 45717 | J14: March
B15: April | C15: 0 | D15: =D14+C15 -> 0 | E15: 0 | F15: =D15*E15 -> 0 | H15: =EDATE(H14,1) -> 45748 | J15: April
B16: May | C16: 0 | D16: =D15+C16 -> 0 | E16: 0 | F16: =D16*E16 -> 0 | H16: =EDATE(H15,1) -> 45778 | J16: May
B17: June | C17: 0 | D17: =D16+C17 -> 0 | E17: 0 | F17: =D17*E17 -> 0 | H17: =EDATE(H16,1) -> 45809 | J17: June
B18: July | C18: 0 | D18: =D17+C18 -> 0 | E18: 0 | F18: =D18*E18 -> 0 | H18: =EDATE(H17,1) -> 45839 | J18: July
B19: August | C19: 0 | D19: =D18+C19 -> 0 | E19: 0 | F19: =D19*E19 -> 0 | H19: =EDATE(H18,1) -> 45870 | J19: August
B20: September | C20: 6 | D20: =D19+C20 -> 6 | E20: 0 | F20: =D20*E20 -> 0 | H20: =EDATE(H19,1) -> 45901 | J20: September
B21: October | C21: 10 | D21: =D20+C21 -> 16 | E21: 0 | F21: =D21*E21 -> 0 | H21: =EDATE(H20,1) -> 45931 | J21: October
B22: November | C22: 15 | D22: =D21+C22 -> 31 | E22: 0 | F22: =D22*E22 -> 0 | H22: =EDATE(H21,1) -> 45962 | J22: November | K22: 0 | L22: CLOSING | N22: =$N$7*Q22 -> 823092.65 | Q22: 0.1 | S22: 0.1
B23: December | C23: 20 | D23: =D22+C23 -> 51 | E23: 0 | F23: =D23*E23 -> 0 | H23: =EDATE(H22,1) -> 45992 | J23: December | K23: =K22+1 -> 1
B24: Totals: | C24: =SUM(C12:C23) -> 51 | D24: =D23 -> 51 | F24: =SUM(F20:F23) -> 0 | H24: =EDATE(H23,1) -> 46023 | I24: =I12+1 -> 2026 | J24: January | K24: =K23+1 -> 2
H25: =EDATE(H24,1) -> 46054 | J25: February | K25: =K24+1 -> 3
H26: =EDATE(H25,1) -> 46082 | J26: March | K26: =K25+1 -> 4
B27: Year | C27: Units Leased | D27: Cumulative | E27: Tax Credit | F27: Monthly | H27: =EDATE(H26,1) -> 46113 | J27: April | K27: =K26+1 -> 5
B28: =B11+1 -> 2030 | C28: In Month | D28: Leased | E28: Factor | F28: Credits | H28: =EDATE(H27,1) -> 46143 | J28: May | K28: =K27+1 -> 6
B29: January | C29: 20 | D29: =D23+C29 -> 71 | E29: =F$6 -> 371.88817 | F29: =D29*E29 -> 26404.06 | H29: =EDATE(H28,1) -> 46174 | J29: June | K29: =K28+1 -> 7
B30: February | C30: 25 | D30: =D29+C30 -> 96 | E30: =F$6 -> 371.88817 | F30: =D30*E30 -> 35701.264 | H30: =EDATE(H29,1) -> 46204 | J30: July | K30: =K29+1 -> 8
B31: March | C31: =MIN($F$5-SUM($C$24,$C$29:C30),$Q$7) -> 25 | D31: =D30+C31 -> 121 | E31: =F$6 -> 371.88817 | F31: =D31*E31 -> 44998.469 | H31: =EDATE(H30,1) -> 46235 | J31: August | K31: =K30+1 -> 9
B32: April | C32: =MIN($F$5-SUM($C$24,$C$29:C31),$Q$7) -> 25 | D32: =D31+C32 -> 146 | E32: =F$6 -> 371.88817 | F32: =D32*E32 -> 54295.673 | H32: =EDATE(H31,1) -> 46266 | J32: September | K32: =K31+1 -> 10
B33: May | C33: =MIN($F$5-SUM($C$24,$C$29:C32),$Q$7) -> 25 | D33: =D32+C33 -> 171 | E33: =F$6 -> 371.88817 | F33: =D33*E33 -> 63592.877 | H33: =EDATE(H32,1) -> 46296 | J33: October | K33: =K32+1 -> 11 | L33: 50% complete | N33: =N10*Q33 -> 0 | Q33: 0
B34: June | C34: 25 | D34: =D33+C34 -> 196 | E34: =F$6 -> 371.88817 | F34: =D34*E34 -> 72890.081 | H34: =EDATE(H33,1) -> 46327 | J34: November | K34: =K33+1 -> 12
B35: July | C35: 25 | D35: =D34+C35 -> 221 | E35: =F$6 -> 371.88817 | F35: =D35*E35 -> 82187.286 | H35: =EDATE(H34,1) -> 46357 | J35: December | K35: =K34+1 -> 13
B36: August | C36: 0 | D36: =D35+C36 -> 221 | E36: =F$6 -> 371.88817 | F36: =D36*E36 -> 82187.286 | H36: =EDATE(H35,1) -> 46388 | I36: =I24+1 -> 2027 | J36: January | K36: =K35+1 -> 14
B37: September | C37: 0 | D37: =D36+C37 -> 221 | E37: =F$6 -> 371.88817 | F37: =D37*E37 -> 82187.286 | H37: =EDATE(H36,1) -> 46419 | J37: February | K37: =K36+1 -> 15
B38: October | C38: 0 | D38: =D37+C38 -> 221 | E38: =F$6 -> 371.88817 | F38: =D38*E38 -> 82187.286 | H38: =EDATE(H37,1) -> 46447 | J38: March | K38: =K37+1 -> 16
B39: November | C39: 0 | D39: =D38+C39 -> 221 | E39: =F$6 -> 371.88817 | F39: =D39*E39 -> 82187.286 | H39: =EDATE(H38,1) -> 46478 | J39: April | K39: =K38+1 -> 17
B40: December | C40: 0 | D40: =D39+C40 -> 221 | E40: =F$6 -> 371.88817 | F40: =D40*E40 -> 82187.286 | H40: =EDATE(H39,1) -> 46508 | J40: May | K40: =K39+1 -> 18
B41: Totals: | C41: =SUM(C29:C40) -> 170 | D41: =D40 -> 221 | F41: =SUM(F29:F40) -> 791006.14 | H41: =EDATE(H40,1) -> 46539 | J41: June | K41: =K40+1 -> 19
H42: =EDATE(H41,1) -> 46569 | J42: July | K42: =K41+1 -> 20
H43: =EDATE(H42,1) -> 46600 | J43: August | K43: =K42+1 -> 21
B44: Year | C44: Units Leased | D44: Cumulative | E44: Tax Credit | F44: Monthly | H44: =EDATE(H43,1) -> 46631 | J44: September | K44: =K43+1 -> 22 | L44: 100% completion-CO | N44: =$N$7*Q44 -> 4446346.5 | Q44: 0.5402 | S44: 22 month construction period per GC contract
B45: =B28+1 -> 2031 | C45: In Month | D45: Leased | E45: Factor | F45: Credits | H45: =EDATE(H44,1) -> 46661 | J45: October | K45: =K44+1 -> 23
B46: January | C46: 0 | D46: =D40+C46 -> 221 | E46: =F$6 -> 371.88817 | F46: =D46*E46 -> 82187.286 | H46: =EDATE(H45,1) -> 46692 | J46: November | K46: =K45+1 -> 24
B47: February | C47: 0 | D47: =D46+C47 -> 221 | E47: =F$6 -> 371.88817 | F47: =D47*E47 -> 82187.286 | H47: =EDATE(H46,1) -> 46722 | J47: December | K47: =K46+1 -> 25
B48: March | C48: 0 | D48: =D47+C48 -> 221 | E48: =F$6 -> 371.88817 | F48: =D48*E48 -> 82187.286 | H48: =EDATE(H47,1) -> 46753 | I48: =I36+1 -> 2028 | J48: January | K48: =K47+1 -> 26
B49: April | C49: 0 | D49: =D48+C49 -> 221 | E49: =F$6 -> 371.88817 | F49: =D49*E49 -> 82187.286 | H49: =EDATE(H48,1) -> 46784 | J49: February | K49: =K48+1 -> 27
B50: May | C50: 0 | D50: =D49+C50 -> 221 | E50: =F$6 -> 371.88817 | F50: =D50*E50 -> 82187.286 | H50: =EDATE(H49,1) -> 46813 | J50: March | K50: =K49+1 -> 28
B51: June | C51: 0 | D51: =D50+C51 -> 221 | E51: =F$6 -> 371.88817 | F51: =D51*E51 -> 82187.286 | H51: =EDATE(H50,1) -> 46844 | J51: April | K51: =K50+1 -> 29
B52: July | C52: 0 | D52: =D51+C52 -> 221 | E52: =F$6 -> 371.88817 | F52: =D52*E52 -> 82187.286 | H52: =EDATE(H51,1) -> 46874 | J52: May | K52: =K51+1 -> 30
B53: August | C53: 0 | D53: =D52+C53 -> 221 | E53: =F$6 -> 371.88817 | F53: =D53*E53 -> 82187.286 | H53: =EDATE(H52,1) -> 46905 | J53: June | K53: =K52+1 -> 31
B54: September | C54: 0 | D54: =D53+C54 -> 221 | E54: =F$6 -> 371.88817 | F54: =D54*E54 -> 82187.286 | H54: =EDATE(H53,1) -> 46935 | J54: July | K54: =K53+1 -> 32
B55: October | C55: 0 | D55: =D54+C55 -> 221 | E55: =F$6 -> 371.88817 | F55: =D55*E55 -> 82187.286 | H55: =EDATE(H54,1) -> 46966 | J55: August | K55: =K54+1 -> 33
B56: November | C56: 0 | D56: =D55+C56 -> 221 | E56: =F$6 -> 371.88817 | F56: =D56*E56 -> 82187.286 | H56: =EDATE(H55,1) -> 46997 | J56: September | K56: =K55+1 -> 34
B57: December | C57: 0 | D57: =D56+C57 -> 221 | E57: =F$6 -> 371.88817 | F57: =D57*E57 -> 82187.286 | H57: =EDATE(H56,1) -> 47027 | J57: October | K57: =K56+1 -> 35
B58: Totals: | C58: 0 | D58: =D57 -> 221 | F58: =SUM(F46:F57) -> 986247.43 | H58: =EDATE(H57,1) -> 47058 | J58: November | K58: =K57+1 -> 36 | L58: Stabilization | N58: =N7*$Q$58 -> 2961487.4 | Q58: =1-SUM(Q14:Q57) -> 0.3598
H59: =EDATE(H58,1) -> 47088 | J59: December | K59: =K58+1 -> 37
K60: TOTAL: | N60: =SUM(N15:N59) -> 8230926.5 | Q60: =SUM(Q15:Q59) -> 1
N61: =N60-'Summary Sources-Uses'!E15 -> 0

Sheet Flow of Funds
B1: FLOW OF FUNDS | F1: ='Summary Sources-Uses'!L1 -> 45960 | G1: ='Summary Sources-Uses'!L2 -> 0
B2: ='Summary Sources-Uses'!A2 -> Project Name | H2: 0 | I2: 1 | J2: =I2+1 -> 2 | K2: =J2+1 -> 3 | L2: =K2+1 -> 4 | M2: =L2+1 -> 5 | N2: =M2+1 -> 6 | O2: =N2+1 -> 7 | P2: =O2+1 -> 8 | Q2: =P2+1 -> 9 | ... AU2: =AT2+1 -> 39
B3: ='Summary Sources-Uses'!L3 -> 0 Family Units | H3: 46447 | I3: =EDATE(H3,1) -> 46478 | J3: =EDATE(I3,1) -> 46508 | K3: =EDATE(J3,1) -> 46539 | L3: =EDATE(K3,1) -> 46569 | M3: =EDATE(L3,1) -> 46600 | N3: =EDATE(M3,1) -> 46631 | O3: =EDATE(N3,1) -> 46661 | P3: =EDATE(O3,1) -> 46692 | ... AU3: =EDATE(AT3,1) -> 47635
F4: Total | G4: Expended | H4: Closing | I4: Construction Start----------> | S4: 50% Completion | AD4: 100% Complete | AE4: Constr Completion | AR4: Stabilization | AV4: Total Drawn | AW4: Variance
A5: SOURCES | AD5: 2nd Installment | AE5: 2nd Installment | AR5: 3rd Installment
B6: Tax Exempt Bonds | F6: ='Summary Sources-Uses'!K67 -> 13562258 | H6: =F6 -> 13562258
B7: ='Summary Sources-Uses'!E68 -> Construction Loan (Taxable) | F7: ='Summary Sources-Uses'!K68 -> -1762837.9 | H7: =H103-H10-H11 -> 2364554.4 | I7: =I103-I13 -> -103667.16 | J7: 0 | K7: 0 | L7: 0 | M7: =M103-M10-M13 -> 300377.8 | N7: =N103-N13 -> 834406.43 | O7: =O103-O10-O13 -> 668617.86 | P7: 0 | Q7: =Q103-Q10-Q13 -> 737699.64 | R7: =R103-R9-R13 -> 991730.41 | T7: =T103-T10-T13 -> 209939.81 | U7: =U103-U13 -> 975839.6 | V7: =V103-V10-V13 -> 691434.96 | X7: =X103-X10-X13 -> -16927970 | Y7: =Y103-Y13 -> 859741.88 | Z7: =Z103-Z13 -> 854470.46 | AA7: =AA103-AA13 -> 922170.05 | AB7: =AB103-AB13 -> 812241.98 | AC7: =AC103-AC13 -> 766709.31 | AD7: =AD103-AD13 -> 3278864.6 | AE7: =(AE103-AE11-AE13) -> 10379008 | AO7: =AO103-AO11-AO13 -> 47388.938 | AP7: =AP103-AP11-AP13 -> 47649.577 | AQ7: =AQ103-AQ11-AQ13 -> 47911.65 | AR7: =-SUM(H7:AQ7) -> -8759120.7 | AV7: =SUM(H7:AU7) -> 0 | AW7: =F7-AV7 -> -1762837.9
B8: First Mortgage (Freddie TEL) | D8: =F8/F$16 -> 0.46441928 | F8: ='Summary Sources-Uses'!E8 -> 0 | AR8: =F8 -> 0 | AV8: =SUM(H8:AU8) -> 0 | AW8: =F8-AV8 -> 0
B9: 2nd Mortgage (HHA Funds) | D9: =F9/F$16 -> 0.09136117 | F9: ='Summary Sources-Uses'!E9 -> 0 | AV9: =SUM(H9:AU9) -> 0 | AW9: =F9-AV9 -> 0
B10: 3rd Mortgage (FEMA) | D10: =F10/F$16 -> 0.73088936 | F10: ='Summary Sources-Uses'!E10 -> 0 | H10: =1714964.59 -> 1714964.6 | J10: =J103-J13 -> 578426.56 | K10: =K103-K13 -> 875422.41 | L10: =L103-L13 -> 957754.35 | M10: =(H7+I7+H11)-(J10+K10+L10) -> 672376.55 | O10: =M7 -> 300377.8 | P10: =P103-P13 -> 967673.07 | Q10: =(N7+O7)-(O10+P10) -> 234973.43 | S10: =S103-S13 -> 967184.93 | T10: =(Q7+R7)-(S10) -> 762245.12 | V10: =T7 -> 209939.81 | W10: =W103-W13 -> 892845.72 | X10: =(F9+F10)-SUM(H10:W10) -> 17865816 | AV10: =SUM(H10:AU10) -> 27000000 | AW10: =F10-AV10 -> -3000000
B11: L.P. Capital Contribution | D11: =F11/F$16 -> 0.25066236 | F11: ='Credit Delivery & Pay-Ins'!N7 -> 8230926.5 | H11: ='Credit Delivery & Pay-Ins'!N22 -> 823092.65 | AE11: =('Credit Delivery & Pay-Ins'!N44)-(SUM(AF11:AN11)) -> 3768179.4 | AF11: =AF103-AF13 -> 105722.27 | AG11: =AG103-AG13 -> 105722.27 | AH11: =AH103-AH13 -> 105722.27 | AI11: =AI103-AI13 -> 105722.27 | AJ11: =AJ103-AJ13 -> 65722.271 | AK11: =AK103-AK13 -> 47388.938 | AL11: =AL103-AL13 -> 47388.938 | AM11: =AM103-AM13 -> 47388.938 | AN11: =AN103-AN13 -> 47388.938 | AP11: 0 | AQ11: 0 | AR11: ='Credit Delivery & Pay-Ins'!N58 -> 2961487.4 | AV11: =SUM(H11:AU11) -> 8230926.5 | AW11: =F11-AV11 -> 0
B12: GAP | D12: =F12/F$16 -> 0 | F12: ='Summary Sources-Uses'!E12 -> 0 | AV12: =SUM(H12:AU12) -> 0 | AW12: =F12-AV12 -> 0
B13: Bond Arbitrage Earnings | D13: =F13/F$16 -> 0.036139361 | F13: ='Summary Sources-Uses'!E18 -> 1186697.6 | H13: =H115 -> 0 | I13: =I115 -> 33905.646 | J13: =J115 -> 33905.646 | K13: =K115 -> 33905.646 | L13: =L115 -> 33905.646 | M13: =M115 -> 33905.646 | N13: =N115 -> 33905.646 | O13: =O115 -> 33905.646 | ... AQ13: =AQ115 -> 33905.646 | AV13: =SUM(H13:AU13) -> 1186697.6 | AW13: =F13-AV13 -> 0
B14: 45L Credits | D14: =F14/F$16 -> 0 | F14: ='Summary Sources-Uses'!E13 -> 0 | AV14: =SUM(H14:AU14) -> 0 | AW14: =F14-AV14 -> 0
B15: Deferred Developer Fee | D15: =F15/F$16 -> -0.57347153 | F15: ='Summary Sources-Uses'!E17 -> -18830917 | AV15: =SUM(H15:AU15) -> 0 | AW15: =F15-AV15 -> -18830917
C16: Total Sources: | F16: =SUM(F8:F15) -> 32836707 | G16: =SUM(G7:G15) -> 0 | H16: =SUM(H7:H15) -> 4902611.6 | I16: =SUM(I7:I15) -> -69761.515 | J16: =SUM(J7:J15) -> 612332.21 | K16: =SUM(K7:K15) -> 909328.05 | L16: =SUM(L7:L15) -> 991660 | M16: =SUM(M7:M15) -> 1006660 | N16: =SUM(N7:N15) -> 868312.08 | ... AR16: =SUM(AR7:AR15) -> 9452366.7 | AT16: =SUM(AT7:AT15) -> 0 | AU16: =SUM(AU7:AU15) -> 0 | AV16: =SUM(H16:AU16) -> 51667624 | AW16: =F16-AV16 -> -18830917
E17: % of Equity Capital | G17: =G11/$F11 -> 0 | H17: =H11/$F11 -> 0.1 | I17: =I11/$F11 -> 0 | J17: =J11/$F11 -> 0 | K17: =K11/$F11 -> 0 | L17: =L11/$F11 -> 0 | M17: =M11/$F11 -> 0 | N17: =N11/$F11 -> 0 | ... AR17: =AR11/$F11 -> 0.3598 | AT17: =AT11/$F11 -> 0 | AU17: =AU11/$F11 -> 0 | AV17: =SUM(H17:AR17) -> 1
A19: USES | F19: =H103-H11 -> 4079519 | H19: =H3 -> 46447 | I19: =I3 -> 46478 | J19: =J3 -> 46508 | K19: =K3 -> 46539 | L19: =L3 -> 46569 | M19: =M3 -> 46600 | N19: =N3 -> 46631 | O19: =O3 -> 46661 | ... AR19: =AR3 -> 47543 | AT19: =AT3 -> 47604 | AU19: =AU3 -> 47635
A20: Acquisition Costs | E20: per unit
B21: ='Development Budget'!C9 -> Land/Ground Lease Prepayment | E21: =F21/'Rent Schedule'!$D$26 -> 0 | F21: ='Development Budget'!G9 -> 0 | H21: =F21 -> 0 | AV21: =SUM(H21:AQ21) -> 0 | AW21: =F21-AV21 -> 0
E22: =F22/[6]Rent_Schedule!$E$25 -> 0
A23: Construction Costs | F23: INSERT % OF HARD COST EXPENDED PER MONTH > | I23: 0.02 | J23: 0.03 | K23: 0.045 | L23: 0.05 | M23: 0.05 | N23: 0.05 | O23: 0.05 | P23: 0.05 | Q23: 0.05 | R23: 0.05 | S23: 0.05 | T23: 0.05 | U23: 0.05 | V23: 0.045 | W23: 0.04 | X23: 0.04 | Y23: 0.04 | Z23: 0.04 | AA23: 0.04 | AB23: 0.04 | AC23: 0.04 | AD23: 0.08 | AE23: 0 | AF23: 0 | AG23: 0 | AH23: 0 | AI23: 0 | AJ23: 0 | AK23: 0 | AL23: 0 | AM23: 0 | AN23: 0 | AO23: 0 | AP23: 0 | AQ23: 0 | AR23: 0 | AT23: 0 | AU23: 0 | AV23: =SUM(G23:AQ23) -> 1
B24: ='Development Budget'!C12 -> Hard Costs | D24: =SUM(I23:AN23) -> 1 | E24: =F24/'Rent Schedule'!$D$26 -> 0 | F24: ='Development Budget'!G12 -> 0 | H24: 0 | I24: =$F$24*I23-H24 -> 0 | J24: =$F$24*J23 -> 0 | K24: =$F$24*K23 -> 0 | L24: =$F$24*L23 -> 0 | M24: =$F$24*M23-H24 -> 0 | N24: =$F$24*N23 -> 0 | O24: =$F$24*O23 -> 0 | P24: =$F$24*P23 -> 0 | Q24: =$F$24*Q23 -> 0 | R24: =$F$24*R23 -> 0 | S24: =$F$24*S23 -> 0 | T24: =$F$24*T23 -> 0 | U24: =$F$24*U23 -> 0 | ... AK24: =$F$24*AK23 -> 0 | AN24: =$F$24*AN23 -> 0 | AO24: =$F$24*AO23 -> 0 | AP24: =$F$24*AP23 -> 0 | AV24: =SUM(G24:AU24) -> 0 | AW24: =F24-AV24 -> 0
B25: ='Development Budget'!C13 -> Sitework & Related Fees | E25: =F25/'Rent Schedule'!$D$26 -> 0 | F25: ='Development Budget'!G13 -> 0 | H25: 0 | I25: =$F$25*I23-H25 -> 0 | J25: =$F$25*J23 -> 0 | K25: =$F$25*K23 -> 0 | L25: =$F$25*L23 -> 0 | M25: =$F$25*M23 -> 0 | N25: =$F$25*N23 -> 0 | O25: =$F$25*O23 -> 0 | P25: =$F$25*P23 -> 0 | Q25: =$F$25*Q23 -> 0 | ... AK25: =$F$25*AK23 -> 0 | AV25: =SUM(G25:AU25) -> 0 | AW25: =F25-AV25 -> 0
B26: ='Development Budget'!C14 -> Structured Parking | E26: =F26/'Rent Schedule'!$D$26 -> 0 | F26: ='Development Budget'!G14 -> 0 | H26: 500000 | I26: =MIN($F$26/8,$F$26-SUM($G$26:H26)) -> -500000 | J26: =MIN($F$26/8,$F$26-SUM($G$26:I26)) -> 0 | K26: =MIN($F$26/8,$F$26-SUM($G$26:J26)) -> 0 | L26: =MIN($F$26/8,$F$26-SUM($G$26:K26)) -> 0 | M26: =MIN($F$26/8,$F$26-SUM($G$26:L26)) -> 0 | N26: =MIN($F$26/8,$F$26-SUM($G$26:M26)) -> 0 | O26: =MIN($F$26/8,$F$26-SUM($G$26:N26)) -> 0 | P26: =MIN($F$26/8,$F$26-SUM($G$26:O26)) -> 0 | ... R26: =MIN($F$26/8,$F$26-SUM($G$26:Q26)) -> 0 | S26: =MIN(P26/8,$F$26-SUM($G$26:R26)) -> 0 | U26: 0 | W26: 0 | AA26: 0 | AB26: 0 | AV26: =SUM(G26:AU26) -> 0 | AW26: =F26-AV26 -> 0
B27: ='Development Budget'!C15 -> General Conditions | E27: =F27/'Rent Schedule'!$D$26 -> 0 | F27: ='Development Budget'!G15 -> 0 | H27: 0 | I27: =$F$27*I23-H27 -> 0 | J27: =$F$27*J23 -> 0 | K27: =$F$27*K23 -> 0 | L27: =$F$27*L23 -> 0 | M27: =$F$27*M23 -> 0 | N27: =$F$27*N23 -> 0 | O27: =$F$27*O23 -> 0 | P27: =$F$27*P23 -> 0 | Q27: =$F$27*Q23 -> 0 | ... AK27: =$F$27*AK23 -> 0 | AN27: 0 | AO27: 0 | AP27: 0 | AV27: =SUM(G27:AU27) -> 0 | AW27: =F27-AV27 -> 0
B28: ='Development Budget'!C16 -> GC Overhead | E28: =F28/'Rent Schedule'!$D$26 -> 0 | F28: ='Development Budget'!G16 -> 0 | H28: 0 | I28: =$F$28*I23-H28 -> 0 | J28: =$F$28*J23 -> 0 | K28: =$F$28*K23 -> 0 | L28: =$F$28*L23 -> 0 | M28: =$F$28*M23 -> 0 | N28: =$F$28*N23 -> 0 | O28: =$F$28*O23 -> 0 | P28: =$F$28*P23 -> 0 | Q28: =$F$28*Q23 -> 0 | ... AK28: =$F$28*AK23 -> 0 | AN28: 0 | AO28: 0 | AP28: 0 | AV28: =SUM(G28:AU28) -> 0 | AW28: =F28-AV28 -> 0
B29: ='Development Budget'!C17 -> GC Profit | E29: =F29/'Rent Schedule'!$D$26 -> 0 | F29: ='Development Budget'!G17 -> 0 | H29: 0 | I29: =$F$29*I23-H29 -> 0 | J29: =$F$29*J23 -> 0 | K29: =$F$29*K23 -> 0 | L29: =$F$29*L23 -> 0 | M29: =$F$29*M23 -> 0 | N29: =$F$29*N23 -> 0 | O29: =$F$29*O23 -> 0 | P29: =$F$29*P23 -> 0 | Q29: =$F$29*Q23 -> 0 | ... AK29: =$F$29*AK23 -> 0 | AN29: 0 | AO29: 0 | AP29: 0 | AV29: =SUM(G29:AU29) -> 0 | AW29: =F29-AV29 -> 0
B30: ='Development Budget'!C18 -> Builders Risk Insurance | E30: =F30/'Rent Schedule'!$D$26 -> 0 | F30: ='Development Budget'!G18 -> 0 | H30: =F30 -> 0 | AV30: =SUM(G30:AU30) -> 0 | AW30: =F30-AV30 -> 0
B31: ='Development Budget'!C19 -> Payment and Performance Bond | E31: =F31/'Rent Schedule'!$D$26 -> 0 | F31: ='Development Budget'!G19 -> 0 | H31: =F31 -> 0 | AV31: =SUM(G31:AU31) -> 0 | AW31: =F31-AV31 -> 0
B32: ='Development Budget'!C20 -> Construction Contingency (5%) | D32: =F32/F24 -> #DIV/0! | E32: =F32/'Rent Schedule'!$D$26 -> 0 | F32: ='Development Budget'!G20 -> 0 | H32: 0 | I32: =$F$32*I23 -> 0 | J32: =$F$32*J23 -> 0 | K32: =$F$32*K23 -> 0 | L32: =$F$32*L23 -> 0 | M32: =$F$32*M23 -> 0 | N32: =$F$32*N23 -> 0 | O32: =$F$32*O23 -> 0 | P32: =$F$32*P23 -> 0 | ... AK32: =$F$32*AK23 -> 0 | AN32: =$F$32*AN23 -> 0 | AO32: =$F$32*AO23 -> 0 | AP32: =$F$32*AP23 -> 0 | AV32: =SUM(G32:AU32) -> 0 | AW32: =F32-AV32 -> 0
B33: Warehouse key | E33: =F33/[6]Rent_Schedule!$E$25 -> 0 | F33: 0 | AV33: =F33-SUM(G33:AB33) -> 0
B34: Multivista Documentation Allowance | E34: =F34/[6]Rent_Schedule!$E$25 -> 0 | F34: 0 | AV34: =F34-SUM(G34:AB34) -> 0
B35: Parking lot rental allowance | E35: =F35/[6]Rent_Schedule!$E$25 -> 0 | F35: 0 | AV35: =F35-SUM(G35:AB35) -> 0
E36: =F36/[6]Rent_Schedule!$E$25 -> 0
D37: Construction Cost Subtotals | E37: =F37/'Rent Schedule'!$D$26 -> 0 | F37: =SUM(F24:F32)+F21 -> 0 | G37: 0 | H37: =SUM(H24:H35)+H21 -> 500000 | I37: =SUM(I24:I35) -> -500000 | J37: =SUM(J24:J35) -> 0 | K37: =SUM(K24:K35) -> 0 | L37: =SUM(L24:L35) -> 0 | M37: =SUM(M24:M35) -> 0 | N37: =SUM(N24:N35) -> 0 | O37: =SUM(O24:O35) -> 0 | P37: =SUM(P24:P35) -> 0 | ... AQ37: =SUM(AQ24:AQ35) -> 0 | AU37: =SUM(AU24:AU35) -> 0 | AV37: =SUM(G37:AQ37) -> 0 | AW37: =F37-AV37 -> 0
E38: =F38/[6]Rent_Schedule!$E$25 -> 0
A39: Predevelopment Costs | E39: =F39/[6]Rent_Schedule!$E$25 -> 0
B40: ='Development Budget'!C23 -> Property Appraisal | E40: =F40/'Rent Schedule'!$D$26 -> 0 | F40: ='Development Budget'!G23 -> 0 | H40: =F40 -> 0 | AV40: =SUM(H40:AU40) -> 0 | AW40: =F40-AV40 -> 0
B41: ='Development Budget'!C24 -> Market Study | E41: =F41/'Rent Schedule'!$D$26 -> 0 | F41: ='Development Budget'!G24 -> 0 | H41: =F41 -> 0 | AV41: =SUM(H41:AU41) -> 0 | AW41: =F41-AV41 -> 0
B42: ='Development Budget'!C25 -> Environmental Report(s) | E42: =F42/'Rent Schedule'!$D$26 -> 0 | F42: ='Development Budget'!G25 -> 0 | H42: =F42 -> 0 | AV42: =SUM(H42:AU42) -> 0 | AW42: =F42-AV42 -> 0
B43: ='Development Budget'!C26 -> Soil Borings | E43: =F43/'Rent Schedule'!$D$26 -> 0 | F43: ='Development Budget'!G26 -> 0 | H43: =F43 -> 0 | I43: 0 | AV43: =SUM(H43:AU43) -> 0 | AW43: =F43-AV43 -> 0
B44: ='Development Budget'!C27 -> Boundary and Topographical Survey | E44: =F44/'Rent Schedule'!$D$26 -> 0 | F44: ='Development Budget'!G27 -> 0 | H44: =F44 -> 0 | AV44: =SUM(H44:AU44) -> 0 | AW44: =F44-AV44 -> 0
B45: ='Development Budget'!C28 -> Zoning/Site Plan Fees | E45: =F45/'Rent Schedule'!$D$26 -> 0 | F45: ='Development Budget'!G28 -> 0 | H45: =F45 -> 0 | AV45: =SUM(H45:AU45) -> 0 | AW45: =F45-AV45 -> 0
A46: Construction Period Financing
B47: ='Development Budget'!C31 -> Construction Financing and Placement Fees | E47: =F47/'Rent Schedule'!$D$26 -> -103.69635 | F47: ='Development Budget'!G31 -> -22916.893 | H47: =F47 -> -22916.893 | AV47: =SUM(H47:AU47) -> -22916.893 | AW47: =F47-AV47 -> 0
B48: ='Development Budget'!C32 -> Construction Loan Interest | E48: =F48/'Rent Schedule'!$D$26 -> 3218.2164 | F48: =H159 -> 711225.82 | H48: =H158 -> 0 | I48: =I158 -> 13005.049 | J48: =J158 -> 12434.88 | K48: =K158 -> 12434.88 | L48: =L158 -> 12434.88 | M48: =M158 -> 12434.88 | N48: =N158 -> 14086.958 | O48: =O158 -> 18676.193 | ... AQ48: =AQ158 -> 47911.65 | AV48: =SUM(H48:AU48) -> 711225.82 | AW48: =F48-AV48 -> 0
B49: ='Development Budget'!C33 -> Bond Interst (Fully Drawn) | F49: ='Development Budget'!G33 -> 1186697.6 | I49: =I115 -> 33905.646 | J49: =J115 -> 33905.646 | K49: =K115 -> 33905.646 | L49: =L115 -> 33905.646 | M49: =M115 -> 33905.646 | N49: =N115 -> 33905.646 | O49: =O115 -> 33905.646 | P49: =P115 -> 33905.646 | ... AQ49: =AQ115 -> 33905.646 | AV49: =SUM(H49:AU49) -> 1186697.6 | AW49: =F49-AV49 -> 0
B50: ='Development Budget'!C34 -> Bond issuer Fee (APV) | E50: =F50/'Rent Schedule'!$D$26 -> 0 | F50: ='Development Budget'!G34 -> 0 | H50: =F50 -> 0 | AV50: =SUM(H50:AU50) -> 0 | AW50: =F50-AV50 -> 0
B51: ='Development Budget'!C35 -> Lender's Legal Fees | E51: =F51/'Rent Schedule'!$D$26 -> 226.24434 | F51: ='Development Budget'!G35 -> 50000 | H51: =F51 -> 50000 | AQ51: 0 | AV51: =SUM(H51:AU51) -> 50000 | AW51: =F51-AV51 -> 0
B52: ='Development Budget'!C36 -> Construction Period Real Estate Tax | E52: =F52/'Rent Schedule'!$D$26 -> 0 | F52: ='Development Budget'!G36 -> 0 | H52: 0 | AV52: =SUM(H52:AU52) -> 0 | AW52: =F52-AV52 -> 0
B53: ='Development Budget'!C37 -> GL Insurance & BR Security during construction | E53: =F53/'Rent Schedule'!$D$26 -> 542.98643 | F53: ='Development Budget'!G37 -> 120000 | H53: 120000 | K53: =200000/20 -> 10000 | L53: =200000/20 -> 10000 | M53: =200000/20 -> 10000 | N53: =200000/20 -> 10000 | O53: =200000/20 -> 10000 | P53: =200000/20 -> 10000 | Q53: =200000/20 -> 10000 | R53: =200000/20 -> 10000 | ... AD53: =200000/20 -> 10000 | AV53: =SUM(H53:AU53) -> 320000 | AW53: =F53-AV53 -> -200000
B54: ='Development Budget'!C38 -> Bond Issuer Legal-Bond Board and Trustee Fees | E54: =F54/'Rent Schedule'!$D$26 -> 0 | F54: ='Development Budget'!G38 -> 0 | H54: =F54 -> 0 | AV54: =SUM(H54:AU54) -> 0 | AW54: =F54-AV54 -> 0
B55: ='Development Budget'!C39 -> Freddie TEL legal & Associated Fees | E55: =F55/'Rent Schedule'!$D$26 -> 0 | F55: ='Development Budget'!G39 -> 0 | H55: =F55/2 -> 0 | AG55: =F55/4 -> 0 | AR55: =$F$55/4 -> 0 | AV55: =SUM(H55:AU55) -> 0 | AW55: =F55-AV55 -> 0
A56: Professional Services
B57: ='Development Budget'!C42 -> Architectural Fee - Design | E57: =F57/'Rent Schedule'!$D$26 -> 678.73303 | F57: ='Development Budget'!G42 -> 150000 | H57: =F57 -> 150000 | I57: 0 | AH57: =S57 -> 0 | AV57: =SUM(G57:AU57) -> 150000 | AW57: =F57-AV57 -> 0
B58: ='Development Budget'!C43 -> Architectural Fee - Supervision | E58: =F58/'Rent Schedule'!$D$26 -> 395.47511 | F58: ='Development Budget'!G43 -> 87400 | H58: =19250+133150 -> 152400 | I58: 10000 | J58: 10000 | K58: 10000 | L58: 10000 | M58: 10000 | N58: =MIN(5000,$F$58-SUM($H$58:M58)) -> -115000 | O58: =MIN(5000,$F$58-SUM($H$58:N58)) -> 0 | P58: =MIN(5000,$F$58-SUM($H$58:O58)) -> 0 | Q58: =MIN(5000,$F$58-SUM($H$58:P58)) -> 0 | R58: =MIN(5000,$F$58-SUM($H$58:Q58)) -> 0 | S58: =MIN(5000,$F$58-SUM($H$58:R58)) -> 0 | T58: =MIN(5000,$F$58-SUM($H$58:S58)) -> 0 | U58: =MIN(5000,$F$58-SUM($H$58:T58)) -> 0 | ... AD58: =MIN(5000,$F$58-SUM($H$58:AC58)) -> 0 | AE58: 0 | AF58: 0 | AG58: =MIN(5000,$F$58-SUM($H$58:AF58)) -> 0 | AH58: =MIN(5000,$F$58-SUM($H$58:AG58)) -> 0 | AI58: =MIN(5000,$F$58-SUM($H$58:AH58)) -> 0 | AJ58: =MIN(5000,$F$58-SUM($H$58:AI58)) -> 0 | AK58: =MIN(5000,$F$58-SUM($H$58:AJ58)) -> 0 | AL58: =MIN(5000,$F$58-SUM($H$58:AK58)) -> 0 | AM58: =MIN(5000,$F$58-SUM($H$58:AL58)) -> 0 | AN58: =MIN(5000,$F$58-SUM($H$58:AM58)) -> 0 | ... AP58: =MIN(5000,$F$58-SUM($H$58:AO58)) -> 0 | AQ58: =MIN(5000,$F$58-SUM($H$58:AN58)) -> 0 | AU58: =MIN(5000,$F$58-SUM($H$58:AR58)) -> 0 | AV58: =SUM(G58:AU58) -> 87400 | AW58: =F58-AV58 -> 0
B59: ='Development Budget'!C44 -> Architectural Fee - Reimbursables | E59: =F59/'Rent Schedule'!$D$26 -> 90.497738 | F59: ='Development Budget'!G44 -> 20000 | H59: =F59/2 -> 10000 | M59: 5000 | N59: 0 | R59: 5000 | X59: 5000 | AA59: 5000 | AB59: 0 | AC59: 0 | AD59: 10000 | AE59: 0 | AF59: 0 | AH59: =N59 -> 0 | AN59: =N59 -> 0 | AO59: =O59 -> 0 | AP59: =P59 -> 0 | AV59: =SUM(G59:AU59) -> 40000 | AW59: =F59-AV59 -> -20000
B60: ='Development Budget'!C45 -> Landscape Architect | E60: =F60/'Rent Schedule'!$D$26 -> 158.37104 | F60: ='Development Budget'!G45 -> 35000 | H60: =50000 -> 50000 | U60: 7500 | AD60: =I60-SUM(K60:AC60)*-1 -> 7500 | AE60: 0 | AF60: 0 | AV60: =SUM(G60:AU60) -> 65000 | AW60: =F60-AV60 -> -30000
B61: ='Development Budget'!C46 -> Engineering | E61: =F61/'Rent Schedule'!$D$26 -> 678.73303 | F61: ='Development Budget'!G46 -> 150000 | H61: 165000 | K61: 10000 | O61: 10000 | P61: 10000 | V61: 10000 | Y61: 10000 | AA61: 10000 | AB61: 0 | AC61: 0 | AD61: 100000 | AE61: 0 | AF61: 0 | AQ61: 0 | AV61: =SUM(G61:AU61) -> 325000 | AW61: =F61-AV61 -> -175000
B62: ='Development Budget'!C47 -> Real Estate Attorney | E62: =F62/'Rent Schedule'!$D$26 -> 339.36652 | F62: ='Development Budget'!G47 -> 75000 | H62: 165000 | AB62: 0 | AC62: 0 | AD62: 10000 | AE62: 0 | AF62: 0 | AQ62: 0 | AV62: =SUM(G62:AU62) -> 175000 | AW62: =F62-AV62 -> -100000
B63: ='Development Budget'!C48 -> HHA Legal (Coats Rose) | E63: =F63/'Rent Schedule'!$D$26 -> 226.24434 | F63: ='Development Budget'!G48 -> 50000 | H63: =F63 -> 50000 | AA63: =F63-SUM(H63:Z63) -> 0 | AB63: 0 | AC63: 0 | AD63: 0 | AE63: 0 | AF63: 0 | AV63: =SUM(G63:AU63) -> 50000 | AW63: =F63-AV63 -> 0
B64: ='Development Budget'!C49 -> Accounting | E64: =F64/'Rent Schedule'!$D$26 -> 316.74208 | F64: ='Development Budget'!G49 -> 70000 | H64: 50000 | AB64: 0 | AC64: 0 | AD64: 50000 | AE64: 0 | AF64: 0 | AQ64: 0 | AV64: =SUM(G64:AU64) -> 100000 | AW64: =F64-AV64 -> -30000
B65: ='Development Budget'!C50 -> Green Building Certification/Registration | E65: =F65/'Rent Schedule'!$D$26 -> 0 | F65: ='Development Budget'!G50 -> 0 | H65: =25000 -> 25000 | Q65: 5000 | AB65: 0 | AC65: 0 | AD65: 25000 | AE65: 0 | AF65: 0 | AQ65: 0 | AV65: =SUM(G65:AU65) -> 55000 | AW65: =F65-AV65 -> -55000
B66: ='Development Budget'!C51 -> Construction Inspection Fees | E66: =F66/'Rent Schedule'!$D$26 -> 180.99548 | F66: ='Development Budget'!G51 -> 40000 | H66: 0 | I66: 4000 | J66: 2000 | K66: 2000 | L66: 2000 | M66: 2000 | N66: 2000 | O66: 2000 | P66: 2000 | Q66: 2000 | R66: 2000 | S66: 2000 | T66: 2000 | U66: 2000 | V66: 2000 | W66: 2000 | X66: 2000 | Y66: 2000 | Z66: 2000 | AB66: 0 | AC66: 0 | AD66: 2000 | AE66: 0 | AF66: 0 | AV66: =SUM(G66:AU66) -> 40000 | AW66: =F66-AV66 -> 0
B67: ='Development Budget'!C52 -> Accessibility Consulting | E67: =F67/'Rent Schedule'!$D$26 -> 135.74661 | F67: ='Development Budget'!G52 -> 30000 | H67: =15000 -> 15000 | O67: 5000 | AB67: 0 | AC67: 0 | AD67: 10000 | AE67: 0 | AF67: 0 | AV67: =SUM(G67:AU67) -> 30000 | AW67: =F67-AV67 -> 0
B68: ='Development Budget'!C53 -> Construction Materials Testing | E68: =F68/'Rent Schedule'!$D$26 -> 203.61991 | F68: ='Development Budget'!G53 -> 45000 | H68: 0 | M68: 10000 | Q68: 10000 | T68: 5000 | V68: 10000 | AB68: 0 | AC68: 0 | AD68: 10000 | AE68: 0 | AF68: 0 | AV68: =SUM(G68:AU68) -> 45000 | AW68: =F68-AV68 -> 0
A69: Local Government Fees
B70: ='Development Budget'!C56 -> Building Permits | E70: =F70/'Rent Schedule'!$D$26 -> 723.9819 | F70: ='Development Budget'!G56 -> 160000 | H70: =F70 -> 160000 | AV70: =SUM(H70:AU70) -> 160000 | AW70: =F70-AV70 -> 0
B71: ='Development Budget'!C57 -> Impact Fees | E71: =F71/'Rent Schedule'!$D$26 -> 842.32701 | F71: ='Development Budget'!G57 -> 186154.27 | H71: =F71 -> 186154.27 | AV71: =SUM(H71:AU71) -> 186154.27 | AW71: =F71-AV71 -> 0
B72: ='Development Budget'!C58 -> Plan review | E72: =F72/'Rent Schedule'!$D$26 -> 116.42986 | F72: ='Development Budget'!G58 -> 25731 | H72: =F72 -> 25731 | AV72: =SUM(H72:AU72) -> 25731 | AW72: =F72-AV72 -> 0
B73: ='Development Budget'!C59 -> Other local fees | E73: =F73/'Rent Schedule'!$D$26 -> 0 | F73: ='Development Budget'!G59 -> 0 | H73: =F73 -> 0 | AV73: =SUM(H73:AU73) -> 0 | AW73: =F73-AV73 -> 0
A74: Permanent Financing Fees
B75: ='Development Budget'!C62 -> Permanent Loan Fees | E75: =F75/'Rent Schedule'!$D$26 -> 1397.6244 | F75: ='Development Budget'!G62 -> 308875 | H75: =F75 -> 308875 | AV75: =SUM(H75:AU75) -> 308875 | AW75: =F75-AV75 -> 0
B76: ='Development Budget'!C63 -> Permanent Loan Legal Fees | E76: =F76/'Rent Schedule'!$D$26 -> 542.98643 | F76: ='Development Budget'!G63 -> 120000 | H76: 30000 | AR76: 90000 | AV76: =SUM(H76:AU76) -> 120000 | AW76: =F76-AV76 -> 0
B77: ='Development Budget'!C64 -> Title and Recording Fees | E77: =F77/'Rent Schedule'!$D$26 -> 520.36199 | F77: ='Development Budget'!G64 -> 115000 | H77: =F77 -> 115000 | AR77: 0 | AV77: =SUM(H77:AU77) -> 115000 | AW77: =F77-AV77 -> 0
B78: ='Development Budget'!C65 -> As-Built Survey | E78: =F78/'Rent Schedule'!$D$26 -> 135.74661 | F78: ='Development Budget'!G65 -> 30000 | H78: 0 | AR78: 30000 | AV78: =SUM(H78:AU78) -> 30000 | AW78: =F78-AV78 -> 0
B79: ='Development Budget'!C66 -> Conversion Fee | E79: =F79/'Rent Schedule'!$D$26 -> 45.248869 | F79: ='Development Budget'!G66 -> 10000 | H79: 0 | AR79: 10000 | AV79: =SUM(H79:AU79) -> 10000 | AW79: =F79-AV79 -> 0
A80: Tax Credit Costs
B81: ='Development Budget'!C69 -> Application Fee | E81: =F81/'Rent Schedule'!$D$26 -> 0 | F81: ='Development Budget'!G69 -> 0 | H81: =F81 -> 0 | AV81: =SUM(H81:AU81) -> 0 | AW81: =F81-AV81 -> 0
B82: ='Development Budget'!C70 -> Pre-application Fee | E82: =F82/'Rent Schedule'!$D$26 -> 0 | F82: ='Development Budget'!G70 -> 0 | H82: =F82 -> 0 | AV82: =SUM(H82:AU82) -> 0 | AW82: =F82-AV82 -> 0
B83: ='Development Budget'!C71 -> Commitment Fee | E83: =F83/'Rent Schedule'!$D$26 -> 171.25396 | F83: ='Development Budget'!G71 -> 37847.125 | H83: =F83 -> 37847.125 | AV83: =SUM(H83:AU83) -> 37847.125 | AW83: =F83-AV83 -> 0
B84: ='Development Budget'!C72 -> Bond Development Determination Fee | E84: =F84/'Rent Schedule'!$D$26 -> 171.25396 | F84: ='Development Budget'!G72 -> 37847.125 | H84: =F84 -> 37847.125 | AV84: =SUM(H84:AU84) -> 37847.125 | AW84: =F84-AV84 -> 0
B85: ='Development Budget'!C73 -> LIHTC Allocation Processing Fee | E85: =F85/'Rent Schedule'!$D$26 -> 316.74208 | F85: ='Development Budget'!G73 -> 70000 | H85: =F85 -> 70000 | AV85: =SUM(H85:AU85) -> 70000 | AW85: =F85-AV85 -> 0
B86: ='Development Budget'!C74 -> LIHTC Compliance Monitoring Fee | E86: =F86/'Rent Schedule'!$D$26 -> 38.371041 | F86: ='Development Budget'!G74 -> 8480 | H86: 0 | AD86: =F86 -> 8480 | AV86: =SUM(H86:AU86) -> 8480 | AW86: =F86-AV86 -> 0
A87: Equity Costs
B88: ='Development Budget'!C77 -> Partnership Organization Fees | E88: =F88/'Rent Schedule'!$D$26 -> 158.37104 | F88: ='Development Budget'!G77 -> 35000 | H88: =F88 -> 35000 | AV88: =SUM(H88:AU88) -> 35000 | AW88: =F88-AV88 -> 0
B89: ='Development Budget'!C78 -> Tax Credit Legal Opinion | E89: =F89/'Rent Schedule'!$D$26 -> 135.74661 | F89: ='Development Budget'!G78 -> 30000 | H89: =F89 -> 30000 | AV89: =SUM(H89:AU89) -> 30000 | AW89: =F89-AV89 -> 0
B90: ='Development Budget'!C79 -> Syndicator Legal Fees | E90: =F90/'Rent Schedule'!$D$26 -> 135.74661 | F90: ='Development Budget'!G79 -> 30000 | H90: =F90 -> 30000 | AV90: =SUM(H90:AU90) -> 30000 | AW90: =F90-AV90 -> 0
B91: ='Development Budget'!C80 -> Syndicator Due Diligence Fee | E91: =F91/'Rent Schedule'!$D$26 -> 90.497738 | F91: ='Development Budget'!G80 -> 20000 | H91: =F91 -> 20000 | AV91: =SUM(H91:AU91) -> 20000 | AW91: =F91-AV91 -> 0
A92: Start Up and Reserves
B93: ='Development Budget'!C83 -> Marketing | E93: =F93/'Rent Schedule'!$D$26 -> 226.24434 | F93: ='Development Budget'!G83 -> 50000 | H93: 0 | U93: 0 | X93: 0 | AB93: 0 | AC93: 0 | AD93: 0 | AE93: =MIN($F$93/6,$F$93-SUM($G$93:AD93)) -> 8333.3333 | AF93: =MIN($F$93/6,$F$93-SUM($G$93:AE93)) -> 8333.3333 | AG93: =MIN($F$93/6,$F$93-SUM($G$93:AF93)) -> 8333.3333 | AH93: =MIN($F$93/6,$F$93-SUM($G$93:AG93)) -> 8333.3333 | AI93: =MIN($F$93/6,$F$93-SUM($G$93:AH93)) -> 8333.3333 | AJ93: =MIN($F$93/6,$F$93-SUM($G$93:AI93)) -> 8333.3333 | AK93: 0 | AV93: =SUM(H93:AU93) -> 50000 | AW93: =F93-AV93 -> 0
B94: ='Development Budget'!C84 -> Rent-Up Reserves | E94: =F94/'Rent Schedule'!$D$26 -> 2714.9321 | F94: ='Development Budget'!G84 -> 600000 | H94: 0 | X94: 40000 | Y94: =$F94/12 -> 50000 | Z94: =MIN($F$94-SUM($G$94:Y94),$F94/12) -> 50000 | AA94: =MIN($F$94-SUM($G$94:Z94),$F94/12) -> 50000 | AB94: =MIN($F$94-SUM($G$94:AA94),$F94/12) -> 50000 | AC94: =MIN($F$94-SUM($G$94:AB94),$F94/12) -> 50000 | AD94: =MIN($F$94-SUM($G$94:AC94),$F94/12) -> 50000 | AE94: =MIN($F$94-SUM($G$94:AD94),$F94/12) -> 50000 | AF94: =MIN($F$94-SUM($G$94:AE94),$F94/12) -> 50000 | AG94: =MIN($F$94-SUM($G$94:AF94),$F94/12) -> 50000 | ... AP94: =MIN($F$94-SUM($G$94:AO94),$F94/12) -> 0 | AQ94: =MIN($F$94-SUM($G$94:AN94),$F94/12) -> 0 | AU94: =MIN($F$94-SUM($G$94:AR94),$F94/12) -> 0 | AV94: =SUM(H94:AU94) -> 600000 | AW94: =F94-AV94 -> 0
B95: ='Development Budget'!C85 -> Operating Deficit Reserve | E95: =F95/'Rent Schedule'!$D$26 -> 6651.5965 | F95: ='Development Budget'!G85 -> 1470002.8 | H95: 0 | AA95: 0 | AD95: =F95 -> 1470002.8 | AE95: 0 | AQ95: 0 | AV95: =SUM(H95:AU95) -> 1470002.8 | AW95: =F95-AV95 -> 0
B96: ='Development Budget'!C86 -> Replacement Reserve | E96: =F96/'Rent Schedule'!$D$26 -> 300 | F96: ='Development Budget'!G86 -> 66300 | H96: 0 | AA96: 0 | AD96: =F96 -> 66300 | AQ96: 0 | AV96: =SUM(H96:AU96) -> 66300 | AW96: =F96-AV96 -> 0
B97: ='Development Budget'!C87 -> Furniture, Fixtures and Equipment | E97: =F97/'Rent Schedule'!$D$26 -> 1131.2217 | F97: ='Development Budget'!G87 -> 250000 | H97: 100000 | W97: 100000 | X97: 100000 | Y97: 100000 | Z97: 100000 | AA97: 100000 | AB97: 50000 | AC97: 0 | AL97: 0 | AM97: 0 | AU97: 0 | AV97: =SUM(H97:AU97) -> 650000 | AW97: =F97-AV97 -> -400000
A98: Other Costs
B99: ='Development Budget'!C90 -> Soft Cost Contingency | E99: =F99/'Rent Schedule'!$D$26 -> 339.36652 | F99: ='Development Budget'!G90 -> 75000 | H99: 0 | M99: =L99 -> 0 | N99: =M99 -> 0 | O99: =N99 -> 0 | P99: =O99 -> 0 | R99: 25000 | AA99: =F99-SUM(H99:Z99) -> 50000 | AB99: 0 | AQ99: 0 | AV99: =SUM(H99:AU99) -> 75000 | AW99: =F99-AV99 -> 0
B100: Developer Fee - Overhead (30%) | E100: =F100/'Rent Schedule'!$D$26 -> 6334.8416 | F100: ='Developer Fee Schedule'!A12 -> 1400000 | H100: ='Developer Fee Schedule'!E9 -> 1400000 | AB100: =Z100 -> 0 | AN100: =SUM('[6]Developer Fee Schedule'!F13:F16) -> 0 | AO100: =SUM('[6]Developer Fee Schedule'!G13:G16) -> 0 | AP100: =SUM('[6]Developer Fee Schedule'!H13:H16) -> 0 | AV100: =SUM(H100:AU100) -> 1400000 | AW100: =F100-AV100 -> 0
B101: Developer Fee - Net Fee (80%) | E101: =F101/'Rent Schedule'!$D$26 -> 110547.13 | F101: ='Developer Fee Schedule'!F18+'Developer Fee Schedule'!G18 -> 24430917 | H101: 0 | AB101: 0 | AE101: ='Developer Fee Schedule'!F9 -> 14098550 | AQ101: 0 | AR101: ='Developer Fee Schedule'!G9 -> 10332367 | AV101: =SUM(H101:AU101) -> 24430917 | AW101: =F101-AV101 -> 0
...

Sheet Developer Fee Schedule
A1: ='Summary Sources-Uses'!A2 -> Project Name | J1: ='Summary Sources-Uses'!L2 -> 0 | K1: ='Summary Sources-Uses'!L1 -> 45960
A2: Affordable / Mixed-Income Family Housing (221 units)
A3: APV Redevelopment Corp.
A4: SDK Independence Heights LLC | E4: I. Closing | F4: II. Completion | G4: III. Stabilization | H4: IV. Final Install | I4: deferred fee
A5: New Affordable Housing Partners, LLC | D5: investor LPA- % of paid fee | E5: =E9/A9 -> 0.2 | F5: 0.4 | G5: 0.4 | H5: 0 | I5: from
E6: ='Flow of Funds'!H3 -> 46447 | F6: ='Flow of Funds'!AE3 -> 47150 | G6: 46966 | H6: =G6 -> 46966 | I6: cash flow | K6: sum totals
C7: Fee Scheduled to be Paid* | E7: =A12 -> 1400000 | F7: =($K7-$I7)*(F5+E5)-E7 -> 14098550 | G7: =($K7-$I7)*G5 -> 10332367 | H7: =($K7-$I7)*H5 -> 0 | I7: ='Summary Sources-Uses'!E17 -> -18830917 | K7: =A9 -> 7000000
A9: ='Summary Sources-Uses'!K20 -> 7000000 | B9: Total Development Fee | D9: (actual paid fee) -------> | E9: =E7 -> 1400000 | F9: =F7 -> 14098550 | G9: =G7 -> 10332367 | H9: =H7 -> 0 | I9: =I7 -> -18830917 | K9: =SUM(E9:I9) -> 7000000
M11: =2752572/7000000 -> 0.39322457
A12: =1400000 -> 1400000 | B12: 20% Developer Overhead:
B13: 40% to APV Redevelopment Corp (HHA) | E13: =A12*0.4 -> 560000 | K13: =SUM(E13:I13) -> 560000
B14: 60% to New AHP LLC/SDK Interests
C15: To SDK Independence LLC | E15: =A12*D21 -> 336000 | K15: =SUM(E15:I15) -> 336000
C16: To New AHP LLC | E16: =A12*D22 -> 504000 | K16: =SUM(E16:I16) -> 504000
A18: =A9-A12 -> 5600000 | B18: remaining to pay out | D18: 0.8 | E18: =E9-SUM(E13:E16) -> 0 | F18: =F9-SUM(F13:F16) -> 14098550 | G18: =G9-G13+G15 -> 10332367 | H18: =H9-H13+H15 -> 0 | I18: =I9-I13+I15 -> -18830917 | K18: =SUM(E18:I18) -> 5600000
A20: =A18*D20 -> 2240000 | B20: split to APV Redevelopment Corp (HHA) | D20: =O29 -> 0.4 | E20: =E18*0.3 -> 0 | F20: =F18*D20 -> 5639420 | G20: =G18*D20 -> 4132946.7 | H20: =H18*D20 -> 0 | I20: =I18*D20 -> -7532366.7 | K20: =SUM(E20:I20) -> 2240000
A21: =A18*D21 -> 1344000 | B21: split to SDK Independence LLC | D21: =O31 -> 0.24 | E21: =E18*0.28 -> 0 | F21: =F18*D21 -> 3383652 | G21: =G18*D21 -> 2479768 | H21: =H18*D21 -> 0 | I21: =I18*D21 -> -4519420 | K21: =SUM(E21:I21) -> 1344000
A22: =A18*D22 -> 2016000 | B22: split to New AHP LLC | D22: =O30 -> 0.36 | E22: =E18*0.42 -> 0 | F22: =F18*D22 -> 5075478 | G22: =G18*D22 -> 3719652 | H22: =H18*D22 -> 0 | I22: =I18*D22 -> -6779130 | K22: =SUM(E22:I22) -> 2016000
B24: Total Fee Splits | C24: APV Redevelopment Corp (HHA) | E24: =E13+E20 -> 560000 | F24: =F13+F20 -> 5639420 | G24: =G13+G20 -> 4132946.7 | H24: =H13+H20 -> 0 | I24: =I13+I20 -> -7532366.7 | K24: =SUM(E24:I24) -> 2800000
C25: SDK Independence LLC | E25: =E15+E21 -> 336000 | F25: =F14+F21 -> 3383652 | G25: =G14+G21 -> 2479768 | H25: =H14+H21 -> 0 | I25: =I14+I21 -> -4519420 | K25: =SUM(E25:I25) -> 1680000
C26: New AHP LLC | E26: =E16+E22 -> 504000 | F26: =F15+F22 -> 5075478 | G26: =G15+G22 -> 3719652 | H26: =H15+H22 -> 0 | I26: =I15+I22 -> -6779130 | K26: =SUM(E26:I26) -> 2520000
B28: * Development Fee is paid upon satisfaction of benchmarks as set out in the Limited Partnership Agreement and Development Services Agreement of Independence Heights Apartments II, Limited Partnership.
B29: Payment dates are estimated based on when we believe benchmarks will be met, but are subject to change. In addition, paid fee amounts are projected assuming a succesful project. | M29: HHA | N29: =K7*0.4 -> 2800000 | O29: =N29/K9 -> 0.4
B30: The amount of paid fee could change depending on how successful the project is. | M30: Columbia | N30: =(K7*0.6)*0.6 -> 2520000 | O30: =N30/K9 -> 0.36
M31: SDK | N31: =(K9*0.6)*0.4 -> 1680000 | O31: =N31/K9 -> 0.24
N32: =N29+N30+N31 -> 7000000 | O32: =O29+O30+O31 -> 1

Sheet 50% Test
C2: Uses from Development Budget:
C3: Aggregate Basis | D3: ='Development Budget'!J94 -> 24658652
D4: =SUM(D3:D3) -> 24658652 | E4: Total Bond Needed: | F4: =D4*0.5 -> 12329326
E5: Max Bond Amt: | F5: =D4*0.55 -> 13562258
C6: Total Bonds | D6: =F5 -> 13562258
C8: Total Bond Proceeds
C10: 50% Test | D10: =D6/D4 -> 0.55 | F10: Cannot exceed 55% per 2024 QAP

Sheet Income (2)
A1: =[1]Input!B1&", "&TEXT(TtlUnits,"0,0")&" units ("&Tenancy&"), "&[1]Input!E2&", "&[1]Input!H2&", "&[1]Input!$R$1 -> Flats at Lake View, 80 units (Family), Warner Robins, Houston County, GA
A2: Unit Mix Set-Asides, County AMI and Rent Limits, and Utility Allowances
M3: Average Income Targeting: | N3: =A6*B6/SUM(B6,B14)+A14*B14/SUM(B6,B14) -> 0.56507937 | Q3: Stabilized Net Operating Income
A4: AMI Set-Asides | B4: Targeted / | C4: Unit Style | F4: Number | G4: Net | H4: Total | I4: Max Net | J4: Net Rent | K4: Total | L4: Rent | M4: Min BR | N4: Hourly | V4: Rent
B5: Actual | C5: BR | D5: Type | E5: BA | F5: of Units | G5: Area | H5: SqFt | I5: Rent | J5: p/Unit | K5: Rent/Mo | L5: p/SqFt | M5: Income | N5: Wages | Q5: Rental Inc. | R5: =K30*12 -> 982800 | U5: Market | V5: Advantage | W5: % RA
A6: 0.5 | B6: =SUM(F6:F13)/TtlUnits -> 0.275 | C6: =IFERROR(VLOOKUP(D6,'[1]Unit Mix'!$V$7:$W$21,2,FALSE),0) -> 1 | D6: A | E6: 1 | F6: 6 | G6: =IF(OR(F6=0,F6=""),0,SUMIF('[1]Unit Mix'!$V$7:$V$21,D6,'[1]Unit Mix'!$X$7:$X$21)) -> #VALUE! | H6: =G6*F6 -> #VALUE! | I6: =IFERROR(IF(F6=0,0,HLOOKUP(C6,$K$32:$O$53,8,FALSE)),0) -> 677 | J6: 715 | K6: =IFERROR(IF(F6=0,"",F6*J6),0) -> 4290 | L6: =IF(F6=0,"",IFERROR(J6/G6,0)) -> 0 | M6: =IF($F6=0,"",((J6+SUMIF($E$43:$H$43,$C6,$E$53:$H$53))*12)/0.3) -> 37000 | N6: =IF(F6=0,"",M6/2080) -> 17.788462 | O6: =Tenancy -> Family | P6: =IF(F6=0,"",M6*(F6/TtlUnits)) -> 2775 | Q6: Garage/Comm. | R6: =CommSqFt*CommRent -> 0 | U6: 1319 | V6: =U6-J6 -> 604 | W6: =V6/U6 -> 0.45792267
A7: LIHTC | C7: =IFERROR(VLOOKUP(D7,'[1]Unit Mix'!$V$7:$W$21,2,FALSE),0) -> 2 | D7: B | E7: =IF(OR(LEFT(D7,1)="0",LEFT(D7,1)="1"),1,2) -> 2 | F7: 8 | G7: =IF(OR(F7=0,F7=""),0,SUMIF('[1]Unit Mix'!$V$7:$V$21,D7,'[1]Unit Mix'!$X$7:$X$21)) -> #VALUE! | H7: =G7*F7 -> #VALUE! | I7: =IFERROR(IF(F7=0,0,HLOOKUP(C7,$K$32:$O$53,8,FALSE)),0) -> 786 | J7: 855 | K7: =IFERROR(IF(F7=0,"",F7*J7),0) -> 6840 | L7: =IF(F7=0,"",IFERROR(J7/G7,0)) -> 0 | M7: =IF($F7=0,"",((J7+SUMIF($E$43:$H$43,$C7,$E$53:$H$53))*12)/0.3) -> 45360 | N7: =IF(F7=0,"",M7/2080) -> 21.807692 | P7: =IF(F7=0,"",M7*(F7/TtlUnits)) -> 4536 | Q7: Other Inc. | R7: =[1]Input!H33 -> 8000 | U7: 1438 | V7: =U7-J7 -> 583 | W7: =V7/U7 -> 0.4054242
A8: =A7 -> LIHTC | C8: =IFERROR(VLOOKUP(D8,'[1]Unit Mix'!$V$7:$W$21,2,FALSE),0) -> 3 | D8: C | E8: =IF(OR(LEFT(D8,1)="0",LEFT(D8,1)="1"),1,2) -> 2 | F8: 3 | G8: =IF(OR(F8=0,F8=""),0,SUMIF('[1]Unit Mix'!$V$7:$V$21,D8,'[1]Unit Mix'!$X$7:$X$21)) -> #VALUE! | H8: =G8*F8 -> #VALUE! | I8: =IFERROR(IF(F8=0,0,HLOOKUP(C8,$K$32:$O$53,8,FALSE)),0) -> 881 | J8: 975 | K8: =IFERROR(IF(F8=0,"",F8*J8),0) -> 2925 | L8: =IF(F8=0,"",IFERROR(J8/G8,0)) -> 0 | M8: =IF($F8=0,"",((J8+SUMIF($E$43:$H$43,$C8,$E$53:$H$53))*12)/0.3) -> 52960 | N8: =IF(F8=0,"",M8/2080) -> 25.461538 | P8: =IF(F8=0,"",M8*(F8/TtlUnits)) -> 1986 | Q8: Gross Potential | R8: =SUM(R5:R7) -> 990800 | U8: 1758 | V8: =U8-J8 -> 783 | W8: =V8/U8 -> 0.44539249
A9: =A5 -> 0 | C9: =IFERROR(VLOOKUP(D9,'[1]Unit Mix'!$V$7:$W$21,2,FALSE),0) -> 4 | D9: D | E9: =IF(OR(LEFT(D9,1)="0",LEFT(D9,1)="1"),1,2) -> 2 | F9: 1 | G9: =IF(OR(F9=0,F9=""),0,SUMIF('[1]Unit Mix'!$V$7:$V$21,D9,'[1]Unit Mix'!$X$7:$X$21)) -> #VALUE! | H9: =G9*F9 -> #VALUE! | I9: =IFERROR(IF(F9=0,0,HLOOKUP(C9,$K$32:$O$53,8,FALSE)),0) -> 1372 | J9: 1075 | K9: =IFERROR(IF(F9=0,"",F9*J9),0) -> 1075 | L9: =IF(F9=0,"",IFERROR(J9/G9,0)) -> 0 | M9: =IF($F9=0,"",((J9+SUMIF($E$43:$H$43,$C9,$E$53:$H$53))*12)/0.3) -> 43000 | N9: =IF(F9=0,"",M9/2080) -> 20.673077 | P9: =IF(F9=0,"",M9*(F9/TtlUnits)) -> 537.5 | Q9: Vacancy | R9: =-R8*Vacancy -> -69356 | U9: 1869 | V9: =U9-J9 -> 794 | W9: =V9/U9 -> 0.42482611
A10: =A6 -> 0.5 | C10: =IFERROR(VLOOKUP(D10,'[1]Unit Mix'!$V$7:$W$21,2,FALSE),0) -> 4 | D10: E | E10: =IF(OR(LEFT(D10,1)="0",LEFT(D10,1)="1"),1,2) -> 2 | F10: 1 | G10: =IF(OR(F10=0,F10=""),0,SUMIF('[1]Unit Mix'!$V$7:$V$21,D10,'[1]Unit Mix'!$X$7:$X$21)) -> #VALUE! | H10: =G10*F10 -> #VALUE! | I10: =IFERROR(IF(F10=0,0,HLOOKUP(C10,$K$32:$O$53,8,FALSE)),0) -> 1372 | J10: 1075 | K10: =IFERROR(IF(F10=0,"",F10*J10),0) -> 1075 | L10: =IF(F10=0,"",IFERROR(J10/G10,0)) -> 0 | M10: =IF($F10=0,"",((J10+SUMIF($E$43:$H$43,$C10,$E$53:$H$53))*12)/0.3) -> 43000 | N10: =IF(F10=0,"",M10/2080) -> 20.673077 | P10: =IF(F10=0,"",M10*(F10/TtlUnits)) -> 537.5 | Q10: Effective Gross | R10: =SUM(R8:R9) -> 921444 | U10: 1869 | V10: =U10-J10 -> 794 | W10: =V10/U10 -> 0.42482611
A11: =A7 -> LIHTC | C11: =IFERROR(VLOOKUP(D11,'[1]Unit Mix'!$V$7:$W$21,2,FALSE),0) -> 3 | D11: F | E11: =IF(OR(LEFT(D11,1)="0",LEFT(D11,1)="1"),1,2) -> 2 | F11: 1 | G11: =IF(OR(F11=0,F11=""),0,SUMIF('[1]Unit Mix'!$V$7:$V$21,D11,'[1]Unit Mix'!$X$7:$X$21)) -> #VALUE! | H11: =G11*F11 -> #VALUE! | I11: =IFERROR(IF(F11=0,0,HLOOKUP(C11,$K$32:$O$53,8,FALSE)),0) -> 881 | J11: 975 | K11: =IFERROR(IF(F11=0,"",F11*J11),0) -> 975 | L11: =IF(F11=0,"",IFERROR(J11/G11,0)) -> 0 | M11: =IF($F11=0,"",((J11+SUMIF($E$43:$H$43,$C11,$E$53:$H$53))*12)/0.3) -> 52960 | N11: =IF(F11=0,"",M11/2080) -> 25.461538 | P11: =IF(F11=0,"",M11*(F11/TtlUnits)) -> 662 | Q11: Net OpEx | R11: =-(GrossOpEx-PropTaxes-ReplRes) -> -402315.65 | U11: 1758 | V11: =U11-J11 -> 783 | W11: =V11/U11 -> 0.44539249
A12: =A8 -> LIHTC | C12: =IFERROR(VLOOKUP(D12,'[1]Unit Mix'!$V$7:$W$21,2,FALSE),0) -> 2 | D12: G | E12: =IF(OR(LEFT(D12,1)="0",LEFT(D12,1)="1"),1,2) -> 2 | F12: 1 | G12: =IF(OR(F12=0,F12=""),0,SUMIF('[1]Unit Mix'!$V$7:$V$21,D12,'[1]Unit Mix'!$X$7:$X$21)) -> #VALUE! | H12: =G12*F12 -> #VALUE! | I12: =IFERROR(IF(F12=0,0,HLOOKUP(C12,$K$32:$O$53,8,FALSE)),0) -> 786 | J12: 855 | K12: =IFERROR(IF(F12=0,"",F12*J12),0) -> 855 | L12: =IF(F12=0,"",IFERROR(J12/G12,0)) -> 0 | M12: =IF($F12=0,"",((J12+SUMIF($E$43:$H$43,$C12,$E$53:$H$53))*12)/0.3) -> 45360 | N12: =IF(F12=0,"",M12/2080) -> 21.807692 | P12: =IF(F12=0,"",M12*(F12/TtlUnits)) -> 567 | Q12: 1 | R12: =-PropTaxes -> -87345.622 | U12: 1438 | V12: =U12-J12 -> 583 | W12: =V12/U12 -> 0.4054242
A13: =A12 -> LIHTC | C13: =IFERROR(VLOOKUP(D13,'[1]Unit Mix'!$V$7:$W$21,2,FALSE),0) -> 1 | D13: H | E13: 1 | F13: 1 | G13: =IF(OR(F13=0,F13=""),0,SUMIF('[1]Unit Mix'!$V$7:$V$21,D13,'[1]Unit Mix'!$X$7:$X$21)) -> #VALUE! | H13: =G13*F13 -> #VALUE! | I13: =IFERROR(IF(F13=0,0,HLOOKUP(C13,$K$32:$O$53,8,FALSE)),0) -> 677 | J13: 715 | K13: =IFERROR(IF(F13=0,"",F13*J13),0) -> 715 | L13: =IF(F13=0,"",IFERROR(J13/G13,0)) -> 0 | M13: =IF($F13=0,"",((J13+SUMIF($E$43:$H$43,$C13,$E$53:$H$53))*12)/0.3) -> 37000 | N13: =IF(F13=0,"",M13/2080) -> 17.788462 | P13: =IF(F13=0,"",M13*(F13/TtlUnits)) -> 462.5 | Q13: Repl. Res. | R13: =-ReplRes -> -20000 | U13: 1319 | V13: =U13-J13 -> 604 | W13: =V13/U13 -> 0.45792267
A14: 0.6 | B14: =SUM(F14:F21)/TtlUnits -> 0.5125 | C14: =IFERROR(VLOOKUP(D14,'[1]Unit Mix'!$V$7:$W$21,2,FALSE),0) -> 1 | D14: =D6 -> A | E14: =E6 -> 1 | F14: 12 | G14: =IF(OR(F14=0,F14=""),0,SUMIF('[1]Unit Mix'!$V$7:$V$21,D14,'[1]Unit Mix'!$X$7:$X$21)) -> #VALUE! | H14: =G14*F14 -> #VALUE! | I14: =IFERROR(IF(F14=0,0,HLOOKUP(C14,$K$32:$O$53,10,FALSE)),0) -> 855 | J14: 850 | K14: =IFERROR(IF(F14=0,"",F14*J14),0) -> 10200 | L14: =IF(F14=0,"",IFERROR(J14/G14,0)) -> 0 | M14: =IF($F14=0,"",((J14+SUMIF($E$43:$H$43,$C14,$E$53:$H$53))*12)/0.3) -> 42400 | N14: =IF(F14=0,"",M14/2080) -> 20.384615 | O14: =Tenancy -> Family | P14: =IF(F14=0,"",M14*(F14/TtlUnits)) -> 6360 | Q14: Total OpEx | R14: =SUM(R11:R13) -> -509661.27 | U14: 1319 | V14: =U14-J14 -> 469 | W14: =V14/U14 -> 0.3555724
A15: LIHTC | C15: =IFERROR(VLOOKUP(D15,'[1]Unit Mix'!$V$7:$W$21,2,FALSE),0) -> 2 | D15: =D7 -> B | E15: =E7 -> 2 | F15: 16 | G15: =IF(OR(F15=0,F15=""),0,SUMIF('[1]Unit Mix'!$V$7:$V$21,D15,'[1]Unit Mix'!$X$7:$X$21)) -> #VALUE! | H15: =G15*F15 -> #VALUE! | I15: =IFERROR(IF(F15=0,0,HLOOKUP(C15,$K$32:$O$53,10,FALSE)),0) -> 999 | J15: 1000 | K15: =IFERROR(IF(F15=0,"",F15*J15),0) -> 16000 | L15: =IF(F15=0,"",IFERROR(J15/G15,0)) -> 0 | M15: =IF($F15=0,"",((J15+SUMIF($E$43:$H$43,$C15,$E$53:$H$53))*12)/0.3) -> 51160 | N15: =IF(F15=0,"",M15/2080) -> 24.596154 | P15: =IF(F15=0,"",M15*(F15/TtlUnits)) -> 10232 | Q15: Net Oper. Inc. | R15: =R10+R14 -> 411782.73 | U15: 1438 | V15: =U15-J15 -> 438 | W15: =V15/U15 -> 0.30458971
A16: =A15 -> LIHTC | C16: =IFERROR(VLOOKUP(D16,'[1]Unit Mix'!$V$7:$W$21,2,FALSE),0) -> 3 | D16: =D8 -> C | E16: =E8 -> 2 | F16: 8 | G16: =IF(OR(F16=0,F16=""),0,SUMIF('[1]Unit Mix'!$V$7:$V$21,D16,'[1]Unit Mix'!$X$7:$X$21)) -> #VALUE! | H16: =G16*F16 -> #VALUE! | I16: =IFERROR(IF(F16=0,0,HLOOKUP(C16,$K$32:$O$53,10,FALSE)),0) -> 1127 | J16: 1100 | K16: =IFERROR(IF(F16=0,"",F16*J16),0) -> 8800 | L16: =IF(F16=0,"",IFERROR(J16/G16,0)) -> 0 | M16: =IF($F16=0,"",((J16+SUMIF($E$43:$H$43,$C16,$E$53:$H$53))*12)/0.3) -> 57960 | N16: =IF(F16=0,"",M16/2080) -> 27.865385 | P16: =IF(F16=0,"",M16*(F16/TtlUnits)) -> 5796 | R16: =R15-NOI -> 0 | U16: 1758 | V16: =U16-J16 -> 658 | W16: =V16/U16 -> 0.37428896
A17: =A13 -> LIHTC | C17: =IFERROR(VLOOKUP(D17,'[1]Unit Mix'!$V$7:$W$21,2,FALSE),0) -> 4 | D17: =D9 -> D | E17: =E9 -> 2 | F17: 5 | G17: =IF(OR(F17=0,F17=""),0,SUMIF('[1]Unit Mix'!$V$7:$V$21,D17,'[1]Unit Mix'!$X$7:$X$21)) -> #VALUE! | H17: =G17*F17 -> #VALUE! | I17: =IFERROR(IF(F17=0,0,HLOOKUP(C17,$K$32:$O$53,10,FALSE)),0) -> 1647 | J17: 1200 | K17: =IFERROR(IF(F17=0,"",F17*J17),0) -> 6000 | L17: =IF(F17=0,"",IFERROR(J17/G17,0)) -> 0 | M17: =IF($F17=0,"",((J17+SUMIF($E$43:$H$43,$C17,$E$53:$H$53))*12)/0.3) -> 48000 | N17: =IF(F17=0,"",M17/2080) -> 23.076923 | P17: =IF(F17=0,"",M17*(F17/TtlUnits)) -> 3000 | U17: 1869 | V17: =U17-J17 -> 669 | W17: =V17/U17 -> 0.35794543
A18: =A14 -> 0.6 | C18: =IFERROR(VLOOKUP(D18,'[1]Unit Mix'!$V$7:$W$21,2,FALSE),0) -> 4 | D18: =D10 -> E | E18: =E10 -> 2 | F18: 0 | G18: =IF(OR(F18=0,F18=""),0,SUMIF('[1]Unit Mix'!$V$7:$V$21,D18,'[1]Unit Mix'!$X$7:$X$21)) -> 0 | H18: =G18*F18 -> 0 | I18: =IFERROR(IF(F18=0,0,HLOOKUP(C18,$K$32:$O$53,10,FALSE)),0) -> 0 | K18: =IFERROR(IF(F18=0,"",F18*J18),0) | L18: =IF(F18=0,"",IFERROR(J18/G18,0)) | M18: =IF($F18=0,"",((J18+SUMIF($E$43:$H$43,$C18,$E$53:$H$53))*12)/0.3) | N18: =IF(F18=0,"",M18/2080) | P18: =IF(F18=0,"",M18*(F18/TtlUnits)) | Q18: Houston-The Woodlands-Sugar Land, TX HUD Metro FMR Area
A19: =A15 -> LIHTC | C19: =IFERROR(VLOOKUP(D19,'[1]Unit Mix'!$V$7:$W$21,2,FALSE),0) -> 3 | D19: =D11 -> F | E19: =E11 -> 2 | G19: =IF(OR(F19=0,F19=""),0,SUMIF('[1]Unit Mix'!$V$7:$V$21,D19,'[1]Unit Mix'!$X$7:$X$21)) -> 0 | H19: =G19*F19 -> 0 | I19: =IFERROR(IF(F19=0,0,HLOOKUP(C19,$K$32:$O$53,10,FALSE)),0) -> 0 | K19: =IFERROR(IF(F19=0,"",F19*J19),0) | L19: =IF(F19=0,"",IFERROR(J19/G19,0)) | M19: =IF($F19=0,"",((J19+SUMIF($E$43:$H$43,$C19,$E$53:$H$53))*12)/0.3) | N19: =IF(F19=0,"",M19/2080) | P19: =IF(F19=0,"",M19*(F19/TtlUnits))
A20: =A16 -> LIHTC | C20: =IFERROR(VLOOKUP(D20,'[1]Unit Mix'!$V$7:$W$21,2,FALSE),0) -> 2 | D20: =D12 -> G | E20: =E12 -> 2 | G20: =IF(OR(F20=0,F20=""),0,SUMIF('[1]Unit Mix'!$V$7:$V$21,D20,'[1]Unit Mix'!$X$7:$X$21)) -> 0 | H20: =G20*F20 -> 0 | I20: =IFERROR(IF(F20=0,0,HLOOKUP(C20,$K$32:$O$53,10,FALSE)),0) -> 0 | K20: =IFERROR(IF(F20=0,"",F20*J20),0) | L20: =IF(F20=0,"",IFERROR(J20/G20,0)) | M20: =IF($F20=0,"",((J20+SUMIF($E$43:$H$43,$C20,$E$53:$H$53))*12)/0.3) | N20: =IF(F20=0,"",M20/2080) | P20: =IF(F20=0,"",M20*(F20/TtlUnits)) | Q20: NNMMI
A21: =A20 -> LIHTC | C21: =IFERROR(VLOOKUP(D21,'[1]Unit Mix'!$V$7:$W$21,2,FALSE),0) -> 1 | D21: =D13 -> H | E21: =E13 -> 1 | G21: =IF(OR(F21=0,F21=""),0,SUMIF('[1]Unit Mix'!$V$7:$V$21,D21,'[1]Unit Mix'!$X$7:$X$21)) -> 0 | H21: =G21*F21 -> 0 | I21: =IFERROR(IF(F21=0,0,HLOOKUP(C21,$K$32:$O$53,10,FALSE)),0) -> 0 | K21: =IFERROR(IF(F21=0,"",F21*J21),0) | L21: =IF(F21=0,"",IFERROR(J21/G21,0)) | M21: =IF($F21=0,"",((J21+SUMIF($E$43:$H$43,$C21,$E$53:$H$53))*12)/0.3) | N21: =IF(F21=0,"",M21/2080) | P21: =IF(F21=0,"",M21*(F21/TtlUnits)) | Q21: Harris County
A22: 1 | B22: =SUM(F22:F29)/TtlUnits -> #VALUE! | C22: =IFERROR(VLOOKUP(D22,'[1]Unit Mix'!$V$7:$W$21,2,FALSE),0) -> 1 | D22: =D14 -> A | E22: =E14 -> 1 | F22: 5 | G22: =IF(OR(F22=0,F22=""),0,SUMIF('[1]Unit Mix'!$V$7:$V$21,D22,'[1]Unit Mix'!$X$7:$X$21)) -> #VALUE! | H22: =G22*F22 -> #VALUE! | I22: =IFERROR(HLOOKUP(C22,$K$32:$O$53,4,FALSE),"N/A") -> 322 | J22: 1175 | K22: =IFERROR(IF(F22=0,"",F22*J22),0) -> 5875 | L22: =IF(F22=0,"",IFERROR(J22/G22,0)) -> 0 | M22: =IF($F22=0,"",((J22+SUMIF($E$43:$H$43,$C22,$E$53:$H$53))*12)/0.3) -> 55400 | N22: =IF(F22=0,"",M22/2080) -> 26.634615 | O22: =Tenancy -> Family | P22: =IF(F22=0,"",M22*(F22/TtlUnits)) -> 3462.5 | U22: 1319 | V22: =U22-J22 -> 144 | W22: =V22/U22 -> 0.10917362
A23: =A22 -> 1 | C23: =IFERROR(VLOOKUP(D23,'[1]Unit Mix'!$V$7:$W$21,2,FALSE),0) -> 2 | D23: =D15 -> B | E23: =E15 -> 2 | F23: 7 | G23: =IF(OR(F23=0,F23=""),0,SUMIF('[1]Unit Mix'!$V$7:$V$21,D23,'[1]Unit Mix'!$X$7:$X$21)) -> #VALUE! | H23: =G23*F23 -> #VALUE! | I23: =IFERROR(HLOOKUP(C23,$K$32:$O$53,4,FALSE),"N/A") -> 149 | J23: 1275 | K23: =IFERROR(IF(F23=0,"",F23*J23),0) -> 8925 | L23: =IF(F23=0,"",IFERROR(J23/G23,0)) -> 0 | M23: =IF($F23=0,"",((J23+SUMIF($E$43:$H$43,$C23,$E$53:$H$53))*12)/0.3) -> 62160 | N23: =IF(F23=0,"",M23/2080) -> 29.884615 | P23: =IF(F23=0,"",M23*(F23/TtlUnits)) -> 5439 | U23: 1438 | V23: =U23-J23 -> 163 | W23: =V23/U23 -> 0.11335188
A24: =A23 -> 1 | C24: =IFERROR(VLOOKUP(D24,'[1]Unit Mix'!$V$7:$W$21,2,FALSE),0) -> 3 | D24: =D16 -> C | E24: =E16 -> 2 | F24: 4 | G24: =IF(OR(F24=0,F24=""),0,SUMIF('[1]Unit Mix'!$V$7:$V$21,D24,'[1]Unit Mix'!$X$7:$X$21)) -> #VALUE! | H24: =G24*F24 -> #VALUE! | I24: =IFERROR(HLOOKUP(C24,$K$32:$O$53,4,FALSE),"N/A") -> 145 | J24: 1450 | K24: =IFERROR(IF(F24=0,"",F24*J24),0) -> 5800 | L24: =IF(F24=0,"",IFERROR(J24/G24,0)) -> 0 | M24: =IF($F24=0,"",((J24+SUMIF($E$43:$H$43,$C24,$E$53:$H$53))*12)/0.3) -> 71960 | N24: =IF(F24=0,"",M24/2080) -> 34.596154 | P24: =IF(F24=0,"",M24*(F24/TtlUnits)) -> 3598 | Q24: Per Unit Type Income Averaging | U24: 1758 | V24: =U24-J24 -> 308 | W24: =V24/U24 -> 0.17519909
A25: =A24 -> 1 | C25: =IFERROR(VLOOKUP(D25,'[1]Unit Mix'!$V$7:$W$21,2,FALSE),0) -> 4 | D25: =D17 -> D | E25: =E17 -> 2 | F25: 1 | G25: =IF(OR(F25=0,F25=""),0,SUMIF('[1]Unit Mix'!$V$7:$V$21,D25,'[1]Unit Mix'!$X$7:$X$21)) -> #VALUE! | H25: =G25*F25 -> #VALUE! | I25: =IFERROR(HLOOKUP(C25,$K$32:$O$53,4,FALSE),"N/A") -> 823 | J25: 1550 | K25: =IFERROR(IF(F25=0,"",F25*J25),0) -> 1550 | L25: =IF(F25=0,"",IFERROR(J25/G25,0)) -> 0 | M25: =IF($F25=0,"",((J25+SUMIF($E$43:$H$43,$C25,$E$53:$H$53))*12)/0.3) -> 62000 | N25: =IF(F25=0,"",M25/2080) -> 29.807692 | P25: =IF(F25=0,"",M25*(F25/TtlUnits)) -> 775 | Q25: =D6 -> A | R25: =IFERROR(($A$6*(F6/(SUMIF('[1]Unit Mix'!$C$5:$Q$5,Q25,'[1]Unit Mix'!$C$7:$Q$7)-F22)))+($A$14*(F14/(SUMIF('[1]Unit Mix'!$C$5:$Q$5,Q25,'[1]Unit Mix'!$C$7:$Q$7)-F22))),"N/A") -> N/A | U25: 1869 | V25: =U25-J25 -> 319 | W25: =V25/U25 -> 0.17067951
A26: =A25 -> 1 | C26: =IFERROR(VLOOKUP(D26,'[1]Unit Mix'!$V$7:$W$21,2,FALSE),0) -> 4 | D26: =D18 -> E | E26: =E18 -> 2 | F26: =SUMIF('[1]Unit Mix'!$V$7:$V$21,D26,'[1]Unit Mix'!$AA$7:$AA$21) -> #VALUE! | G26: =IF(OR(F26=0,F26=""),0,SUMIF('[1]Unit Mix'!$V$7:$V$21,D26,'[1]Unit Mix'!$X$7:$X$21)) -> #VALUE! | H26: =G26*F26 -> #VALUE! | I26: =IFERROR(HLOOKUP(C26,$K$32:$O$53,4,FALSE),"N/A") -> 823 | J26: =IF(F26=0,0,SUMIF('[1]Unit Mix'!$V$7:$V$21,D26,'[1]Unit Mix'!$Z$7:$Z$21)) -> #VALUE! | K26: =IFERROR(IF(F26=0,"",F26*J26),0) -> 0 | L26: =IF(F26=0,"",IFERROR(J26/G26,0)) -> #VALUE! | M26: =IF($F26=0,"",((J26+SUMIF($E$43:$H$43,$C26,$E$53:$H$53))*12)/0.3) -> #VALUE! | N26: =IF(F26=0,"",M26/2080) -> #VALUE! | P26: =IF(F26=0,"",M26*(F26/TtlUnits)) -> #VALUE! | Q26: =D7 -> B | R26: =IFERROR(($A$6*(F7/(SUMIF('[1]Unit Mix'!$C$5:$Q$5,Q26,'[1]Unit Mix'!$C$7:$Q$7)-F23)))+($A$14*(F15/(SUMIF('[1]Unit Mix'!$C$5:$Q$5,Q26,'[1]Unit Mix'!$C$7:$Q$7)-F23))),"N/A") -> N/A
A27: =A26 -> 1 | C27: =IFERROR(VLOOKUP(D27,'[1]Unit Mix'!$V$7:$W$21,2,FALSE),0) -> 3 | D27: =D19 -> F | E27: =E19 -> 2 | F27: =SUMIF('[1]Unit Mix'!$V$7:$V$21,D27,'[1]Unit Mix'!$AA$7:$AA$21) -> #VALUE! | G27: =IF(OR(F27=0,F27=""),0,SUMIF('[1]Unit Mix'!$V$7:$V$21,D27,'[1]Unit Mix'!$X$7:$X$21)) -> #VALUE! | H27: =G27*F27 -> #VALUE! | I27: =IFERROR(HLOOKUP(C27,$K$32:$O$53,4,FALSE),"N/A") -> 145 | J27: =IF(F27=0,0,SUMIF('[1]Unit Mix'!$V$7:$V$21,D27,'[1]Unit Mix'!$Z$7:$Z$21)) -> #VALUE! | K27: =IFERROR(IF(F27=0,"",F27*J27),0) -> 0 | L27: =IF(F27=0,"",IFERROR(J27/G27,0)) -> #VALUE! | M27: =IF($F27=0,"",((J27+SUMIF($E$43:$H$43,$C27,$E$53:$H$53))*12)/0.3) -> #VALUE! | N27: =IF(F27=0,"",M27/2080) -> #VALUE! | P27: =IF(F27=0,"",M27*(F27/TtlUnits)) -> #VALUE! | Q27: =D8 -> C | R27: =IFERROR(($A$6*(F8/(SUMIF('[1]Unit Mix'!$C$5:$Q$5,Q27,'[1]Unit Mix'!$C$7:$Q$7)-F24)))+($A$14*(F16/(SUMIF('[1]Unit Mix'!$C$5:$Q$5,Q27,'[1]Unit Mix'!$C$7:$Q$7)-F24))),"N/A") -> N/A
A28: =A27 -> 1 | C28: =IFERROR(VLOOKUP(D28,'[1]Unit Mix'!$V$7:$W$21,2,FALSE),0) -> 2 | D28: =D20 -> G | E28: =E20 -> 2 | F28: =SUMIF('[1]Unit Mix'!$V$7:$V$21,D28,'[1]Unit Mix'!$AA$7:$AA$21) -> #VALUE! | G28: =IF(OR(F28=0,F28=""),0,SUMIF('[1]Unit Mix'!$V$7:$V$21,D28,'[1]Unit Mix'!$X$7:$X$21)) -> #VALUE! | H28: =G28*F28 -> #VALUE! | I28: =IFERROR(HLOOKUP(C28,$K$32:$O$53,4,FALSE),"N/A") -> 149 | J28: =IF(F28=0,0,SUMIF('[1]Unit Mix'!$V$7:$V$21,D28,'[1]Unit Mix'!$Z$7:$Z$21)) -> #VALUE! | K28: =IFERROR(IF(F28=0,"",F28*J28),0) -> 0 | L28: =IF(F28=0,"",IFERROR(J28/G28,0)) -> #VALUE! | M28: =IF($F28=0,"",((J28+SUMIF($E$43:$H$43,$C28,$E$53:$H$53))*12)/0.3) -> #VALUE! | N28: =IF(F28=0,"",M28/2080) -> #VALUE! | P28: =IF(F28=0,"",M28*(F28/TtlUnits)) -> #VALUE! | Q28: =D9 -> D | R28: =IFERROR(($A$6*(F9/(SUMIF('[1]Unit Mix'!$C$5:$Q$5,Q28,'[1]Unit Mix'!$C$7:$Q$7)-F25)))+($A$14*(F17/(SUMIF('[1]Unit Mix'!$C$5:$Q$5,Q28,'[1]Unit Mix'!$C$7:$Q$7)-F25))),"N/A") -> N/A
A29: =A28 -> 1 | C29: =IFERROR(VLOOKUP(D29,'[1]Unit Mix'!$V$7:$W$21,2,FALSE),0) -> 1 | D29: =D21 -> H | E29: =E21 -> 1 | F29: =SUMIF('[1]Unit Mix'!$V$7:$V$21,D29,'[1]Unit Mix'!$AA$7:$AA$21) -> #VALUE! | G29: =IF(OR(F29=0,F29=""),0,SUMIF('[1]Unit Mix'!$V$7:$V$21,D29,'[1]Unit Mix'!$X$7:$X$21)) -> #VALUE! | H29: =G29*F29 -> #VALUE! | I29: =IFERROR(HLOOKUP(C29,$K$32:$O$53,4,FALSE),"N/A") -> 322 | J29: =IF(F29=0,0,SUMIF('[1]Unit Mix'!$V$7:$V$21,D29,'[1]Unit Mix'!$Z$7:$Z$21)) -> #VALUE! | K29: =IFERROR(IF(F29=0,"",F29*J29),0) -> 0 | L29: =IF(F29=0,"",IFERROR(J29/G29,0)) -> #VALUE! | M29: =IF($F29=0,"",((J29+SUMIF($E$43:$H$43,$C29,$E$53:$H$53))*12)/0.3) -> #VALUE! | N29: =IF(F29=0,"",M29/2080) -> #VALUE! | P29: =IF(F29=0,"",M29*(F29/TtlUnits)) -> #VALUE! | Q29: =D10 -> E | R29: =IFERROR(($A$6*(F10/(SUMIF('[1]Unit Mix'!$C$5:$Q$5,Q29,'[1]Unit Mix'!$C$7:$Q$7)-F26)))+($A$14*(F18/(SUMIF('[1]Unit Mix'!$C$5:$Q$5,Q29,'[1]Unit Mix'!$C$7:$Q$7)-F26))),"N/A") -> N/A
E30: Totals | F30: =SUM(F6:F29) -> #VALUE! | H30: =SUM(H6:H29) -> #VALUE! | K30: =SUM(K6:K29) -> 81900 | M30: =SUM(P6:P29) -> #VALUE! | N30: Average Income | Q30: =D11 -> F | R30: =IFERROR(($A$6*(F11/(SUMIF('[1]Unit Mix'!$C$5:$Q$5,Q30,'[1]Unit Mix'!$C$7:$Q$7)-F27)))+($A$14*(F19/(SUMIF('[1]Unit Mix'!$C$5:$Q$5,Q30,'[1]Unit Mix'!$C$7:$Q$7)-F27))),"N/A") -> N/A
Q31: =D12 -> G | R31: =IFERROR(($A$6*(F12/(SUMIF('[1]Unit Mix'!$C$5:$Q$5,Q31,'[1]Unit Mix'!$C$7:$Q$7)-F28)))+($A$14*(F20/(SUMIF('[1]Unit Mix'!$C$5:$Q$5,Q31,'[1]Unit Mix'!$C$7:$Q$7)-F28))),"N/A") -> N/A
B32: 1 | C32: =B32+1 -> 2 | D32: =C32+1 -> 3 | E32: =D32+1 -> 4 | F32: =E32+1 -> 5 | G32: =F32+1 -> 6 | K32: =D43 -> 0 | L32: =E43 -> 1 | M32: =F43 -> 2 | N32: =G43 -> 3 | O32: =H43 -> 4 | Q32: =D13 -> H | R32: =IFERROR(($A$6*(F13/(SUMIF('[1]Unit Mix'!$C$5:$Q$5,Q32,'[1]Unit Mix'!$C$7:$Q$7)-F29)))+($A$14*(F21/(SUMIF('[1]Unit Mix'!$C$5:$Q$5,Q32,'[1]Unit Mix'!$C$7:$Q$7)-F29))),"N/A") -> N/A
A33: 0.3 | B33: =ROUNDDOWN(B$35*($A33/$A$35),-1) -> 19890 | C33: =ROUNDDOWN(C$35*($A33/$A$35),-1) -> 22710 | D33: =ROUNDDOWN(D$35*($A33/$A$35),-1) -> 25560 | E33: =ROUNDDOWN(E$35*($A33/$A$35),-1) -> 28380 | F33: =ROUNDDOWN(F$35*($A33/$A$35),-1) -> 30660 | G33: =ROUNDDOWN(G$35*($A33/$A$35),-1) -> 32940 | J33: Utilities | K33: =-D53 -> 0 | L33: =-'Income (2)'!E53 -> -210 | M33: =-'Income (2)'!F53 -> -279 | N33: =-'Income (2)'!G53 -> -349 | O33: =-'Income (2)'!H53 -> 0
A34: 0.4 | B34: =ROUNDDOWN(B$35*($A34/$A$35),-1) -> 26520 | C34: =ROUNDDOWN(C$35*($A34/$A$35),-1) -> 30280 | D34: =ROUNDDOWN(D$35*($A34/$A$35),-1) -> 34080 | E34: =ROUNDDOWN(E$35*($A34/$A$35),-1) -> 37840 | F34: =ROUNDDOWN(F$35*($A34/$A$35),-1) -> 40880 | G34: =ROUNDDOWN(G$35*($A34/$A$35),-1) -> 43920 | J34: =A33 -> 0.3 | K34: =ROUNDDOWN(SUM('Income (2)'!B33)*0.3/12,0) -> 497 | L34: =ROUNDDOWN(SUM('Income (2)'!B33:C33)/2*0.3/12,0) -> 532 | M34: =ROUNDDOWN(SUM('Income (2)'!D33)*0.3/12,0)*0+428 -> 428 | N34: =ROUNDDOWN(SUM('Income (2)'!E33:F33)/2*0.3/12,0)*0+494 -> 494 | O34: =ROUNDDOWN(SUM('Income (2)'!G33)*0.3/12,0) -> 823 | Q34: Per BR Type Income Averaging
A35: 0.5 | B35: 33150 | C35: 37850 | D35: 42600 | E35: 47300 | F35: 51100 | G35: 54900 | J35: Max Rent | K35: =K34+K$33 -> 497 | L35: =L34+L$33 -> 322 | M35: =M34+M$33 -> 149 | N35: =N34+N$33 -> 145 | O35: =O34+O$33 -> 823 | Q35: 1 | R35: =((F6+F13)*$A$6)/SUMIF($C$6:$C$21,$Q$35,$F$6:$F$21)+((F14+F21)*$A$14)/SUMIF($C$6:$C$21,$Q$35,$F$6:$F$21) -> 0.56315789
A36: 0.6 | B36: =ROUNDDOWN(B$35*($A36/$A$35),-1) -> 39780 | C36: =ROUNDDOWN(C$35*($A36/$A$35),-1) -> 45420 | D36: =ROUNDDOWN(D$35*($A36/$A$35),-1) -> 51120 | E36: =ROUNDDOWN(E$35*($A36/$A$35),-1) -> 56760 | F36: =ROUNDDOWN(F$35*($A36/$A$35),-1) -> 61320 | G36: =ROUNDDOWN(G$35*($A36/$A$35),-1) -> 65880 | J36: =A34 -> 0.4 | K36: =ROUNDDOWN(SUM('Income (2)'!B34)*0.3/12,0) -> 663 | L36: =ROUNDDOWN(SUM('Income (2)'!B34:C34)/2*0.3/12,0) -> 710 | M36: =ROUNDDOWN(SUM('Income (2)'!D34)*0.3/12,0) -> 852 | N36: =ROUNDDOWN(SUM('Income (2)'!E34:F34)/2*0.3/12,0) -> 984 | O36: =ROUNDDOWN(SUM('Income (2)'!G34)*0.3/12,0) -> 1098 | Q36: 2 | R36: =((F7+F12)*$A$6)/SUMIF($C$6:$C$21,$Q$36,$F$6:$F$21)+((F15+F20)*$A$14)/SUMIF($C$6:$C$21,$Q$36,$F$6:$F$21) -> 0.564
A37: 0.7 | B37: =ROUNDDOWN(B$35*($A37/$A$35),-1) -> 46410 | C37: =ROUNDDOWN(C$35*($A37/$A$35),-1) -> 52990 | D37: =ROUNDDOWN(D$35*($A37/$A$35),-1) -> 59640 | E37: =ROUNDDOWN(E$35*($A37/$A$35),-1) -> 66220 | F37: =ROUNDDOWN(F$35*($A37/$A$35),-1) -> 71540 | G37: =ROUNDDOWN(G$35*($A37/$A$35),-1) -> 76860 | J37: Max Rent | K37: =K36+K$33 -> 663 | L37: =L36+L$33 -> 500 | M37: =M36+M$33 -> 573 | N37: =N36+N$33 -> 635 | O37: =O36+O$33 -> 1098 | Q37: 3 | R37: =((F8+F11)*$A$6)/SUMIF($C$6:$C$21,$Q$37,$F$6:$F$21)+((F16+F19)*$A$14)/SUMIF($C$6:$C$21,$Q$37,$F$6:$F$21) -> 0.56666667
A38: 0.8 | B38: =ROUNDDOWN(B$35*($A38/$A$35),-1) -> 53040 | C38: =ROUNDDOWN(C$35*($A38/$A$35),-1) -> 60560 | D38: =ROUNDDOWN(D$35*($A38/$A$35),-1) -> 68160 | E38: =ROUNDDOWN(E$35*($A38/$A$35),-1) -> 75680 | F38: =ROUNDDOWN(F$35*($A38/$A$35),-1) -> 81760 | G38: =ROUNDDOWN(G$35*($A38/$A$35),-1) -> 87840 | J38: =A35 -> 0.5 | K38: =ROUNDDOWN(SUM('Income (2)'!B35)*0.3/12,0) -> 828 | L38: =ROUNDDOWN(SUM('Income (2)'!B35:C35)/2*0.3/12,0) -> 887 | M38: =ROUNDDOWN(SUM('Income (2)'!D35)*0.3/12,0) -> 1065 | N38: =ROUNDDOWN(SUM('Income (2)'!E35:F35)/2*0.3/12,0) -> 1230 | O38: =ROUNDDOWN(SUM('Income (2)'!G35)*0.3/12,0) -> 1372 | Q38: 4 | R38: =((F9+F10)*$A$6)/SUMIF($C$6:$C$21,$Q$38,$F$6:$F$21)+((F17+F18)*$A$14)/SUMIF($C$6:$C$21,$Q$38,$F$6:$F$21) -> 0.57142857
A39: 1 | B39: =ROUNDDOWN(B$35*($A39/$A$35),-1) -> 66300 | C39: =ROUNDDOWN(C$35*($A39/$A$35),-1) -> 75700 | D39: =ROUNDDOWN(D$35*($A39/$A$35),-1) -> 85200 | E39: =ROUNDDOWN(E$35*($A39/$A$35),-1) -> 94600 | F39: =ROUNDDOWN(F$35*($A39/$A$35),-1) -> 102200 | G39: =ROUNDDOWN(G$35*($A39/$A$35),-1) -> 109800 | J39: Max Rent | K39: =K38+K$33 -> 828 | L39: =L38+L$33 -> 677 | M39: =M38+M$33 -> 786 | N39: =N38+N$33 -> 881 | O39: =O38+O$33 -> 1372
J40: =A36 -> 0.6 | K40: =ROUNDDOWN(SUM('Income (2)'!B36)*0.3/12,0) -> 994 | L40: =ROUNDDOWN(SUM('Income (2)'!B36:C36)/2*0.3/12,0) -> 1065 | M40: =ROUNDDOWN(SUM('Income (2)'!D36)*0.3/12,0) -> 1278 | N40: =ROUNDDOWN(SUM('Income (2)'!E36:F36)/2*0.3/12,0) -> 1476 | O40: =ROUNDDOWN(SUM('Income (2)'!G36)*0.3/12,0) -> 1647
G41: Building: | H41: LowRise | J41: Max Rent | K41: =K40+K$33 -> 994 | L41: =L40+L$33 -> 855 | M41: =M40+M$33 -> 999 | N41: =N40+N$33 -> 1127 | O41: =O40+O$33 -> 1647
A42: Utility Allowances | C42: Houston Housing Authority | G42: Effective: | H42: 45658 | J42: =A37 -> 0.7 | K42: =ROUNDDOWN(SUM('Income (2)'!B37)*0.3/12,0) -> 1160 | L42: =ROUNDDOWN(SUM('Income (2)'!B37:C37)/2*0.3/12,0) -> 1242 | M42: =ROUNDDOWN(SUM('Income (2)'!D37)*0.3/12,0) -> 1491 | N42: =ROUNDDOWN(SUM('Income (2)'!E37:F37)/2*0.3/12,0) -> 1722 | O42: =ROUNDDOWN(SUM('Income (2)'!G37)*0.3/12,0) -> 1921
A43: Use | C43: Tenant Pd? | D43: 0 | E43: 1 | F43: =E43+1 -> 2 | G43: =F43+1 -> 3 | H43: =G43+1 -> 4 | J43: Max Rent | K43: =K42+K$33 -> 1160 | L43: =L42+L$33 -> 1032 | M43: =M42+M$33 -> 1212 | N43: =N42+N$33 -> 1373 | O43: =O42+O$33 -> 1921
A44: Heating - Electric | C44: Y | E44: 19 | F44: 22 | G44: 26 | J44: =A38 -> 0.8 | K44: =ROUNDDOWN(SUM('Income (2)'!B38)*0.3/12,0) -> 1326 | L44: =ROUNDDOWN(SUM('Income (2)'!B38:C38)/2*0.3/12,0) -> 1420 | M44: =ROUNDDOWN(SUM('Income (2)'!D38)*0.3/12,0) -> 1704 | N44: =ROUNDDOWN(SUM('Income (2)'!E38:F38)/2*0.3/12,0) -> 1968 | O44: =ROUNDDOWN(SUM('Income (2)'!G38)*0.3/12,0) -> 2196
A45: Cooking - Electric | C45: Y | E45: 11 | F45: 16 | G45: 21 | J45: Max Rent | K45: =K44+K$33 -> 1326 | L45: =L44+L$33 -> 1210 | M45: =M44+M$33 -> 1425 | N45: =N44+N$33 -> 1619 | O45: =O44+O$33 -> 2196
A46: Other: | B46: Electric | C46: Y | E46: 43 | F46: 59 | G46: 76 | J46: =A39 -> 1 | K46: =ROUNDDOWN(SUM('Income (2)'!B39)*0.3/12,0) -> 1657 | L46: =ROUNDDOWN(SUM('Income (2)'!B39:C39)/2*0.3/12,0) -> 1775 | M46: =ROUNDDOWN(SUM('Income (2)'!D39)*0.3/12,0) -> 2130 | N46: =ROUNDDOWN(SUM('Income (2)'!E39:F39)/2*0.3/12,0) -> 2460 | O46: =ROUNDDOWN(SUM('Income (2)'!G39)*0.3/12,0) -> 2745
A47: Other: | B47: A/C | C47: Y | E47: 38 | F47: 53 | G47: 68 | J47: Max Rent | K47: =K46+K$33 -> 1657 | L47: =L46+L$33 -> 1565 | M47: =M46+M$33 -> 1851 | N47: =N46+N$33 -> 2111 | O47: =O46+O$33 -> 2745
A48: Hot Water - Electric | C48: Y | E48: 25 | F48: 32 | G48: 39 | J48: FMR
A49: Water | C49: Y | E49: 30 | F49: 40 | G49: 49 | J49: =J37 -> Max Rent | K49: =IF(K48=0,"",K48+K$33) | L49: =IF(L48=0,"",L48+L$33) | M49: =IF(M48=0,"",M48+M$33) | N49: =IF(N48=0,"",N48+N$33) | O49: =IF(O48=0,"",O48+O$33)
A50: Sewer | C50: Y | E50: 44 | F50: 57 | G50: 70 | J50: Low HOME
A51: Trash Collection | C51: N | J51: =J39 -> Max Rent | K51: =IF(K50=0,"",K50+K$33) | L51: =IF(L50=0,"",L50+L$33) | M51: =IF(M50=0,"",M50+M$33) | N51: =IF(N50=0,"",N50+N$33) | O51: =IF(O50=0,"",O50+O$33)
A52: Other: | E52: 15 | F52: 15 | G52: 15 | J52: High HOME
C53: Sum "Y" = | D53: =ROUNDUP(SUMIF($C$44:$C$52,"Y",D44:D52),0) -> 0 | E53: =ROUNDUP(SUMIF($C$44:$C$52,"Y",E44:E52),0) -> 210 | F53: =ROUNDUP(SUMIF($C$44:$C$52,"Y",F44:F52),0) -> 279 | G53: =ROUNDUP(SUMIF($C$44:$C$52,"Y",G44:G52),0) -> 349 | H53: =ROUNDUP(SUMIF($C$44:$C$52,"Y",H44:H52),0) -> 0 | J53: =J41 -> Max Rent | K53: =IF(K52=0,"",K52+K$33) | L53: =IF(L52=0,"",L52+L$33) | M53: =IF(M52=0,"",M52+M$33) | N53: =IF(N52=0,"",N52+N$33) | O53: =IF(O52=0,"",O52+O$33)

Sheet Income
A1: ='Summary Sources-Uses'!A2 -> Project Name
A2: Unit Mix Set-Asides, County AMI and Rent Limits, and Utility Allowances
M3: Average Income Targeting: | N3: =A6*B6/SUM(B6,B14)+A14*B14/SUM(B6,B14) -> 0.56507937 | Q3: Stabilized Net Operating Income
A4: AMI Set-Asides | B4: Targeted / | C4: Unit Style | F4: Number | G4: Net | H4: Total | I4: Max Net | J4: Net Rent | K4: Total | L4: Rent | M4: Min BR | N4: Hourly | V4: Rent
B5: Actual | C5: BR | D5: Type | E5: BA | F5: of Units | G5: Area | H5: SqFt | I5: Rent | J5: p/Unit | K5: Rent/Mo | L5: p/SqFt | M5: Income | N5: Wages | Q5: Rental Inc. | R5: =GrossRentIncomeY1 -> 3724992 | U5: Market | V5: Advantage | W5: % RA
A6: 0.5 | B6: =SUM(F6:F13)/TtlUnits -> 0.275 | C6: 1 | D6: A | E6: 1 | F6: 6 | G6: 0 | H6: =G6*F6 -> 0 | I6: =IFERROR(IF(F6=0,0,HLOOKUP(C6,$K$32:$O$53,8,FALSE)),0) -> 662 | J6: 715 | K6: =IFERROR(IF(F6=0,"",F6*J6),0) -> 4290 | L6: =IF(F6=0,"",IFERROR(J6/G6,0)) -> 0 | M6: =IF($F6=0,"",((J6+SUMIF($E$43:$H$43,$C6,$E$53:$H$53))*12)/0.3) -> 37600 | N6: =IF(F6=0,"",M6/2080) -> 18.076923 | O6: =Tenancy -> Family | P6: =IF(F6=0,"",M6*(F6/TtlUnits)) -> 2820 | Q6: Garage/Comm. | R6: ='Rent Schedule'!K36 -> 100 | U6: 1319 | V6: =U6-J6 -> 604 | W6: =V6/U6 -> 0.45792267
A7: LIHTC | C7: 2 | D7: B | E7: =IF(OR(LEFT(D7,1)="0",LEFT(D7,1)="1"),1,2) -> 2 | F7: 8 | G7: 0 | H7: =G7*F7 -> 0 | I7: =IFERROR(IF(F7=0,0,HLOOKUP(C7,$K$32:$O$53,8,FALSE)),0) -> 771 | J7: 855 | K7: =IFERROR(IF(F7=0,"",F7*J7),0) -> 6840 | L7: =IF(F7=0,"",IFERROR(J7/G7,0)) -> 0 | M7: =IF($F7=0,"",((J7+SUMIF($E$43:$H$43,$C7,$E$53:$H$53))*12)/0.3) -> 45960 | N7: =IF(F7=0,"",M7/2080) -> 22.096154 | P7: =IF(F7=0,"",M7*(F7/TtlUnits)) -> 4596 | Q7: Other Inc. | R7: =AddRevY1 -> 31824 | U7: 1438 | V7: =U7-J7 -> 583 | W7: =V7/U7 -> 0.4054242
A8: =A7 -> LIHTC | C8: 3 | D8: C | E8: =IF(OR(LEFT(D8,1)="0",LEFT(D8,1)="1"),1,2) -> 2 | F8: 3 | G8: 0 | H8: =G8*F8 -> 0 | I8: =IFERROR(IF(F8=0,0,HLOOKUP(C8,$K$32:$O$53,8,FALSE)),0) -> 866 | J8: 975 | K8: =IFERROR(IF(F8=0,"",F8*J8),0) -> 2925 | L8: =IF(F8=0,"",IFERROR(J8/G8,0)) -> 0 | M8: =IF($F8=0,"",((J8+SUMIF($E$43:$H$43,$C8,$E$53:$H$53))*12)/0.3) -> 53560 | N8: =IF(F8=0,"",M8/2080) -> 25.75 | P8: =IF(F8=0,"",M8*(F8/TtlUnits)) -> 2008.5 | Q8: Gross Potential | R8: =SUM(R5:R7) -> 3756916 | U8: 1758 | V8: =U8-J8 -> 783 | W8: =V8/U8 -> 0.44539249
A9: =A5 -> 0 | C9: 4 | D9: D | E9: =IF(OR(LEFT(D9,1)="0",LEFT(D9,1)="1"),1,2) -> 2 | F9: 1 | G9: 0 | H9: =G9*F9 -> 0 | I9: =IFERROR(IF(F9=0,0,HLOOKUP(C9,$K$32:$O$53,8,FALSE)),0) -> 1372 | J9: 1075 | K9: =IFERROR(IF(F9=0,"",F9*J9),0) -> 1075 | L9: =IF(F9=0,"",IFERROR(J9/G9,0)) -> 0 | M9: =IF($F9=0,"",((J9+SUMIF($E$43:$H$43,$C9,$E$53:$H$53))*12)/0.3) -> 43000 | N9: =IF(F9=0,"",M9/2080) -> 20.673077 | P9: =IF(F9=0,"",M9*(F9/TtlUnits)) -> 537.5 | Q9: Vacancy | R9: =-R8*Vacancy -> -262984.12 | U9: 1869 | V9: =U9-J9 -> 794 | W9: =V9/U9 -> 0.42482611
A10: =A6 -> 0.5 | C10: 4 | D10: E | E10: =IF(OR(LEFT(D10,1)="0",LEFT(D10,1)="1"),1,2) -> 2 | F10: 1 | G10: 0 | H10: =G10*F10 -> 0 | I10: =IFERROR(IF(F10=0,0,HLOOKUP(C10,$K$32:$O$53,8,FALSE)),0) -> 1372 | J10: 1075 | K10: =IFERROR(IF(F10=0,"",F10*J10),0) -> 1075 | L10: =IF(F10=0,"",IFERROR(J10/G10,0)) -> 0 | M10: =IF($F10=0,"",((J10+SUMIF($E$43:$H$43,$C10,$E$53:$H$53))*12)/0.3) -> 43000 | N10: =IF(F10=0,"",M10/2080) -> 20.673077 | P10: =IF(F10=0,"",M10*(F10/TtlUnits)) -> 537.5 | Q10: Effective Gross | R10: =SUM(R8:R9) -> 3493931.9 | U10: 1869 | V10: =U10-J10 -> 794 | W10: =V10/U10 -> 0.42482611
A11: =A7 -> LIHTC | C11: 3 | D11: F | E11: =IF(OR(LEFT(D11,1)="0",LEFT(D11,1)="1"),1,2) -> 2 | F11: 1 | G11: 0 | H11: =G11*F11 -> 0 | I11: =IFERROR(IF(F11=0,0,HLOOKUP(C11,$K$32:$O$53,8,FALSE)),0) -> 866 | J11: 975 | K11: =IFERROR(IF(F11=0,"",F11*J11),0) -> 975 | L11: =IF(F11=0,"",IFERROR(J11/G11,0)) -> 0 | M11: =IF($F11=0,"",((J11+SUMIF($E$43:$H$43,$C11,$E$53:$H$53))*12)/0.3) -> 53560 | N11: =IF(F11=0,"",M11/2080) -> 25.75 | P11: =IF(F11=0,"",M11*(F11/TtlUnits)) -> 669.5 | Q11: Net OpEx | R11: =-ExpTotalY1 -> -1915198.2 | U11: 1758 | V11: =U11-J11 -> 783 | W11: =V11/U11 -> 0.44539249
A12: =A8 -> LIHTC | C12: 2 | D12: G | E12: =IF(OR(LEFT(D12,1)="0",LEFT(D12,1)="1"),1,2) -> 2 | F12: 1 | G12: 0 | H12: =G12*F12 -> 0 | I12: =IFERROR(IF(F12=0,0,HLOOKUP(C12,$K$32:$O$53,8,FALSE)),0) -> 771 | J12: 855 | K12: =IFERROR(IF(F12=0,"",F12*J12),0) -> 855 | L12: =IF(F12=0,"",IFERROR(J12/G12,0)) -> 0 | M12: =IF($F12=0,"",((J12+SUMIF($E$43:$H$43,$C12,$E$53:$H$53))*12)/0.3) -> 45960 | N12: =IF(F12=0,"",M12/2080) -> 22.096154 | P12: =IF(F12=0,"",M12*(F12/TtlUnits)) -> 574.5 | Q12: 1 | R12: 0 | U12: 1438 | V12: =U12-J12 -> 583 | W12: =V12/U12 -> 0.4054242
A13: =A12 -> LIHTC | C13: 1 | D13: H | E13: 1 | F13: 1 | G13: 0 | H13: =G13*F13 -> 0 | I13: =IFERROR(IF(F13=0,0,HLOOKUP(C13,$K$32:$O$53,8,FALSE)),0) -> 662 | J13: 715 | K13: =IFERROR(IF(F13=0,"",F13*J13),0) -> 715 | L13: =IF(F13=0,"",IFERROR(J13/G13,0)) -> 0 | M13: =IF($F13=0,"",((J13+SUMIF($E$43:$H$43,$C13,$E$53:$H$53))*12)/0.3) -> 37600 | N13: =IF(F13=0,"",M13/2080) -> 18.076923 | P13: =IF(F13=0,"",M13*(F13/TtlUnits)) -> 470 | Q13: Repl. Res. | R13: =-'Operating Expense'!E21 -> -66300 | U13: 1319 | V13: =U13-J13 -> 604 | W13: =V13/U13 -> 0.45792267
A14: 0.6 | B14: =SUM(F14:F21)/TtlUnits -> 0.5125 | C14: 1 | D14: =D6 -> A | E14: =E6 -> 1 | F14: 12 | G14: 0 | H14: =G14*F14 -> 0 | I14: =IFERROR(IF(F14=0,0,HLOOKUP(C14,$K$32:$O$53,10,FALSE)),0) -> 840 | J14: 850 | K14: =IFERROR(IF(F14=0,"",F14*J14),0) -> 10200 | L14: =IF(F14=0,"",IFERROR(J14/G14,0)) -> 0 | M14: =IF($F14=0,"",((J14+SUMIF($E$43:$H$43,$C14,$E$53:$H$53))*12)/0.3) -> 43000 | N14: =IF(F14=0,"",M14/2080) -> 20.673077 | O14: =Tenancy -> Family | P14: =IF(F14=0,"",M14*(F14/TtlUnits)) -> 6450 | Q14: Total OpEx | R14: =SUM(R11:R13) -> -1981498.2 | U14: 1319 | V14: =U14-J14 -> 469 | W14: =V14/U14 -> 0.3555724
A15: LIHTC | C15: 2 | D15: =D7 -> B | E15: =E7 -> 2 | F15: 16 | G15: 0 | H15: =G15*F15 -> 0 | I15: =IFERROR(IF(F15=0,0,HLOOKUP(C15,$K$32:$O$53,10,FALSE)),0) -> 984 | J15: 1000 | K15: =IFERROR(IF(F15=0,"",F15*J15),0) -> 16000 | L15: =IF(F15=0,"",IFERROR(J15/G15,0)) -> 0 | M15: =IF($F15=0,"",((J15+SUMIF($E$43:$H$43,$C15,$E$53:$H$53))*12)/0.3) -> 51760 | N15: =IF(F15=0,"",M15/2080) -> 24.884615 | P15: =IF(F15=0,"",M15*(F15/TtlUnits)) -> 10352 | Q15: Net Oper. Inc. | R15: =R10+R14 -> 1512433.7 | U15: 1438 | V15: =U15-J15 -> 438 | W15: =V15/U15 -> 0.30458971
A16: =A15 -> LIHTC | C16: 3 | D16: =D8 -> C | E16: =E8 -> 2 | F16: 8 | G16: 0 | H16: =G16*F16 -> 0 | I16: =IFERROR(IF(F16=0,0,HLOOKUP(C16,$K$32:$O$53,10,FALSE)),0) -> 1112 | J16: 1100 | K16: =IFERROR(IF(F16=0,"",F16*J16),0) -> 8800 | L16: =IF(F16=0,"",IFERROR(J16/G16,0)) -> 0 | M16: =IF($F16=0,"",((J16+SUMIF($E$43:$H$43,$C16,$E$53:$H$53))*12)/0.3) -> 58560 | N16: =IF(F16=0,"",M16/2080) -> 28.153846 | P16: =IF(F16=0,"",M16*(F16/TtlUnits)) -> 5856 | R16: =R15-NOI -> 0 | U16: 1758 | V16: =U16-J16 -> 658 | W16: =V16/U16 -> 0.37428896
A17: =A13 -> LIHTC | C17: 4 | D17: =D9 -> D | E17: =E9 -> 2 | F17: 5 | G17: 0 | H17: =G17*F17 -> 0 | I17: =IFERROR(IF(F17=0,0,HLOOKUP(C17,$K$32:$O$53,10,FALSE)),0) -> 1647 | J17: 1200 | K17: =IFERROR(IF(F17=0,"",F17*J17),0) -> 6000 | L17: =IF(F17=0,"",IFERROR(J17/G17,0)) -> 0 | M17: =IF($F17=0,"",((J17+SUMIF($E$43:$H$43,$C17,$E$53:$H$53))*12)/0.3) -> 48000 | N17: =IF(F17=0,"",M17/2080) -> 23.076923 | P17: =IF(F17=0,"",M17*(F17/TtlUnits)) -> 3000 | U17: 1869 | V17: =U17-J17 -> 669 | W17: =V17/U17 -> 0.35794543
A18: =A14 -> 0.6 | C18: 4 | D18: =D10 -> E | E18: =E10 -> 2 | F18: 0 | G18: 0 | H18: =G18*F18 -> 0 | I18: =IFERROR(IF(F18=0,0,HLOOKUP(C18,$K$32:$O$53,10,FALSE)),0) -> 0 | K18: =IFERROR(IF(F18=0,"",F18*J18),0) | L18: =IF(F18=0,"",IFERROR(J18/G18,0)) | M18: =IF($F18=0,"",((J18+SUMIF($E$43:$H$43,$C18,$E$53:$H$53))*12)/0.3) | N18: =IF(F18=0,"",M18/2080) | P18: =IF(F18=0,"",M18*(F18/TtlUnits))
A19: =A15 -> LIHTC | C19: 3 | D19: =D11 -> F | E19: =E11 -> 2 | G19: 0 | H19: =G19*F19 -> 0 | I19: =IFERROR(IF(F19=0,0,HLOOKUP(C19,$K$32:$O$53,10,FALSE)),0) -> 0 | K19: =IFERROR(IF(F19=0,"",F19*J19),0) | L19: =IF(F19=0,"",IFERROR(J19/G19,0)) | M19: =IF($F19=0,"",((J19+SUMIF($E$43:$H$43,$C19,$E$53:$H$53))*12)/0.3) | N19: =IF(F19=0,"",M19/2080) | P19: =IF(F19=0,"",M19*(F19/TtlUnits))
A20: =A16 -> LIHTC | C20: 2 | D20: =D12 -> G | E20: =E12 -> 2 | G20: 0 | H20: =G20*F20 -> 0 | I20: =IFERROR(IF(F20=0,0,HLOOKUP(C20,$K$32:$O$53,10,FALSE)),0) -> 0 | K20: =IFERROR(IF(F20=0,"",F20*J20),0) | L20: =IF(F20=0,"",IFERROR(J20/G20,0)) | M20: =IF($F20=0,"",((J20+SUMIF($E$43:$H$43,$C20,$E$53:$H$53))*12)/0.3) | N20: =IF(F20=0,"",M20/2080) | P20: =IF(F20=0,"",M20*(F20/TtlUnits)) | Q20: NNMMI | R20: 52400
A21: =A20 -> LIHTC | C21: 1 | D21: =D13 -> H | E21: =E13 -> 1 | G21: 0 | H21: =G21*F21 -> 0 | I21: =IFERROR(IF(F21=0,0,HLOOKUP(C21,$K$32:$O$53,10,FALSE)),0) -> 0 | K21: =IFERROR(IF(F21=0,"",F21*J21),0) | L21: =IF(F21=0,"",IFERROR(J21/G21,0)) | M21: =IF($F21=0,"",((J21+SUMIF($E$43:$H$43,$C21,$E$53:$H$53))*12)/0.3) | N21: =IF(F21=0,"",M21/2080) | P21: =IF(F21=0,"",M21*(F21/TtlUnits)) | Q21: Houston-The Woolands-Sugar Land
A22: 1 | B22: =SUM(F22:F29)/TtlUnits -> #VALUE! | C22: 1 | D22: =D14 -> A | E22: =E14 -> 1 | F22: 5 | G22: 0 | H22: =G22*F22 -> 0 | I22: =IFERROR(HLOOKUP(C22,$K$32:$O$53,4,FALSE),"N/A") -> 307 | J22: 1175 | K22: =IFERROR(IF(F22=0,"",F22*J22),0) -> 5875 | L22: =IF(F22=0,"",IFERROR(J22/G22,0)) -> 0 | M22: =IF($F22=0,"",((J22+SUMIF($E$43:$H$43,$C22,$E$53:$H$53))*12)/0.3) -> 56000 | N22: =IF(F22=0,"",M22/2080) -> 26.923077 | O22: =Tenancy -> Family | P22: =IF(F22=0,"",M22*(F22/TtlUnits)) -> 3500 | Q22: 82000 | U22: 1319 | V22: =U22-J22 -> 144 | W22: =V22/U22 -> 0.10917362
A23: =A22 -> 1 | C23: 2 | D23: =D15 -> B | E23: =E15 -> 2 | F23: 7 | G23: 0 | H23: =G23*F23 -> 0 | I23: =IFERROR(HLOOKUP(C23,$K$32:$O$53,4,FALSE),"N/A") -> 134 | J23: 1275 | K23: =IFERROR(IF(F23=0,"",F23*J23),0) -> 8925 | L23: =IF(F23=0,"",IFERROR(J23/G23,0)) -> 0 | M23: =IF($F23=0,"",((J23+SUMIF($E$43:$H$43,$C23,$E$53:$H$53))*12)/0.3) -> 62760 | N23: =IF(F23=0,"",M23/2080) -> 30.173077 | P23: =IF(F23=0,"",M23*(F23/TtlUnits)) -> 5491.5 | U23: 1438 | V23: =U23-J23 -> 163 | W23: =V23/U23 -> 0.11335188
A24: =A23 -> 1 | C24: 3 | D24: =D16 -> C | E24: =E16 -> 2 | F24: 4 | G24: 0 | H24: =G24*F24 -> 0 | I24: =IFERROR(HLOOKUP(C24,$K$32:$O$53,4,FALSE),"N/A") -> 130 | J24: 1450 | K24: =IFERROR(IF(F24=0,"",F24*J24),0) -> 5800 | L24: =IF(F24=0,"",IFERROR(J24/G24,0)) -> 0 | M24: =IF($F24=0,"",((J24+SUMIF($E$43:$H$43,$C24,$E$53:$H$53))*12)/0.3) -> 72560 | N24: =IF(F24=0,"",M24/2080) -> 34.884615 | P24: =IF(F24=0,"",M24*(F24/TtlUnits)) -> 3628 | Q24: Per Unit Type Income Averaging | U24: 1758 | V24: =U24-J24 -> 308 | W24: =V24/U24 -> 0.17519909
A25: =A24 -> 1 | C25: 4 | D25: =D17 -> D | E25: =E17 -> 2 | F25: 1 | G25: 0 | H25: =G25*F25 -> 0 | I25: =IFERROR(HLOOKUP(C25,$K$32:$O$53,4,FALSE),"N/A") -> 823 | J25: 1550 | K25: =IFERROR(IF(F25=0,"",F25*J25),0) -> 1550 | L25: =IF(F25=0,"",IFERROR(J25/G25,0)) -> 0 | M25: =IF($F25=0,"",((J25+SUMIF($E$43:$H$43,$C25,$E$53:$H$53))*12)/0.3) -> 62000 | N25: =IF(F25=0,"",M25/2080) -> 29.807692 | P25: =IF(F25=0,"",M25*(F25/TtlUnits)) -> 775 | Q25: =D6 -> A | R25: 0 | S25: 0.56666667 | U25: 1869 | V25: =U25-J25 -> 319 | W25: =V25/U25 -> 0.17067951
A26: =A25 -> 1 | C26: 4 | D26: =D18 -> E | E26: =E18 -> 2 | F26: =SUMIF('[1]Unit Mix'!$V$7:$V$21,D26,'[1]Unit Mix'!$AA$7:$AA$21) -> #VALUE! | G26: 0 | H26: =G26*F26 -> #VALUE! | I26: =IFERROR(HLOOKUP(C26,$K$32:$O$53,4,FALSE),"N/A") -> 823 | J26: =IF(F26=0,0,SUMIF('[1]Unit Mix'!$V$7:$V$21,D26,'[1]Unit Mix'!$Z$7:$Z$21)) -> #VALUE! | K26: =IFERROR(IF(F26=0,"",F26*J26),0) -> 0 | L26: =IF(F26=0,"",IFERROR(J26/G26,0)) -> #VALUE! | M26: =IF($F26=0,"",((J26+SUMIF($E$43:$H$43,$C26,$E$53:$H$53))*12)/0.3) -> #VALUE! | N26: =IF(F26=0,"",M26/2080) -> #VALUE! | P26: =IF(F26=0,"",M26*(F26/TtlUnits)) -> #VALUE! | Q26: =D7 -> B | R26: 0 | S26: 0.56666667
A27: =A26 -> 1 | C27: 3 | D27: =D19 -> F | E27: =E19 -> 2 | F27: =SUMIF('[1]Unit Mix'!$V$7:$V$21,D27,'[1]Unit Mix'!$AA$7:$AA$21) -> #VALUE! | G27: 0 | H27: =G27*F27 -> #VALUE! | I27: =IFERROR(HLOOKUP(C27,$K$32:$O$53,4,FALSE),"N/A") -> 130 | J27: =IF(F27=0,0,SUMIF('[1]Unit Mix'!$V$7:$V$21,D27,'[1]Unit Mix'!$Z$7:$Z$21)) -> #VALUE! | K27: =IFERROR(IF(F27=0,"",F27*J27),0) -> 0 | L27: =IF(F27=0,"",IFERROR(J27/G27,0)) -> #VALUE! | M27: =IF($F27=0,"",((J27+SUMIF($E$43:$H$43,$C27,$E$53:$H$53))*12)/0.3) -> #VALUE! | N27: =IF(F27=0,"",M27/2080) -> #VALUE! | P27: =IF(F27=0,"",M27*(F27/TtlUnits)) -> #VALUE! | Q27: =D8 -> C | R27: 0 | S27: 0.57272727
A28: =A27 -> 1 | C28: 2 | D28: =D20 -> G | E28: =E20 -> 2 | F28: =SUMIF('[1]Unit Mix'!$V$7:$V$21,D28,'[1]Unit Mix'!$AA$7:$AA$21) -> #VALUE! | G28: 0 | H28: =G28*F28 -> #VALUE! | I28: =IFERROR(HLOOKUP(C28,$K$32:$O$53,4,FALSE),"N/A") -> 134 | J28: =IF(F28=0,0,SUMIF('[1]Unit Mix'!$V$7:$V$21,D28,'[1]Unit Mix'!$Z$7:$Z$21)) -> #VALUE! | K28: =IFERROR(IF(F28=0,"",F28*J28),0) -> 0 | L28: =IF(F28=0,"",IFERROR(J28/G28,0)) -> #VALUE! | M28: =IF($F28=0,"",((J28+SUMIF($E$43:$H$43,$C28,$E$53:$H$53))*12)/0.3) -> #VALUE! | N28: =IF(F28=0,"",M28/2080) -> #VALUE! | P28: =IF(F28=0,"",M28*(F28/TtlUnits)) -> #VALUE! | Q28: =D9 -> D | R28: 0 | S28: 0.58333333
A29: =A28 -> 1 | C29: 1 | D29: =D21 -> H | E29: =E21 -> 1 | F29: =SUMIF('[1]Unit Mix'!$V$7:$V$21,D29,'[1]Unit Mix'!$AA$7:$AA$21) -> #VALUE! | G29: 0 | H29: =G29*F29 -> #VALUE! | I29: =IFERROR(HLOOKUP(C29,$K$32:$O$53,4,FALSE),"N/A") -> 307 | J29: =IF(F29=0,0,SUMIF('[1]Unit Mix'!$V$7:$V$21,D29,'[1]Unit Mix'!$Z$7:$Z$21)) -> #VALUE! | K29: =IFERROR(IF(F29=0,"",F29*J29),0) -> 0 | L29: =IF(F29=0,"",IFERROR(J29/G29,0)) -> #VALUE! | M29: =IF($F29=0,"",((J29+SUMIF($E$43:$H$43,$C29,$E$53:$H$53))*12)/0.3) -> #VALUE! | N29: =IF(F29=0,"",M29/2080) -> #VALUE! | P29: =IF(F29=0,"",M29*(F29/TtlUnits)) -> #VALUE! | Q29: =D10 -> E | R29: 0 | S29: 0.5
E30: Totals | F30: =SUM(F6:F29) -> #VALUE! | H30: =SUM(H6:H29) -> #VALUE! | K30: =SUM(K6:K29) -> 81900 | M30: =SUM(P6:P29) -> #VALUE! | N30: Average Income | Q30: =D11 -> F | R30: 0 | S30: 0.5
Q31: =D12 -> G | R31: 0 | S31: 0.5
B32: 1 | C32: =B32+1 -> 2 | D32: =C32+1 -> 3 | E32: =D32+1 -> 4 | F32: =E32+1 -> 5 | G32: =F32+1 -> 6 | K32: =D43 -> 0 | L32: =E43 -> 1 | M32: =F43 -> 2 | N32: =G43 -> 3 | O32: =H43 -> 4 | Q32: =D13 -> H | R32: 0 | S32: 0.5
A33: 0.3 | B33: =ROUNDDOWN(B$35*($A33/$A$35),-1) -> 19890 | C33: =ROUNDDOWN(C$35*($A33/$A$35),-1) -> 22710 | D33: =ROUNDDOWN(D$35*($A33/$A$35),-1) -> 25560 | E33: =ROUNDDOWN(E$35*($A33/$A$35),-1) -> 28380 | F33: =ROUNDDOWN(F$35*($A33/$A$35),-1) -> 30660 | G33: =ROUNDDOWN(G$35*($A33/$A$35),-1) -> 32940 | J33: Utilities | K33: =-D53 -> 0 | L33: =-Income!E53 -> -225 | M33: =-Income!F53 -> -294 | N33: =-Income!G53 -> -364 | O33: =-Income!H53 -> 0
A34: 0.4 | B34: =ROUNDDOWN(B$35*($A34/$A$35),-1) -> 26520 | C34: =ROUNDDOWN(C$35*($A34/$A$35),-1) -> 30280 | D34: =ROUNDDOWN(D$35*($A34/$A$35),-1) -> 34080 | E34: =ROUNDDOWN(E$35*($A34/$A$35),-1) -> 37840 | F34: =ROUNDDOWN(F$35*($A34/$A$35),-1) -> 40880 | G34: =ROUNDDOWN(G$35*($A34/$A$35),-1) -> 43920 | J34: =A33 -> 0.3 | K34: =ROUNDDOWN(SUM(Income!B33)*0.3/12,0) -> 497 | L34: =ROUNDDOWN(SUM(Income!B33:C33)/2*0.3/12,0) -> 532 | M34: =ROUNDDOWN(SUM(Income!D33)*0.3/12,0)*0+428 -> 428 | N34: =ROUNDDOWN(SUM(Income!E33:F33)/2*0.3/12,0)*0+494 -> 494 | O34: =ROUNDDOWN(SUM(Income!G33)*0.3/12,0) -> 823 | Q34: Per BR Type Income Averaging
A35: 0.5 | B35: 33150 | C35: 37850 | D35: 42600 | E35: 47300 | F35: 51100 | G35: 54900 | J35: Max Rent | K35: =K34+K$33 -> 497 | L35: =L34+L$33 -> 307 | M35: =M34+M$33 -> 134 | N35: =N34+N$33 -> 130 | O35: =O34+O$33 -> 823 | Q35: 1 | R35: =((F6+F13)*$A$6)/SUMIF($C$6:$C$21,$Q$35,$F$6:$F$21)+((F14+F21)*$A$14)/SUMIF($C$6:$C$21,$Q$35,$F$6:$F$21) -> 0.56315789
A36: 0.6 | B36: =ROUNDDOWN(B$35*($A36/$A$35),-1) -> 39780 | C36: =ROUNDDOWN(C$35*($A36/$A$35),-1) -> 45420 | D36: =ROUNDDOWN(D$35*($A36/$A$35),-1) -> 51120 | E36: =ROUNDDOWN(E$35*($A36/$A$35),-1) -> 56760 | F36: =ROUNDDOWN(F$35*($A36/$A$35),-1) -> 61320 | G36: =ROUNDDOWN(G$35*($A36/$A$35),-1) -> 65880 | J36: =A34 -> 0.4 | K36: =ROUNDDOWN(SUM(Income!B34)*0.3/12,0) -> 663 | L36: =ROUNDDOWN(SUM(Income!B34:C34)/2*0.3/12,0) -> 710 | M36: =ROUNDDOWN(SUM(Income!D34)*0.3/12,0) -> 852 | N36: =ROUNDDOWN(SUM(Income!E34:F34)/2*0.3/12,0) -> 984 | O36: =ROUNDDOWN(SUM(Income!G34)*0.3/12,0) -> 1098 | Q36: 2 | R36: =((F7+F12)*$A$6)/SUMIF($C$6:$C$21,$Q$36,$F$6:$F$21)+((F15+F20)*$A$14)/SUMIF($C$6:$C$21,$Q$36,$F$6:$F$21) -> 0.564
A37: 0.7 | B37: =ROUNDDOWN(B$35*($A37/$A$35),-1) -> 46410 | C37: =ROUNDDOWN(C$35*($A37/$A$35),-1) -> 52990 | D37: =ROUNDDOWN(D$35*($A37/$A$35),-1) -> 59640 | E37: =ROUNDDOWN(E$35*($A37/$A$35),-1) -> 66220 | F37: =ROUNDDOWN(F$35*($A37/$A$35),-1) -> 71540 | G37: =ROUNDDOWN(G$35*($A37/$A$35),-1) -> 76860 | J37: Max Rent | K37: =K36+K$33 -> 663 | L37: =L36+L$33 -> 485 | M37: =M36+M$33 -> 558 | N37: =N36+N$33 -> 620 | O37: =O36+O$33 -> 1098 | Q37: 3 | R37: =((F8+F11)*$A$6)/SUMIF($C$6:$C$21,$Q$37,$F$6:$F$21)+((F16+F19)*$A$14)/SUMIF($C$6:$C$21,$Q$37,$F$6:$F$21) -> 0.56666667
A38: 0.8 | B38: =ROUNDDOWN(B$35*($A38/$A$35),-1) -> 53040 | C38: =ROUNDDOWN(C$35*($A38/$A$35),-1) -> 60560 | D38: =ROUNDDOWN(D$35*($A38/$A$35),-1) -> 68160 | E38: =ROUNDDOWN(E$35*($A38/$A$35),-1) -> 75680 | F38: =ROUNDDOWN(F$35*($A38/$A$35),-1) -> 81760 | G38: =ROUNDDOWN(G$35*($A38/$A$35),-1) -> 87840 | J38: =A35 -> 0.5 | K38: =ROUNDDOWN(SUM(Income!B35)*0.3/12,0) -> 828 | L38: =ROUNDDOWN(SUM(Income!B35:C35)/2*0.3/12,0) -> 887 | M38: =ROUNDDOWN(SUM(Income!D35)*0.3/12,0) -> 1065 | N38: =ROUNDDOWN(SUM(Income!E35:F35)/2*0.3/12,0) -> 1230 | O38: =ROUNDDOWN(SUM(Income!G35)*0.3/12,0) -> 1372 | Q38: 4 | R38: =((F9+F10)*$A$6)/SUMIF($C$6:$C$21,$Q$38,$F$6:$F$21)+((F17+F18)*$A$14)/SUMIF($C$6:$C$21,$Q$38,$F$6:$F$21) -> 0.57142857
A39: 1 | B39: =ROUNDDOWN(B$35*($A39/$A$35),-1) -> 66300 | C39: =ROUNDDOWN(C$35*($A39/$A$35),-1) -> 75700 | D39: =ROUNDDOWN(D$35*($A39/$A$35),-1) -> 85200 | E39: =ROUNDDOWN(E$35*($A39/$A$35),-1) -> 94600 | F39: =ROUNDDOWN(F$35*($A39/$A$35),-1) -> 102200 | G39: =ROUNDDOWN(G$35*($A39/$A$35),-1) -> 109800 | J39: Max Rent | K39: =K38+K$33 -> 828 | L39: =L38+L$33 -> 662 | M39: =M38+M$33 -> 771 | N39: =N38+N$33 -> 866 | O39: =O38+O$33 -> 1372
J40: =A36 -> 0.6 | K40: =ROUNDDOWN(SUM(Income!B36)*0.3/12,0) -> 994 | L40: =ROUNDDOWN(SUM(Income!B36:C36)/2*0.3/12,0) -> 1065 | M40: =ROUNDDOWN(SUM(Income!D36)*0.3/12,0) -> 1278 | N40: =ROUNDDOWN(SUM(Income!E36:F36)/2*0.3/12,0) -> 1476 | O40: =ROUNDDOWN(SUM(Income!G36)*0.3/12,0) -> 1647
G41: Building: | H41: LowRise | J41: Max Rent | K41: =K40+K$33 -> 994 | L41: =L40+L$33 -> 840 | M41: =M40+M$33 -> 984 | N41: =N40+N$33 -> 1112 | O41: =O40+O$33 -> 1647
A42: Utility Allowances | C42: HHA | G42: Effective: | H42: 44562 | J42: =A37 -> 0.7 | K42: =ROUNDDOWN(SUM(Income!B37)*0.3/12,0) -> 1160 | L42: =ROUNDDOWN(SUM(Income!B37:C37)/2*0.3/12,0) -> 1242 | M42: =ROUNDDOWN(SUM(Income!D37)*0.3/12,0) -> 1491 | N42: =ROUNDDOWN(SUM(Income!E37:F37)/2*0.3/12,0) -> 1722 | O42: =ROUNDDOWN(SUM(Income!G37)*0.3/12,0) -> 1921
A43: Use | C43: Tenant Pd? | D43: 0 | E43: 1 | F43: =E43+1 -> 2 | G43: =F43+1 -> 3 | H43: =G43+1 -> 4 | J43: Max Rent | K43: =K42+K$33 -> 1160 | L43: =L42+L$33 -> 1017 | M43: =M42+M$33 -> 1197 | N43: =N42+N$33 -> 1358 | O43: =O42+O$33 -> 1921
A44: Heating - Electric | C44: Y | E44: 19 | F44: 22 | G44: 26 | J44: =A38 -> 0.8 | K44: =ROUNDDOWN(SUM(Income!B38)*0.3/12,0) -> 1326 | L44: =ROUNDDOWN(SUM(Income!B38:C38)/2*0.3/12,0) -> 1420 | M44: =ROUNDDOWN(SUM(Income!D38)*0.3/12,0) -> 1704 | N44: =ROUNDDOWN(SUM(Income!E38:F38)/2*0.3/12,0) -> 1968 | O44: =ROUNDDOWN(SUM(Income!G38)*0.3/12,0) -> 2196
A45: Cooking - Electric | C45: Y | E45: 11 | F45: 16 | G45: 21 | J45: Max Rent | K45: =K44+K$33 -> 1326 | L45: =L44+L$33 -> 1195 | M45: =M44+M$33 -> 1410 | N45: =N44+N$33 -> 1604 | O45: =O44+O$33 -> 2196
A46: Other: | B46: Electric | C46: Y | E46: 43 | F46: 59 | G46: 76 | J46: =A39 -> 1 | K46: =ROUNDDOWN(SUM(Income!B39)*0.3/12,0) -> 1657 | L46: =ROUNDDOWN(SUM(Income!B39:C39)/2*0.3/12,0) -> 1775 | M46: =ROUNDDOWN(SUM(Income!D39)*0.3/12,0) -> 2130 | N46: =ROUNDDOWN(SUM(Income!E39:F39)/2*0.3/12,0) -> 2460 | O46: =ROUNDDOWN(SUM(Income!G39)*0.3/12,0) -> 2745
A47: Other: | B47: A/C | C47: Y | E47: 38 | F47: 53 | G47: 68 | J47: Max Rent | K47: =K46+K$33 -> 1657 | L47: =L46+L$33 -> 1550 | M47: =M46+M$33 -> 1836 | N47: =N46+N$33 -> 2096 | O47: =O46+O$33 -> 2745
A48: Hot Water - Electric | C48: Y | E48: 25 | F48: 32 | G48: 39 | J48: FMR | K48: 0 | L48: 0 | M48: 0 | N48: 0 | O48: 0
A49: Water | C49: Y | E49: 30 | F49: 40 | G49: 49 | J49: =J37 -> Max Rent | K49: =IF(K48=0,"",K48+K$33) | L49: =IF(L48=0,"",L48+L$33) | M49: =IF(M48=0,"",M48+M$33) | N49: =IF(N48=0,"",N48+N$33) | O49: =IF(O48=0,"",O48+O$33)
A50: Sewer | C50: Y | E50: 44 | F50: 57 | G50: 70 | J50: Low HOME | K50: 0 | L50: 0 | M50: 0 | N50: 0 | O50: 0
A51: Trash Collection | C51: N | J51: =J39 -> Max Rent | K51: =IF(K50=0,"",K50+K$33) | L51: =IF(L50=0,"",L50+L$33) | M51: =IF(M50=0,"",M50+M$33) | N51: =IF(N50=0,"",N50+N$33) | O51: =IF(O50=0,"",O50+O$33)
A52: Other: | C52: Y | E52: 15 | F52: 15 | G52: 15 | J52: High HOME | K52: 0 | L52: 0 | M52: 0 | N52: 0 | O52: 0
C53: Sum "Y" = | D53: =ROUNDUP(SUMIF($C$44:$C$52,"Y",D44:D52),0) -> 0 | E53: =ROUNDUP(SUMIF($C$44:$C$52,"Y",E44:E52),0) -> 225 | F53: =ROUNDUP(SUMIF($C$44:$C$52,"Y",F44:F52),0) -> 294 | G53: =ROUNDUP(SUMIF($C$44:$C$52,"Y",G44:G52),0) -> 364 | H53: =ROUNDUP(SUMIF($C$44:$C$52,"Y",H44:H52),0) -> 0 | J53: =J41 -> Max Rent | K53: =IF(K52=0,"",K52+K$33) | L53: =IF(L52=0,"",L52+L$33) | M53: =IF(M52=0,"",M52+M$33) | N53: =IF(N52=0,"",N52+N$33) | O53: =IF(O52=0,"",O52+O$33)

Sheet Construction Sources-Uses
A1: CONSTRUCTION SOURCES & USES and BOND COSTS | P1: ='[6]Summary_Sources-Uses'!L2 -> Financial Proforma Model 5.5
A2: ='[6]Summary_Sources-Uses'!A2 -> 2100 Memorial Redevelopment - Houston | P2: ='[6]Summary_Sources-Uses'!L1 -> 44403
C4: Bond Proceeds | E4: Bond Proceeds | G4: Other Sources | I4: Other Sources | K4: LIHTC Equity | N4: Deferred Fee | P4: Total Funds
C5: Tax-Exempt | E5: Taxable | G5: (City DR-17 Loan) | I5: (HHA FEMA loan) | P5: (Construction)
A6: DEVELOPMENT SOURCES
A8: Construction Loan - Bonds "A") | C8: 32000000 | P8: =SUM(C8:O8) -> 32000000
A9: Permanent Loan Bonds "B") | C9: 0 | P9: =SUM(C9:O9) -> 0
A10: City of Houston Loan - Tranche I (2nd) | G10: ='[6]Flow of Funds'!H8 -> 8000000 | P10: =SUM(D10:O10) -> 8000000
A11: City of Houston Loan - Tranche II (2nd) | G11: 7568802.9 | P11: =SUM(D11:O11) -> 7568802.9
A12: HHA /FEMA Loan (3rd) | I12: 5092079 | P12: =SUM(D12:O12) -> 5092079
A13: LIHTC Equity (investor) | K13: ='[6]Flow of Funds'!J11+'[6]Flow of Funds'!N11 -> 3576491 | P13: =SUM(D13:O13) -> 3576491
A14: Deferred Development Fee | N14: 0 | P14: =SUM(C14:O14) -> 0 | S14: =S16-P16 -> -538877.33
A16: TOTAL DEVELOPMENT SOURCES | C16: =SUM(C8:C14) -> 32000000 | E16: =SUM(E8:E14) -> 0 | G16: =SUM(G8:G14) -> 15568803 | I16: =SUM(I8:I14) -> 5092079 | K16: =SUM(K8:K14) -> 3576491 | N16: =SUM(N8:N14) -> 0 | P16: =SUM(P8:P14) -> 56237373 | R16: =SUM(C16:N16) -> 56237373 | S16: =SUM('[6]Flow of Funds'!H102:AM102) -> 55698496
S17: =S16-P16 -> -538877.33
A18: DEVELOPMENT USES
A20: ACQUISITION
A21: Building | B21: 0 | C21: 0 | G21: 0 | I21: 0 | P21: =SUM(C21:O21) -> 0 | Q21: =B21-P21 -> 0 | R21: =B21-P21 -> 0
A22: Land | B22: ='[6]Development_Budget_(detail)'!G9 -> 4656689.8 | G22: =B22 -> 4656689.8 | I22: 0 | P22: =SUM(C22:O22) -> 4656689.8 | Q22: =B22-P22 -> 0 | R22: =B22-P22 -> 0
P23: =SUM(C23:O23) -> 0 | Q23: =B23-P23 -> 0 | R23: =B23-P23 -> 0
A24: HARD COST CONSTRUCTION | P24: =SUM(C24:O24) -> 0 | Q24: =B24-P24 -> 0 | R24: =B24-P24 -> 0
A25: Demo/Abatement Contract | B25: ='[6]Development_Budget_(detail)'!G10 -> 3016378 | C25: =B25 -> 3016378 | I25: 0 | P25: =SUM(C25:O25) -> 3016378 | Q25: =B25-P25 -> 0
A26: Demo/Abatement Contingency | B26: ='[6]Development_Budget_(detail)'!G11 -> 326932.18 | C26: 250000 | G26: =B26-250000 -> 76932.18 | P26: =SUM(C26:O26) -> 326932.18 | Q26: =B26-P26 -> 0
A27: Construction Hard Costs | B27: ='[6]Development_Budget_(detail)'!G14 -> 29663009 | C27: 20245170 | G27: =6677902.42+94266 -> 6772168.4 | I27: 2645670.4 | P27: =SUM(C27:O27) -> 29663009 | Q27: =B27-P27 -> 0 | R27: =B27-P27 -> 0 | S27: =('[7]DRAW SCHEDULE'!$E$4+'[7]DRAW SCHEDULE'!$E$9)-P27 -> -7542929
A28: Sitework | B28: ='[6]Development_Budget_(detail)'!G15 -> 1833281 | C28: =B28 -> 1833281 | K28: 0 | P28: =SUM(C28:O28) -> 1833281 | Q28: =B28-P28 -> 0
A29: Contingency | B29: ='[6]Development_Budget_(detail)'!G21 -> 1795459.6 | C29: 0 | G29: =B29 -> 1795459.6 | P29: =SUM(C29:O29) -> 1795459.6 | Q29: =B29-P29 -> 0 | R29: =B29-P29 -> 0
A30: GC Profit | B30: ='[6]Development_Budget_(detail)'!G18 -> 662560 | C30: =B30 -> 662560 | P30: =SUM(C30:O30) -> 662560 | Q30: =B30-P30 -> 0 | R30: =B30-P30 -> 0 | S30: ='[7]DRAW SCHEDULE'!$E$13+'[7]DRAW SCHEDULE'!$E$12 -> 1659007
A31: GC Overhead | B31: ='[6]Development_Budget_(detail)'!G17 -> 1875171 | C31: =B31 -> 1875171 | G31: =B31-C31 -> 0 | P31: =SUM(C31:O31) -> 1875171 | Q31: =B31-P31 -> 0
A32: GC General Conditions | B32: ='[6]Development_Budget_(detail)'!G16 -> 1875171 | C32: =B32 -> 1875171 | G32: 0 | P32: =SUM(C32:O32) -> 1875171 | Q32: =B32-P32 -> 0 | R32: =B32-P32 -> 0 | S32: ='[7]DRAW SCHEDULE'!$E$11-I32 -> 1548407
A33: P&P Bond | B33: ='[6]Development_Budget_(detail)'!G20 -> 255000 | C33: =B33 -> 255000 | K33: 0 | P33: =SUM(C33:O33) -> 255000 | Q33: =B33-P33 -> 0 | R33: =B33-P33 -> 0
A34: Builders Risk Insurance | B34: ='[6]Development_Budget_(detail)'!G19 -> 400000 | C34: 305000 | I34: 165000 | K34: 0 | P34: =SUM(C34:O34) -> 470000 | Q34: =B34-P34 -> -70000 | R34: =B34-P34 -> -70000 | S34: =SUM(P27:P34) -> 38429652
A35: Demolition | P35: =SUM(C35:O35) -> 0 | Q35: =B35-P35 -> 0 | R35: =B35-P35 -> 0
A36: Site Preparation | B36: 0 | P36: =SUM(C36:O36) -> 0 | Q36: =B36-P36 -> 0 | R36: =B36-P36 -> 0
A37: Site Utilities | B37: 0 | P37: =SUM(C37:O37) -> 0 | Q37: =B37-P37 -> 0 | R37: =B37-P37 -> 0
A38: Landscaping | B38: 0 | P38: =SUM(C38:O38) -> 0 | Q38: =B38-P38 -> 0 | R38: =B38-P38 -> 0
A39: Retaining walls | P39: =SUM(C39:O39) -> 0 | Q39: =B39-P39 -> 0 | R39: =B39-P39 -> 0
A40: Fencing and Vehicle Gates | P40: =SUM(C40:O40) -> 0 | Q40: =B40-P40 -> 0 | R40: =B40-P40 -> 0
A41: Roads | B41: 0 | P41: =SUM(C41:O41) -> 0 | Q41: =B41-P41 -> 0 | R41: =B41-P41 -> 0
A42: Sidewalks | B42: 0 | P42: =SUM(C42:O42) -> 0 | Q42: =B42-P42 -> 0 | R42: =B42-P42 -> 0
A43: Exterior Amenities | B43: 0 | P43: =SUM(C43:O43) -> 0 | Q43: =B43-P43 -> 0 | R43: =B43-P43 -> 0
P44: =SUM(C44:O44) -> 0 | Q44: =B44-P44 -> 0 | R44: =B44-P44 -> 0
A45: DEVELOPMENT COSTS | P45: =SUM(C45:O45) -> 0 | Q45: =B45-P45 -> 0 | R45: =B45-P45 -> 0
A46: ='[6]Development_Budget_(detail)'!C24 -> Property Appraisal | B46: ='[6]Development_Budget_(detail)'!G24 -> 20000 | K46: =B46 -> 20000 | P46: =SUM(C46:O46) -> 20000 | Q46: =B46-P46 -> 0 | R46: =B46-P46 -> 0
A47: ='[6]Development_Budget_(detail)'!C25 -> Market Study | B47: ='[6]Development_Budget_(detail)'!G25 -> 20000 | K47: =B47 -> 20000 | P47: =SUM(C47:O47) -> 20000 | Q47: =B47-P47 -> 0 | R47: =B47-P47 -> 0
A48: ='[6]Development_Budget_(detail)'!C26 -> Environmental Report(s) | B48: ='[6]Development_Budget_(detail)'!G26 -> 25000 | C48: 16208 | K48: =B48-C48 -> 8792 | P48: =SUM(C48:O48) -> 25000 | Q48: =B48-P48 -> 0
A49: ='[6]Development_Budget_(detail)'!C27 -> Soil Borings | B49: ='[6]Development_Budget_(detail)'!G27 -> 80000 | C49: 85688 | K49: =B49-C49 -> -5688 | P49: =SUM(C49:O49) -> 80000 | Q49: =B49-P49 -> 0
A50: ='[6]Development_Budget_(detail)'!C28 -> Boundary and Topographical Survey | B50: ='[6]Development_Budget_(detail)'!G28 -> 16000 | K50: =B50 -> 16000 | P50: =SUM(C50:O50) -> 16000 | Q50: =B50-P50 -> 0
A51: ='[6]Development_Budget_(detail)'!C29 -> Zoning/Site Plan Fees | B51: ='[6]Development_Budget_(detail)'!G29 -> 0 | K51: =B51 -> 0 | P51: =SUM(C51:O51) -> 0 | Q51: =B51-P51 -> 0
A52: ='[6]Development_Budget_(detail)'!C32 -> Bond Issuer Closing Fee | B52: ='[6]Development_Budget_(detail)'!G32 -> 320000 | K52: =B52 -> 320000 | P52: =SUM(C52:O52) -> 320000 | Q52: =B52-P52 -> 0
A53: ='[6]Development_Budget_(detail)'!C33 -> Construction Loan fee | B53: ='[6]Development_Budget_(detail)'!G33 -> 256000 | K53: 256000 | P53: =SUM(C53:O53) -> 256000 | Q53: =B53-P53 -> 0
A54: ='[6]Development_Budget_(detail)'!C34 -> Construction Loan Interest | B54: ='[6]Development_Budget_(detail)'!G34 -> 2925000 | I54: =784173.15+15000+510023.18 -> 1309196.3 | K54: =2319781-I54 -> 1010584.7 | P54: =SUM(C54:O54) -> 2319781 | Q54: =B54-P54 -> 605219 | R54: =B54-P54 -> 605219
A55: ='[6]Development_Budget_(detail)'!C35 -> Construction Legal Fees (Lender) | B55: ='[6]Development_Budget_(detail)'!G35 -> 47500 | K55: =B55 -> 47500 | P55: =SUM(C55:O55) -> 47500 | Q55: =B55-P55 -> 0 | R55: =B55-P55 -> 0
A56: ='[6]Development_Budget_(detail)'!C36 -> Construction loan costs | B56: ='[6]Development_Budget_(detail)'!G36 -> 9855 | K56: =B56 -> 9855 | P56: =SUM(C56:O56) -> 9855 | Q56: =B56-P56 -> 0 | R56: =B56-P56 -> 0
A57: ='[6]Development_Budget_(detail)'!C37 -> Construction Insurance | B57: ='[6]Development_Budget_(detail)'!G37 -> 50000 | G57: 93183.36 | K57: =SUM('[6]Flow of Funds'!J54:AM54)-G57 -> -68183.36 | P57: =SUM(C57:O57) -> 25000 | Q57: =B57-P57 -> 25000 | R57: =B57-P57 -> 25000
A58: ='[6]Development_Budget_(detail)'!C38 -> Bond Issuer Legal | B58: ='[6]Development_Budget_(detail)'!G38 -> 175000 | K58: =B58 -> 175000 | P58: =SUM(C58:O58) -> 175000 | Q58: =B58-P58 -> 0 | R58: =B58-P58 -> 0
A59: ='[6]Development_Budget_(detail)'!C44 -> Architectural Fee-all services and reimbursables | B59: ='[6]Development_Budget_(detail)'!G44 -> 737600 | C59: =SUM('[6]Flow of Funds'!J57:AM57) -> 737600 | P59: =SUM(C59:O59) -> 737600 | Q59: =B59-P59 -> 0 | R59: =B59-P59 -> 0
A60: ='[6]Development_Budget_(detail)'!C45 -> Landscape Architect | B60: ='[6]Development_Budget_(detail)'!G45 -> 20000 | C60: =SUM('[6]Flow of Funds'!J58:AM58) -> 20000 | P60: =SUM(C60:O60) -> 20000 | Q60: =B60-P60 -> -2.910383e-11 | R60: =B60-P60 -> -2.910383e-11
A61: ='[6]Development_Budget_(detail)'!C46 -> Engineering | B61: ='[6]Development_Budget_(detail)'!G46 -> 275000 | C61: 233348.21 | K61: 41651.79 | P61: =SUM(C61:O61) -> 275000 | Q61: =B61-P61 -> 0 | R61: =B61-P61 -> 0
A62: ='[6]Development_Budget_(detail)'!C47 -> City of Houston Legal | B62: ='[6]Development_Budget_(detail)'!G47 -> 40000 | K62: 30000 | P62: =SUM(C62:O62) -> 30000 | Q62: =B62-P62 -> 10000 | R62: =B62-P62 -> 10000
A63: ='[6]Development_Budget_(detail)'!C48 -> HHA Legal | B63: ='[6]Development_Budget_(detail)'!G48 -> 150000 | K63: 140000 | P63: =SUM(C63:O63) -> 140000 | Q63: =B63-P63 -> 10000 | R63: =B63-P63 -> 10000
A64: ='[6]Development_Budget_(detail)'!C49 -> Partnership Legal | B64: ='[6]Development_Budget_(detail)'!G49 -> 150000 | G64: 50000 | K64: 56200.03 | P64: =SUM(C64:O64) -> 106200.03 | Q64: =B64-P64 -> 43799.97 | R64: =B64-P64 -> 43799.97
A65: ='[6]Development_Budget_(detail)'!C50 -> Accounting | B65: ='[6]Development_Budget_(detail)'!G50 -> 200000 | K65: =SUM('[6]Flow of Funds'!J63:AM63) -> 142500 | P65: =SUM(C65:O65) -> 142500 | Q65: =B65-P65 -> 57500 | R65: =B65-P65 -> 57500
A66: ='[6]Development_Budget_(detail)'!C51 -> Green Building Certification/Registration | B66: ='[6]Development_Budget_(detail)'!G51 -> 50000 | C66: 23000 | I66: =27000-15000 -> 12000 | K66: 0 | P66: =SUM(C66:O66) -> 35000 | Q66: =B66-P66 -> 15000 | R66: =B66-P66 -> 15000
A67: ='[6]Development_Budget_(detail)'!C52 -> Construction Inspection Fees | B67: ='[6]Development_Budget_(detail)'!G52 -> 47600 | G67: =B67 -> 47600 | P67: =SUM(C67:O67) -> 47600 | Q67: =B67-P67 -> 0 | R67: =B67-P67 -> 0
A68: ='[6]Development_Budget_(detail)'!C53 -> Accessibility Consulting | B68: ='[6]Development_Budget_(detail)'!G53 -> 50000 | C68: 6200 | G68: =B68-C68 -> 43800 | P68: =SUM(C68:O68) -> 50000 | Q68: =B68-P68 -> 0 | R68: =B68-P68 -> 0
A69: ='[6]Development_Budget_(detail)'!C54 -> Construction Materials Testing | B69: ='[6]Development_Budget_(detail)'!G54 -> 0 | G69: =B69 -> 0 | P69: =SUM(C69:O69) -> 0 | Q69: =B69-P69 -> 0 | R69: =B69-P69 -> 0
A70: ='[6]Development_Budget_(detail)'!C57 -> Building Permits | B70: ='[6]Development_Budget_(detail)'!G57 -> 57400 | C70: 47935.38 | K70: 9464.62 | P70: =SUM(C70:O70) -> 57400 | Q70: =B70-P70 -> 0 | R70: =B70-P70 -> 0
A71: ='[6]Development_Budget_(detail)'!C58 -> Impact Fees | B71: ='[6]Development_Budget_(detail)'!G58 -> 152000 | K71: =B71 -> 152000 | P71: =SUM(C71:O71) -> 152000 | Q71: =B71-P71 -> 0 | R71: =B71-P71 -> 0
A72: ='[6]Development_Budget_(detail)'!C59 -> Plan Review | B72: ='[6]Development_Budget_(detail)'!G59 -> 15250 | K72: =B72 -> 15250 | P72: =SUM(C72:O72) -> 15250 | Q72: =B72-P72 -> 0 | R72: =B72-P72 -> 0
A73: ='[6]Development_Budget_(detail)'!C60 -> Other Local fees | B73: ='[6]Development_Budget_(detail)'!G60 -> 50000 | K73: 50000 | P73: =SUM(C73:O73) -> 50000 | Q73: =B73-P73 -> 0 | R73: =B73-P73 -> 0
A74: ='[6]Development_Budget_(detail)'!C63 -> Permanent Loan Fees | B74: ='[6]Development_Budget_(detail)'!G63 -> 128700 | K74: 112000 | P74: =SUM(C74:O74) -> 112000 | Q74: =B74-P74 -> 16700 | R74: =B74-P74 -> 16700
A75: ='[6]Development_Budget_(detail)'!C64 -> Permanent Loan Legal Fees | B75: ='[6]Development_Budget_(detail)'!G64 -> 50000 | K75: 30000 | P75: =SUM(C75:O75) -> 30000 | Q75: =B75-P75 -> 20000 | R75: =B75-P75 -> 20000
A76: ='[6]Development_Budget_(detail)'!C65 -> Title and Recording Fees | B76: ='[6]Development_Budget_(detail)'!G65 -> 212056 | C76: 190492.4 | K76: 0 | P76: =SUM(C76:O76) -> 190492.4 | Q76: =B76-P76 -> 21563.6 | R76: =B76-P76 -> 21563.6
A77: ='[6]Development_Budget_(detail)'!C66 -> As-Built Survey | B77: ='[6]Development_Budget_(detail)'!G66 -> 5000 | K77: 0 | P77: =SUM(C77:O77) -> 0 | Q77: =B77-P77 -> 5000
A78: ='[6]Development_Budget_(detail)'!C67 -> Conversion Fee | B78: ='[6]Development_Budget_(detail)'!G67 -> 10000 | I78: 10000 | K78: 0 | P78: =SUM(C78:O78) -> 10000 | Q78: =B78-P78 -> 0 | R78: =B78-P78 -> 0
A79: ='[6]Development_Budget_(detail)'!C71 -> TDHCA Application Fees | B79: ='[6]Development_Budget_(detail)'!G71 -> 5910 | K79: =B79 -> 5910 | P79: =SUM(C79:O79) -> 5910 | Q79: =B79-P79 -> 0 | R79: =B79-P79 -> 0
A80: ='[6]Development_Budget_(detail)'!C72 -> TDHCA Commitment Fee | B80: ='[6]Development_Budget_(detail)'!G72 -> 77750 | K80: =B80 -> 77750 | P80: =SUM(C80:O80) -> 77750 | Q80: =B80-P80 -> 0 | R80: =B80-P80 -> 0
A81: ='[6]Development_Budget_(detail)'!C73 -> Bond Development Determination Fee | B81: ='[6]Development_Budget_(detail)'!G73 -> 82974 | K81: =B81 -> 82974 | P81: =SUM(C81:O81) -> 82974 | Q81: =B81-P81 -> 0 | R81: =B81-P81 -> 0
A82: ='[6]Development_Budget_(detail)'!C74 -> LIHTC Allocation Processing Fee | B82: ='[6]Development_Budget_(detail)'!G74 -> 50000 | K82: =B82 -> 50000 | P82: =SUM(C82:O82) -> 50000 | Q82: =B82-P82 -> 0 | R82: =B82-P82 -> 0
A83: ='[6]Development_Budget_(detail)'!C75 -> LIHTC Complaince Monitoring Fee | B83: ='[6]Development_Budget_(detail)'!G75 -> 6360 | K83: 0 | P83: =SUM(C83:O83) -> 0 | Q83: =B83-P83 -> 6360 | R83: =B83-P83 -> 6360
A84: ='[6]Development_Budget_(detail)'!C78 -> Partnership Organization Fees | B84: ='[6]Development_Budget_(detail)'!G78 -> 0 | K84: 0 | P84: =SUM(C84:O84) -> 0 | Q84: =B84-P84 -> 0 | R84: =B84-P84 -> 0
A85: ='[6]Development_Budget_(detail)'!C79 -> Tax Credit Legal Opinion | B85: ='[6]Development_Budget_(detail)'!G79 -> 0 | K85: 0 | P85: =SUM(C85:O85) -> 0 | Q85: =B85-P85 -> 0 | R85: =B85-P85 -> 0
A86: ='[6]Development_Budget_(detail)'!C80 -> Syndicator Legal Fees | B86: ='[6]Development_Budget_(detail)'!G80 -> 0 | K86: =SUM('[6]Flow of Funds'!J84:AM84) -> 0 | P86: =SUM(C86:O86) -> 0 | Q86: =B86-P86 -> 0 | R86: =B86-P86 -> 0
A87: ='[6]Development_Budget_(detail)'!C81 -> Syndicator Due Diligence Fee | B87: ='[6]Development_Budget_(detail)'!G81 -> 55000 | K87: 55000 | P87: =SUM(C87:O87) -> 55000 | Q87: =B87-P87 -> 0 | R87: =B87-P87 -> 0
A88: ='[6]Development_Budget_(detail)'!C84 -> Marketing | B88: ='[6]Development_Budget_(detail)'!G84 -> 75000 | K88: =SUM('[6]Flow of Funds'!J86:AM86) -> 0 | P88: =SUM(C88:O88) -> 0 | Q88: =B88-P88 -> 75000 | R88: =B88-P88 -> 75000
A89: ='[6]Development_Budget_(detail)'!C85 -> Rent -Up Reserves (3mos exp) | B89: ='[6]Development_Budget_(detail)'!G85 -> 565804 | K89: 198031 | P89: =SUM(C89:O89) -> 198031 | Q89: =B89-P89 -> 367773 | R89: =B89-P89 -> 367773
A90: ='[6]Development_Budget_(detail)'!C86 -> Operating Deficit Reserve | B90: ='[6]Development_Budget_(detail)'!G86 -> 921000 | I90: 0 | K90: =SUM('[6]Flow of Funds'!J88:AM88) -> 0 | P90: =SUM(C90:O90) -> 0 | Q90: =B90-P90 -> 921000 | R90: =B90-P90 -> 921000
A91: ='[6]Development_Budget_(detail)'!C87 -> Replacement Reserve | B91: ='[6]Development_Budget_(detail)'!G87 -> 59100 | I91: 0 | K91: =SUM('[6]Flow of Funds'!J89:AM89) -> 55000 | P91: =SUM(C91:O91) -> 55000 | Q91: =B91-P91 -> 4100 | R91: =B91-P91 -> 4100
A92: ='[6]Development_Budget_(detail)'!C88 -> Furniture, Fixtures and Equipment | B92: ='[6]Development_Budget_(detail)'!G88 -> 500000 | C92: 8000 | G92: =SUM('[6]Flow of Funds'!J95:AM95)-C92 -> 492000 | P92: =SUM(C92:O92) -> 500000 | Q92: =B92-P92 -> 0
A93: ='[6]Development_Budget_(detail)'!C91 -> Relocation | B93: ='[6]Development_Budget_(detail)'!G91 -> 0 | P93: =SUM(C93:O93) -> 0 | Q93: =B93-P93 -> 0 | R93: =B93-P93 -> 0
A94: ='[6]Development_Budget_(detail)'!C92 -> Soft cost contingecy | B94: ='[6]Development_Budget_(detail)'!G92 -> 97146 | I94: 75000 | K94: 0 | P94: =SUM(C94:O94) -> 75000 | Q94: =B94-P94 -> 22146 | R94: =B94-P94 -> 22146
A95: Developer Overhead | B95: ='[6]Development_Budget_(detail)'!G99*0.2 -> 1360000 | C95: 303796.78 | G95: =115193.5+15256.4 -> 130449.9 | I95: 875212.32 | K95: 50541 | P95: =SUM(C95:O95) -> 1360000 | Q95: =B95-P95 -> 0 | R95: =B95-P95 -> 0
A96: Developer Fee | B96: ='[6]Development_Budget_(detail)'!G99-'[6]Construction Sources & Uses'!B95 -> 5440000 | G96: ='[6]Flow of Funds'!AM100-15256.4 -> 1366215.6 | P96: =SUM(C96:O96) -> 1366215.6 | Q96: =B96-P96 -> 4073784.4 | R96: =B96-P96 -> 4073784.4
Q97: =B97-P97 -> 0
A98: TOTAL DEVELOPMENT USES | B98: =SUM(B21:B97) -> 62000657 | C98: =SUM(C21:C97) -> 31990000 | E98: =SUM(E21:E97) -> 0 | G98: =SUM(G21:G97) -> 15524499 | H98: =SUM(H22:H96) -> 0 | I98: =SUM(I17:I97) -> 5092079 | K98: =SUM(K17:K97) -> 3164132.8 | L98: =SUM(L22:L96) -> 0 | M98: =SUM(M22:M96) -> 0 | N98: =SUM(N21:N97) -> 0 | O98: =SUM(O22:O96) -> 0 | P98: =SUM(P21:P97) -> 55770711 | Q98: =B98-P98 -> 6229946 | R98: =SUM(R21:R97) -> 6224946
B99: =B98-'[6]Development_Budget_(detail)'!G96 -> -44083.33 | C99: =C16-C98 -> 10000 | D99: =D16-D98 -> 0 | E99: =E16-E98 -> 0 | F99: =F16-F98 -> 0 | G99: =G16-G98 -> 44304 | H99: =H16-H98 -> 0 | I99: =I16-I98 -> 0 | K99: =K16-K98 -> 412358.25 | L99: =L16-L98 -> 0 | M99: =M16-M98 -> 0 | N99: =N16-N98 -> 0 | O99: =O16-O98 -> 0 | P99: =P16-P98 -> 466662.25
P100: Equity pays down TEBonds to TEL loan amount
A101: EQUITY PAY-IN SCHEDULE | B101: =B98-B100 -> 62000657 | C101: AMOUNT | E101: DUE DATE
I102: 50% Test: | K102: =C98/B98 -> 0.51596228
A103: Initial Cap contribution (Closing) | C103: ='[6]Credit Delivery & Pay-Ins'!M15 -> 2846768 | E103: 44378
A104: 2nd cap contribution | C104: ='[6]Credit Delivery & Pay-Ins'!M44 -> 9738021 | E104: 45261 | K104: meets 50% test
...
