Workbook
Name AddRevY1: 'Rent Schedule'!$K$34
Name CommRent: Inputs!$E$58
Name CommSqFt: Inputs!$C$58
Name ExpInfl: Inputs!$C$36
Name ExpTotalY1: 'Operating Expense'!$E$20
Name GrossOpEx: 'Operating Expense'!$E$20
Name GrossRentIncomeY1: 'Rent Schedule'!$K$26
Name LIUnits: 'Rent Schedule'!$D$26
Name NetIncomeY1: 'Rent Schedule'!$K$42
Name NOI: '20yr Proforma'!$F$24
Name ProjName: 'Constr Sources-Uses'!$A$2
Name ProjName: 'Perm Sources-Uses'!$A$2
Name ProjName: "'Summary_Sources-Uses'!$A$2"
Name PropTaxes: 'Operating Expense'!$E$133
Name ReplRes: 'Operating Expense'!$E$21
Name ReplReserve: Inputs!$C$37
Name RevInfl: Inputs!$C$35
Name Tenancy: 1-Inputs!$C$34
Name TotalUnitCount: Inputs!$C$2
Name TtlUnits: 'Rent Schedule'!$D$26
Name Vacancy: Inputs!$C$34
Name VacRate: Inputs!$C$34

Sheet READ ME — TEMPLATE
A1: I | B1: REO, LLC — LIHTC UNDERWRITING MODEL TEMPLATE
B2: Based on Columbia at Independence Heights II Structure
B4: HOW TO USE THIS TEMPLATE
B5: 1. Save a copy of this file with your new project name before editing.
B6: 2. Start on the INPUTS sheet — fill in all blue-highlighted cells with your deal assumptions.
B7: 3. Move to RENT SCHEDULE — enter your unit mix, set-asides, and projected rents.
B8: 4. Complete DEVELOPMENT BUDGET — enter all line-item costs and basis eligibility.
B9: 5. Complete OPERATING EXPENSE — enter your projected operating budget.
B10: 6. Update SUMMARY SOURCES-USES — enter debt terms, equity pricing, source names.
B11: 7. Complete CREDIT DELIVERY & PAY-INS — enter lease-up schedule and equity pay-in timing.
B12: 8. Complete FLOW OF FUNDS — enter monthly construction draw percentages.
B13: 9. Update DEVELOPER FEE SCHEDULE — enter partner entities and split percentages.
B14: 10. Review 20YR PROFORMA and 25% TEST — these are formula-driven and auto-calculate.
... B45: LHC (Louisiana) applications with minor modifications to scoring/compliance sheets

Sheet Inputs
B1: Project | C1: Live Oak Manor Residences — Phase 1 | E1: [Version] | L1: apex apartments with ext detention
B2: Number of Units | C2: 61
K3: 231250 | L3: buildable NRSF per JHP
B4: Acres | K4: 1200 | L4: avg unit SF
B5: Units/Acre | C5: 4.88 | K5: 192.70833
B6: Acquisition Price | E6: per unit
B8: Type of Allocation
B10: Max Credit Allocation | F10: GA: $950,000; TX: $1,500,000
B11: Max Dev. Fee Allowable | F11: GA: $1.8MM for 9%, $2.5MM for 4%
B13: Rents
C14: 2025 FY MTSP LIHTC rents | G14: 2023 FMR+10%
C15: 30% LIHTC | D15: 50% LIHTC | E15: 60% LIHTC | F15: 30% PBV | G15: 50% PBV | H15: 80% LIHTC | J15: Market | K15: FMR | L15: UA | N15: SF | O15: Mix | P15: Market Rate/SF
B16: 1 BR | L16: 130 | P16: 0
B17: 2 BR | L17: 173 | P17: 0
B18: 3 BR | L18: 214 | P18: 0
B19: 4 BR | O19: 0
B20: UA's | C20: Y | D20: Y | E20: Y | F20: Y | G20: Y | H20: y | I20: Y | J20: N
L21: *asssume $20/unit savings
B22: Set Asides | C22: Income Limits | D22: Total Mix | F22: Of | G22: Less
B23: 30% PBV | F23: of Total | H23: 0
B24: 50% PBV | F24: of Total | H24: 0 | L24: Tax Abatement
B25: 60% LIHTC | F25: Plug | T25: 1.592
B26: 80% LIHTC | F26: of Total | H26: 0 | L26: 2
F27: of Total | H27: 0 | L27: 3
F28: of Total | G28: 0 | H28: 0 | L28: 4
F29: of Total | G29: 0 | H29: 0 | L29: 5
F30: of Total | G30: 0 | H30: 0 | L30: 6
F31: of Total | G31: 0 | H31: 0 | L31: 7
B32: Market | C32: None | L32: 8
D33: 61 | E33: 0.5852459 | F33: income avg | L33: 9
B34: Vacancy Rate | L34: 10
B35: Revenue Inflation | L35: 11 | O35: 1115.4
B36: Expense Inflation | L36: 12 | O36: 1328.8
B37: Replacement Reserve | D37: per units | L37: 13 | O37: 1763.3
L38: 14
L39: 15
B40: Start Year | L40: 16
A41: Month | D41: Equity Schedule | E41: Fee Schedule | L41: 17
B42: Start | L42: 18
B43: Application | L43: 19
B44: Closing | H44: months from app date | L44: 20
A45: 0 | B45: Completion
A46: 150 | B46: Stabilization | H46: Units/month | J46: 5 | K46: months
A47: 240 | B47: 8609's | E47: -0.55
D48: 0.83 | E48: 0
B51: Hard Cost Per Unit | D51: *Incl. comm SF | F51: 20878836 | G51: const contract per unit | I51: 17399.03 | J51: per NRSF
B52: Contingency | F52: 1273608996 | G52: total const contract
G53: deferred fee target
B54: Developer Fee Interest | F54: 1.2716362e+09 | G54: target const contract | I54: 20846495 | J54: target per unit cost
F55: 1972779.1 | G55: need to cut
B56: Construction Duration | F56: 32340.641 | G56: need to cut per unit
E57: Rent
B58: Commercial SF | F58: /sf/year | G58: 0
B59: Parking | D59: per 1000
B60: spaces
B61: SF | D61: average
B62: Total SF | C62: 0
B63: acres | C63: 0
B64: Cost per SF
B65: total cost | C65: 0

Sheet Constr Sources-Uses
A1: CONSTRUCTION SOURCES & USES
A2: [Project Name]
A3: [Project Description] | L3: =G5&" Family Units" -> Family Units
L4: [Affordability Mix]
A5: SOURCES & USES - Construction Period | H5: units
B7: Sources: | F7: Per Unit | H7: Uses: | K7: Total | L7: Per Unit
B8: First Mortgage | D8: Tax-Exempt Bonds (25% Test) | E8: ='25% Test'!F5 -> 0 | F8: =E8/G$5 -> #DIV/0! | G8: =E8/$E$23 -> #DIV/0! | H8: Acquisition Costs | K8: ='Development Budget'!H10 -> 0 | L8: =K8/G$5 -> #DIV/0! | M8: =K8/$K$23 -> #DIV/0!
B9: 2nd Mortgage | D9: Gap Funding (TBD Source) | E9: =K23-SUM(E8,E10:E18) -> 0 | F9: =E9/G$5 -> #DIV/0! | G9: =E9/$E$23 -> #DIV/0! | H9: Construction Costs | K9: ='Development Budget'!H21 -> 0 | L9: =K9/G$5 -> #DIV/0! | M9: =K9/$K$23 -> #DIV/0! | P9: CHANGES to SOURCES
B10: 3rd Mortgage | D10: LHC Soft Loan / Capital Magnet / FHLB AHP | F10: =E10/G$5 -> #DIV/0! | G10: =E10/$E$23 -> #DIV/0! | H10: Predevelopment Costs | K10: ='Development Budget'!H29 -> 0 | L10: =K10/G$5 -> #DIV/0! | M10: =K10/$K$23 -> #DIV/0!
B11: 4th Mortgage | D11: =E56 -> 0 | F11: =E11/G$5 -> #DIV/0! | G11: =E11/$E$23 -> #DIV/0! | H11: Financing | K11: ='Development Budget'!H40 -> 0 | L11: =K11/G$5 -> #DIV/0! | M11: =K11/$K$23 -> #DIV/0! | P11: 1 | S11: QCT Credits
B12: Funding Gap (Unfunded) | D12: n.a. | F12: =E12/G$5 -> #DIV/0! | G12: =E12/$E$23 -> #DIV/0! | H12: Professional Services | K12: ='Development Budget'!H54 -> 0 | L12: =K12/G$5 -> #DIV/0! | M12: =K12/$K$23 -> #DIV/0! | R12: =E37*10 -> 0 | S12: noQCT
B13: Other Equity | D13: Developer Cash Equity | F13: =E13/G$5 -> #DIV/0! | G13: =E13/$E$23 -> #DIV/0! | H13: Local Government Fees | K13: ='Development Budget'!H60 -> 0 | L13: =K13/G$5 -> #DIV/0! | M13: =K13/$K$23 -> #DIV/0! | R13: =R12-R11 -> 0 | S13: Loss in credits
B14: Other grant/loan | D14: FHLB of Dallas AHP (included in 3rd Mortgage) | F14: =E14/G$5 -> #DIV/0! | G14: =E14/$E$23 -> #DIV/0! | H14: Permanent Financing Fees | K14: ='Development Budget'!H67 -> 0 | L14: =K14/G$5 -> #DIV/0! | M14: =K14/$K$23 -> #DIV/0!
B15: LIHTC Equity (4%)-Fed | D15: TBD — Tax Credit Investor | E15: =E39 -> 0 | F15: =E15/G$5 -> #DIV/0! | G15: =E15/$E$23 -> #DIV/0! | H15: Tax Credit Costs | K15: ='Development Budget'!H75 -> 0 | L15: =K15/G$5 -> #DIV/0! | M15: =K15/$K$23 -> #DIV/0! | S15: QCT Equity
B16: LIHTC Equity (4%)-State | D16: [State Investor] | E16: =E41 -> 0 | F16: =E16/G$5 -> #DIV/0! | G16: =E16/$E$23 -> #DIV/0! | H16: Equity Costs | K16: ='Development Budget'!H81 -> 0 | L16: =K16/G$5 -> #DIV/0! | M16: =K16/$K$23 -> #DIV/0! | R16: =E15 -> 0 | S16: noQCT
B17: Deferred Devel Fee | D17: developer | E17: =K20 -> 0 | F17: =E17/G$5 -> #DIV/0! | G17: =E17/$E$23 -> #DIV/0! | H17: Start Up and Reserves | K17: ='Development Budget'!H88 -> 0 | L17: =K17/G$5 -> #DIV/0! | M17: =K17/$K$23 -> #DIV/0! | R17: =R16-R15 -> 0 | S17: Loss in Equity
B18: Earnings on GIC (set equal to interest exp) | G18: =E18/$E$23 -> #DIV/0! | H18: Other Costs | K18: ='Development Budget'!H91 -> 0 | L18: =K18/G$5 -> #DIV/0! | M18: =K18/$K$23 -> #DIV/0!
C20: percent of fee deferred | D20: =E17/K20 -> #DIV/0! | H20: Developer Fee | L20: =K20/G$5 -> #DIV/0! | M20: =K20/$K$23 -> #DIV/0!
C21: Payback period | D21: ='20yr Proforma'!C54 -> #REF!
R22: Permanent Debt
B23: Total Sources: | E23: =SUM(E8:E18) -> 0 | F23: =E23/G$5 -> #DIV/0! | H23: Total Uses: | K23: =SUM(K8:K18)+K20 -> 0 | L23: =K23/G$5 -> #DIV/0! | S23: QCT Perm Debt
R24: =E8+K51 -> 0 | S24: noQCT
B25: Funding Gap (Sources - Uses): | E25: =E23-K23 -> 0 | F25: =E25/G$5 -> #DIV/0! | Q25: =R25/R23 -> #DIV/0! | R25: =R24-R23 -> 0 | S25: Increase in debt
R27: Deferred Developer Fee
B28: LIHTC Equity | S28: QCT DDF
B29: Total Eligible Costs | E29: ='Development Budget'!J94 -> 0 | R29: =E17 -> 0 | S29: noQCT
B30: Percentage Low Income | D30: 1 | Q30: =R30/R28 -> #DIV/0! | R30: =R29-R28 -> 0 | S30: Increase in DDF
B31: Eligible Basis Acquis. | D31: 1
B32: Eligible Basis-Dev. Cost | D32: ='Rent Schedule'!D27 -> 1 | E32: =E29*D32 -> 0 | R32: FEMA Allocation
B33: Combined Basis | E33: =E31+E32 -> 0 | R33: 0 | S33: QCT FEMA
B34: Boost | D34: 1 | R34: =E10 -> 0 | S34: noQCT
B35: Qualified Basis: | E35: =E33*D34 -> 0 | Q35: =R35/R33 -> #DIV/0! | R35: =R34-R33 -> 0 | S35: Increase in FEMA
B36: Eligible Annual Credit: | D36: 0.04 | E36: =E35*D36 -> 0
B37: LIHTC allocation | E37: =E36 -> 0
B38: Federal Equity Pricing ($/credit) | E38: =E37*10*D38 -> 0
B39: Total Federal LIHTC Equity | E39: =E38*0.9999 -> 0 | F39: 99.99% to LP investor
B40: State Equity Pricing ($/credit) | E40: =E37*10*D40 -> 0
B41: Total State LIHTC Equity | E41: =E40*0.9999 -> 0
B43: Total Equity Yield | E43: =E39+E41 -> 0
B45: 45L Credits | D45: =D38 -> 0
W46: Total Funds
B47: Debt Sources: | H47: rate | I47: amortiz | J47: term | K47: principal | L47: annual DS | N47: annual DS/unit | Q47: DSCR Y1 | R47: DSCR Y15 | S47: DSCR Y20
B49: 1st Mortgage: | E49: Tax-Exempt Bonds (25% Test) | K49: =E8 -> 0 | L49: =PMT(H49/12,I49*12,K49)*-12 -> #NUM! | N49: =L49/G5 -> #NUM! | Q49: ='20yr Proforma'!F51 -> 0 | R49: ='20yr Proforma'!T51 -> 0 | S49: ='20yr Proforma'!Y51 -> 0 | W49: TBDPortion
F50: *10yr (4.05%) + 184bp spread + 25bp cushion | W50: Wells Portion | Y50: =Y46-Y49 -> 0
B51: 2nd Mortgage | E51: 2nd Mortgage | L51: =PMT(H51/12,I51*12,K51)*-12 -> #NUM! | N51: =L51/G5 -> #NUM!
B53: Soft Loan | E53: GAP Funding (TBD) | L53: =K53*H53 -> 0 | M53: cash flow-interest only | N53: =L53/G5 -> #DIV/0!
B55: Soft Loan B | L55: =K55*H55 -> 0 | N55: =L55/G5 -> #DIV/0!
B57: 4th Mortgage | E57: n.a.
B59: 5th Mortgage | E59: n.a.
B61: 6th Mortgage | E61: n. a.
D63: totals: | L63: =SUM(L49:L61) -> #NUM!
B66: Debt Sources:
E67: Bond Allocation: | G67: (LHC, Bond Issuer) | K67: ='25% Test'!F5 -> 0
E68: Construction Loan (Taxable) | H68: =0.04+0.0245+0.0015 -> 0.066 | I68: * | K68: ='Flow of Funds'!AD134 -> 0
E69: 25% Test Calculation: | K69: ='25% Test'!D10 -> #DIV/0!
F70: * rate is 30-day SOFR 4.00% + 245bp with 15 bps hedge

Sheet Perm Sources-Uses
A1: PERMANENT SOURCES & USES
A2: [Project Name]
A3: [Project Description] | L3: =G5&" Family Units" -> Family Units
L4: [Affordability Mix]
A5: SOURCES & USES - Permanent Financing | H5: units
B7: Sources: | F7: Per Unit | H7: Uses: | K7: Total | L7: Per Unit
B8: First Mortgage | D8: Tax-Exempt Bonds (25% Test) | E8: ='25% Test'!F5 -> 0 | F8: =E8/G$5 -> #DIV/0! | G8: =E8/$E$23 -> #DIV/0! | H8: Acquisition Costs | K8: ='Development Budget'!H10 -> 0 | L8: =K8/G$5 -> #DIV/0! | M8: =K8/$K$23 -> #DIV/0!
B9: 2nd Mortgage | D9: Gap Funding (TBD Source) | E9: =K23-SUM(E8,E10:E18) -> 0 | F9: =E9/G$5 -> #DIV/0! | G9: =E9/$E$23 -> #DIV/0! | H9: Construction Costs | K9: ='Development Budget'!H21 -> 0 | L9: =K9/G$5 -> #DIV/0! | M9: =K9/$K$23 -> #DIV/0! | P9: CHANGES to SOURCES
B10: 3rd Mortgage | D10: LHC Soft Loan / Capital Magnet / FHLB AHP | F10: =E10/G$5 -> #DIV/0! | G10: =E10/$E$23 -> #DIV/0! | H10: Predevelopment Costs | K10: ='Development Budget'!H29 -> 0 | L10: =K10/G$5 -> #DIV/0! | M10: =K10/$K$23 -> #DIV/0!
B11: 4th Mortgage | D11: =E56 -> 0 | F11: =E11/G$5 -> #DIV/0! | G11: =E11/$E$23 -> #DIV/0! | H11: Financing | K11: ='Development Budget'!H40 -> 0 | L11: =K11/G$5 -> #DIV/0! | M11: =K11/$K$23 -> #DIV/0! | P11: 1 | S11: QCT Credits
B12: Funding Gap (Unfunded) | D12: n.a. | F12: =E12/G$5 -> #DIV/0! | G12: =E12/$E$23 -> #DIV/0! | H12: Professional Services | K12: ='Development Budget'!H54 -> 0 | L12: =K12/G$5 -> #DIV/0! | M12: =K12/$K$23 -> #DIV/0! | R12: =E37*10 -> 0 | S12: noQCT
B13: Other Equity | D13: Developer Cash Equity | F13: =E13/G$5 -> #DIV/0! | G13: =E13/$E$23 -> #DIV/0! | H13: Local Government Fees | K13: ='Development Budget'!H60 -> 0 | L13: =K13/G$5 -> #DIV/0! | M13: =K13/$K$23 -> #DIV/0! | R13: =R12-R11 -> 0 | S13: Loss in credits
B14: Other grant/loan | D14: FHLB of Dallas AHP (included in 3rd Mortgage) | F14: =E14/G$5 -> #DIV/0! | G14: =E14/$E$23 -> #DIV/0! | H14: Permanent Financing Fees | K14: ='Development Budget'!H67 -> 0 | L14: =K14/G$5 -> #DIV/0! | M14: =K14/$K$23 -> #DIV/0!
B15: LIHTC Equity (4%)-Fed | D15: TBD — Tax Credit Investor | E15: =E39 -> 0 | F15: =E15/G$5 -> #DIV/0! | G15: =E15/$E$23 -> #DIV/0! | H15: Tax Credit Costs | K15: ='Development Budget'!H75 -> 0 | L15: =K15/G$5 -> #DIV/0! | M15: =K15/$K$23 -> #DIV/0! | S15: QCT Equity
B16: LIHTC Equity (4%)-State | D16: [State Investor] | E16: =E41 -> 0 | F16: =E16/G$5 -> #DIV/0! | G16: =E16/$E$23 -> #DIV/0! | H16: Equity Costs | K16: ='Development Budget'!H81 -> 0 | L16: =K16/G$5 -> #DIV/0! | M16: =K16/$K$23 -> #DIV/0! | R16: =E15 -> 0 | S16: noQCT
B17: Deferred Devel Fee | D17: developer | E17: =K20 -> 0 | F17: =E17/G$5 -> #DIV/0! | G17: =E17/$E$23 -> #DIV/0! | H17: Start Up and Reserves | K17: ='Development Budget'!H88 -> 0 | L17: =K17/G$5 -> #DIV/0! | M17: =K17/$K$23 -> #DIV/0! | R17: =R16-R15 -> 0 | S17: Loss in Equity
B18: Earnings on GIC (set equal to interest exp) | G18: =E18/$E$23 -> #DIV/0! | H18: Other Costs | K18: ='Development Budget'!H91 -> 0 | L18: =K18/G$5 -> #DIV/0! | M18: =K18/$K$23 -> #DIV/0!
C20: percent of fee deferred | D20: =E17/K20 -> #DIV/0! | H20: Developer Fee | L20: =K20/G$5 -> #DIV/0! | M20: =K20/$K$23 -> #DIV/0!
C21: Payback period | D21: ='20yr Proforma'!C54 -> #REF!
R22: Permanent Debt
B23: Total Sources: | E23: =SUM(E8:E18) -> 0 | F23: =E23/G$5 -> #DIV/0! | H23: Total Uses: | K23: =SUM(K8:K18)+K20 -> 0 | L23: =K23/G$5 -> #DIV/0! | S23: QCT Perm Debt
R24: =E8+K51 -> 0 | S24: noQCT
B25: Funding Gap (Sources - Uses): | E25: =E23-K23 -> 0 | F25: =E25/G$5 -> #DIV/0! | Q25: =R25/R23 -> #DIV/0! | R25: =R24-R23 -> 0 | S25: Increase in debt
R27: Deferred Developer Fee
B28: LIHTC Equity | S28: QCT DDF
B29: Total Eligible Costs | E29: ='Development Budget'!J94 -> 0 | R29: =E17 -> 0 | S29: noQCT
B30: Percentage Low Income | D30: 1 | Q30: =R30/R28 -> #DIV/0! | R30: =R29-R28 -> 0 | S30: Increase in DDF
B31: Eligible Basis Acquis. | D31: 1
B32: Eligible Basis-Dev. Cost | D32: ='Rent Schedule'!D27 -> 1 | E32: =E29*D32 -> 0 | R32: FEMA Allocation
B33: Combined Basis | E33: =E31+E32 -> 0 | R33: =20000000 -> 20000000 | S33: QCT FEMA
B34: Boost | D34: 1 | R34: =E10 -> 0 | S34: noQCT
B35: Qualified Basis: | E35: =E33*D34 -> 0 | Q35: =R35/R33 -> -1 | R35: =R34-R33 -> -20000000 | S35: Increase in FEMA
B36: Eligible Annual Credit: | D36: 0.04 | E36: =E35*D36 -> 0
B37: LIHTC allocation | E37: =E36 -> 0
B38: Federal Equity Pricing ($/credit) | E38: =E37*10*D38 -> 0
B39: Total Federal LIHTC Equity | E39: =E38*0.9999 -> 0 | F39: 99.99% to LP investor
B40: State Equity Pricing ($/credit) | E40: =E37*10*D40 -> 0
B41: Total State LIHTC Equity | E41: =E40*0.9999 -> 0
B43: Total Equity Yield | E43: =E39+E41 -> 0
B45: 45L Credits | D45: =D38 -> 0
W46: Total Funds
B47: Debt Sources: | H47: rate | I47: amortiz | J47: term | K47: principal | L47: annual DS | N47: annual DS/unit | Q47: DSCR Y1 | R47: DSCR Y15 | S47: DSCR Y20
B49: 1st Mortgage: | E49: Tax-Exempt Bonds (25% Test) | K49: =E8 -> 0 | L49: =PMT(H49/12,I49*12,K49)*-12 -> #NUM! | N49: =L49/G5 -> #NUM! | Q49: ='20yr Proforma'!F51 -> 0 | R49: ='20yr Proforma'!T51 -> 0 | S49: ='20yr Proforma'!Y51 -> 0 | W49: TBDPortion
F50: *10yr (4.05%) + 184bp spread + 25bp cushion | W50: Wells Portion | Y50: =Y46-Y49 -> 0
B51: 2nd Mortgage | E51: 2nd Mortgage | L51: =PMT(H51/12,I51*12,K51)*-12 -> #NUM! | N51: =L51/G5 -> #NUM!
B53: Soft Loan | E53: GAP Funding (TBD) | L53: =K53*H53 -> 0 | M53: cash flow-interest only | N53: =L53/G5 -> #DIV/0!
B55: Soft Loan B | L55: =K55*H55 -> 0 | N55: =L55/G5 -> #DIV/0!
B57: 4th Mortgage | E57: n.a.
B59: 5th Mortgage | E59: n.a.
B61: 6th Mortgage | E61: n. a.
D63: totals: | L63: =SUM(L49:L61) -> #NUM!
B66: Debt Sources:
E67: Bond Allocation: | G67: (Bond Issuer) | K67: ='25% Test'!F5 -> 0
E68: Construction Loan (Taxable) | H68: =0.04+0.0245+0.0015 -> 0.066 | I68: * | K68: ='Flow of Funds'!AD134 -> 0
E69: 25% Test Calculation: | K69: ='25% Test'!D10 -> #DIV/0!
F70: * rate is 30-day SOFR 4.00% + 245bp with 15 bps hedge

Sheet Amortization Table
A1: AMORTIZATION TABLE — DEBT CAPACITY ANALYSIS
A2: ='[1]Summary_Sources-Uses'!A2 -> #REF!
A3: Project Type
A5: LOAN ASSUMPTIONS
A6: Loan Amount (1st Mortgage) | C6: ='Perm Sources-Uses'!K49 -> 0
A7: Interest Rate | C7: ='Perm Sources-Uses'!H49 -> 0
A8: Amortization (years) | C8: ='Perm Sources-Uses'!I49 -> 0
A9: Loan Term (years) | C9: ='Perm Sources-Uses'!J49 -> 0
A10: Monthly Payment | C10: =IF(C6=0,0,-PMT(C7/12,C8*12,C6)) -> 0
A11: Annual Debt Service | C11: =C10*12 -> 0
A13: DEBT CAPACITY ANALYSIS
A14: Year 1 NOI | C14: ='20yr Proforma'!F24 -> #VALUE!
A15: Required DSCR (underwriting) | C15: 1.2
A16: Max Annual Debt Service at DSCR | C16: =IF(C15=0,0,C14/C15) -> #VALUE!
A17: Max Supportable Debt | C17: =IF(C7=0,0,-PV(C7/12,C8*12,C16/12)) -> 0
A19: AMORTIZATION SCHEDULE
A20: Year | B20: Beg. Balance | C20: Annual Payment | D20: Interest | E20: Principal | F20: End. Balance | G20: NOI | H20: DSCR
A21: 1 | B21: =C6 -> 0 | C21: =IF($C$6=0,0,$C$11) -> 0 | D21: =B21*$C$7 -> 0 | E21: =C21-D21 -> 0 | F21: =B21-E21 -> 0 | G21: ='20yr Proforma'!F24 -> #VALUE! | H21: =IF(C21=0,0,G21/C21) -> 0
A22: 2 | B22: =F21 -> 0 | C22: =IF($C$6=0,0,$C$11) -> 0 | D22: =B22*$C$7 -> 0 | E22: =C22-D22 -> 0 | F22: =B22-E22 -> 0 | G22: ='20yr Proforma'!G24 -> #VALUE! | H22: =IF(C22=0,0,G22/C22) -> 0
A23: 3 | B23: =F22 -> 0 | C23: =IF($C$6=0,0,$C$11) -> 0 | D23: =B23*$C$7 -> 0 | E23: =C23-D23 -> 0 | F23: =B23-E23 -> 0 | G23: ='20yr Proforma'!H24 -> #VALUE! | H23: =IF(C23=0,0,G23/C23) -> 0
A24: 4 | B24: =F23 -> 0 | C24: =IF($C$6=0,0,$C$11) -> 0 | D24: =B24*$C$7 -> 0 | E24: =C24-D24 -> 0 | F24: =B24-E24 -> 0 | G24: ='20yr Proforma'!I24 -> #VALUE! | H24: =IF(C24=0,0,G24/C24) -> 0
A25: 5 | B25: =F24 -> 0 | C25: =IF($C$6=0,0,$C$11) -> 0 | D25: =B25*$C$7 -> 0 | E25: =C25-D25 -> 0 | F25: =B25-E25 -> 0 | G25: ='20yr Proforma'!J24 -> #VALUE! | H25: =IF(C25=0,0,G25/C25) -> 0
A26: 6 | B26: =F25 -> 0 | C26: =IF($C$6=0,0,$C$11) -> 0 | D26: =B26*$C$7 -> 0 | E26: =C26-D26 -> 0 | F26: =B26-E26 -> 0 | G26: ='20yr Proforma'!K24 -> #VALUE! | H26: =IF(C26=0,0,G26/C26) -> 0
A27: 7 | B27: =F26 -> 0 | C27: =IF($C$6=0,0,$C$11) -> 0 | D27: =B27*$C$7 -> 0 | E27: =C27-D27 -> 0 | F27: =B27-E27 -> 0 | G27: ='20yr Proforma'!L24 -> #VALUE! | H27: =IF(C27=0,0,G27/C27) -> 0
A28: 8 | B28: =F27 -> 0 | C28: =IF($C$6=0,0,$C$11) -> 0 | D28: =B28*$C$7 -> 0 | E28: =C28-D28 -> 0 | F28: =B28-E28 -> 0 | G28: ='20yr Proforma'!M24 -> #VALUE! | H28: =IF(C28=0,0,G28/C28) -> 0
A29: 9 | B29: =F28 -> 0 | C29: =IF($C$6=0,0,$C$11) -> 0 | D29: =B29*$C$7 -> 0 | E29: =C29-D29 -> 0 | F29: =B29-E29 -> 0 | G29: ='20yr Proforma'!N24 -> #VALUE! | H29: =IF(C29=0,0,G29/C29) -> 0
A30: 10 | B30: =F29 -> 0 | C30: =IF($C$6=0,0,$C$11) -> 0 | D30: =B30*$C$7 -> 0 | E30: =C30-D30 -> 0 | F30: =B30-E30 -> 0 | G30: ='20yr Proforma'!O24 -> #VALUE! | H30: =IF(C30=0,0,G30/C30) -> 0
A31: 11 | B31: =F30 -> 0 | C31: =IF($C$6=0,0,$C$11) -> 0 | D31: =B31*$C$7 -> 0 | E31: =C31-D31 -> 0 | F31: =B31-E31 -> 0 | G31: ='20yr Proforma'!P24 -> #VALUE! | H31: =IF(C31=0,0,G31/C31) -> 0
A32: 12 | B32: =F31 -> 0 | C32: =IF($C$6=0,0,$C$11) -> 0 | D32: =B32*$C$7 -> 0 | E32: =C32-D32 -> 0 | F32: =B32-E32 -> 0 | G32: ='20yr Proforma'!Q24 -> #VALUE! | H32: =IF(C32=0,0,G32/C32) -> 0
A33: 13 | B33: =F32 -> 0 | C33: =IF($C$6=0,0,$C$11) -> 0 | D33: =B33*$C$7 -> 0 | E33: =C33-D33 -> 0 | F33: =B33-E33 -> 0 | G33: ='20yr Proforma'!R24 -> #VALUE! | H33: =IF(C33=0,0,G33/C33) -> 0
A34: 14 | B34: =F33 -> 0 | C34: =IF($C$6=0,0,$C$11) -> 0 | D34: =B34*$C$7 -> 0 | E34: =C34-D34 -> 0 | F34: =B34-E34 -> 0 | G34: ='20yr Proforma'!S24 -> #VALUE! | H34: =IF(C34=0,0,G34/C34) -> 0
A35: 15 | B35: =F34 -> 0 | C35: =IF($C$6=0,0,$C$11) -> 0 | D35: =B35*$C$7 -> 0 | E35: =C35-D35 -> 0 | F35: =B35-E35 -> 0 | G35: ='20yr Proforma'!T24 -> #VALUE! | H35: =IF(C35=0,0,G35/C35) -> 0
A36: 16 | B36: =F35 -> 0 | C36: =IF($C$6=0,0,$C$11) -> 0 | D36: =B36*$C$7 -> 0 | E36: =C36-D36 -> 0 | F36: =B36-E36 -> 0 | G36: ='20yr Proforma'!U24 -> #VALUE! | H36: =IF(C36=0,0,G36/C36) -> 0
A37: 17 | B37: =F36 -> 0 | C37: =IF($C$6=0,0,$C$11) -> 0 | D37: =B37*$C$7 -> 0 | E37: =C37-D37 -> 0 | F37: =B37-E37 -> 0 | G37: ='20yr Proforma'!V24 -> #VALUE! | H37: =IF(C37=0,0,G37/C37) -> 0
A38: 18 | B38: =F37 -> 0 | C38: =IF($C$6=0,0,$C$11) -> 0 | D38: =B38*$C$7 -> 0 | E38: =C38-D38 -> 0 | F38: =B38-E38 -> 0 | G38: ='20yr Proforma'!W24 -> #VALUE! | H38: =IF(C38=0,0,G38/C38) -> 0
A40: TOTALS | C40: =SUM(C21:C38) -> 0 | D40: =SUM(D21:D38) -> 0 | E40: =SUM(E21:E38) -> 0
A42: ="Balloon Balance at Maturity (Year "&C9&")" -> Balloon Balance at Maturity (Year 0) | C42: =F38 -> 0
A44: Cumulative Interest Paid | C44: =D40 -> 0
A45: Cumulative Principal Paid | C45: =E40 -> 0
A46: Interest as % of Total Payments | C46: =IF(C40=0,0,C44/C40) -> 0

Sheet DDF Note
A1: DEFERRED DEVELOPER FEE NOTE
A2: [Project Name]
A3: Project Type
A5: NOTE TERMS
A6: Total Developer Fee | C6: ='Developer Fee Schedule'!A9 -> 0
A7: Developer Fee Paid at Milestones (Max Fee) | C7: ='Developer Fee Schedule'!K9 -> 0
A8: Deferred Developer Fee (DDF) | C8: ='Perm Sources-Uses'!K20 -> 0
A9: % of Total Fee Deferred | C9: =C8/C6 -> #DIV/0!
A10: Interest Rate on DDF Note | C10: ='20yr Proforma'!D64 -> 0
A11: Payback Period (years) | C11: ='20yr Proforma'!E33 -> 12
A12: Payment Source | C12: Available Cash Flow after Debt Service & LP A/M Fee
A14: DEFERRED DEVELOPER FEE SCHEDULE
A15: Year | B15: Beg. DDF Balance | C15: Interest Accrued | D15: Cash Flow after DS | E15: LP A/M Fee | F15: Available for DDF | G15: DDF Payment | H15: End. DDF Balance | I15: Cumul. Paid
A16: 1 | B16: =$C$8 -> 0 | C16: =B16*$C$10 -> 0 | D16: ='20yr Proforma'!F39 -> #VALUE! | E16: =-'20yr Proforma'!F41 -> 8500 | F16: =MAX(D16-E16,0) -> #VALUE! | G16: =MIN(F16,B16+C16) -> #VALUE! | H16: =B16+C16-G16 -> #VALUE! | I16: =G16 -> #VALUE!
A17: 2 | B17: =H16 -> #VALUE! | C17: =B17*$C$10 -> #VALUE! | D17: ='20yr Proforma'!G39 -> #VALUE! | E17: =-'20yr Proforma'!G41 -> #VALUE! | F17: =MAX(D17-E17,0) -> #VALUE! | G17: =MIN(F17,B17+C17) -> #VALUE! | H17: =B17+C17-G17 -> #VALUE! | I17: =I16+G17 -> #VALUE!
A18: 3 | B18: =H17 -> #VALUE! | C18: =B18*$C$10 -> #VALUE! | D18: ='20yr Proforma'!H39 -> #VALUE! | E18: =-'20yr Proforma'!H41 -> #VALUE! | F18: =MAX(D18-E18,0) -> #VALUE! | G18: =MIN(F18,B18+C18) -> #VALUE! | H18: =B18+C18-G18 -> #VALUE! | I18: =I17+G18 -> #VALUE!
A19: 4 | B19: =H18 -> #VALUE! | C19: =B19*$C$10 -> #VALUE! | D19: ='20yr Proforma'!I39 -> #VALUE! | E19: =-'20yr Proforma'!I41 -> #VALUE! | F19: =MAX(D19-E19,0) -> #VALUE! | G19: =MIN(F19,B19+C19) -> #VALUE! | H19: =B19+C19-G19 -> #VALUE! | I19: =I18+G19 -> #VALUE!
A20: 5 | B20: =H19 -> #VALUE! | C20: =B20*$C$10 -> #VALUE! | D20: ='20yr Proforma'!J39 -> #VALUE! | E20: =-'20yr Proforma'!J41 -> #VALUE! | F20: =MAX(D20-E20,0) -> #VALUE! | G20: =MIN(F20,B20+C20) -> #VALUE! | H20: =B20+C20-G20 -> #VALUE! | I20: =I19+G20 -> #VALUE!
A21: 6 | B21: =H20 -> #VALUE! | C21: =B21*$C$10 -> #VALUE! | D21: ='20yr Proforma'!K39 -> #VALUE! | E21: =-'20yr Proforma'!K41 -> #VALUE! | F21: =MAX(D21-E21,0) -> #VALUE! | G21: =MIN(F21,B21+C21) -> #VALUE! | H21: =B21+C21-G21 -> #VALUE! | I21: =I20+G21 -> #VALUE!
A22: 7 | B22: =H21 -> #VALUE! | C22: =B22*$C$10 -> #VALUE! | D22: ='20yr Proforma'!L39 -> #VALUE! | E22: =-'20yr Proforma'!L41 -> #VALUE! | F22: =MAX(D22-E22,0) -> #VALUE! | G22: =MIN(F22,B22+C22) -> #VALUE! | H22: =B22+C22-G22 -> #VALUE! | I22: =I21+G22 -> #VALUE!
A23: 8 | B23: =H22 -> #VALUE! | C23: =B23*$C$10 -> #VALUE! | D23: ='20yr Proforma'!M39 -> #VALUE! | E23: =-'20yr Proforma'!M41 -> #VALUE! | F23: =MAX(D23-E23,0) -> #VALUE! | G23: =MIN(F23,B23+C23) -> #VALUE! | H23: =B23+C23-G23 -> #VALUE! | I23: =I22+G23 -> #VALUE!
A24: 9 | B24: =H23 -> #VALUE! | C24: =B24*$C$10 -> #VALUE! | D24: ='20yr Proforma'!N39 -> #VALUE! | E24: =-'20yr Proforma'!N41 -> #VALUE! | F24: =MAX(D24-E24,0) -> #VALUE! | G24: =MIN(F24,B24+C24) -> #VALUE! | H24: =B24+C24-G24 -> #VALUE! | I24: =I23+G24 -> #VALUE!
A25: 10 | B25: =H24 -> #VALUE! | C25: =B25*$C$10 -> #VALUE! | D25: ='20yr Proforma'!O39 -> #VALUE! | E25: =-'20yr Proforma'!O41 -> #VALUE! | F25: =MAX(D25-E25,0) -> #VALUE! | G25: =MIN(F25,B25+C25) -> #VALUE! | H25: =B25+C25-G25 -> #VALUE! | I25: =I24+G25 -> #VALUE!
A26: 11 | B26: =H25 -> #VALUE! | C26: =B26*$C$10 -> #VALUE! | D26: ='20yr Proforma'!P39 -> #VALUE! | E26: =-'20yr Proforma'!P41 -> #VALUE! | F26: =MAX(D26-E26,0) -> #VALUE! | G26: =MIN(F26,B26+C26) -> #VALUE! | H26: =B26+C26-G26 -> #VALUE! | I26: =I25+G26 -> #VALUE!
A27: 12 | B27: =H26 -> #VALUE! | C27: =B27*$C$10 -> #VALUE! | D27: ='20yr Proforma'!Q39 -> #VALUE! | E27: =-'20yr Proforma'!Q41 -> #VALUE! | F27: =MAX(D27-E27,0) -> #VALUE! | G27: =MIN(F27,B27+C27) -> #VALUE! | H27: =B27+C27-G27 -> #VALUE! | I27: =I26+G27 -> #VALUE!
A28: 13 | B28: =H27 -> #VALUE! | C28: =B28*$C$10 -> #VALUE! | D28: ='20yr Proforma'!R39 -> #VALUE! | E28: =-'20yr Proforma'!R41 -> #VALUE! | F28: =MAX(D28-E28,0) -> #VALUE! | G28: =MIN(F28,B28+C28) -> #VALUE! | H28: =B28+C28-G28 -> #VALUE! | I28: =I27+G28 -> #VALUE!
A29: 14 | B29: =H28 -> #VALUE! | C29: =B29*$C$10 -> #VALUE! | D29: ='20yr Proforma'!S39 -> #VALUE! | E29: =-'20yr Proforma'!S41 -> #VALUE! | F29: =MAX(D29-E29,0) -> #VALUE! | G29: =MIN(F29,B29+C29) -> #VALUE! | H29: =B29+C29-G29 -> #VALUE! | I29: =I28+G29 -> #VALUE!
A30: 15 | B30: =H29 -> #VALUE! | C30: =B30*$C$10 -> #VALUE! | D30: ='20yr Proforma'!T39 -> #VALUE! | E30: =-'20yr Proforma'!T41 -> #VALUE! | F30: =MAX(D30-E30,0) -> #VALUE! | G30: =MIN(F30,B30+C30) -> #VALUE! | H30: =B30+C30-G30 -> #VALUE! | I30: =I29+G30 -> #VALUE!
A32: TOTALS | C32: =SUM(C16:C30) -> #VALUE! | G32: =SUM(G16:G30) -> #VALUE!
A34: SUMMARY
A35: Deferred Developer Fee (original) | C35: =C8 -> 0
A36: Total Interest Accrued | C36: =C32 -> #VALUE!
A37: Total DDF Repaid | C37: =G32 -> #VALUE!
A38: Remaining Unpaid Balance | C38: =C35+C36-C37 -> #VALUE!
A39: % of DDF Repaid within Payback Period | C39: =C37/(C35+C36) -> #VALUE!
A41: Year DDF Fully Repaid | C41: =IFERROR(MATCH(0,H16:H30,0),"Not within "&C11&" years") -> Not within 12 years

Sheet Development Budget
A2: Development Costs & Tax Treatment
A3: Live Oak Residences | G3: ='Rent Schedule'!D26 -> 0 | K3: 46111
B5: MATCHES LHC CORE APP (4%) | J5: Construction:
G6: Total | I6: Per Unit | J6: Section 42 | K6: Notes
J7: Basis Eligible
B8: Acquisition Costs
C9: Land/Ground Lease Prepayment | G9: =I9*$G$3 -> 0 | I9: 3798.3607 | J9: =G9 -> 0
G10: =G9 -> 0 | H10: =G10 -> 0 | J10: =J9 -> 0
B11: Construction Costs
C12: Hard Costs | G12: =I12*$G$3 -> 0 | I12: 233754.33 | J12: =G12 -> 0
C13: Sitework & Related Fees | G13: =I13*$G$3 -> 0 | I13: 44196.721 | J13: =G13 -> 0
C14: Structured Parking | G14: =I14*$G$3 -> 0 | J14: 0
C15: Utility Connection Fees | G15: =I15*$G$3 -> 0 | I15: 2708.1967 | J15: =G15 -> 0
C16: GC Overhead | G16: =I16*$G$3 -> 0 | J16: 0
C17: GC Profit | G17: =I17*$G$3 -> 0 | J17: 0
C18: Builders Risk Insurance | G18: =I18*$G$3 -> 0 | J18: 0
C19: Payment and Performance Bond | G19: =I19*$G$3 -> 0 | J19: 0
C20: Construction Contingency (5%) | G20: =I20*$G$3 -> 0 | I20: 13897.552 | J20: =G20 -> 0
G21: =SUM(G12:G20) -> 0 | H21: =G21 -> 0 | J21: =SUM(J12:J20) -> 0
B22: Predevelopment Costs
C23: Property Appraisal | G23: =I23*$G$3 -> 0 | J23: 0
C24: Market Study | G24: =I24*$G$3 -> 0 | I24: 573.77049 | J24: =G24 -> 0
C25: Environmental Report(s) | G25: =I25*$G$3 -> 0 | I25: 459.01639 | J25: =G25 -> 0
C26: Soil Borings | G26: =I26*$G$3 -> 0 | I26: 737.70492 | J26: =G26 -> 0
C27: Boundary and Topographical Survey | G27: =I27*$G$3 -> 0 | I27: 295.08197 | J27: =G27 -> 0
C28: Zoning/Site Plan Fees | G28: =I28*$G$3 -> 0 | J28: 0
G29: =SUM(G23:G28) -> 0 | H29: =G29 -> 0 | J29: =SUM(J23:J28) -> 0
B30: Financing
C31: Construction Financing and Placement Fees | G31: =I31*$G$3 -> 0 | J31: 0
C32: Construction Loan Interest | G32: =I32*$G$3 -> 0 | I32: 16461.213 | J32: =G32 -> 0
C33: Bond Interst (Fully Drawn) | G33: =I33*$G$3 -> 0 | J33: =G33 -> 0
C34: Bond issuer Fee (APV) | G34: =I34*$G$3 -> 0 | J34: 0
C35: Lender's Legal Fees | G35: =I35*$G$3 -> 0 | I35: 459.01639 | J35: =G35 -> 0
C36: Construction Period Real Estate Tax | G36: =I36*$G$3 -> 0 | I36: 622.95082 | J36: =G36 -> 0
C37: GL Insurance & BR Security during construction | G37: =I37*$G$3 -> 0 | I37: 2377.0492 | J37: =G37 -> 0
C38: Performance & Payment Bonds | G38: =I38*$G$3 -> 0 | I38: 4169.2657 | J38: =G38 -> 0
C39: Freddie TEL legal & Associated Fees | G39: =I39*$G$3 -> 0 | J39: =G39 -> 0
G40: =SUM(G31:G39) -> 0 | H40: =G40 -> 0 | J40: =SUM(J31:J39) -> 0
B41: Professional Services
C42: Architectural Fee - Design | G42: =I42*$G$3 -> 0 | I42: 2860.6557 | J42: =G42 -> 0
C43: Project Management / GC Overhead | G43: =I43*$G$3 -> 0 | I43: 5559.021 | J43: =G43 -> 0
C44: Architectural Fee - Reimbursables | G44: =I44*$G$3 -> 0 | J44: 0
C45: Landscape Architect | G45: =I45*$G$3 -> 0 | J45: 0
C46: Engineering | G46: =I46*$G$3 -> 0 | I46: 1803.2787 | J46: =G46 -> 0
C47: Developer Attorney | G47: =I47*$G$3 -> 0 | J47: 0
C48: Legal (TBD) | G48: =I48*$G$3 -> 0 | J48: 0
C49: Accounting | G49: =I49*$G$3 -> 0 | I49: 491.80328 | J49: =G49 -> 0
C50: Green Building Certification/Registration | G50: =I50*$G$3 -> 0 | J50: 0
C51: Construction Inspection Fees | G51: =I51*$G$3 -> 0 | I51: 1500 | J51: =G51 -> 0
C52: Accessibility Consulting | G52: =I52*$G$3 -> 0 | J52: 0
C53: Construction Materials Testing | G53: =I53*$G$3 -> 0 | J53: 0
G54: =SUM(G42:G53) -> 0 | H54: =G54 -> 0 | J54: =SUM(J42:J53) -> 0
B55: Local Government Fees
C56: Building Permits | G56: =I56*$G$3 -> 0 | I56: 2636.0656 | J56: =G56 -> 0
C57: Impact Fees | G57: =I57*$G$3 -> 0 | I57: 1200 | J57: =G57 -> 0
C58: Plan review | G58: =I58*$G$3 -> 0 | I58: 122.95082 | J58: =G58 -> 0
C59: Other local fees | G59: =I59*$G$3 -> 0 | I59: 409.83607 | J59: =G59 -> 0
G60: =SUM(G56:G59) -> 0 | H60: =G60 -> 0 | J60: =SUM(J56:J59) -> 0
B61: Permanent Financing Fees
C62: Permanent Loan Fees | G62: =I62*$G$3 -> 0 | I62: 2817.4941 | J62: =G62 -> 0
C63: Permanent Loan Legal Fees | G63: =I63*$G$3 -> 0 | I63: 573.77049 | J63: =G63 -> 0
C64: Title and Recording Fees | G64: =I64*$G$3 -> 0 | I64: 360.65574 | J64: =G64 -> 0
C65: As-Built Survey | G65: =I65*$G$3 -> 0 | I65: 901.63934 | J65: =G65 -> 0
C66: Conversion Fee | G66: =I66*$G$3 -> 0 | J66: =G66 -> 0
G67: =SUM(G62:G66) -> 0 | H67: =G67 -> 0 | J67: =SUM(J62:J66) -> 0
B68: Tax Credit Costs
C69: Application Fee | G69: =I69*$G$3 -> 0 | I69: 41 | J69: =G69 -> 0 | O69: per unit
C70: Pre-application Fee | G70: =I70*$G$3 -> 0 | I70: 10 | J70: =G70 -> 0 | O70: per unit
C71: Commitment Fee | G71: =I71*$G$3 -> 0 | I71: 557.34426 | J71: =G71 -> 0 | O71: of annual LIHTC
C72: Bond Development Determination Fee | G72: =I72*$G$3 -> 0 | I72: 557.34426 | J72: =G72 -> 0 | O72: of annual LIHTC
C73: LIHTC Allocation Processing Fee | G73: =I73*$G$3 -> 0 | J73: =G73 -> 0
C74: LIHTC Compliance Monitoring Fee | G74: =I74*$G$3 -> 0 | I74: 40 | J74: =G74 -> 0 | O74: per tax credit unit
G75: =SUM(G69:G74) -> 0 | H75: =G75 -> 0 | J75: =SUM(J69:J74) -> 0
B76: Equity Costs
C77: Partnership Organization Fees | G77: =I77*$G$3 -> 0 | J77: =G77 -> 0
C78: Tax Credit Legal Opinion | G78: =I78*$G$3 -> 0 | J78: =G78 -> 0
C79: Syndicator Legal Fees | G79: =I79*$G$3 -> 0 | J79: =G79 -> 0
C80: Syndicator Due Diligence Fee | G80: =I80*$G$3 -> 0 | J80: =G80 -> 0
G81: =SUM(G77:G80) -> 0 | H81: =G81 -> 0 | J81: =SUM(J77:J80) -> 0
B82: Start Up and Reserves
C83: Marketing | G83: =I83*$G$3 -> 0 | J83: =G83 -> 0
C84: Rent-Up Reserves | G84: =I84*$G$3 -> 0 | J84: =G84 -> 0
C85: Operating Deficit Reserve | G85: =I85*$G$3 -> 0 | I85: 1229.5082 | J85: =G85 -> 0
C86: Replacement Reserve | G86: =I86*$G$3 -> 0 | I86: 300 | J86: =G86 -> 0
C87: Furniture, Fixtures and Equipment | G87: =I87*$G$3 -> 0 | I87: 800 | J87: =G87 -> 0
G88: =SUM(G83:G87) -> 0 | H88: =G88 -> 0 | J88: =SUM(J83:J87) -> 0
B89: Other Costs
C90: Soft Cost Contingency | G90: =I90*$G$3 -> 0 | I90: 2690.0651 | J90: =G90 -> 0
G91: =G90 -> 0 | H91: =G91 -> 0 | J91: =J90 -> 0
B92: Total, Excluding Developer Fee | G92: =G10+G21+G29+G40+G54+G60+G67+G75+G81+G88+G91 -> 0 | H92: =G92 -> 0 | I92: =IF($G$3=0,0,G92/$G$3) -> 0 | J92: =J10+J21+J29+J40+J54+J60+J67+J75+J81+J88+J91 -> 0
C93: Developer Fee | G93: =I93*$G$3 -> 0 | I93: =IF($G$3=0,0,G93/$G$3) -> 0 | J93: =G93 -> 0
B94: Total, With Developer Fee | G94: =G92+G93 -> 0 | H94: =G94 -> 0 | I94: =IF($G$3=0,0,G94/$G$3) -> 0 | J94: =J92+J93 -> 0
K96: Summary_Sources-Uses'!$A$2
K98: Page 3
H101: 0

Sheet Rent Schedule
A1: Live Oak Manor Residences — Phase 1
A2: Maximum Eligible & Projected Rents | K2: 46111 | U2: =K26*D26 -> 0
H3: PBV rents are 110% of 2025 FMR Rents | N3: 1971.2 | U3: =U2*12 -> 0
A4: RENT ROLL | H4: LIHTC rents are 2025 rents per Novogradac
H5: Utility Allowances (UA) are based on JHA 1/25 schedule
A6: Unit Type | B6: Set-Aside | C6: Income Limit | D6: Number of Units | E6: Avg NRSF | F6: Max Eligible Gross Rent | G6: UA | H6: Net Rent | I6: $/NRSF | K6: Annual Rent | N6: 0 | O6: 0 | P6: 0 | U6: =U3*20 -> 0
A7: 1 BR | B7: 30% LIHTC | C7: 0.3 | H7: =F7-G7 -> 0 | I7: =IF(E7=0,0,H7/E7) -> 0 | K7: =H7*D7*12 -> 0 | L7: LIHTC
A8: 1 BR | B8: 50% LIHTC | C8: 0.5 | H8: =F8-G8 -> 0 | I8: =IF(E8=0,0,H8/E8) -> 0 | K8: =H8*D8*12 -> 0 | L8: LIHTC | N8: Total Required HAP Vouchers from HHA | R8: =D26 -> 0
A9: 1 BR | B9: 60% LIHTC | C9: 0.6 | H9: =F9-G9 -> 0 | I9: =IF(E9=0,0,H9/E9) -> 0 | K9: =H9*D9*12 -> 0 | L9: LIHTC | N9: HAP Voucher Payment Standard | S9: of HUD FMR rent
A10: 2 BR | B10: 30% LIHTC | C10: 0.3 | H10: =F10-G10 -> 0 | I10: =IF(E10=0,0,H10/E10) -> 0 | K10: =H10*D10*12 -> 0 | L10: LIHTC | N10: Total Affordable Units below 60% AMI | R10: {=D26-SUMPRODUCT((B7:B25="Market")*(D7:D25))} -> 0
A11: 2 BR | B11: 50% LIHTC | C11: 0.5 | H11: =F11-G11 -> 0 | I11: =IF(E11=0,0,H11/E11) -> 0 | K11: =H11*D11*12 -> 0 | L11: LIHTC | W11: 1248.5
A12: 2 BR | B12: 60% LIHTC | C12: 0.6 | H12: =F12-G12 -> 0 | I12: =IF(E12=0,0,H12/E12) -> 0 | K12: =H12*D12*12 -> 0 | L12: LIHTC | W12: 1492.7
A13: 3 BR | B13: 30% LIHTC | C13: 0.3 | H13: =F13-G13 -> 0 | I13: =IF(E13=0,0,H13/E13) -> 0 | K13: =H13*D13*12 -> 0 | L13: LIHTC | W13: 1971.2
A14: 3 BR | B14: 50% LIHTC | C14: 0.5 | H14: =F14-G14 -> 0 | I14: =IF(E14=0,0,H14/E14) -> 0 | K14: =H14*D14*12 -> 0 | L14: LIHTC | P14: {=SUMPRODUCT((C7:C25=0.3)*(D7:D25))} -> 0 | Q14: 30% PBV
A15: 3 BR | B15: 60% LIHTC | C15: 0.6 | H15: =F15-G15 -> 0 | I15: =IF(E15=0,0,H15/E15) -> 0 | K15: =H15*D15*12 -> 0 | L15: LIHTC | P15: {=SUMPRODUCT((C7:C25=0.5)*(D7:D25))} -> 0 | Q15: 50% PBV
A16: 4 BR | B16: 30% LIHTC | C16: 0.3 | H16: =F16-G16 -> 0 | I16: =IF(E16=0,0,H16/E16) -> 0 | K16: =H16*D16*12 -> 0 | L16: LIHTC | P16: {=SUMPRODUCT((C7:C25=0.6)*(D7:D25))} -> 0 | Q16: 60% PBV
A17: 4 BR | B17: 50% LIHTC | C17: 0.5 | H17: =F17-G17 -> 0 | I17: =IF(E17=0,0,H17/E17) -> 0 | K17: =H17*D17*12 -> 0 | L17: LIHTC | P17: 0 | Q17: 60% LIHTC
A18: 4 BR | B18: 60% LIHTC | C18: 0.6 | H18: =F18-G18 -> 0 | I18: =IF(E18=0,0,H18/E18) -> 0 | K18: =H18*D18*12 -> 0 | L18: LIHTC | P18: =D19 -> 0 | Q18: market
A19: Market | B19: Market | H19: =F19-G19 -> 0 | I19: =IF(E19=0,0,H19/E19) -> 0 | K19: =H19*D19*12 -> 0 | L19: Market
A26: TOTAL | D26: =SUM(D7:D25) -> 0 | E26: =IF(D26=0,0,SUMPRODUCT(D7:D25,E7:E25)/D26) -> 0 | H26: =IF(D26=0,0,SUMPRODUCT(D7:D25,H7:H25)/D26) -> 0 | K26: =SUM(K7:K25) -> 0 | L26: =IF(D26=0,0,K26/D26) -> 0 | P26: Target Total Distribution | U26: Actual Distribution by Unit Type
D27: 1
A28: Other Income | F28: Per Unit/Mo. | H28: All Units/Mo. | K28: Annual Revenue
A29: Laundry Machine Collections | H29: 0 | K29: =H29*D26*12 -> 0
A30: Late Fees | H30: 610 | K30: =H30*D26*12 -> 0
A31: Application Fees | H31: 305 | K31: =H31*D26*12 -> 0
A32: Security Deposit Forfeitures | H32: 122 | K32: =H32*D26*12 -> 0
A33: Other | H33: 122 | K33: =H33*D26*12 -> 0 | M33: 0.44185311
F34: 19 | H34: =SUM(H29:H33) -> 1159 | K34: =SUM(K29:K33) -> 0
A35: Commerical Space | E35: SF | H35: Monthly | I35: per SF/mo | J35: per year | K35: Annual Revenue
A36: Commercial Space | I36: 0 | J36: 0
A38: Subsidy Type | C38: Units | D38: Share | H38: Gross Potential Income | K38: =K26 -> 0
A39: PHA Sec 8 PBV-HAP | C39: {=SUMPRODUCT((LEFT(B7:B25,3)="PBV")*(D7:D25))} -> 0 | D39: =IF(C42=0,0,C39/C42) -> 0 | H39: Other Income | K39: =K34 -> 0
A40: LIHTC | C40: {=SUMPRODUCT((LEFT(B7:B25,1)<>"")*(LEFT(B7:B25,3)<>"PBV")*(LEFT(B7:B25,3)<>"Mar")*(D7:D25))} -> 0 | D40: =IF(C42=0,0,C40/C42) -> 0 | H40: Commercial Income per year | K40: =J36 -> 0
A41: Market Rate | C41: {=SUMPRODUCT((B7:B25="Market")*(D7:D25))} -> 0 | D41: =IF(C42=0,0,C41/C42) -> 0 | H41: Vacancy | J41: 0.07 | K41: =-(K38+K39+K40)*J41 -> 0
A42: Total | C42: =SUM(C39:C41) -> 0 | D42: =SUM(D39:D41) -> 0 | H42: Net Income | K42: =K38+K39+K40+K41 -> 0
A44: Unit Count | C44: 3 BR | D44: 4 BR | F44: Total | H44: % of Total | I44: % of LI
A45: 30% LIHTC | C45: {=SUMPRODUCT((C7:C25=0.3)*(LEFT(A7:A25,1)="3")*(D7:D25))} -> 0 | D45: {=SUMPRODUCT((C7:C25=0.3)*(LEFT(A7:A25,1)="4")*(D7:D25))} -> 0 | F45: =SUM(C45:E45) -> 0 | H45: =IF(F51=0,0,F45/F51) -> 0 | I45: =IF(F51=0,0,F45/(F51-F50)) -> 0
A46: 60% LIHTC | C46: {=SUMPRODUCT((C7:C25>=0.6)*(LEFT(A7:A25,1)="3")*(D7:D25))} -> 0 | D46: {=SUMPRODUCT((C7:C25>=0.6)*(LEFT(A7:A25,1)="4")*(D7:D25))} -> 0 | F46: =SUM(C46:E46) -> 0 | H46: =IF(F51=0,0,F46/F51) -> 0 | I46: =IF(F51=0,0,F46/(F51-F50)) -> 0
F47: =SUM(C47:E47) -> 0 | H47: =IF(F51=0,0,F47/F51) -> 0 | I47: =IF(F51=0,0,F47/(F51-F50)) -> 0
F48: =SUM(C48:E48) -> 0 | H48: =IF(F51=0,0,F48/F51) -> 0 | I48: =IF(F51=0,0,F48/(F51-F50)) -> 0
F49: =SUM(C49:E49) -> 0 | H49: =IF(F51=0,0,F49/F51) -> 0 | I49: =IF(F51=0,0,F49/(F51-F50)) -> 0
F50: =SUM(C50:E50) -> 0 | H50: =IF(F51=0,0,F50/F51) -> 0
A51: Total | C51: =SUM(C45:C50) -> 0 | D51: =SUM(D45:D50) -> 0 | F51: =SUM(F45:F50) -> 0 | H51: =SUM(H45:H50) -> 0 | I51: =SUM(I45:I50) -> 0
A52: Unit Mix | C52: =IF(D26=0,0,C51/D26) -> 0 | D52: =IF(D26=0,0,D51/D26) -> 0 | F52: =IF(D26=0,0,F51/D26) -> 0
C56: =D26 -> 0 | D56: {=SUMPRODUCT((B7:B25="Market")*(D7:D25))} -> 0 | E56: =C56-D56 -> 0 | F56: 61
C57: =IF(C56=0,0,D27/C56) -> 0 | D57: =IF(C56=0,0,D56/C56) -> 0 | E57: =IF(C56=0,0,E56/C56) -> 0
A59: Utility | C59: Who Pays | D59: Energy Source | E59: 0-BR | F59: 1-BR | G59: 2-BR | H59: 3BR | I59: 4BR | K59: Source of Utility Allowance & Effective Date
A60: Heating | C60: Tenant | D60: Electric | K60: PHA 1/1/2026
A61: Cooking | C61: Tenant | D61: Electric | K61: PHA 1/1/2026
A62: Other Electric | C62: Tenant | K62: PHA 1/1/2026
A63: Air Conditioning | C63: Tenant | D63: Electric | K63: PHA 1/1/2026
A64: Water Heater | C64: Tenant | D64: Electric | K64: PHA 1/1/2026
A65: Water | C65: Tenant | K65: PHA 1/1/2026
A66: Sewer | C66: Tenant | K66: PHA 1/1/2026
A67: Trash | C67: Landlord
A68: Flat Fee | C68: Tenant | K68: PHA 1/1/2026
A69: Other | C69: Tenant
B70: Total Paid by Tenant | E70: $ - | F70: 206 | G70: 269 | H70: 331 | I70: $ -

Sheet Operating Expense
A1: OPERATING BUDGET / EXPENSES | M1: LOR Feasibility Analysis Template
A2: Project Name | M2: 46111
N3: NOTE: Expenses updated. Do not match LHC application
E5: Project | J5: Average of Comparable Properties
A6: EXPENSES | F6: units | J6: 61 | K6: units
A8: OPERATING EXPENSES | E8: 2027 Baseline | F8: per unit | J8: bad debt | K8: 108.98292
J9: other admin | K9: 370.96086
A10: TOTAL ADMINISTRATIVE EXPENSES | E10: 0 | F10: 450 | J10: 29276.57 | K10: 479.94378
A11: TOTAL MARKETING EXPENSES | E11: 0 | F11: 200 | J11: 1743.7306 | K11: 28.585747
A12: TOTAL PAYROLL EXPENSES | E12: 0 | F12: 1803.2787 | J12: 64858.662 | K12: 1063.2567
A13: TOTAL MAINTENANCE EXPENSES | E13: 0 | F13: 1407.0492 | J13: 32366.195 | K13: 530.59337
A14: TOTAL CONTRACT EXPENSES | E14: 0 | F14: 675 | G14: * adjusted for security expense | J14: 41931.692 | K14: 687.40479
A15: TOTAL UTILITY EXPENSES | E15: 0 | F15: 1195.9016 | G15: *adjusted for tenant paid utilities | J15: 42065.069 | K15: 689.59129
A16: TOTAL MANAGEMENT AND PROFESSIONAL EXPENSES | E16: 0 | F16: 997.03279 | J16: 46358.912 | K16: 759.98216
A17: TOTAL TAXES AND INSURANCE | E17: 0 | F17: 2500 | G17: *adjusted for flood insurance where applicable | J17: 43882.8 | K17: 719.39016
A18: Bond Issuer Fee (Annually) | E18: 0 | F18: 0
B20: TOTAL EXPENSE | E20: 562924 | F20: 9228.2623 | J20: 302483.63 | K20: 4958.748
B21: Replacement Reserves | E21: 18300 | F21: 300
B22: TOTAL EXPENSE + Repl Res. | E22: 581224 | F22: 9528.2623
A24: Property Taxes | G24: per unit
A25: W/o Property Taxes or replacement reserves | E25: 562924 | F25: 9228.2623 | G25: per unit
A28: Net Revenue | E28: 942655.44 | H28: 46910.333
A29: Expense Ratio | E29: 0.59716836 | F29: <- may not exceed 65% per TDHCA
A30: NOI/Net Revenue | E30: 0.40283164
A37: OPERATING BUDGET / EXPENSES
A38: COMPARABLES
G40: 2026 Full Year | I40: 2026 Full Year | K40: 2026 Full Year | M40: 2026 Full Year | O40: 2026 Full Year | Q40: 2026 Full Year
G41: Property Name #1 | I41: Property Name #2 | K41: Property Name #3 | M41: Property Name #4 | O41: Property Name #5 | Q41: Property Name #6
A42: EXPENSES | H42: units | J42: units | K42: 270 | L42: units | M42: 330 | N42: units | P42: units | R42: units
A44: OPERATING EXPENSES
B46: Bad Debt Expense | H46: 0 | J46: 0 | K46: 47873.01 | L46: 177.30744 | M46: 49265 | N46: 149.28788 | P46: 82.265929 | R46: 245.03627
B47: All Other Admin Expense | G47: 96635.82 | H47: 483.1791 | I47: 115284.62 | J47: 603.5844 | K47: 79063.2 | L47: 292.82667 | M47: 71665.96 | N47: 217.16958 | O47: 35454.08 | P47: 253.24343 | Q47: 175105.08 | R47: 375.76197
A48: TOTAL ADMINISTRATIVE EXPENSES | G48: 96635.82 | H48: 483.1791 | I48: 115284.62 | J48: 603.5844 | K48: 126936.21 | L48: 470.13411 | M48: 120930.96 | N48: 366.45745 | O48: 46971.31 | P48: 335.50936 | Q48: 289291.98 | R48: 620.79824
A49: TOTAL MARKETING EXPENSES | H49: 0 | J49: 0 | K49: 7986.05 | L49: 29.577963 | M49: 10952.49 | N49: 33.189364 | P49: 50.733786 | R49: 58.013369
A50: TOTAL PAYROLL EXPENSES | H50: 0 | J50: 0 | K50: 376100.39 | L50: 1392.9644 | M50: 528359.88 | N50: 1601.0905 | O50: 206601.03 | P50: 1475.7216 | R50: 1909.7639
A51: TOTAL MAINTENANCE EXPENSES | H51: 0 | J51: 0 | K51: 203205.79 | L51: 752.61404 | M51: 205305.75 | N51: 622.13864 | P51: 869.56064 | R51: 939.24689
A52: TOTAL CONTRACT EXPENSES | H52: 0 | J52: 0 | K52: 258642.18 | L52: 957.934 | M52: 292920.98 | N52: 887.63933 | O52: 84763.73 | P52: 605.45521 | R52: 1673.4002
A53: TOTAL UTILITY EXPENSES | C53: net of water/sewer collection | G53: 128012.75 | H53: 640.06375 | I53: 141397.59 | J53: 740.30152 | K53: 124275.6 | L53: 460.28 | M53: 500882.87 | N53: 1517.8269 | O53: 43891.65 | P53: 313.51179 | Q53: 216952.74 | R53: 465.56382
A54: TOTAL MANAGEMENT & PROFESSIONAL EXPENSES | H54: 0 | J54: 0 | K54: 318097.01 | L54: 1178.1371 | M54: 413436.6 | N54: 1252.8382 | P54: 1059.7732 | R54: 1069.1445
A55: TOTAL TAX & INSURANCE EXPENSES* | H55: 0 | J55: 0 | K55: 277166.78 | L55: 1026.5436 | M55: 24333.7 | N55: 73.738485 | P55: 1457.8077 | R55: 1758.2512
A56: * includes anticipated tax abatement for RAD/PBV
B57: TOTAL EXPENSES: | G57: 224648.57 | H57: 1123.2429 | I57: 256682.21 | J57: 1343.8859 | K57: 1692410 | L57: 6268.1852 | M57: 2097123.2 | N57: 6354.9189 | O57: 863530.27 | P57: 6168.0734 | Q57: 3958288.8 | R57: 8494.182
A59: TOTAL OPERATING EXPENSES
G60: includes full property tax; regional mgr charges | I60: no property tax payment; social services costs ($95K/yr); high w&s cost; high security cost | K60: combined two phases in single office; high contract labor; short-staffed | M60: low taxation; water & sewer paid by property; operates as combined site; insurance seems incorrect | O60: Full taxation; contract leasing & maint added into payroll; some shared cost with Ren II | Q60: water/sewer indiv billed; very high contract expenses; lower turn costs; PILOT taxes; very high insurance
A68: OPERATING EXPENSES | E68: Annual
A70: ADMINISTRATIVE EXPENSES
A71: Office Supplies / Postage
A72: Equipment Rental
A73: Travel
A74: Uniforms
A75: Employee Education/Training
A76: Cable/Internet Expense
A77: Telephones
A78: Computer Equipment
A79: Reports / Screening
A80: Social Entertainment
A81: TOTAL ADMINISTRATIVE EXPENSES | E81: 27450
A83: MARKETING EXPENSES
A84: Apartment Guide/Blue Book
A85: Promotional/Other Marketing
A86: TOTAL MARKETING EXPENSES | E86: 12200
A88: PAYROLL EXPENSES
A89: Manager
A90: Leasing Consultant
A91: Assistant Manager
A92: Resident Services
A93: Maintenance
A94: Grounds/Porter
A95: Benefits/Taxes | E95: 22000
A96: TOTAL PAYROLL EXPENSES | E96: 110000
A98: INTERIOR SUPPLIES & REPAIRS
A99: Cleaning/Painting
A100: Fire Inspection/Repairs
A101: Dryer Vent Cleaning
A102: EXTERIOR SUPPLIES & REPAIRS
A103: Grounds Supplies
A104: Landscape Supplies
A105: Maintenance Equipment/Supplies
A106: TOTAL MAINTENANCE EXPENSES | E106: 85830
A108: CONTRACT EXPENSES
A109: Landscaping
A110: Pest Control
A111: Sanitation
A112: Elevator
A113: Security Services
A114: TOTAL CONTRACT EXPENSES | E114: 41175
A116: UTILITY EXPENSES
A117: Water / Sewer
A118: Vacant Electricity
A119: Common Electricity
A120: Trash Collection
A121: TOTAL UTILITY EXPENSES | E121: 72950
A123: MANAGEMENT & PROFESSIONAL EXPENSES
A124: Management Fee
A125: Computer Software/Network
A126: Accounting Fees
A127: Legal Fees
A128: Resident Services | F128: update based on Apt Life quote
A129: Misc. Professional Fees
A130: TOTAL MANAGEMENT & PROFESSIONAL EXPENSES | E130: 60819
...

Sheet 20yr Proforma
A1: SUMMARY PROFORMA | D1: 46111
A2: Development Name: | F2: [Project Name] | K2: 46111
C4: Year | F4: 1 | G4: 2 | H4: 3 | I4: 4 | J4: 5 | K4: 6 | L4: 7 | M4: 8 | N4: 9 | O4: 10 | P4: 11 | Q4: 12 | R4: 13 | S4: 14 | T4: 15 | U4: 16 | V4: 17 | W4: 18 | X4: 19 | Y4: 20
A5: Units: | C5: =_xlfn.SINGLE(TotalUnitCount) -> 61 | F5: Annual Income Growth Rate: | H5: 0.02 | I5: Vacancy Loss | K5: Annual Operating Expense/unit | M5: 9228.2623 | N5: * on sqr. foot basis | O5: LP Investor Asset Mgmt Fee: | R5: fee increases 3% per annum
A6: Total Rentable SF: | C6: ='Rent Schedule'!E26*'Rent Schedule'!D26 -> 0 | F6: Annual Expense Growth Rate: | K6: Annual Replacement Reserve/unit | M6: 300 | O6: Other Asset Mgmt. Fee: | R6: fee increases 3% per annum
A7: Stabilized Year 1 = | M7: 9528.2623 | O7: SLP Asset Mgt fee | R7: fee increases 3% per annum
F9: Year 1 | G9: Year 2 | H9: Year 3 | I9: Year 4 | J9: Year 5 | K9: Year 6 | L9: Year 7 | M9: Year 8 | N9: Year 9 | O9: Year 10 | P9: Year 11 | Q9: Year 12 | R9: Year 13 | S9: Year 14 | T9: Year 15 | U9: Year 16 | V9: Year 17 | W9: Year 18 | X9: Year 19 | Y9: Year 20
E10: baseline | G10: 2029 | H10: 2030 | I10: 2031 | J10: 2032 | K10: 2033 | L10: 2034 | M10: 2035 | N10: 2036 | O10: 2037 | P10: 2038 | Q10: 2039 | R10: 2040 | S10: 2041 | T10: 2042 | U10: 2043 | V10: 2044 | W10: 2045 | X10: 2046 | Y10: 2047
E11: * note that rents/expenses are trended from current levels
A12: Total Potential Rent Income | E12: ='Rent Schedule'!K26 -> 0 | F12: =E12*(1+$H$5) -> 0 | G12: =F12*(1+$H$5) -> 0 | H12: =G12*(1+$H$5) -> 0 | I12: =H12*(1+$H$5) -> 0 | J12: =I12*(1+$H$5) -> 0 | K12: =J12*(1+$H$5) -> 0 | L12: =K12*(1+$H$5) -> 0 | M12: =L12*(1+$H$5) -> 0 | ... Y12: =X12*(1+$H$5) -> 0
A13: ADD: | B13: Commercial + Other Income | E13: =K29+K30 -> 0 | F13: =E13*(1+$H$5) -> 0 | G13: =F13*(1+$H$5) -> 0 | H13: =G13*(1+$H$5) -> 0 | I13: =H13*(1+$H$5) -> 0 | J13: =I13*(1+$H$5) -> 0 | K13: =J13*(1+$H$5) -> 0 | L13: =K13*(1+$H$5) -> 0 | M13: =L13*(1+$H$5) -> 0 | ... Y13: =X13*(1+$H$5) -> 0
A15: Gross Potential Income | E15: =E12+E13 -> 0 | F15: =F12+F13 -> 0 | G15: =G12+G13 -> 0 | H15: =H12+H13 -> 0 | I15: =I12+I13 -> 0 | J15: =J12+J13 -> 0 | K15: =K12+K13 -> 0 | L15: =L12+L13 -> 0 | ... Y15: =Y12+Y13 -> 0
A17: LESS: | B17: Vacancy Allowance/Bad Debts/Concessions | E17: =E15*J5 -> 0 | F17: =F15*$J$5 -> 0 | G17: =G15*$J$5 -> 0 | H17: =H15*$J$5 -> 0 | I17: =I15*$J$5 -> 0 | J17: =J15*$J$5 -> 0 | K17: =K15*$J$5 -> 0 | L17: =L15*$J$5 -> 0 | M17: =M15*$J$5 -> 0 | ... Y17: =Y15*$J$5 -> 0
A19: Stabilized Income | E19: =E15-E17 -> 0 | F19: =F15-F17 -> 0 | G19: =G15-G17 -> 0 | H19: =H15-H17 -> 0 | I19: =I15-I17 -> 0 | J19: =J15-J17 -> 0 | K19: =K15-K17 -> 0 | L19: =L15-L17 -> 0 | ... Y19: =Y15-Y17 -> 0
A21: LESS: | B21: Operating Expenses | E21: ='Operating Expense'!H19 -> 0 | F21: =E21*(1+$I$5) -> #VALUE! | G21: =F21*(1+$I$5) -> #VALUE! | H21: =G21*(1+$I$5) -> #VALUE! | I21: =H21*(1+$I$5) -> #VALUE! | J21: =I21*(1+$I$5) -> #VALUE! | K21: =J21*(1+$I$5) -> #VALUE! | L21: =K21*(1+$I$5) -> #VALUE! | M21: =L21*(1+$I$5) -> #VALUE! | ... Y21: =X21*(1+$I$5) -> #VALUE!
A22: ADD: Property Tax Reduction | D22: yes | E22: 0 | F22: 0 | G22: 0 | H22: 0 | I22: 0 | J22: 0 | K22: 0 | L22: 0 | M22: 0 | N22: 0 | O22: 0 | P22: 0 | Q22: 0 | R22: 0 | S22: 0 | T22: 0 | U22: 0 | V22: 0 | W22: 0 | X22: 0 | Y22: 0
A23: LESS: | B23: Replacement Reserves | E23: ='Operating Expense'!H31 -> 0 | F23: =E23*(1+$I$5) -> #VALUE! | G23: =F23*(1+$I$5) -> #VALUE! | H23: =G23*(1+$I$5) -> #VALUE! | I23: =H23*(1+$I$5) -> #VALUE! | J23: =I23*(1+$I$5) -> #VALUE! | K23: =J23*(1+$I$5) -> #VALUE! | L23: =K23*(1+$I$5) -> #VALUE! | M23: =L23*(1+$I$5) -> #VALUE! | ... Y23: =X23*(1+$I$5) -> #VALUE!
A24: Net Operating Income | E24: =E19-E21+E22-E23 -> 0 | F24: =F19-F21+F22-F23 -> #VALUE! | G24: =G19-G21+G22-G23 -> #VALUE! | H24: =H19-H21+H22-H23 -> #VALUE! | I24: =I19-I21+I22-I23 -> #VALUE! | J24: =J19-J21+J22-J23 -> #VALUE! | K24: =K19-K21+K22-K23 -> #VALUE! | L24: =L19-L21+L22-L23 -> #VALUE! | ... Y24: =Y19-Y21+Y22-Y23 -> #VALUE!
B26: SCHEDULED DEBT SERVICE:
A27: LESS: | B27: Debt Service 1st | E27: =IFERROR(#REF!,0) -> 0 | F27: =IFERROR(#REF!,0) -> 0 | G27: =F27 -> 0 | H27: =G27 -> 0 | I27: =H27 -> 0 | J27: =I27 -> 0 | K27: =J27 -> 0 | L27: =K27 -> 0 | M27: =L27 -> 0 | N27: =M27 -> 0 | ... Y27: =X27 -> 0
B28: Debt Service 2nd | E28: =IFERROR(#REF!,0) -> 0 | F28: =IFERROR(#REF!,0) -> 0 | G28: =F28 -> 0 | H28: =G28 -> 0 | I28: =H28 -> 0 | J28: =I28 -> 0 | K28: =J28 -> 0 | L28: =K28 -> 0 | M28: =L28 -> 0 | N28: =M28 -> 0 | ... Y28: =X28 -> 0
B29: Debt Service 3rd | E29: =IFERROR(#REF!,0) -> 0 | F29: =IFERROR(#REF!,0) -> 0 | G29: =F29 -> 0 | H29: =G29 -> 0 | I29: =H29 -> 0 | J29: =I29 -> 0 | K29: =J29 -> 0 | L29: =K29 -> 0 | M29: =L29 -> 0 | N29: =M29 -> 0 | ... Y29: =X29 -> 0
B30: Debt Service 4th | E30: 0 | F30: =IFERROR(#REF!,0) -> 0 | G30: =F30 -> 0 | H30: =G30 -> 0 | I30: =H30 -> 0 | J30: =I30 -> 0 | K30: =J30 -> 0 | L30: =K30 -> 0 | M30: =L30 -> 0 | N30: =M30 -> 0 | ... Y30: =X30 -> 0
B31: Debt Service 5th | E31: 0 | F31: =IFERROR(#REF!,0) -> 0 | G31: =F31 -> 0 | H31: =G31 -> 0 | I31: =H31 -> 0 | J31: =I31 -> 0 | K31: =J31 -> 0 | L31: =K31 -> 0 | M31: =L31 -> 0 | N31: =M31 -> 0 | ... Y31: =X31 -> 0
B32: Debt Service 6th
C33: deferred fee note | E33: 12 | F33: =F39+F41 -> #VALUE! | G33: =G39+G41 -> #VALUE! | H33: =H39+H41 -> #VALUE! | I33: =I39+I41 -> #VALUE! | J33: =J39+J41 -> #VALUE! | K33: =K39+K41 -> #VALUE! | L33: =L39+L41 -> #VALUE! | M33: =M39+M41 -> #VALUE! | ... Y33: =Y39+Y41 -> #VALUE!
A35: Operating Cash Flow Waterfall:
B36: Net Operating Income: | E36: =E24 -> 0 | F36: =F24 -> #VALUE! | G36: =G24 -> #VALUE! | H36: =H24 -> #VALUE! | I36: =I24 -> #VALUE! | J36: =J24 -> #VALUE! | K36: =K24 -> #VALUE! | L36: =L24 -> #VALUE! | ... Y36: =Y24 -> #VALUE!
B37: (less) First mortgage debt | E37: =-E27 -> 0 | F37: =-F27 -> 0 | G37: =-G27 -> 0 | H37: =-H27 -> 0 | I37: =-I27 -> 0 | J37: =-J27 -> 0 | K37: =-K27 -> 0 | L37: =-L27 -> 0 | ... Y37: =-Y27 -> 0
B38: (less) Second mortgage debt_HHA | E38: =-E28 -> 0 | F38: =-F28 -> 0 | G38: =-G28 -> 0 | H38: =-H28 -> 0 | I38: =-I28 -> 0 | J38: =-J28 -> 0 | K38: =-K28 -> 0 | L38: =-L28 -> 0 | ... Y38: =-Y28 -> 0
B39: Cash Flow after 1st Mortg Debt: | E39: =E36+E37+E38 -> 0 | F39: =F36+F37+F38 -> #VALUE! | G39: =G36+G37+G38 -> #VALUE! | H39: =H36+H37+H38 -> #VALUE! | I39: =I36+I37+I38 -> #VALUE! | J39: =J36+J37+J38 -> #VALUE! | K39: =K36+K37+K38 -> #VALUE! | L39: =L36+L37+L38 -> #VALUE! | ... Y39: =Y36+Y37+Y38 -> #VALUE!
B41: (less) Investor LP Asset Mgmt fee | E41: from cash flow | F41: =-F82 -> -8500 | G41: =-G82 -> #VALUE! | H41: =-H82 -> #VALUE! | I41: =-I82 -> #VALUE! | J41: =-J82 -> #VALUE! | K41: =-K82 -> #VALUE! | L41: =-L82 -> #VALUE! | M41: =-M82 -> #VALUE! | ... Y41: =-Y82 -> #VALUE!
B42: (less) payment to DDF | E42: from cash flow -to P&I | F42: =-IF(SUM(F39:F41)>0,MIN(SUM(F39:F41),F63),0) -> #VALUE! | G42: =-IF(SUM(G39:G41)>0,MIN(SUM(G39:G41),G63),0) -> #VALUE! | H42: =-IF(SUM(H39:H41)>0,MIN(SUM(H39:H41),H63),0) -> #VALUE! | I42: =-IF(SUM(I39:I41)>0,MIN(SUM(I39:I41),I63),0) -> #VALUE! | J42: =-IF(SUM(J39:J41)>0,MIN(SUM(J39:J41),J63),0) -> #VALUE! | K42: =-IF(SUM(K39:K41)>0,MIN(SUM(K39:K41),K63),0) -> #VALUE! | L42: =-IF(SUM(L39:L41)>0,MIN(SUM(L39:L41),L63),0) -> #VALUE! | M42: =-IF(SUM(M39:M41)>0,MIN(SUM(M39:M41),M63),0) -> #VALUE! | ... Y42: =-IF(SUM(Y39:Y41)>0,MIN(SUM(Y39:Y41),Y63),0) -> #VALUE!
B43: (less) SLP Asset Mgmt fee-Columbia SLP | E43: from cash flow | F43: 0 | G43: 0 | H43: 0 | I43: 0 | J43: 0 | K43: 0 | L43: 0 | M43: 0 | N43: 0 | O43: 0 | P43: 0 | Q43: 0 | R43: 0 | S43: 0 | T43: 0 | U43: 0 | V43: 0 | W43: 0 | X43: 0 | Y43: 0
B44: (less) Cash Flow to Investor LP | E44: from cash flow | F44: 0 | G44: 0 | H44: 0 | I44: 0 | J44: 0 | K44: 0 | L44: 0 | M44: 0 | N44: 0 | O44: 0 | P44: 0 | Q44: 0 | R44: 0 | S44: 0 | T44: 0 | U44: 0 | V44: 0 | W44: 0 | X44: 0 | Y44: 0
B45: (less) Cashflow to GP/SLP | E45: from cash flow | F45: 0 | G45: 0 | H45: 0 | I45: 0 | J45: 0 | K45: 0 | L45: 0 | M45: 0 | N45: 0 | O45: 0 | P45: 0 | Q45: 0 | R45: 0 | S45: 0 | T45: 0 | U45: 0 | V45: 0 | W45: 0 | X45: 0 | Y45: 0
B46: (less) Incentive Mgmt Fee to GP/SLP | E46: from cash flow | F46: 0 | G46: 0 | H46: 0 | I46: 0 | J46: 0 | K46: 0 | L46: 0 | M46: 0 | N46: 0 | O46: 0 | P46: 0 | Q46: 0 | R46: 0 | S46: 0 | T46: 0 | U46: 0 | V46: 0 | W46: 0 | X46: 0 | Y46: 0
B47: (less) 2nd mortgage debt-HHA | E47: from cash flow -to P&I | F47: =#REF!+#REF! -> #REF! | G47: =F47 -> #REF! | H47: =G47 -> #REF! | I47: =H47 -> #REF! | J47: =I47 -> #REF! | K47: =J47 -> #REF! | L47: =K47 -> #REF! | M47: =L47 -> #REF! | N47: =M47 -> #REF! | ... Y47: =X47 -> #REF!
B48: (less) | E48: from cash flow -to P&I | F48: 0 | G48: 0 | H48: 0 | I48: 0 | J48: 0 | K48: 0 | L48: 0 | M48: 0 | N48: 0 | O48: 0 | P48: 0 | Q48: 0 | R48: 0 | S48: 0 | T48: 0 | U48: 0 | V48: 0 | W48: 0 | X48: 0 | Y48: 0
B49: Net Cash Flow | E49: =SUM(E39:E48) -> 0 | F49: =SUM(F39:F48) -> #VALUE! | G49: =SUM(G39:G48) -> #VALUE! | H49: =SUM(H39:H48) -> #VALUE! | I49: =SUM(I39:I48) -> #VALUE! | J49: =SUM(J39:J48) -> #VALUE! | K49: =SUM(K39:K48) -> #VALUE! | L49: =SUM(L39:L48) -> #VALUE! | ... Y49: =SUM(Y39:Y48) -> #VALUE!
B51: DSC - 1st & 2nd Mrgt | E51: =IF(-(E37+E38)=0,0,E36/-(E37+E38)) -> 0 | F51: =IF(-(F37+F38)=0,0,F36/-(F37+F38)) -> 0 | G51: =IF(-(G37+G38)=0,0,G36/-(G37+G38)) -> 0 | H51: =IF(-(H37+H38)=0,0,H36/-(H37+H38)) -> 0 | I51: =IF(-(I37+I38)=0,0,I36/-(I37+I38)) -> 0 | J51: =IF(-(J37+J38)=0,0,J36/-(J37+J38)) -> 0 | K51: =IF(-(K37+K38)=0,0,K36/-(K37+K38)) -> 0 | L51: =IF(-(L37+L38)=0,0,L36/-(L37+L38)) -> 0 | ... Y51: =IF(-(Y37+Y38)=0,0,Y36/-(Y37+Y38)) -> 0
B52: DSC 1st & subordinate mortgages+DDF | F52: =IF(-(F37+F38+F42)=0,0,F36/-(F37+F38+F42)) -> #VALUE! | G52: =IF(-(G37+G38+G42)=0,0,G36/-(G37+G38+G42)) -> #VALUE! | H52: =IF(-(H37+H38+H42)=0,0,H36/-(H37+H38+H42)) -> #VALUE! | I52: =IF(-(I37+I38+I42)=0,0,I36/-(I37+I38+I42)) -> #VALUE! | J52: =IF(-(J37+J38+J42)=0,0,J36/-(J37+J38+J42)) -> #VALUE! | K52: =IF(-(K37+K38+K42)=0,0,K36/-(K37+K38+K42)) -> #VALUE! | L52: =IF(-(L37+L38+L42)=0,0,L36/-(L37+L38+L42)) -> #VALUE! | M52: =IF(-(M37+M38+M42)=0,0,M36/-(M37+M38+M42)) -> #VALUE! | ... Y52: =IF(-(Y37+Y38+Y42)=0,0,Y36/-(Y37+Y38+Y42)) -> #VALUE!
C54: =SUM(F54:Y54) -> #REF! | F54: =IF(F63>0,1,0) -> #REF! | G54: =IF(G63>0,1,0) -> #REF! | H54: =IF(H63>0,1,0) -> #REF! | I54: =IF(I63>0,1,0) -> #REF! | J54: =IF(J63>0,1,0) -> #REF! | K54: =IF(K63>0,1,0) -> #REF! | L54: =IF(L63>0,1,0) -> #REF! | M54: =IF(M63>0,1,0) -> #REF! | ... Y54: =IF(Y63>0,1,0) -> #REF!
B55: Total Cash Flow to AHA (prior to residual CF split):
B56: (incl A/M fee; share of DDF; cash flow loan) | F56: 0 | G56: 0 | H56: 0 | I56: 0 | J56: 0 | K56: 0 | L56: 0 | M56: 0 | N56: 0 | O56: 0 | P56: 0 | Q56: 0 | R56: 0 | S56: 0 | T56: 0 | U56: 0 | V56: 0 | W56: 0 | X56: 0 | Y56: 0
B58: Total Cash Flow to ELHC (prior to residual CF split):
B59: (incl A/M fee; share of DDF; cash flow loan)
B61: Total Cash Flow to AHA (prior to residual CF split):
B62: (incl A/M fee; share of DDF; cash flow loan)
C63: DDF Balance & Payments | F63: =#REF! -> #REF! | G63: =F63+F64+F65 -> #REF! | H63: =G63+G64+G65 -> #REF! | I63: =H63+H64+H65 -> #REF! | J63: =I63+I64+I65 -> #REF! | K63: =J63+J64+J65 -> #REF! | L63: =K63+K64+K65 -> #REF! | M63: =L63+L64+L65 -> #REF! | N63: =M63+M64+M65 -> #REF! | ... Y63: =X63+X64+X65 -> #REF!
C64: Interest | F64: 0 | G64: 0 | H64: 0 | I64: 0 | J64: 0 | K64: 0 | L64: 0 | M64: 0 | N64: 0 | O64: 0 | P64: 0 | Q64: 0 | R64: 0 | S64: 0 | T64: 0 | U64: 0 | V64: 0 | W64: 0 | X64: 0 | Y64: 0
C65: Payments | E65: -1972779.1 | F65: =F42 -> #VALUE! | G65: =G42 -> #VALUE! | H65: =H42 -> #VALUE! | I65: =I42 -> #VALUE! | J65: =J42 -> #VALUE! | K65: =K42 -> #VALUE! | L65: =L42 -> #VALUE! | M65: =M42 -> #VALUE! | ... Y65: =Y42 -> #VALUE!
B68: HHA Share of Paid Devel Fee: | E68: =(#REF!-#REF!)*0.4 -> #REF! | F68: =(#REF!-#REF!)*0.4 -> #REF! | G68: =F68 -> #REF! | H68: =G68 -> #REF! | I68: =H68 -> #REF! | J68: =I68 -> #REF! | K68: =J68 -> #REF! | L68: =K68 -> #REF! | M68: =L68 -> #REF! | N68: =M68 -> #REF! | ... Y68: =X68 -> #REF!
B69: HHA Share of Deferred Devel Fee: | E69: 676086.21 | F69: =-F42*0.4 -> #VALUE! | G69: =-G42*0.4 -> #VALUE! | H69: =-H42*0.4 -> #VALUE! | I69: =-I42*0.4 -> #VALUE! | J69: =-J42*0.4 -> #VALUE! | K69: =-K42*0.4 -> #VALUE! | L69: =-L42*0.4 -> #VALUE! | M69: =-M42*0.4 -> #VALUE! | ... Y69: =-Y42*0.4 -> #VALUE!
B70: HHA 2nd Mortgage Loan Pmts (HHA Soft): | E70: 742314.01 | F70: 0 | G70: 0 | H70: 0 | I70: 0 | J70: 0 | K70: 0 | L70: 0 | M70: 0 | N70: 0 | O70: 0 | P70: 0 | Q70: 0 | R70: 0 | S70: 0 | T70: 0 | U70: 0 | V70: 0 | W70: 0 | X70: 0 | Y70: 0 | Z70: 81605.277 | AA70: 84053.436 | AB70: 86575.039 | AC70: 89172.29 | AD70: 91847.459 | AE70: 94602.882 | AF70: 97440.969 | AG70: 100364.2 | AH70: 103375.12 | AI70: 106476.38
B71: HHA 3rd Mortgage Loan Pmts (FEMA): | E71: 0 | F71: 0 | G71: 0 | H71: 0 | I71: 0 | J71: 0 | K71: 0 | L71: 0 | M71: 0 | N71: 0 | O71: 0 | P71: 0 | Q71: 0 | R71: 0 | S71: 0 | T71: 0 | U71: 0 | V71: 0 | W71: 0 | X71: 0 | Y71: 0 | Z71: 0 | AA71: 0 | AB71: 0 | AC71: 0 | AD71: 0 | AE71: 0 | AF71: 0 | AG71: 0 | AH71: 0 | AI71: 0
B72: HHA Share of Net Cash Flow: | E72: 296925.6 | F72: 0 | G72: 0 | H72: 0 | I72: 0 | J72: 0 | K72: 0 | L72: 72.904964 | M72: 38388.982 | N72: 38116.975 | O72: 37800.43 | P72: 37437.283 | Q72: 37025.393 | R72: 36562.542 | S72: 36046.428 | T72: 35474.666 | U72: 34844.784 | V72: 34154.218 | W72: 33400.312 | X72: 32580.313 | Y72: 31691.37 | Z72: 31691.37 | AA72: 31691.37 | AB72: 31691.37 | AC72: 31691.37 | AD72: 31691.37 | AE72: 31691.37 | AF72: 31691.37 | AG72: 31691.37 | AH72: 31691.37 | AI72: 31691.37
B73: 15 Year Total: | E73: 1715325.8
C75: HHA Loan Info-2nd and 3rd Combined
D76: Principal | F76: 0 | G76: 0 | H76: 0 | I76: 0 | J76: 0 | K76: 0 | L76: 0 | M76: -182.26241 | N76: -96154.717 | O76: -191447.16 | P76: -285948.23 | Q76: -379541.44 | R76: -472104.92 | S76: -563511.27 | T76: -653627.34 | U76: -742314.01 | V76: -829425.97 | W76: -914811.51 | X76: -998312.29 | Y76: -1079763.1
D77: Interest | F77: 0 | G77: 0 | H77: 0 | I77: 0 | J77: 0 | K77: 0 | L77: 0 | M77: 0 | N77: 0 | O77: 0 | P77: 0 | Q77: 0 | R77: 0 | S77: 0 | T77: 0 | U77: 0 | V77: 0 | W77: 0 | X77: 0 | Y77: 0
D78: Payments | F78: 0 | G78: 0 | H78: 0 | I78: 0 | J78: 0 | K78: 0 | L78: -182.26241 | M78: -95972.455 | N78: -95292.438 | O78: -94501.075 | P78: -93593.207 | Q78: -92563.482 | R78: -91406.354 | S78: -90116.07 | T78: -88686.665 | U78: -87111.959 | V78: -85385.544 | W78: -83500.779 | X78: -81450.783 | Y78: -79228.425
D79: Cummulative Balance | F79: 0 | G79: 0 | H79: 0 | I79: 0 | J79: 0 | K79: 0 | L79: -182.26241 | M79: -96154.717 | N79: -191447.16 | O79: -285948.23 | P79: -379541.44 | Q79: -472104.92 | R79: -563511.27 | S79: -653627.34 | T79: -742314.01 | U79: -829425.97 | V79: -914811.51 | W79: -998312.29 | X79: -1079763.1 | Y79: -1158991.5
B81: Asset Mgmt Fees projection;
C82: LP Investor Asset Mgmt Fee: | F82: 8500 | G82: =F82*(1+$I$5) -> #VALUE! | H82: =G82*(1+$I$5) -> #VALUE! | I82: =H82*(1+$I$5) -> #VALUE! | J82: =I82*(1+$I$5) -> #VALUE! | K82: =J82*(1+$I$5) -> #VALUE! | L82: =K82*(1+$I$5) -> #VALUE! | M82: =L82*(1+$I$5) -> #VALUE! | N82: =M82*(1+$I$5) -> #VALUE! | ... Y82: =X82*(1+$I$5) -> #VALUE!
C83: SLP Asset Mgt fee | F83: =F82 -> 8500 | G83: =G82 -> #VALUE! | H83: =H82 -> #VALUE! | I83: =I82 -> #VALUE! | J83: =J82 -> #VALUE! | K83: =K82 -> #VALUE! | L83: =L82 -> #VALUE! | M83: =M82 -> #VALUE! | ... Y83: =Y82 -> #VALUE!
B86: Incentive Management Fee
B87: Potential Incentive Mgmt Fee | F87: 0 | G87: 0 | H87: 0 | I87: 0 | J87: 0 | K87: 0 | L87: 0 | M87: 0 | N87: 0 | O87: 0 | P87: 0 | Q87: 0 | R87: 0 | S87: 0 | T87: 0 | U87: 0 | V87: 0 | W87: 0 | X87: 0 | Y87: 0
B88: Max Incentive Mgmt Fee* | F88: =0.12*F19 -> 0 | G88: =0.12*G19 -> 0 | H88: =0.12*H19 -> 0 | I88: =0.12*I19 -> 0 | J88: =0.12*J19 -> 0 | K88: =0.12*K19 -> 0 | L88: =0.12*L19 -> 0 | M88: =0.12*M19 -> 0 | ... Y88: =0.12*Y19 -> 0
B89: Incentive Mgmt Fee Paid | F89: 0 | G89: 0 | H89: 0 | I89: 0 | J89: 0 | K89: 0 | L89: 0 | M89: 0 | N89: 0 | O89: 0 | P89: 0 | Q89: 0 | R89: 0 | S89: 0 | T89: 0 | U89: 0 | V89: 0 | W89: 0 | X89: 0 | Y89: 0
C90: ***Sum of Incentive Management Fee, management fees (assumed 6%) and asset management fee may not exceed 12% of effective gross income.
D91: Mgmt Fee (6% of Stabilized Income): | F91: =F88*0.5 -> 0 | G91: =G88*0.5 -> 0 | H91: =H88*0.5 -> 0 | I91: =I88*0.5 -> 0 | J91: =J88*0.5 -> 0 | K91: =K88*0.5 -> 0 | L91: =L88*0.5 -> 0 | M91: =M88*0.5 -> 0 | ... Y91: =Y88*0.5 -> 0
D92: Asset Mgmt Fee | F92: =F82 -> 8500 | G92: =G82 -> #VALUE! | H92: =H82 -> #VALUE! | I92: =I82 -> #VALUE! | J92: =J82 -> #VALUE! | K92: =K82 -> #VALUE! | L92: =L82 -> #VALUE! | M92: =M82 -> #VALUE! | ... Y92: =Y82 -> #VALUE!
D93: Incentive Mgmt Fee | F93: 0 | G93: 0 | H93: 0 | I93: 0 | J93: 0 | K93: 0 | L93: 0 | M93: 0 | N93: 0 | O93: 0 | P93: 0 | Q93: 0 | R93: 0 | S93: 0 | T93: 0 | U93: 0 | V93: 0 | W93: 0 | X93: 0 | Y93: 0
D94: Total: | F94: =F91+F92 -> 8500 | G94: =G91+G92 -> #VALUE! | H94: =H91+H92 -> #VALUE! | I94: =I91+I92 -> #VALUE! | J94: =J91+J92 -> #VALUE! | K94: =K91+K92 -> #VALUE! | L94: =L91+L92 -> #VALUE! | M94: =M91+M92 -> #VALUE! | ... Y94: =Y91+Y92 -> #VALUE!
D95: Reduction in IMF (Max-Total): | F95: =F94-F82-F83 -> -8500 | G95: =G94-G82-G83 -> #VALUE! | H95: =H94-H82-H83 -> #VALUE! | I95: =I94-I82-I83 -> #VALUE! | J95: =J94-J82-J83 -> #VALUE! | K95: =K94-K82-K83 -> #VALUE! | L95: =L94-L82-L83 -> #VALUE! | M95: =M94-M82-M83 -> #VALUE! | ... Y95: =Y94-Y82-Y83 -> #VALUE!

Sheet Credit Delivery & Pay-Ins
B1: Project Name | G1: RipeSpot Feasibility Analysis Template
C3: Credit Allocation (annual): | F3: 0 | J3: Annual Credits (allocation): | N3: 0 | P3: Closing
C4: Total Units: | F4: 0 | J4: Syndicator Percentage: | N4: 0.9999 | P4: Construction
C5: LIHTC Units: | J5: Equity Pricing (per credit): | N5: 0 | P5: Completion
C6: Cred Factor | F6: 0
K7: Total Equity Pay-In | N7: 0 | P7: Absorbtion Rate
B8: LEASE-UP / CREDIT DELIVERY SCHEDULE
C9: LIHTC Units Only
B10: Year | C10: Units Leased | D10: Cumulative | E10: Tax Credit | F10: Monthly | I10: EQUITY PAY-IN SCHEDULE
B11: 2027 | C11: In Month | D11: Leased | E11: Factor | F11: Credits | K11: Month | L11: Milestone | M11: % complete | N11: Federal | O11: State | P11: total | Q11: % of total
B12: January | D12: 0 | F12: 0 | H12: 45658 | J12: January
B13: February | D13: 0 | F13: 0 | H13: 45689 | J13: February
B14: March | D14: 0 | F14: 0 | H14: 45717 | J14: March
B15: April | D15: 0 | F15: 0 | H15: 45748 | J15: April
B16: May | D16: 0 | F16: 0 | H16: 45778 | J16: May
B17: June | D17: 0 | F17: 0 | H17: 45809 | J17: June
B18: July | D18: 0 | F18: 0 | H18: 45839 | J18: July
B19: August | D19: 0 | F19: 0 | H19: 45870 | J19: August
B20: September | D20: 0 | F20: 0 | H20: 45901 | J20: September
B21: October | D21: 0 | F21: 0 | H21: 45931 | J21: October
B22: November | D22: 0 | F22: 0 | H22: 45962 | J22: November | L22: CLOSING | N22: 0
B23: December | D23: 0 | F23: 0 | H23: 45992 | J23: December | K23: 1
B24: Totals: | C24: 0 | D24: 0 | F24: 0 | H24: 46023 | I24: 2026 | J24: January | K24: 2
H25: 46054 | J25: February | K25: 3
H26: 46082 | J26: March | K26: 4
B27: Year | C27: Units Leased | D27: Cumulative | E27: Tax Credit | F27: Monthly | H27: 46113 | J27: April | K27: 5
B28: 2028 | C28: In Month | D28: Leased | E28: Factor | F28: Credits | H28: 46143 | J28: May | K28: 6
B29: January | D29: 0 | E29: 1159.7834 | F29: 0 | H29: 46174 | J29: June | K29: 7
B30: February | D30: 0 | E30: 1159.7834 | F30: 0 | H30: 46204 | J30: July | K30: 8
B31: March | D31: 0 | E31: 1159.7834 | F31: 0 | H31: 46235 | J31: August | K31: 9
B32: April | D32: 0 | E32: 1159.7834 | F32: 0 | H32: 46266 | J32: September | K32: 10
B33: May | D33: 0 | E33: 1159.7834 | F33: 0 | H33: 46296 | J33: October | K33: 11 | L33: 50% complete | N33: 0
B34: June | D34: 0 | E34: 1159.7834 | F34: 0 | H34: 46327 | J34: November | K34: 12
B35: July | D35: 0 | E35: 1159.7834 | F35: 0 | H35: 46357 | J35: December | K35: 13
B36: August | D36: 0 | E36: 1159.7834 | F36: 0 | H36: 46388 | I36: 2027 | J36: January | K36: 14
B37: September | D37: 0 | E37: 1159.7834 | F37: 0 | H37: 46419 | J37: February | K37: 15
B38: October | D38: 0 | E38: 1159.7834 | F38: 0 | H38: 46447 | J38: March | K38: 16
B39: November | D39: 0 | E39: 1159.7834 | F39: 0 | H39: 46478 | J39: April | K39: 17
B40: December | D40: 0 | E40: 1159.7834 | F40: 0 | H40: 46508 | J40: May | K40: 18
B41: Totals: | C41: 0 | D41: 0 | F41: 0 | H41: 46539 | J41: June | K41: 19
H42: 46569 | J42: July | K42: 20
H43: 46600 | J43: August | K43: 21
B44: Year | C44: Units Leased | D44: Cumulative | E44: Tax Credit | F44: Monthly | H44: 46631 | J44: September | K44: 22 | L44: 100% completion-CO | N44: 0 | S44: 22 month construction period per GC contract
B45: 2029 | C45: In Month | D45: Leased | E45: Factor | F45: Credits | H45: 46661 | J45: October | K45: 23
B46: January | D46: 0 | E46: 1159.7834 | F46: 0 | H46: 46692 | J46: November | K46: 24
B47: February | D47: 0 | E47: 1159.7834 | F47: 0 | H47: 46722 | J47: December | K47: 25
B48: March | D48: 0 | E48: 1159.7834 | F48: 0 | H48: 46753 | I48: 2028 | J48: January | K48: 26
B49: April | D49: 0 | E49: 1159.7834 | F49: 0 | H49: 46784 | J49: February | K49: 27
B50: May | D50: 0 | E50: 1159.7834 | F50: 0 | H50: 46813 | J50: March | K50: 28
B51: June | D51: 0 | E51: 1159.7834 | F51: 0 | H51: 46844 | J51: April | K51: 29
B52: July | D52: 0 | E52: 1159.7834 | F52: 0 | H52: 46874 | J52: May | K52: 30
B53: August | D53: 0 | E53: 1159.7834 | F53: 0 | H53: 46905 | J53: June | K53: 31
B54: September | D54: 0 | E54: 1159.7834 | F54: 0 | H54: 46935 | J54: July | K54: 32
B55: October | D55: 0 | E55: 1159.7834 | F55: 0 | H55: 46966 | J55: August | K55: 33
B56: November | D56: 0 | E56: 1159.7834 | F56: 0 | H56: 46997 | J56: September | K56: 34
B57: December | D57: 0 | E57: 1159.7834 | F57: 0 | H57: 47027 | J57: October | K57: 35
B58: Totals: | D58: 0 | F58: 0 | H58: 47058 | J58: November | K58: 36 | L58: Stabilization | N58: 0 | Q58: 0.3598
H59: 47088 | J59: December | K59: 37
K60: TOTAL: | N60: - | Q60: 1
N61: 0

Sheet Flow of Funds
B1: FLOW OF FUNDS | G1: RipeSpot Feasibility Analysis Template
B2: [Project Name] | H2: 0 | I2: 1 | J2: 2 | K2: 3 | L2: 4 | M2: 5 | N2: 6 | O2: 7 | P2: 8 | Q2: 9 | R2: 10 | S2: 11 | T2: 12 | U2: 13 | V2: 14 | W2: 15 | X2: 16 | Y2: 17 | Z2: 18 | AA2: 19 | AB2: 20 | AC2: 21 | AD2: 22 | AE2: 23 | AF2: 24 | AG2: 25 | AH2: 26 | AI2: 27 | AJ2: 28 | AK2: 29 | AL2: 30 | AM2: 31 | AN2: 32 | AO2: 33 | AP2: 34 | AQ2: 35 | AR2: 36 | AS2: 37 | AT2: 38 | AU2: 39
B3: Units | I3: 45992 | J3: 46023 | K3: 46054 | L3: 46082 | M3: 46113 | N3: 46143 | O3: 46174 | P3: 46204 | Q3: 46235 | R3: 46266 | S3: 46296 | T3: 46327 | U3: 46357 | V3: 46388 | W3: 46419 | X3: 46447 | Y3: 46478 | Z3: 46508 | AA3: 46539 | AB3: 46569 | AC3: 46600 | AD3: 46631 | AE3: 46661 | AF3: 46692 | AG3: 46722 | AH3: 46753 | AI3: 46784 | AJ3: 46813 | AK3: 46844 | AL3: 46874 | AM3: 46905 | AN3: 46935 | AO3: 46966 | AP3: 46997 | AQ3: 47027 | AR3: 47058 | AS3: 47088 | AT3: 47119 | AU3: 47150
F4: Total | G4: Expended | H4: Closing | I4: Construction Start----------> | S4: 50% Completion | AD4: 100% Complete | AE4: Constr Completion | AR4: Stabilization | AV4: Total Drawn | AW4: Variance
A5: SOURCES | AD5: 2nd Installment | AE5: 2nd Installment | AR5: 3rd Installment
B6: Tax Exempt Bonds | E6: 0 | F6: ='Perm Sources-Uses'!K67 -> 0 | G6: 0 | H6: 0 | I6: 0 | J6: 0 | K6: 0 | L6: 0 | M6: 0 | N6: 0 | O6: 0 | P6: 0 | Q6: 0 | R6: 0 | S6: 0 | T6: 0 | U6: 0 | V6: 0 | W6: 0 | X6: 0 | Y6: 0 | Z6: 0 | AA6: 0 | AB6: 0 | AC6: 0 | AD6: 0 | AE6: 0 | AF6: 0 | AG6: 0 | AH6: 0 | AI6: 0 | AJ6: 0 | AK6: 0 | AL6: 0 | AM6: 0 | AN6: 0 | AO6: 0 | AP6: 0 | AQ6: 0 | AR6: 0 | AS6: 0 | AT6: 0 | AU6: 0 | AV6: 0 | AW6: 0
B7: ='Perm Sources-Uses'!K68 -> 0 | E7: 0 | F7: ='Perm Sources-Uses'!K68 -> 0 | G7: 0 | H7: 0 | I7: 0 | J7: 0 | K7: 0 | L7: 0 | M7: 0 | N7: 0 | O7: 0 | P7: 0 | Q7: 0 | R7: 0 | S7: 0 | T7: 0 | U7: 0 | V7: 0 | W7: 0 | X7: 0 | Y7: 0 | Z7: 0 | AA7: 0 | AB7: 0 | AC7: 0 | AD7: 0 | AE7: 0 | AF7: 0 | AG7: 0 | AH7: 0 | AI7: 0 | AJ7: 0 | AK7: 0 | AL7: 0 | AM7: 0 | AN7: 0 | AO7: 0 | AP7: 0 | AQ7: 0 | AR7: 0 | AS7: 0 | AT7: 0 | AU7: 0 | AV7: =SUM(H7:AU7) -> 0 | AW7: =F7-AV7 -> 0
B8: First Mortgage | D8: =IF(F16=0,0,F8/F16) -> 0 | E8: 0 | F8: ='Perm Sources-Uses'!E8 -> 0 | G8: 0 | H8: 0 | I8: 0 | J8: 0 | K8: 0 | L8: 0 | M8: 0 | N8: 0 | O8: 0 | P8: 0 | Q8: 0 | R8: 0 | S8: 0 | T8: 0 | U8: 0 | V8: 0 | W8: 0 | X8: 0 | Y8: 0 | Z8: 0 | AA8: 0 | AB8: 0 | AC8: 0 | AD8: 0 | AE8: 0 | AF8: 0 | AG8: 0 | AH8: 0 | AI8: 0 | AJ8: 0 | AK8: 0 | AL8: 0 | AM8: 0 | AN8: 0 | AO8: 0 | AP8: 0 | AQ8: 0 | AR8: 0 | AS8: 0 | AT8: 0 | AU8: 0 | AV8: =SUM(H8:AU8) -> 0 | AW8: =F8-AV8 -> 0
B9: 2nd Mortgage | D9: =IF(F16=0,0,F9/F16) -> 0 | E9: 0 | F9: ='Perm Sources-Uses'!E9 -> 0 | G9: 0 | H9: 0 | I9: 0 | J9: 0 | K9: 0 | L9: 0 | M9: 0 | N9: 0 | O9: 0 | P9: 0 | Q9: 0 | R9: 0 | S9: 0 | T9: 0 | U9: 0 | V9: 0 | W9: 0 | X9: 0 | Y9: 0 | Z9: 0 | AA9: 0 | AB9: 0 | AC9: 0 | AD9: 0 | AE9: 0 | AF9: 0 | AG9: 0 | AH9: 0 | AI9: 0 | AJ9: 0 | AK9: 0 | AL9: 0 | AM9: 0 | AN9: 0 | AO9: 0 | AP9: 0 | AQ9: 0 | AR9: 0 | AS9: 0 | AT9: 0 | AU9: 0 | AV9: =SUM(H9:AU9) -> 0 | AW9: =F9-AV9 -> 0
B10: 3rd Mortgage | D10: =IF(F16=0,0,F10/F16) -> 0 | E10: 0 | F10: ='Perm Sources-Uses'!E10 -> 0 | G10: 0 | H10: 0 | I10: 0 | J10: 0 | K10: 0 | L10: 0 | M10: 0 | N10: 0 | O10: 0 | P10: 0 | Q10: 0 | R10: 0 | S10: 0 | T10: 0 | U10: 0 | V10: 0 | W10: 0 | X10: 0 | Y10: 0 | Z10: 0 | AA10: 0 | AB10: 0 | AC10: 0 | AD10: 0 | AE10: 0 | AF10: 0 | AG10: 0 | AH10: 0 | AI10: 0 | AJ10: 0 | AK10: 0 | AL10: 0 | AM10: 0 | AN10: 0 | AO10: 0 | AP10: 0 | AQ10: 0 | AR10: 0 | AS10: 0 | AT10: 0 | AU10: 0 | AV10: =SUM(H10:AU10) -> 0 | AW10: =F10-AV10 -> 0
B11: L.P. Capital Contribution | D11: =IF(F16=0,0,F11/F16) -> 0 | E11: 0 | F11: ='Perm Sources-Uses'!E15 -> 0 | G11: 0 | H11: 0 | I11: 0 | J11: 0 | K11: 0 | L11: 0 | M11: 0 | N11: 0 | O11: 0 | P11: 0 | Q11: 0 | R11: 0 | S11: 0 | T11: 0 | U11: 0 | V11: 0 | W11: 0 | X11: 0 | Y11: 0 | Z11: 0 | AA11: 0 | AB11: 0 | AC11: 0 | AD11: 0 | AE11: 0 | AF11: 0 | AG11: 0 | AH11: 0 | AI11: 0 | AJ11: 0 | AK11: 0 | AL11: 0 | AM11: 0 | AN11: 0 | AO11: 0 | AP11: 0 | AQ11: 0 | AR11: 0 | AS11: 0 | AT11: 0 | AU11: 0 | AV11: =SUM(H11:AU11) -> 0 | AW11: =F11-AV11 -> 0
B12: GAP | D12: =IF(F16=0,0,F12/F16) -> 0 | E12: 0 | F12: ='Perm Sources-Uses'!E12 -> 0 | G12: 0 | H12: 0 | I12: 0 | J12: 0 | K12: 0 | L12: 0 | M12: 0 | N12: 0 | O12: 0 | P12: 0 | Q12: 0 | R12: 0 | S12: 0 | T12: 0 | U12: 0 | V12: 0 | W12: 0 | X12: 0 | Y12: 0 | Z12: 0 | AA12: 0 | AB12: 0 | AC12: 0 | AD12: 0 | AE12: 0 | AF12: 0 | AG12: 0 | AH12: 0 | AI12: 0 | AJ12: 0 | AK12: 0 | AL12: 0 | AM12: 0 | AN12: 0 | AO12: 0 | AP12: 0 | AQ12: 0 | AR12: 0 | AS12: 0 | AT12: 0 | AU12: 0 | AV12: =SUM(H12:AU12) -> 0 | AW12: =F12-AV12 -> 0
B13: Bond Arbitrage Earnings | D13: =IF(F16=0,0,F13/F16) -> 0 | E13: 0 | F13: ='Perm Sources-Uses'!E18 -> 0 | G13: 0 | H13: 0 | I13: 0 | J13: 0 | K13: 0 | L13: 0 | M13: 0 | N13: 0 | O13: 0 | P13: 0 | Q13: 0 | R13: 0 | S13: 0 | T13: 0 | U13: 0 | V13: 0 | W13: 0 | X13: 0 | Y13: 0 | Z13: 0 | AA13: 0 | AB13: 0 | AC13: 0 | AD13: 0 | AE13: 0 | AF13: 0 | AG13: 0 | AH13: 0 | AI13: 0 | AJ13: 0 | AK13: 0 | AL13: 0 | AM13: 0 | AN13: 0 | AO13: 0 | AP13: 0 | AQ13: 0 | AR13: 0 | AS13: 0 | AT13: 0 | AU13: 0 | AV13: =SUM(H13:AU13) -> 0 | AW13: =F13-AV13 -> 0
B14: 45L Credits | D14: =IF(F16=0,0,F14/F16) -> 0 | E14: 0 | F14: ='Perm Sources-Uses'!E13 -> 0 | G14: 0 | H14: 0 | I14: 0 | J14: 0 | K14: 0 | L14: 0 | M14: 0 | N14: 0 | O14: 0 | P14: 0 | Q14: 0 | R14: 0 | S14: 0 | T14: 0 | U14: 0 | V14: 0 | W14: 0 | X14: 0 | Y14: 0 | Z14: 0 | AA14: 0 | AB14: 0 | AC14: 0 | AD14: 0 | AE14: 0 | AF14: 0 | AG14: 0 | AH14: 0 | AI14: 0 | AJ14: 0 | AK14: 0 | AL14: 0 | AM14: 0 | AN14: 0 | AO14: 0 | AP14: 0 | AQ14: 0 | AR14: 0 | AS14: 0 | AT14: 0 | AU14: 0 | AV14: =SUM(H14:AU14) -> 0 | AW14: =F14-AV14 -> 0
B15: Deferred Developer Fee | D15: =IF(F16=0,0,F15/F16) -> 0 | E15: 0 | F15: ='Perm Sources-Uses'!E17 -> 0 | G15: 0 | H15: 0 | I15: 0 | J15: 0 | K15: 0 | L15: 0 | M15: 0 | N15: 0 | O15: 0 | P15: 0 | Q15: 0 | R15: 0 | S15: 0 | T15: 0 | U15: 0 | V15: 0 | W15: 0 | X15: 0 | Y15: 0 | Z15: 0 | AA15: 0 | AB15: 0 | AC15: 0 | AD15: 0 | AE15: 0 | AF15: 0 | AG15: 0 | AH15: 0 | AI15: 0 | AJ15: 0 | AK15: 0 | AL15: 0 | AM15: 0 | AN15: 0 | AO15: 0 | AP15: 0 | AQ15: 0 | AR15: 0 | AS15: 0 | AT15: 0 | AU15: 0 | AV15: =SUM(H15:AU15) -> 0 | AW15: =F15-AV15 -> 0
C16: Total Sources: | E16: 0 | F16: =SUM(F7:F15) -> 0 | G16: =SUM(G7:G15) -> 0 | H16: =SUM(H7:H15) -> 0 | I16: =SUM(I7:I15) -> 0 | J16: =SUM(J7:J15) -> 0 | K16: =SUM(K7:K15) -> 0 | L16: =SUM(L7:L15) -> 0 | M16: =SUM(M7:M15) -> 0 | ... AW16: =SUM(AW7:AW15) -> 0
E17: % of Equity Capital | G17: 0 | H17: 0.15 | I17: 0 | J17: 0 | K17: 0 | L17: 0 | M17: 0 | N17: 0 | O17: 0 | P17: 0 | Q17: 0 | R17: 0 | S17: 0.25 | T17: 0 | U17: 0 | V17: 0 | W17: 0 | X17: 0 | Y17: 0 | Z17: 0 | AA17: 0 | AB17: 0 | AC17: 0 | AD17: 0.25 | AE17: 0 | AF17: 0 | AG17: 0 | AH17: 0.1 | AI17: 0 | AJ17: 0.1 | AK17: 0 | AL17: 0 | AM17: 0 | AN17: 0 | AO17: 0 | AP17: 0.1 | AQ17: 0.05 | AR17: 0.3598 | AT17: 0 | AU17: 0 | AV17: 0 | AW17: 0
E18: 0 | G18: 0 | AV18: 0 | AW18: 0
A19: USES | E19: 0 | F19: 0 | G19: 0 | H19: 0 | I19: 0 | J19: 0 | K19: 0 | L19: 0 | M19: 0 | N19: 0 | O19: 0 | P19: 0 | Q19: 0 | R19: 0 | S19: 0 | T19: 0 | U19: 0 | V19: 0 | W19: 0 | X19: 0 | Y19: 0 | Z19: 0 | AA19: 0 | AB19: 0 | AC19: 0 | AD19: 0 | AE19: 0 | AF19: 0 | AG19: 0 | AH19: 0 | AI19: 0 | AJ19: 0 | AK19: 0 | AL19: 0 | AM19: 0 | AN19: 0 | AO19: 0 | AP19: 0 | AQ19: 0 | AR19: 0 | AS19: 0 | AT19: 0 | AU19: 0 | AV19: 0 | AW19: 0
A20: Acquisition Costs | E20: 0 | F20: 0 | G20: 0 | H20: 0 | I20: 0 | J20: 0 | K20: 0 | L20: 0 | M20: 0 | N20: 0 | O20: 0 | P20: 0 | Q20: 0 | R20: 0 | S20: 0 | T20: 0 | U20: 0 | V20: 0 | W20: 0 | X20: 0 | Y20: 0 | Z20: 0 | AA20: 0 | AB20: 0 | AC20: 0 | AD20: 0 | AE20: 0 | AF20: 0 | AG20: 0 | AH20: 0 | AI20: 0 | AJ20: 0 | AK20: 0 | AL20: 0 | AM20: 0 | AN20: 0 | AO20: 0 | AP20: 0 | AQ20: 0 | AR20: 0 | AS20: 0 | AT20: 0 | AU20: 0 | AV20: 0 | AW20: 0
B21: Land/Ground Lease Prepayment | E21: 0 | F21: ='Development Budget'!G9 -> 0 | G21: 0 | H21: 0 | I21: 0 | J21: 0 | K21: 0 | L21: 0 | M21: 0 | N21: 0 | O21: 0 | P21: 0 | Q21: 0 | R21: 0 | S21: 0 | T21: 0 | U21: 0 | V21: 0 | W21: 0 | X21: 0 | Y21: 0 | Z21: 0 | AA21: 0 | AB21: 0 | AC21: 0 | AD21: 0 | AE21: 0 | AF21: 0 | AG21: 0 | AH21: 0 | AI21: 0 | AJ21: 0 | AK21: 0 | AL21: 0 | AM21: 0 | AN21: 0 | AO21: 0 | AP21: 0 | AQ21: 0 | AR21: 0 | AS21: 0 | AT21: 0 | AU21: 0 | AV21: =SUM(H21:AU21) -> 0 | AW21: =F21-AV21 -> 0
E22: 0 | F22: 0 | G22: 0 | H22: 0 | I22: 0 | J22: 0 | K22: 0 | L22: 0 | M22: 0 | N22: 0 | O22: 0 | P22: 0 | Q22: 0 | R22: 0 | S22: 0 | T22: 0 | U22: 0 | V22: 0 | W22: 0 | X22: 0 | Y22: 0 | Z22: 0 | AA22: 0 | AB22: 0 | AC22: 0 | AD22: 0 | AE22: 0 | AF22: 0 | AG22: 0 | AH22: 0 | AI22: 0 | AJ22: 0 | AK22: 0 | AL22: 0 | AM22: 0 | AN22: 0 | AO22: 0 | AP22: 0 | AQ22: 0 | AR22: 0 | AS22: 0 | AT22: 0 | AU22: 0 | AV22: 0 | AW22: 0
A23: Construction Costs | F23: 0 | G23: 0 | H23: 0 | I23: 0 | J23: 0 | K23: 0 | L23: 0 | M23: 0 | N23: 0 | O23: 0 | P23: 0 | Q23: 0 | R23: 0 | S23: 0 | T23: 0 | U23: 0 | V23: 0 | W23: 0 | X23: 0 | Y23: 0 | Z23: 0 | AA23: 0 | AB23: 0 | AC23: 0 | AD23: 0 | AE23: 0 | AF23: 0 | AG23: 0 | AH23: 0 | AI23: 0 | AJ23: 0 | AK23: 0 | AL23: 0 | AM23: 0 | AN23: 0 | AO23: 0 | AP23: 0 | AQ23: 0 | AR23: 0 | AS23: 0 | AT23: 0 | AU23: 0 | AV23: 0 | AW23: 0
B24: Hard Costs | D24: 23.27 | E24: 0 | F24: ='Development Budget'!G12 -> 0 | G24: 0 | H24: 0 | I24: 0 | J24: 0 | K24: 0 | L24: 0 | M24: 0 | N24: 0 | O24: 0 | P24: 0 | Q24: 0 | R24: 0 | S24: 0 | T24: 0 | U24: 0 | V24: 0 | W24: 0 | X24: 0 | Y24: 0 | Z24: 0 | AA24: 0 | AB24: 0 | AC24: 0 | AD24: 0 | AE24: 0 | AF24: 0 | AG24: 0 | AH24: 0 | AI24: 0 | AJ24: 0 | AK24: 0 | AL24: 0 | AM24: 0 | AN24: 0 | AO24: 0 | AP24: 0 | AQ24: 0 | AR24: 0 | AS24: 0 | AT24: 0 | AU24: 0 | AV24: =SUM(H24:AU24) -> 0 | AW24: =F24-AV24 -> 0
B25: Sitework & Related Fees | E25: 0 | F25: ='Development Budget'!G13 -> 0 | G25: 0 | H25: 0 | I25: 0 | J25: 0 | K25: 0 | L25: 0 | M25: 0 | N25: 0 | O25: 0 | P25: 0 | Q25: 0 | R25: 0 | S25: 0 | T25: 0 | U25: 0 | V25: 0 | W25: 0 | X25: 0 | Y25: 0 | Z25: 0 | AA25: 0 | AB25: 0 | AC25: 0 | AD25: 0 | AE25: 0 | AF25: 0 | AG25: 0 | AH25: 0 | AI25: 0 | AJ25: 0 | AK25: 0 | AL25: 0 | AM25: 0 | AN25: 0 | AO25: 0 | AP25: 0 | AQ25: 0 | AR25: 0 | AS25: 0 | AT25: 0 | AU25: 0 | AV25: =SUM(H25:AU25) -> 0 | AW25: =F25-AV25 -> 0
B26: Structured Parking | E26: 0 | F26: ='Development Budget'!G14 -> 0 | G26: 0 | H26: 0 | I26: 0 | J26: 0 | K26: 0 | L26: 0 | M26: 0 | N26: 0 | O26: 0 | P26: 0 | Q26: 0 | R26: 0 | S26: 0 | T26: 0 | U26: 0 | V26: 0 | W26: 0 | X26: 0 | Y26: 0 | Z26: 0 | AA26: 0 | AB26: 0 | AC26: 0 | AD26: 0 | AE26: 0 | AF26: 0 | AG26: 0 | AH26: 0 | AI26: 0 | AJ26: 0 | AK26: 0 | AL26: 0 | AM26: 0 | AN26: 0 | AO26: 0 | AP26: 0 | AQ26: 0 | AR26: 0 | AS26: 0 | AT26: 0 | AU26: 0 | AV26: =SUM(H26:AU26) -> 0 | AW26: =F26-AV26 -> 0
B27: Utility Connection Fees | E27: 0 | F27: ='Development Budget'!G15 -> 0 | G27: 0 | H27: 0 | I27: 0 | J27: 0 | K27: 0 | L27: 0 | M27: 0 | N27: 0 | O27: 0 | P27: 0 | Q27: 0 | R27: 0 | S27: 0 | T27: 0 | U27: 0 | V27: 0 | W27: 0 | X27: 0 | Y27: 0 | Z27: 0 | AA27: 0 | AB27: 0 | AC27: 0 | AD27: 0 | AE27: 0 | AF27: 0 | AG27: 0 | AH27: 0 | AI27: 0 | AJ27: 0 | AK27: 0 | AL27: 0 | AM27: 0 | AN27: 0 | AO27: 0 | AP27: 0 | AQ27: 0 | AR27: 0 | AS27: 0 | AT27: 0 | AU27: 0 | AV27: =SUM(H27:AU27) -> 0 | AW27: =F27-AV27 -> 0
B28: GC Overhead | E28: 0 | F28: ='Development Budget'!G16 -> 0 | G28: 0 | H28: 0 | I28: 0 | J28: 0 | K28: 0 | L28: 0 | M28: 0 | N28: 0 | O28: 0 | P28: 0 | Q28: 0 | R28: 0 | S28: 0 | T28: 0 | U28: 0 | V28: 0 | W28: 0 | X28: 0 | Y28: 0 | Z28: 0 | AA28: 0 | AB28: 0 | AC28: 0 | AD28: 0 | AE28: 0 | AF28: 0 | AG28: 0 | AH28: 0 | AI28: 0 | AJ28: 0 | AK28: 0 | AL28: 0 | AM28: 0 | AN28: 0 | AO28: 0 | AP28: 0 | AQ28: 0 | AR28: 0 | AS28: 0 | AT28: 0 | AU28: 0 | AV28: =SUM(H28:AU28) -> 0 | AW28: =F28-AV28 -> 0
B29: GC Profit | E29: 0 | F29: ='Development Budget'!G17 -> 0 | G29: 0 | H29: 0 | I29: 0 | J29: 0 | K29: 0 | L29: 0 | M29: 0 | N29: 0 | O29: 0 | P29: 0 | Q29: 0 | R29: 0 | S29: 0 | T29: 0 | U29: 0 | V29: 0 | W29: 0 | X29: 0 | Y29: 0 | Z29: 0 | AA29: 0 | AB29: 0 | AC29: 0 | AD29: 0 | AE29: 0 | AF29: 0 | AG29: 0 | AH29: 0 | AI29: 0 | AJ29: 0 | AK29: 0 | AL29: 0 | AM29: 0 | AN29: 0 | AO29: 0 | AP29: 0 | AQ29: 0 | AR29: 0 | AS29: 0 | AT29: 0 | AU29: 0 | AV29: =SUM(H29:AU29) -> 0 | AW29: =F29-AV29 -> 0
B30: Builders Risk Insurance | E30: 0 | F30: ='Development Budget'!G18 -> 0 | G30: 0 | H30: 0 | I30: 0 | J30: 0 | K30: 0 | L30: 0 | M30: 0 | N30: 0 | O30: 0 | P30: 0 | Q30: 0 | R30: 0 | S30: 0 | T30: 0 | U30: 0 | V30: 0 | W30: 0 | X30: 0 | Y30: 0 | Z30: 0 | AA30: 0 | AB30: 0 | AC30: 0 | AD30: 0 | AE30: 0 | AF30: 0 | AG30: 0 | AH30: 0 | AI30: 0 | AJ30: 0 | AK30: 0 | AL30: 0 | AM30: 0 | AN30: 0 | AO30: 0 | AP30: 0 | AQ30: 0 | AR30: 0 | AS30: 0 | AT30: 0 | AU30: 0 | AV30: =SUM(H30:AU30) -> 0 | AW30: =F30-AV30 -> 0
B31: Payment and Performance Bond | E31: 0 | F31: ='Development Budget'!G19 -> 0 | G31: 0 | H31: 0 | I31: 0 | J31: 0 | K31: 0 | L31: 0 | M31: 0 | N31: 0 | O31: 0 | P31: 0 | Q31: 0 | R31: 0 | S31: 0 | T31: 0 | U31: 0 | V31: 0 | W31: 0 | X31: 0 | Y31: 0 | Z31: 0 | AA31: 0 | AB31: 0 | AC31: 0 | AD31: 0 | AE31: 0 | AF31: 0 | AG31: 0 | AH31: 0 | AI31: 0 | AJ31: 0 | AK31: 0 | AL31: 0 | AM31: 0 | AN31: 0 | AO31: 0 | AP31: 0 | AQ31: 0 | AR31: 0 | AS31: 0 | AT31: 0 | AU31: 0 | AV31: =SUM(H31:AU31) -> 0 | AW31: =F31-AV31 -> 0
B32: Construction Contingency (5%) | D32: 0.059453669 | E32: 0 | F32: ='Development Budget'!G20 -> 0 | G32: 0 | H32: 0 | I32: 0 | J32: 0 | K32: 0 | L32: 0 | M32: 0 | N32: 0 | O32: 0 | P32: 0 | Q32: 0 | R32: 0 | S32: 0 | T32: 0 | U32: 0 | V32: 0 | W32: 0 | X32: 0 | Y32: 0 | Z32: 0 | AA32: 0 | AB32: 0 | AC32: 0 | AD32: 0 | AE32: 0 | AF32: 0 | AG32: 0 | AH32: 0 | AI32: 0 | AJ32: 0 | AK32: 0 | AL32: 0 | AM32: 0 | AN32: 0 | AO32: 0 | AP32: 0 | AQ32: 0 | AR32: 0 | AS32: 0 | AT32: 0 | AU32: 0 | AV32: =SUM(H32:AU32) -> 0 | AW32: =F32-AV32 -> 0
B33: Warehouse key | E33: 0 | F33: 0 | G33: 0 | H33: 0 | I33: 0 | J33: 0 | K33: 0 | L33: 0 | M33: 0 | N33: 0 | O33: 0 | P33: 0 | Q33: 0 | R33: 0 | S33: 0 | T33: 0 | U33: 0 | V33: 0 | W33: 0 | X33: 0 | Y33: 0 | Z33: 0 | AA33: 0 | AB33: 0 | AC33: 0 | AD33: 0 | AE33: 0 | AF33: 0 | AG33: 0 | AH33: 0 | AI33: 0 | AJ33: 0 | AK33: 0 | AL33: 0 | AM33: 0 | AN33: 0 | AO33: 0 | AP33: 0 | AQ33: 0 | AR33: 0 | AS33: 0 | AT33: 0 | AU33: 0 | AV33: =SUM(H33:AU33) -> 0 | AW33: =F33-AV33 -> 0
B34: Multivista Documentation Allowance | E34: 0 | F34: 0 | G34: 0 | H34: 0 | I34: 0 | J34: 0 | K34: 0 | L34: 0 | M34: 0 | N34: 0 | O34: 0 | P34: 0 | Q34: 0 | R34: 0 | S34: 0 | T34: 0 | U34: 0 | V34: 0 | W34: 0 | X34: 0 | Y34: 0 | Z34: 0 | AA34: 0 | AB34: 0 | AC34: 0 | AD34: 0 | AE34: 0 | AF34: 0 | AG34: 0 | AH34: 0 | AI34: 0 | AJ34: 0 | AK34: 0 | AL34: 0 | AM34: 0 | AN34: 0 | AO34: 0 | AP34: 0 | AQ34: 0 | AR34: 0 | AS34: 0 | AT34: 0 | AU34: 0 | AV34: =SUM(H34:AU34) -> 0 | AW34: =F34-AV34 -> 0
B35: Parking lot rental allowance | E35: 0 | F35: 0 | G35: 0 | H35: 0 | I35: 0 | J35: 0 | K35: 0 | L35: 0 | M35: 0 | N35: 0 | O35: 0 | P35: 0 | Q35: 0 | R35: 0 | S35: 0 | T35: 0 | U35: 0 | V35: 0 | W35: 0 | X35: 0 | Y35: 0 | Z35: 0 | AA35: 0 | AB35: 0 | AC35: 0 | AD35: 0 | AE35: 0 | AF35: 0 | AG35: 0 | AH35: 0 | AI35: 0 | AJ35: 0 | AK35: 0 | AL35: 0 | AM35: 0 | AN35: 0 | AO35: 0 | AP35: 0 | AQ35: 0 | AR35: 0 | AS35: 0 | AT35: 0 | AU35: 0 | AV35: =SUM(H35:AU35) -> 0 | AW35: =F35-AV35 -> 0
E36: 0 | F36: 0 | G36: 0 | H36: 0 | I36: 0 | J36: 0 | K36: 0 | L36: 0 | M36: 0 | N36: 0 | O36: 0 | P36: 0 | Q36: 0 | R36: 0 | S36: 0 | T36: 0 | U36: 0 | V36: 0 | W36: 0 | X36: 0 | Y36: 0 | Z36: 0 | AA36: 0 | AB36: 0 | AC36: 0 | AD36: 0 | AE36: 0 | AF36: 0 | AG36: 0 | AH36: 0 | AI36: 0 | AJ36: 0 | AK36: 0 | AL36: 0 | AM36: 0 | AN36: 0 | AO36: 0 | AP36: 0 | AQ36: 0 | AR36: 0 | AS36: 0 | AT36: 0 | AU36: 0 | AV36: 0 | AW36: 0
D37: Construction Cost Subtotals | E37: 0 | F37: =SUM(F24:F35) -> 0 | G37: =SUM(G24:G35) -> 0 | H37: =SUM(H24:H35) -> 0 | I37: =SUM(I24:I35) -> 0 | J37: =SUM(J24:J35) -> 0 | K37: =SUM(K24:K35) -> 0 | L37: =SUM(L24:L35) -> 0 | M37: =SUM(M24:M35) -> 0 | ... AW37: =SUM(AW24:AW35) -> 0
E38: 0 | F38: 0 | G38: 0 | H38: 0 | I38: 0 | J38: 0 | K38: 0 | L38: 0 | M38: 0 | N38: 0 | O38: 0 | P38: 0 | Q38: 0 | R38: 0 | S38: 0 | T38: 0 | U38: 0 | V38: 0 | W38: 0 | X38: 0 | Y38: 0 | Z38: 0 | AA38: 0 | AB38: 0 | AC38: 0 | AD38: 0 | AE38: 0 | AF38: 0 | AG38: 0 | AH38: 0 | AI38: 0 | AJ38: 0 | AK38: 0 | AL38: 0 | AM38: 0 | AN38: 0 | AO38: 0 | AP38: 0 | AQ38: 0 | AR38: 0 | AS38: 0 | AT38: 0 | AU38: 0 | AV38: 0 | AW38: 0
A39: Predevelopment Costs | E39: 0 | F39: 0 | G39: 0 | H39: 0 | I39: 0 | J39: 0 | K39: 0 | L39: 0 | M39: 0 | N39: 0 | O39: 0 | P39: 0 | Q39: 0 | R39: 0 | S39: 0 | T39: 0 | U39: 0 | V39: 0 | W39: 0 | X39: 0 | Y39: 0 | Z39: 0 | AA39: 0 | AB39: 0 | AC39: 0 | AD39: 0 | AE39: 0 | AF39: 0 | AG39: 0 | AH39: 0 | AI39: 0 | AJ39: 0 | AK39: 0 | AL39: 0 | AM39: 0 | AN39: 0 | AO39: 0 | AP39: 0 | AQ39: 0 | AR39: 0 | AS39: 0 | AT39: 0 | AU39: 0 | AV39: 0 | AW39: 0
B40: Property Appraisal | E40: 0 | F40: ='Development Budget'!G23 -> 0 | G40: 0 | H40: 0 | I40: 0 | J40: 0 | K40: 0 | L40: 0 | M40: 0 | N40: 0 | O40: 0 | P40: 0 | Q40: 0 | R40: 0 | S40: 0 | T40: 0 | U40: 0 | V40: 0 | W40: 0 | X40: 0 | Y40: 0 | Z40: 0 | AA40: 0 | AB40: 0 | AC40: 0 | AD40: 0 | AE40: 0 | AF40: 0 | AG40: 0 | AH40: 0 | AI40: 0 | AJ40: 0 | AK40: 0 | AL40: 0 | AM40: 0 | AN40: 0 | AO40: 0 | AP40: 0 | AQ40: 0 | AR40: 0 | AS40: 0 | AT40: 0 | AU40: 0 | AV40: =SUM(H40:AU40) -> 0 | AW40: =F40-AV40 -> 0
B41: Market Study | E41: 0 | F41: ='Development Budget'!G24 -> 0 | G41: 0 | H41: 0 | I41: 0 | J41: 0 | K41: 0 | L41: 0 | M41: 0 | N41: 0 | O41: 0 | P41: 0 | Q41: 0 | R41: 0 | S41: 0 | T41: 0 | U41: 0 | V41: 0 | W41: 0 | X41: 0 | Y41: 0 | Z41: 0 | AA41: 0 | AB41: 0 | AC41: 0 | AD41: 0 | AE41: 0 | AF41: 0 | AG41: 0 | AH41: 0 | AI41: 0 | AJ41: 0 | AK41: 0 | AL41: 0 | AM41: 0 | AN41: 0 | AO41: 0 | AP41: 0 | AQ41: 0 | AR41: 0 | AS41: 0 | AT41: 0 | AU41: 0 | AV41: =SUM(H41:AU41) -> 0 | AW41: =F41-AV41 -> 0
B42: Environmental Report(s) | E42: 0 | F42: ='Development Budget'!G25 -> 0 | G42: 0 | H42: 0 | I42: 0 | J42: 0 | K42: 0 | L42: 0 | M42: 0 | N42: 0 | O42: 0 | P42: 0 | Q42: 0 | R42: 0 | S42: 0 | T42: 0 | U42: 0 | V42: 0 | W42: 0 | X42: 0 | Y42: 0 | Z42: 0 | AA42: 0 | AB42: 0 | AC42: 0 | AD42: 0 | AE42: 0 | AF42: 0 | AG42: 0 | AH42: 0 | AI42: 0 | AJ42: 0 | AK42: 0 | AL42: 0 | AM42: 0 | AN42: 0 | AO42: 0 | AP42: 0 | AQ42: 0 | AR42: 0 | AS42: 0 | AT42: 0 | AU42: 0 | AV42: =SUM(H42:AU42) -> 0 | AW42: =F42-AV42 -> 0
B43: Soil Borings | E43: 0 | F43: ='Development Budget'!G26 -> 0 | G43: 0 | H43: 0 | I43: 0 | J43: 0 | K43: 0 | L43: 0 | M43: 0 | N43: 0 | O43: 0 | P43: 0 | Q43: 0 | R43: 0 | S43: 0 | T43: 0 | U43: 0 | V43: 0 | W43: 0 | X43: 0 | Y43: 0 | Z43: 0 | AA43: 0 | AB43: 0 | AC43: 0 | AD43: 0 | AE43: 0 | AF43: 0 | AG43: 0 | AH43: 0 | AI43: 0 | AJ43: 0 | AK43: 0 | AL43: 0 | AM43: 0 | AN43: 0 | AO43: 0 | AP43: 0 | AQ43: 0 | AR43: 0 | AS43: 0 | AT43: 0 | AU43: 0 | AV43: =SUM(H43:AU43) -> 0 | AW43: =F43-AV43 -> 0
B44: Boundary and Topographical Survey | E44: 0 | F44: ='Development Budget'!G27 -> 0 | G44: 0 | H44: 0 | I44: 0 | J44: 0 | K44: 0 | L44: 0 | M44: 0 | N44: 0 | O44: 0 | P44: 0 | Q44: 0 | R44: 0 | S44: 0 | T44: 0 | U44: 0 | V44: 0 | W44: 0 | X44: 0 | Y44: 0 | Z44: 0 | AA44: 0 | AB44: 0 | AC44: 0 | AD44: 0 | AE44: 0 | AF44: 0 | AG44: 0 | AH44: 0 | AI44: 0 | AJ44: 0 | AK44: 0 | AL44: 0 | AM44: 0 | AN44: 0 | AO44: 0 | AP44: 0 | AQ44: 0 | AR44: 0 | AS44: 0 | AT44: 0 | AU44: 0 | AV44: =SUM(H44:AU44) -> 0 | AW44: =F44-AV44 -> 0
B45: Zoning/Site Plan Fees | E45: 0 | F45: ='Development Budget'!G28 -> 0 | G45: 0 | H45: 0 | I45: 0 | J45: 0 | K45: 0 | L45: 0 | M45: 0 | N45: 0 | O45: 0 | P45: 0 | Q45: 0 | R45: 0 | S45: 0 | T45: 0 | U45: 0 | V45: 0 | W45: 0 | X45: 0 | Y45: 0 | Z45: 0 | AA45: 0 | AB45: 0 | AC45: 0 | AD45: 0 | AE45: 0 | AF45: 0 | AG45: 0 | AH45: 0 | AI45: 0 | AJ45: 0 | AK45: 0 | AL45: 0 | AM45: 0 | AN45: 0 | AO45: 0 | AP45: 0 | AQ45: 0 | AR45: 0 | AS45: 0 | AT45: 0 | AU45: 0 | AV45: =SUM(H45:AU45) -> 0 | AW45: =F45-AV45 -> 0
A46: Construction Period Financing | E46: 0 | F46: 0 | G46: 0 | H46: 0 | I46: 0 | J46: 0 | K46: 0 | L46: 0 | M46: 0 | N46: 0 | O46: 0 | P46: 0 | Q46: 0 | R46: 0 | S46: 0 | T46: 0 | U46: 0 | V46: 0 | W46: 0 | X46: 0 | Y46: 0 | Z46: 0 | AA46: 0 | AB46: 0 | AC46: 0 | AD46: 0 | AE46: 0 | AF46: 0 | AG46: 0 | AH46: 0 | AI46: 0 | AJ46: 0 | AK46: 0 | AL46: 0 | AM46: 0 | AN46: 0 | AO46: 0 | AP46: 0 | AQ46: 0 | AR46: 0 | AS46: 0 | AT46: 0 | AU46: 0 | AV46: 0 | AW46: 0
B47: Construction Financing and Placement Fees | E47: 0 | F47: ='Development Budget'!G31 -> 0 | G47: 0 | H47: 0 | I47: 0 | J47: 0 | K47: 0 | L47: 0 | M47: 0 | N47: 0 | O47: 0 | P47: 0 | Q47: 0 | R47: 0 | S47: 0 | T47: 0 | U47: 0 | V47: 0 | W47: 0 | X47: 0 | Y47: 0 | Z47: 0 | AA47: 0 | AB47: 0 | AC47: 0 | AD47: 0 | AE47: 0 | AF47: 0 | AG47: 0 | AH47: 0 | AI47: 0 | AJ47: 0 | AK47: 0 | AL47: 0 | AM47: 0 | AN47: 0 | AO47: 0 | AP47: 0 | AQ47: 0 | AR47: 0 | AS47: 0 | AT47: 0 | AU47: 0 | AV47: =SUM(H47:AU47) -> 0 | AW47: =F47-AV47 -> 0
B48: Construction Loan Interest | E48: 0 | F48: ='Development Budget'!G32 -> 0 | G48: 0 | H48: 0 | I48: 0 | J48: 0 | K48: 0 | L48: 0 | M48: 0 | N48: 0 | O48: 0 | P48: 0 | Q48: 0 | R48: 0 | S48: 0 | T48: 0 | U48: 0 | V48: 0 | W48: 0 | X48: 0 | Y48: 0 | Z48: 0 | AA48: 0 | AB48: 0 | AC48: 0 | AD48: 0 | AE48: 0 | AF48: 0 | AG48: 0 | AH48: 0 | AI48: 0 | AJ48: 0 | AK48: 0 | AL48: 0 | AM48: 0 | AN48: 0 | AO48: 0 | AP48: 0 | AQ48: 0 | AR48: 0 | AS48: 0 | AT48: 0 | AU48: 0 | AV48: =SUM(H48:AU48) -> 0 | AW48: =F48-AV48 -> 0
B49: Bond Interst (Fully Drawn) | E49: 0 | F49: ='Development Budget'!G33 -> 0 | G49: 0 | H49: 0 | I49: 0 | J49: 0 | K49: 0 | L49: 0 | M49: 0 | N49: 0 | O49: 0 | P49: 0 | Q49: 0 | R49: 0 | S49: 0 | T49: 0 | U49: 0 | V49: 0 | W49: 0 | X49: 0 | Y49: 0 | Z49: 0 | AA49: 0 | AB49: 0 | AC49: 0 | AD49: 0 | AE49: 0 | AF49: 0 | AG49: 0 | AH49: 0 | AI49: 0 | AJ49: 0 | AK49: 0 | AL49: 0 | AM49: 0 | AN49: 0 | AO49: 0 | AP49: 0 | AQ49: 0 | AR49: 0 | AS49: 0 | AT49: 0 | AU49: 0 | AV49: =SUM(H49:AU49) -> 0 | AW49: =F49-AV49 -> 0
B50: Bond issuer Fee (APV) | E50: 0 | F50: ='Development Budget'!G34 -> 0 | G50: 0 | H50: 0 | I50: 0 | J50: 0 | K50: 0 | L50: 0 | M50: 0 | N50: 0 | O50: 0 | P50: 0 | Q50: 0 | R50: 0 | S50: 0 | T50: 0 | U50: 0 | V50: 0 | W50: 0 | X50: 0 | Y50: 0 | Z50: 0 | AA50: 0 | AB50: 0 | AC50: 0 | AD50: 0 | AE50: 0 | AF50: 0 | AG50: 0 | AH50: 0 | AI50: 0 | AJ50: 0 | AK50: 0 | AL50: 0 | AM50: 0 | AN50: 0 | AO50: 0 | AP50: 0 | AQ50: 0 | AR50: 0 | AS50: 0 | AT50: 0 | AU50: 0 | AV50: =SUM(H50:AU50) -> 0 | AW50: =F50-AV50 -> 0
B51: Lender's Legal Fees | E51: 0 | F51: ='Development Budget'!G35 -> 0 | G51: 0 | H51: 0 | I51: 0 | J51: 0 | K51: 0 | L51: 0 | M51: 0 | N51: 0 | O51: 0 | P51: 0 | Q51: 0 | R51: 0 | S51: 0 | T51: 0 | U51: 0 | V51: 0 | W51: 0 | X51: 0 | Y51: 0 | Z51: 0 | AA51: 0 | AB51: 0 | AC51: 0 | AD51: 0 | AE51: 0 | AF51: 0 | AG51: 0 | AH51: 0 | AI51: 0 | AJ51: 0 | AK51: 0 | AL51: 0 | AM51: 0 | AN51: 0 | AO51: 0 | AP51: 0 | AQ51: 0 | AR51: 0 | AS51: 0 | AT51: 0 | AU51: 0 | AV51: =SUM(H51:AU51) -> 0 | AW51: =F51-AV51 -> 0
B52: Construction Period Real Estate Tax | E52: 0 | F52: ='Development Budget'!G36 -> 0 | G52: 0 | H52: 0 | I52: 0 | J52: 0 | K52: 0 | L52: 0 | M52: 0 | N52: 0 | O52: 0 | P52: 0 | Q52: 0 | R52: 0 | S52: 0 | T52: 0 | U52: 0 | V52: 0 | W52: 0 | X52: 0 | Y52: 0 | Z52: 0 | AA52: 0 | AB52: 0 | AC52: 0 | AD52: 0 | AE52: 0 | AF52: 0 | AG52: 0 | AH52: 0 | AI52: 0 | AJ52: 0 | AK52: 0 | AL52: 0 | AM52: 0 | AN52: 0 | AO52: 0 | AP52: 0 | AQ52: 0 | AR52: 0 | AS52: 0 | AT52: 0 | AU52: 0 | AV52: =SUM(H52:AU52) -> 0 | AW52: =F52-AV52 -> 0
B53: GL Insurance & BR Security during construction | E53: 0 | F53: ='Development Budget'!G37 -> 0 | G53: 0 | H53: 0 | I53: 0 | J53: 0 | K53: 0 | L53: 0 | M53: 0 | N53: 0 | O53: 0 | P53: 0 | Q53: 0 | R53: 0 | S53: 0 | T53: 0 | U53: 0 | V53: 0 | W53: 0 | X53: 0 | Y53: 0 | Z53: 0 | AA53: 0 | AB53: 0 | AC53: 0 | AD53: 0 | AE53: 0 | AF53: 0 | AG53: 0 | AH53: 0 | AI53: 0 | AJ53: 0 | AK53: 0 | AL53: 0 | AM53: 0 | AN53: 0 | AO53: 0 | AP53: 0 | AQ53: 0 | AR53: 0 | AS53: 0 | AT53: 0 | AU53: 0 | AV53: =SUM(H53:AU53) -> 0 | AW53: =F53-AV53 -> 0
B54: Performance & Payment Bonds | E54: 0 | F54: ='Development Budget'!G38 -> 0 | G54: 0 | H54: 0 | I54: 0 | J54: 0 | K54: 0 | L54: 0 | M54: 0 | N54: 0 | O54: 0 | P54: 0 | Q54: 0 | R54: 0 | S54: 0 | T54: 0 | U54: 0 | V54: 0 | W54: 0 | X54: 0 | Y54: 0 | Z54: 0 | AA54: 0 | AB54: 0 | AC54: 0 | AD54: 0 | AE54: 0 | AF54: 0 | AG54: 0 | AH54: 0 | AI54: 0 | AJ54: 0 | AK54: 0 | AL54: 0 | AM54: 0 | AN54: 0 | AO54: 0 | AP54: 0 | AQ54: 0 | AR54: 0 | AS54: 0 | AT54: 0 | AU54: 0 | AV54: =SUM(H54:AU54) -> 0 | AW54: =F54-AV54 -> 0
B55: Freddie TEL legal & Associated Fees | E55: 0 | F55: ='Development Budget'!G39 -> 0 | G55: 0 | H55: 0 | I55: 0 | J55: 0 | K55: 0 | L55: 0 | M55: 0 | N55: 0 | O55: 0 | P55: 0 | Q55: 0 | R55: 0 | S55: 0 | T55: 0 | U55: 0 | V55: 0 | W55: 0 | X55: 0 | Y55: 0 | Z55: 0 | AA55: 0 | AB55: 0 | AC55: 0 | AD55: 0 | AE55: 0 | AF55: 0 | AG55: 0 | AH55: 0 | AI55: 0 | AJ55: 0 | AK55: 0 | AL55: 0 | AM55: 0 | AN55: 0 | AO55: 0 | AP55: 0 | AQ55: 0 | AR55: 0 | AS55: 0 | AT55: 0 | AU55: 0 | AV55: =SUM(H55:AU55) -> 0 | AW55: =F55-AV55 -> 0
A56: Professional Services | E56: 0 | F56: 0 | G56: 0 | H56: 0 | I56: 0 | J56: 0 | K56: 0 | L56: 0 | M56: 0 | N56: 0 | O56: 0 | P56: 0 | Q56: 0 | R56: 0 | S56: 0 | T56: 0 | U56: 0 | V56: 0 | W56: 0 | X56: 0 | Y56: 0 | Z56: 0 | AA56: 0 | AB56: 0 | AC56: 0 | AD56: 0 | AE56: 0 | AF56: 0 | AG56: 0 | AH56: 0 | AI56: 0 | AJ56: 0 | AK56: 0 | AL56: 0 | AM56: 0 | AN56: 0 | AO56: 0 | AP56: 0 | AQ56: 0 | AR56: 0 | AS56: 0 | AT56: 0 | AU56: 0 | AV56: 0 | AW56: 0
B57: Architectural Fee - Design | E57: 0 | F57: ='Development Budget'!G42 -> 0 | G57: 0 | H57: 0 | I57: 0 | J57: 0 | K57: 0 | L57: 0 | M57: 0 | N57: 0 | O57: 0 | P57: 0 | Q57: 0 | R57: 0 | S57: 0 | T57: 0 | U57: 0 | V57: 0 | W57: 0 | X57: 0 | Y57: 0 | Z57: 0 | AA57: 0 | AB57: 0 | AC57: 0 | AD57: 0 | AE57: 0 | AF57: 0 | AG57: 0 | AH57: 0 | AI57: 0 | AJ57: 0 | AK57: 0 | AL57: 0 | AM57: 0 | AN57: 0 | AO57: 0 | AP57: 0 | AQ57: 0 | AR57: 0 | AS57: 0 | AT57: 0 | AU57: 0 | AV57: =SUM(H57:AU57) -> 0 | AW57: =F57-AV57 -> 0
B58: Project Management / GC Overhead | E58: 0 | F58: ='Development Budget'!G43 -> 0 | G58: 0 | H58: 0 | I58: 0 | J58: 0 | K58: 0 | L58: 0 | M58: 0 | N58: 0 | O58: 0 | P58: 0 | Q58: 0 | R58: 0 | S58: 0 | T58: 0 | U58: 0 | V58: 0 | W58: 0 | X58: 0 | Y58: 0 | Z58: 0 | AA58: 0 | AB58: 0 | AC58: 0 | AD58: 0 | AE58: 0 | AF58: 0 | AG58: 0 | AH58: 0 | AI58: 0 | AJ58: 0 | AK58: 0 | AL58: 0 | AM58: 0 | AN58: 0 | AO58: 0 | AP58: 0 | AQ58: 0 | AR58: 0 | AS58: 0 | AT58: 0 | AU58: 0 | AV58: =SUM(H58:AU58) -> 0 | AW58: =F58-AV58 -> 0
B59: Architectural Fee - Reimbursables | E59: 0 | F59: ='Development Budget'!G44 -> 0 | G59: 0 | H59: 0 | I59: 0 | J59: 0 | K59: 0 | L59: 0 | M59: 0 | N59: 0 | O59: 0 | P59: 0 | Q59: 0 | R59: 0 | S59: 0 | T59: 0 | U59: 0 | V59: 0 | W59: 0 | X59: 0 | Y59: 0 | Z59: 0 | AA59: 0 | AB59: 0 | AC59: 0 | AD59: 0 | AE59: 0 | AF59: 0 | AG59: 0 | AH59: 0 | AI59: 0 | AJ59: 0 | AK59: 0 | AL59: 0 | AM59: 0 | AN59: 0 | AO59: 0 | AP59: 0 | AQ59: 0 | AR59: 0 | AS59: 0 | AT59: 0 | AU59: 0 | AV59: =SUM(H59:AU59) -> 0 | AW59: =F59-AV59 -> 0
B60: Landscape Architect | E60: 0 | F60: ='Development Budget'!G45 -> 0 | G60: 0 | H60: 0 | I60: 0 | J60: 0 | K60: 0 | L60: 0 | M60: 0 | N60: 0 | O60: 0 | P60: 0 | Q60: 0 | R60: 0 | S60: 0 | T60: 0 | U60: 0 | V60: 0 | W60: 0 | X60: 0 | Y60: 0 | Z60: 0 | AA60: 0 | AB60: 0 | AC60: 0 | AD60: 0 | AE60: 0 | AF60: 0 | AG60: 0 | AH60: 0 | AI60: 0 | AJ60: 0 | AK60: 0 | AL60: 0 | AM60: 0 | AN60: 0 | AO60: 0 | AP60: 0 | AQ60: 0 | AR60: 0 | AS60: 0 | AT60: 0 | AU60: 0 | AV60: =SUM(H60:AU60) -> 0 | AW60: =F60-AV60 -> 0
B61: Engineering | E61: 0 | F61: ='Development Budget'!G46 -> 0 | G61: 0 | H61: 0 | I61: 0 | J61: 0 | K61: 0 | L61: 0 | M61: 0 | N61: 0 | O61: 0 | P61: 0 | Q61: 0 | R61: 0 | S61: 0 | T61: 0 | U61: 0 | V61: 0 | W61: 0 | X61: 0 | Y61: 0 | Z61: 0 | AA61: 0 | AB61: 0 | AC61: 0 | AD61: 0 | AE61: 0 | AF61: 0 | AG61: 0 | AH61: 0 | AI61: 0 | AJ61: 0 | AK61: 0 | AL61: 0 | AM61: 0 | AN61: 0 | AO61: 0 | AP61: 0 | AQ61: 0 | AR61: 0 | AS61: 0 | AT61: 0 | AU61: 0 | AV61: =SUM(H61:AU61) -> 0 | AW61: =F61-AV61 -> 0
B62: Developer Attorney | E62: 0 | F62: ='Development Budget'!G47 -> 0 | G62: 0 | H62: 0 | I62: 0 | J62: 0 | K62: 0 | L62: 0 | M62: 0 | N62: 0 | O62: 0 | P62: 0 | Q62: 0 | R62: 0 | S62: 0 | T62: 0 | U62: 0 | V62: 0 | W62: 0 | X62: 0 | Y62: 0 | Z62: 0 | AA62: 0 | AB62: 0 | AC62: 0 | AD62: 0 | AE62: 0 | AF62: 0 | AG62: 0 | AH62: 0 | AI62: 0 | AJ62: 0 | AK62: 0 | AL62: 0 | AM62: 0 | AN62: 0 | AO62: 0 | AP62: 0 | AQ62: 0 | AR62: 0 | AS62: 0 | AT62: 0 | AU62: 0 | AV62: =SUM(H62:AU62) -> 0 | AW62: =F62-AV62 -> 0
B63: Legal (TBD) | E63: 0 | F63: ='Development Budget'!G48 -> 0 | G63: 0 | H63: 0 | I63: 0 | J63: 0 | K63: 0 | L63: 0 | M63: 0 | N63: 0 | O63: 0 | P63: 0 | Q63: 0 | R63: 0 | S63: 0 | T63: 0 | U63: 0 | V63: 0 | W63: 0 | X63: 0 | Y63: 0 | Z63: 0 | AA63: 0 | AB63: 0 | AC63: 0 | AD63: 0 | AE63: 0 | AF63: 0 | AG63: 0 | AH63: 0 | AI63: 0 | AJ63: 0 | AK63: 0 | AL63: 0 | AM63: 0 | AN63: 0 | AO63: 0 | AP63: 0 | AQ63: 0 | AR63: 0 | AS63: 0 | AT63: 0 | AU63: 0 | AV63: =SUM(H63:AU63) -> 0 | AW63: =F63-AV63 -> 0
B64: Accounting | E64: 0 | F64: ='Development Budget'!G49 -> 0 | G64: 0 | H64: 0 | I64: 0 | J64: 0 | K64: 0 | L64: 0 | M64: 0 | N64: 0 | O64: 0 | P64: 0 | Q64: 0 | R64: 0 | S64: 0 | T64: 0 | U64: 0 | V64: 0 | W64: 0 | X64: 0 | Y64: 0 | Z64: 0 | AA64: 0 | AB64: 0 | AC64: 0 | AD64: 0 | AE64: 0 | AF64: 0 | AG64: 0 | AH64: 0 | AI64: 0 | AJ64: 0 | AK64: 0 | AL64: 0 | AM64: 0 | AN64: 0 | AO64: 0 | AP64: 0 | AQ64: 0 | AR64: 0 | AS64: 0 | AT64: 0 | AU64: 0 | AV64: =SUM(H64:AU64) -> 0 | AW64: =F64-AV64 -> 0
B65: Green Building Certification/Registration | E65: 0 | F65: ='Development Budget'!G50 -> 0 | G65: 0 | H65: 0 | I65: 0 | J65: 0 | K65: 0 | L65: 0 | M65: 0 | N65: 0 | O65: 0 | P65: 0 | Q65: 0 | R65: 0 | S65: 0 | T65: 0 | U65: 0 | V65: 0 | W65: 0 | X65: 0 | Y65: 0 | Z65: 0 | AA65: 0 | AB65: 0 | AC65: 0 | AD65: 0 | AE65: 0 | AF65: 0 | AG65: 0 | AH65: 0 | AI65: 0 | AJ65: 0 | AK65: 0 | AL65: 0 | AM65: 0 | AN65: 0 | AO65: 0 | AP65: 0 | AQ65: 0 | AR65: 0 | AS65: 0 | AT65: 0 | AU65: 0 | AV65: =SUM(H65:AU65) -> 0 | AW65: =F65-AV65 -> 0
B66: Construction Inspection Fees | E66: 0 | F66: ='Development Budget'!G51 -> 0 | G66: 0 | H66: 0 | I66: 0 | J66: 0 | K66: 0 | L66: 0 | M66: 0 | N66: 0 | O66: 0 | P66: 0 | Q66: 0 | R66: 0 | S66: 0 | T66: 0 | U66: 0 | V66: 0 | W66: 0 | X66: 0 | Y66: 0 | Z66: 0 | AA66: 0 | AB66: 0 | AC66: 0 | AD66: 0 | AE66: 0 | AF66: 0 | AG66: 0 | AH66: 0 | AI66: 0 | AJ66: 0 | AK66: 0 | AL66: 0 | AM66: 0 | AN66: 0 | AO66: 0 | AP66: 0 | AQ66: 0 | AR66: 0 | AS66: 0 | AT66: 0 | AU66: 0 | AV66: =SUM(H66:AU66) -> 0 | AW66: =F66-AV66 -> 0
B67: Accessibility Consulting | E67: 0 | F67: ='Development Budget'!G52 -> 0 | G67: 0 | H67: 0 | I67: 0 | J67: 0 | K67: 0 | L67: 0 | M67: 0 | N67: 0 | O67: 0 | P67: 0 | Q67: 0 | R67: 0 | S67: 0 | T67: 0 | U67: 0 | V67: 0 | W67: 0 | X67: 0 | Y67: 0 | Z67: 0 | AA67: 0 | AB67: 0 | AC67: 0 | AD67: 0 | AE67: 0 | AF67: 0 | AG67: 0 | AH67: 0 | AI67: 0 | AJ67: 0 | AK67: 0 | AL67: 0 | AM67: 0 | AN67: 0 | AO67: 0 | AP67: 0 | AQ67: 0 | AR67: 0 | AS67: 0 | AT67: 0 | AU67: 0 | AV67: =SUM(H67:AU67) -> 0 | AW67: =F67-AV67 -> 0
B68: Construction Materials Testing | E68: 0 | F68: ='Development Budget'!G53 -> 0 | G68: 0 | H68: 0 | I68: 0 | J68: 0 | K68: 0 | L68: 0 | M68: 0 | N68: 0 | O68: 0 | P68: 0 | Q68: 0 | R68: 0 | S68: 0 | T68: 0 | U68: 0 | V68: 0 | W68: 0 | X68: 0 | Y68: 0 | Z68: 0 | AA68: 0 | AB68: 0 | AC68: 0 | AD68: 0 | AE68: 0 | AF68: 0 | AG68: 0 | AH68: 0 | AI68: 0 | AJ68: 0 | AK68: 0 | AL68: 0 | AM68: 0 | AN68: 0 | AO68: 0 | AP68: 0 | AQ68: 0 | AR68: 0 | AS68: 0 | AT68: 0 | AU68: 0 | AV68: =SUM(H68:AU68) -> 0 | AW68: =F68-AV68 -> 0
A69: Local Government Fees | E69: 0 | F69: 0 | G69: 0 | H69: 0 | I69: 0 | J69: 0 | K69: 0 | L69: 0 | M69: 0 | N69: 0 | O69: 0 | P69: 0 | Q69: 0 | R69: 0 | S69: 0 | T69: 0 | U69: 0 | V69: 0 | W69: 0 | X69: 0 | Y69: 0 | Z69: 0 | AA69: 0 | AB69: 0 | AC69: 0 | AD69: 0 | AE69: 0 | AF69: 0 | AG69: 0 | AH69: 0 | AI69: 0 | AJ69: 0 | AK69: 0 | AL69: 0 | AM69: 0 | AN69: 0 | AO69: 0 | AP69: 0 | AQ69: 0 | AR69: 0 | AS69: 0 | AT69: 0 | AU69: 0 | AV69: 0 | AW69: 0
B70: Building Permits | E70: 0 | F70: ='Development Budget'!G56 -> 0 | G70: 0 | H70: 0 | I70: 0 | J70: 0 | K70: 0 | L70: 0 | M70: 0 | N70: 0 | O70: 0 | P70: 0 | Q70: 0 | R70: 0 | S70: 0 | T70: 0 | U70: 0 | V70: 0 | W70: 0 | X70: 0 | Y70: 0 | Z70: 0 | AA70: 0 | AB70: 0 | AC70: 0 | AD70: 0 | AE70: 0 | AF70: 0 | AG70: 0 | AH70: 0 | AI70: 0 | AJ70: 0 | AK70: 0 | AL70: 0 | AM70: 0 | AN70: 0 | AO70: 0 | AP70: 0 | AQ70: 0 | AR70: 0 | AS70: 0 | AT70: 0 | AU70: 0 | AV70: =SUM(H70:AU70) -> 0 | AW70: =F70-AV70 -> 0
B71: Impact Fees | E71: 0 | F71: ='Development Budget'!G57 -> 0 | G71: 0 | H71: 0 | I71: 0 | J71: 0 | K71: 0 | L71: 0 | M71: 0 | N71: 0 | O71: 0 | P71: 0 | Q71: 0 | R71: 0 | S71: 0 | T71: 0 | U71: 0 | V71: 0 | W71: 0 | X71: 0 | Y71: 0 | Z71: 0 | AA71: 0 | AB71: 0 | AC71: 0 | AD71: 0 | AE71: 0 | AF71: 0 | AG71: 0 | AH71: 0 | AI71: 0 | AJ71: 0 | AK71: 0 | AL71: 0 | AM71: 0 | AN71: 0 | AO71: 0 | AP71: 0 | AQ71: 0 | AR71: 0 | AS71: 0 | AT71: 0 | AU71: 0 | AV71: =SUM(H71:AU71) -> 0 | AW71: =F71-AV71 -> 0
B72: Plan review | E72: 0 | F72: ='Development Budget'!G58 -> 0 | G72: 0 | H72: 0 | I72: 0 | J72: 0 | K72: 0 | L72: 0 | M72: 0 | N72: 0 | O72: 0 | P72: 0 | Q72: 0 | R72: 0 | S72: 0 | T72: 0 | U72: 0 | V72: 0 | W72: 0 | X72: 0 | Y72: 0 | Z72: 0 | AA72: 0 | AB72: 0 | AC72: 0 | AD72: 0 | AE72: 0 | AF72: 0 | AG72: 0 | AH72: 0 | AI72: 0 | AJ72: 0 | AK72: 0 | AL72: 0 | AM72: 0 | AN72: 0 | AO72: 0 | AP72: 0 | AQ72: 0 | AR72: 0 | AS72: 0 | AT72: 0 | AU72: 0 | AV72: =SUM(H72:AU72) -> 0 | AW72: =F72-AV72 -> 0
B73: Other local fees | E73: 0 | F73: ='Development Budget'!G59 -> 0 | G73: 0 | H73: 0 | I73: 0 | J73: 0 | K73: 0 | L73: 0 | M73: 0 | N73: 0 | O73: 0 | P73: 0 | Q73: 0 | R73: 0 | S73: 0 | T73: 0 | U73: 0 | V73: 0 | W73: 0 | X73: 0 | Y73: 0 | Z73: 0 | AA73: 0 | AB73: 0 | AC73: 0 | AD73: 0 | AE73: 0 | AF73: 0 | AG73: 0 | AH73: 0 | AI73: 0 | AJ73: 0 | AK73: 0 | AL73: 0 | AM73: 0 | AN73: 0 | AO73: 0 | AP73: 0 | AQ73: 0 | AR73: 0 | AS73: 0 | AT73: 0 | AU73: 0 | AV73: =SUM(H73:AU73) -> 0 | AW73: =F73-AV73 -> 0
A74: Permanent Financing Fees | E74: 0 | F74: 0 | G74: 0 | H74: 0 | I74: 0 | J74: 0 | K74: 0 | L74: 0 | M74: 0 | N74: 0 | O74: 0 | P74: 0 | Q74: 0 | R74: 0 | S74: 0 | T74: 0 | U74: 0 | V74: 0 | W74: 0 | X74: 0 | Y74: 0 | Z74: 0 | AA74: 0 | AB74: 0 | AC74: 0 | AD74: 0 | AE74: 0 | AF74: 0 | AG74: 0 | AH74: 0 | AI74: 0 | AJ74: 0 | AK74: 0 | AL74: 0 | AM74: 0 | AN74: 0 | AO74: 0 | AP74: 0 | AQ74: 0 | AR74: 0 | AS74: 0 | AT74: 0 | AU74: 0 | AV74: 0 | AW74: 0
B75: Permanent Loan Fees | E75: 0 | F75: ='Development Budget'!G62 -> 0 | G75: 0 | H75: 0 | I75: 0 | J75: 0 | K75: 0 | L75: 0 | M75: 0 | N75: 0 | O75: 0 | P75: 0 | Q75: 0 | R75: 0 | S75: 0 | T75: 0 | U75: 0 | V75: 0 | W75: 0 | X75: 0 | Y75: 0 | Z75: 0 | AA75: 0 | AB75: 0 | AC75: 0 | AD75: 0 | AE75: 0 | AF75: 0 | AG75: 0 | AH75: 0 | AI75: 0 | AJ75: 0 | AK75: 0 | AL75: 0 | AM75: 0 | AN75: 0 | AO75: 0 | AP75: 0 | AQ75: 0 | AR75: 0 | AS75: 0 | AT75: 0 | AU75: 0 | AV75: =SUM(H75:AU75) -> 0 | AW75: =F75-AV75 -> 0
B76: Permanent Loan Legal Fees | E76: 0 | F76: ='Development Budget'!G63 -> 0 | G76: 0 | H76: 0 | I76: 0 | J76: 0 | K76: 0 | L76: 0 | M76: 0 | N76: 0 | O76: 0 | P76: 0 | Q76: 0 | R76: 0 | S76: 0 | T76: 0 | U76: 0 | V76: 0 | W76: 0 | X76: 0 | Y76: 0 | Z76: 0 | AA76: 0 | AB76: 0 | AC76: 0 | AD76: 0 | AE76: 0 | AF76: 0 | AG76: 0 | AH76: 0 | AI76: 0 | AJ76: 0 | AK76: 0 | AL76: 0 | AM76: 0 | AN76: 0 | AO76: 0 | AP76: 0 | AQ76: 0 | AR76: 0 | AS76: 0 | AT76: 0 | AU76: 0 | AV76: =SUM(H76:AU76) -> 0 | AW76: =F76-AV76 -> 0
B77: Title and Recording Fees | E77: 0 | F77: ='Development Budget'!G64 -> 0 | G77: 0 | H77: 0 | I77: 0 | J77: 0 | K77: 0 | L77: 0 | M77: 0 | N77: 0 | O77: 0 | P77: 0 | Q77: 0 | R77: 0 | S77: 0 | T77: 0 | U77: 0 | V77: 0 | W77: 0 | X77: 0 | Y77: 0 | Z77: 0 | AA77: 0 | AB77: 0 | AC77: 0 | AD77: 0 | AE77: 0 | AF77: 0 | AG77: 0 | AH77: 0 | AI77: 0 | AJ77: 0 | AK77: 0 | AL77: 0 | AM77: 0 | AN77: 0 | AO77: 0 | AP77: 0 | AQ77: 0 | AR77: 0 | AS77: 0 | AT77: 0 | AU77: 0 | AV77: =SUM(H77:AU77) -> 0 | AW77: =F77-AV77 -> 0
B78: As-Built Survey | E78: 0 | F78: ='Development Budget'!G65 -> 0 | G78: 0 | H78: 0 | I78: 0 | J78: 0 | K78: 0 | L78: 0 | M78: 0 | N78: 0 | O78: 0 | P78: 0 | Q78: 0 | R78: 0 | S78: 0 | T78: 0 | U78: 0 | V78: 0 | W78: 0 | X78: 0 | Y78: 0 | Z78: 0 | AA78: 0 | AB78: 0 | AC78: 0 | AD78: 0 | AE78: 0 | AF78: 0 | AG78: 0 | AH78: 0 | AI78: 0 | AJ78: 0 | AK78: 0 | AL78: 0 | AM78: 0 | AN78: 0 | AO78: 0 | AP78: 0 | AQ78: 0 | AR78: 0 | AS78: 0 | AT78: 0 | AU78: 0 | AV78: =SUM(H78:AU78) -> 0 | AW78: =F78-AV78 -> 0
B79: Conversion Fee | E79: 0 | F79: ='Development Budget'!G66 -> 0 | G79: 0 | H79: 0 | I79: 0 | J79: 0 | K79: 0 | L79: 0 | M79: 0 | N79: 0 | O79: 0 | P79: 0 | Q79: 0 | R79: 0 | S79: 0 | T79: 0 | U79: 0 | V79: 0 | W79: 0 | X79: 0 | Y79: 0 | Z79: 0 | AA79: 0 | AB79: 0 | AC79: 0 | AD79: 0 | AE79: 0 | AF79: 0 | AG79: 0 | AH79: 0 | AI79: 0 | AJ79: 0 | AK79: 0 | AL79: 0 | AM79: 0 | AN79: 0 | AO79: 0 | AP79: 0 | AQ79: 0 | AR79: 0 | AS79: 0 | AT79: 0 | AU79: 0 | AV79: =SUM(H79:AU79) -> 0 | AW79: =F79-AV79 -> 0
A80: Tax Credit Costs | E80: 0 | F80: 0 | G80: 0 | H80: 0 | I80: 0 | J80: 0 | K80: 0 | L80: 0 | M80: 0 | N80: 0 | O80: 0 | P80: 0 | Q80: 0 | R80: 0 | S80: 0 | T80: 0 | U80: 0 | V80: 0 | W80: 0 | X80: 0 | Y80: 0 | Z80: 0 | AA80: 0 | AB80: 0 | AC80: 0 | AD80: 0 | AE80: 0 | AF80: 0 | AG80: 0 | AH80: 0 | AI80: 0 | AJ80: 0 | AK80: 0 | AL80: 0 | AM80: 0 | AN80: 0 | AO80: 0 | AP80: 0 | AQ80: 0 | AR80: 0 | AS80: 0 | AT80: 0 | AU80: 0 | AV80: 0 | AW80: 0
B81: Application Fee | E81: 0 | F81: ='Development Budget'!G69 -> 0 | G81: 0 | H81: 0 | I81: 0 | J81: 0 | K81: 0 | L81: 0 | M81: 0 | N81: 0 | O81: 0 | P81: 0 | Q81: 0 | R81: 0 | S81: 0 | T81: 0 | U81: 0 | V81: 0 | W81: 0 | X81: 0 | Y81: 0 | Z81: 0 | AA81: 0 | AB81: 0 | AC81: 0 | AD81: 0 | AE81: 0 | AF81: 0 | AG81: 0 | AH81: 0 | AI81: 0 | AJ81: 0 | AK81: 0 | AL81: 0 | AM81: 0 | AN81: 0 | AO81: 0 | AP81: 0 | AQ81: 0 | AR81: 0 | AS81: 0 | AT81: 0 | AU81: 0 | AV81: =SUM(H81:AU81) -> 0 | AW81: =F81-AV81 -> 0
B82: Pre-application Fee | E82: 0 | F82: ='Development Budget'!G70 -> 0 | G82: 0 | H82: 0 | I82: 0 | J82: 0 | K82: 0 | L82: 0 | M82: 0 | N82: 0 | O82: 0 | P82: 0 | Q82: 0 | R82: 0 | S82: 0 | T82: 0 | U82: 0 | V82: 0 | W82: 0 | X82: 0 | Y82: 0 | Z82: 0 | AA82: 0 | AB82: 0 | AC82: 0 | AD82: 0 | AE82: 0 | AF82: 0 | AG82: 0 | AH82: 0 | AI82: 0 | AJ82: 0 | AK82: 0 | AL82: 0 | AM82: 0 | AN82: 0 | AO82: 0 | AP82: 0 | AQ82: 0 | AR82: 0 | AS82: 0 | AT82: 0 | AU82: 0 | AV82: =SUM(H82:AU82) -> 0 | AW82: =F82-AV82 -> 0
B83: Commitment Fee | E83: 0 | F83: ='Development Budget'!G71 -> 0 | G83: 0 | H83: 0 | I83: 0 | J83: 0 | K83: 0 | L83: 0 | M83: 0 | N83: 0 | O83: 0 | P83: 0 | Q83: 0 | R83: 0 | S83: 0 | T83: 0 | U83: 0 | V83: 0 | W83: 0 | X83: 0 | Y83: 0 | Z83: 0 | AA83: 0 | AB83: 0 | AC83: 0 | AD83: 0 | AE83: 0 | AF83: 0 | AG83: 0 | AH83: 0 | AI83: 0 | AJ83: 0 | AK83: 0 | AL83: 0 | AM83: 0 | AN83: 0 | AO83: 0 | AP83: 0 | AQ83: 0 | AR83: 0 | AS83: 0 | AT83: 0 | AU83: 0 | AV83: =SUM(H83:AU83) -> 0 | AW83: =F83-AV83 -> 0
B84: Bond Development Determination Fee | E84: 0 | F84: ='Development Budget'!G72 -> 0 | G84: 0 | H84: 0 | I84: 0 | J84: 0 | K84: 0 | L84: 0 | M84: 0 | N84: 0 | O84: 0 | P84: 0 | Q84: 0 | R84: 0 | S84: 0 | T84: 0 | U84: 0 | V84: 0 | W84: 0 | X84: 0 | Y84: 0 | Z84: 0 | AA84: 0 | AB84: 0 | AC84: 0 | AD84: 0 | AE84: 0 | AF84: 0 | AG84: 0 | AH84: 0 | AI84: 0 | AJ84: 0 | AK84: 0 | AL84: 0 | AM84: 0 | AN84: 0 | AO84: 0 | AP84: 0 | AQ84: 0 | AR84: 0 | AS84: 0 | AT84: 0 | AU84: 0 | AV84: =SUM(H84:AU84) -> 0 | AW84: =F84-AV84 -> 0
B85: LIHTC Allocation Processing Fee | E85: 0 | F85: ='Development Budget'!G73 -> 0 | G85: 0 | H85: 0 | I85: 0 | J85: 0 | K85: 0 | L85: 0 | M85: 0 | N85: 0 | O85: 0 | P85: 0 | Q85: 0 | R85: 0 | S85: 0 | T85: 0 | U85: 0 | V85: 0 | W85: 0 | X85: 0 | Y85: 0 | Z85: 0 | AA85: 0 | AB85: 0 | AC85: 0 | AD85: 0 | AE85: 0 | AF85: 0 | AG85: 0 | AH85: 0 | AI85: 0 | AJ85: 0 | AK85: 0 | AL85: 0 | AM85: 0 | AN85: 0 | AO85: 0 | AP85: 0 | AQ85: 0 | AR85: 0 | AS85: 0 | AT85: 0 | AU85: 0 | AV85: =SUM(H85:AU85) -> 0 | AW85: =F85-AV85 -> 0
B86: LIHTC Compliance Monitoring Fee | E86: 0 | F86: ='Development Budget'!G74 -> 0 | G86: 0 | H86: 0 | I86: 0 | J86: 0 | K86: 0 | L86: 0 | M86: 0 | N86: 0 | O86: 0 | P86: 0 | Q86: 0 | R86: 0 | S86: 0 | T86: 0 | U86: 0 | V86: 0 | W86: 0 | X86: 0 | Y86: 0 | Z86: 0 | AA86: 0 | AB86: 0 | AC86: 0 | AD86: 0 | AE86: 0 | AF86: 0 | AG86: 0 | AH86: 0 | AI86: 0 | AJ86: 0 | AK86: 0 | AL86: 0 | AM86: 0 | AN86: 0 | AO86: 0 | AP86: 0 | AQ86: 0 | AR86: 0 | AS86: 0 | AT86: 0 | AU86: 0 | AV86: =SUM(H86:AU86) -> 0 | AW86: =F86-AV86 -> 0
A87: Equity Costs | E87: 0 | F87: 0 | G87: 0 | H87: 0 | I87: 0 | J87: 0 | K87: 0 | L87: 0 | M87: 0 | N87: 0 | O87: 0 | P87: 0 | Q87: 0 | R87: 0 | S87: 0 | T87: 0 | U87: 0 | V87: 0 | W87: 0 | X87: 0 | Y87: 0 | Z87: 0 | AA87: 0 | AB87: 0 | AC87: 0 | AD87: 0 | AE87: 0 | AF87: 0 | AG87: 0 | AH87: 0 | AI87: 0 | AJ87: 0 | AK87: 0 | AL87: 0 | AM87: 0 | AN87: 0 | AO87: 0 | AP87: 0 | AQ87: 0 | AR87: 0 | AS87: 0 | AT87: 0 | AU87: 0 | AV87: 0 | AW87: 0
B88: Partnership Organization Fees | E88: 0 | F88: ='Development Budget'!G77 -> 0 | G88: 0 | H88: 0 | I88: 0 | J88: 0 | K88: 0 | L88: 0 | M88: 0 | N88: 0 | O88: 0 | P88: 0 | Q88: 0 | R88: 0 | S88: 0 | T88: 0 | U88: 0 | V88: 0 | W88: 0 | X88: 0 | Y88: 0 | Z88: 0 | AA88: 0 | AB88: 0 | AC88: 0 | AD88: 0 | AE88: 0 | AF88: 0 | AG88: 0 | AH88: 0 | AI88: 0 | AJ88: 0 | AK88: 0 | AL88: 0 | AM88: 0 | AN88: 0 | AO88: 0 | AP88: 0 | AQ88: 0 | AR88: 0 | AS88: 0 | AT88: 0 | AU88: 0 | AV88: =SUM(H88:AU88) -> 0 | AW88: =F88-AV88 -> 0
B89: Tax Credit Legal Opinion | E89: 0 | F89: ='Development Budget'!G78 -> 0 | G89: 0 | H89: 0 | I89: 0 | J89: 0 | K89: 0 | L89: 0 | M89: 0 | N89: 0 | O89: 0 | P89: 0 | Q89: 0 | R89: 0 | S89: 0 | T89: 0 | U89: 0 | V89: 0 | W89: 0 | X89: 0 | Y89: 0 | Z89: 0 | AA89: 0 | AB89: 0 | AC89: 0 | AD89: 0 | AE89: 0 | AF89: 0 | AG89: 0 | AH89: 0 | AI89: 0 | AJ89: 0 | AK89: 0 | AL89: 0 | AM89: 0 | AN89: 0 | AO89: 0 | AP89: 0 | AQ89: 0 | AR89: 0 | AS89: 0 | AT89: 0 | AU89: 0 | AV89: =SUM(H89:AU89) -> 0 | AW89: =F89-AV89 -> 0
B90: Syndicator Legal Fees | E90: 0 | F90: ='Development Budget'!G79 -> 0 | G90: 0 | H90: 0 | I90: 0 | J90: 0 | K90: 0 | L90: 0 | M90: 0 | N90: 0 | O90: 0 | P90: 0 | Q90: 0 | R90: 0 | S90: 0 | T90: 0 | U90: 0 | V90: 0 | W90: 0 | X90: 0 | Y90: 0 | Z90: 0 | AA90: 0 | AB90: 0 | AC90: 0 | AD90: 0 | AE90: 0 | AF90: 0 | AG90: 0 | AH90: 0 | AI90: 0 | AJ90: 0 | AK90: 0 | AL90: 0 | AM90: 0 | AN90: 0 | AO90: 0 | AP90: 0 | AQ90: 0 | AR90: 0 | AS90: 0 | AT90: 0 | AU90: 0 | AV90: =SUM(H90:AU90) -> 0 | AW90: =F90-AV90 -> 0
B91: Syndicator Due Diligence Fee | E91: 0 | F91: ='Development Budget'!G80 -> 0 | G91: 0 | H91: 0 | I91: 0 | J91: 0 | K91: 0 | L91: 0 | M91: 0 | N91: 0 | O91: 0 | P91: 0 | Q91: 0 | R91: 0 | S91: 0 | T91: 0 | U91: 0 | V91: 0 | W91: 0 | X91: 0 | Y91: 0 | Z91: 0 | AA91: 0 | AB91: 0 | AC91: 0 | AD91: 0 | AE91: 0 | AF91: 0 | AG91: 0 | AH91: 0 | AI91: 0 | AJ91: 0 | AK91: 0 | AL91: 0 | AM91: 0 | AN91: 0 | AO91: 0 | AP91: 0 | AQ91: 0 | AR91: 0 | AS91: 0 | AT91: 0 | AU91: 0 | AV91: =SUM(H91:AU91) -> 0 | AW91: =F91-AV91 -> 0
A92: Start Up and Reserves | E92: 0 | F92: 0 | G92: 0 | H92: 0 | I92: 0 | J92: 0 | K92: 0 | L92: 0 | M92: 0 | N92: 0 | O92: 0 | P92: 0 | Q92: 0 | R92: 0 | S92: 0 | T92: 0 | U92: 0 | V92: 0 | W92: 0 | X92: 0 | Y92: 0 | Z92: 0 | AA92: 0 | AB92: 0 | AC92: 0 | AD92: 0 | AE92: 0 | AF92: 0 | AG92: 0 | AH92: 0 | AI92: 0 | AJ92: 0 | AK92: 0 | AL92: 0 | AM92: 0 | AN92: 0 | AO92: 0 | AP92: 0 | AQ92: 0 | AR92: 0 | AS92: 0 | AT92: 0 | AU92: 0 | AV92: 0 | AW92: 0
B93: Marketing | E93: 0 | F93: ='Development Budget'!G83 -> 0 | G93: 0 | H93: 0 | I93: 0 | J93: 0 | K93: 0 | L93: 0 | M93: 0 | N93: 0 | O93: 0 | P93: 0 | Q93: 0 | R93: 0 | S93: 0 | T93: 0 | U93: 0 | V93: 0 | W93: 0 | X93: 0 | Y93: 0 | Z93: 0 | AA93: 0 | AB93: 0 | AC93: 0 | AD93: 0 | AE93: 0 | AF93: 0 | AG93: 0 | AH93: 0 | AI93: 0 | AJ93: 0 | AK93: 0 | AL93: 0 | AM93: 0 | AN93: 0 | AO93: 0 | AP93: 0 | AQ93: 0 | AR93: 0 | AS93: 0 | AT93: 0 | AU93: 0 | AV93: =SUM(H93:AU93) -> 0 | AW93: =F93-AV93 -> 0
B94: Rent-Up Reserves | E94: 0 | F94: ='Development Budget'!G84 -> 0 | G94: 0 | H94: 0 | I94: 0 | J94: 0 | K94: 0 | L94: 0 | M94: 0 | N94: 0 | O94: 0 | P94: 0 | Q94: 0 | R94: 0 | S94: 0 | T94: 0 | U94: 0 | V94: 0 | W94: 0 | X94: 0 | Y94: 0 | Z94: 0 | AA94: 0 | AB94: 0 | AC94: 0 | AD94: 0 | AE94: 0 | AF94: 0 | AG94: 0 | AH94: 0 | AI94: 0 | AJ94: 0 | AK94: 0 | AL94: 0 | AM94: 0 | AN94: 0 | AO94: 0 | AP94: 0 | AQ94: 0 | AR94: 0 | AS94: 0 | AT94: 0 | AU94: 0 | AV94: =SUM(H94:AU94) -> 0 | AW94: =F94-AV94 -> 0
B95: Operating Deficit Reserve | E95: 0 | F95: ='Development Budget'!G85 -> 0 | G95: 0 | H95: 0 | I95: 0 | J95: 0 | K95: 0 | L95: 0 | M95: 0 | N95: 0 | O95: 0 | P95: 0 | Q95: 0 | R95: 0 | S95: 0 | T95: 0 | U95: 0 | V95: 0 | W95: 0 | X95: 0 | Y95: 0 | Z95: 0 | AA95: 0 | AB95: 0 | AC95: 0 | AD95: 0 | AE95: 0 | AF95: 0 | AG95: 0 | AH95: 0 | AI95: 0 | AJ95: 0 | AK95: 0 | AL95: 0 | AM95: 0 | AN95: 0 | AO95: 0 | AP95: 0 | AQ95: 0 | AR95: 0 | AS95: 0 | AT95: 0 | AU95: 0 | AV95: =SUM(H95:AU95) -> 0 | AW95: =F95-AV95 -> 0
B96: Replacement Reserve | E96: 0 | F96: ='Development Budget'!G86 -> 0 | G96: 0 | H96: 0 | I96: 0 | J96: 0 | K96: 0 | L96: 0 | M96: 0 | N96: 0 | O96: 0 | P96: 0 | Q96: 0 | R96: 0 | S96: 0 | T96: 0 | U96: 0 | V96: 0 | W96: 0 | X96: 0 | Y96: 0 | Z96: 0 | AA96: 0 | AB96: 0 | AC96: 0 | AD96: 0 | AE96: 0 | AF96: 0 | AG96: 0 | AH96: 0 | AI96: 0 | AJ96: 0 | AK96: 0 | AL96: 0 | AM96: 0 | AN96: 0 | AO96: 0 | AP96: 0 | AQ96: 0 | AR96: 0 | AS96: 0 | AT96: 0 | AU96: 0 | AV96: =SUM(H96:AU96) -> 0 | AW96: =F96-AV96 -> 0
B97: Furniture, Fixtures and Equipment | E97: 0 | F97: ='Development Budget'!G87 -> 0 | G97: 0 | H97: 0 | I97: 0 | J97: 0 | K97: 0 | L97: 0 | M97: 0 | N97: 0 | O97: 0 | P97: 0 | Q97: 0 | R97: 0 | S97: 0 | T97: 0 | U97: 0 | V97: 0 | W97: 0 | X97: 0 | Y97: 0 | Z97: 0 | AA97: 0 | AB97: 0 | AC97: 0 | AD97: 0 | AE97: 0 | AF97: 0 | AG97: 0 | AH97: 0 | AI97: 0 | AJ97: 0 | AK97: 0 | AL97: 0 | AM97: 0 | AN97: 0 | AO97: 0 | AP97: 0 | AQ97: 0 | AR97: 0 | AS97: 0 | AT97: 0 | AU97: 0 | AV97: =SUM(H97:AU97) -> 0 | AW97: =F97-AV97 -> 0
A98: Other Costs | E98: 0 | F98: 0 | G98: 0 | H98: 0 | I98: 0 | J98: 0 | K98: 0 | L98: 0 | M98: 0 | N98: 0 | O98: 0 | P98: 0 | Q98: 0 | R98: 0 | S98: 0 | T98: 0 | U98: 0 | V98: 0 | W98: 0 | X98: 0 | Y98: 0 | Z98: 0 | AA98: 0 | AB98: 0 | AC98: 0 | AD98: 0 | AE98: 0 | AF98: 0 | AG98: 0 | AH98: 0 | AI98: 0 | AJ98: 0 | AK98: 0 | AL98: 0 | AM98: 0 | AN98: 0 | AO98: 0 | AP98: 0 | AQ98: 0 | AR98: 0 | AS98: 0 | AT98: 0 | AU98: 0 | AV98: 0 | AW98: 0
B99: Soft Cost Contingency | E99: 0 | F99: ='Development Budget'!G90 -> 0 | G99: 0 | H99: 0 | I99: 0 | J99: 0 | K99: 0 | L99: 0 | M99: 0 | N99: 0 | O99: 0 | P99: 0 | Q99: 0 | R99: 0 | S99: 0 | T99: 0 | U99: 0 | V99: 0 | W99: 0 | X99: 0 | Y99: 0 | Z99: 0 | AA99: 0 | AB99: 0 | AC99: 0 | AD99: 0 | AE99: 0 | AF99: 0 | AG99: 0 | AH99: 0 | AI99: 0 | AJ99: 0 | AK99: 0 | AL99: 0 | AM99: 0 | AN99: 0 | AO99: 0 | AP99: 0 | AQ99: 0 | AR99: 0 | AS99: 0 | AT99: 0 | AU99: 0 | AV99: =SUM(H99:AU99) -> 0 | AW99: =F99-AV99 -> 0
B100: Developer Fee - Overhead (30%) | E100: 0 | F100: ='Development Budget'!G93*0.4 -> 0 | G100: 0 | H100: 0 | I100: 0 | J100: 0 | K100: 0 | L100: 0 | M100: 0 | N100: 0 | O100: 0 | P100: 0 | Q100: 0 | R100: 0 | S100: 0 | T100: 0 | U100: 0 | V100: 0 | W100: 0 | X100: 0 | Y100: 0 | Z100: 0 | AA100: 0 | AB100: 0 | AC100: 0 | AD100: 0 | AE100: 0 | AF100: 0 | AG100: 0 | AH100: 0 | AI100: 0 | AJ100: 0 | AK100: 0 | AL100: 0 | AM100: 0 | AN100: 0 | AO100: 0 | AP100: 0 | AQ100: 0 | AR100: 0 | AS100: 0 | AT100: 0 | AU100: 0 | AV100: =SUM(H100:AU100) -> 0 | AW100: =F100-AV100 -> 0
...

Sheet Developer Fee Schedule
J1: LOR Feasibility Analysis Template
E4: I. Closing | F4: II. Completion | G4: III. Stabilization | H4: IV. Final Install | I4: deferred fee
D5: investor LPA- % of paid fee | E5: 0 | F5: 0 | G5: 0 | H5: 0 | I5: from
I6: cash flow | K6: sum totals
C7: Fee Scheduled to be Paid* | E7: 0 | F7: 0 | G7: 0 | H7: 0 | I7: 0 | K7: =SUM(E7:I7) -> 0
B9: Total Development Fee | D9: (actual paid fee) -------> | E9: =E7 -> 0 | F9: =F7 -> 0 | G9: =G7 -> 0 | H9: =H7 -> 0 | I9: =I7 -> 0 | K9: =SUM(E9:I9) -> 0
M11: 0.39322457
A12: 0 | B12: 20% Developer Overhead:
B13: 50% to Vic Loraso | E13: 0 | K13: =SUM(E13:I13) -> 0
B14: 50% to Robert Wolf
C15: To Robert Wolf | E15: 0 | K15: =SUM(E15:I15) -> 0
C16: To Vic Loraso | E16: 0 | K16: =SUM(E16:I16) -> 0
A18: 0 | B18: remaining to pay out | E18: =E7-E13-E15-E16 -> 0 | F18: =F7-F13-F15-F16 -> 0 | G18: =G7-G13-G15-G16 -> 0 | H18: =H7-H13-H15-H16 -> 0 | I18: =I7-I13-I15-I16 -> 0 | K18: =SUM(E18:I18) -> 0
A20: 0 | B20: split to SDK Independence LLC | D20: 0 | E20: =E18*$D$20 -> 0 | F20: =F18*$D$20 -> 0 | G20: =G18*$D$20 -> 0 | H20: =H18*$D$20 -> 0 | I20: =I18*$D$20 -> 0 | K20: =SUM(E20:I20) -> 0
A21: 0 | B21: split to New AHP LLC | D21: 0 | E21: =E18*$D$21 -> 0 | F21: =F18*$D$21 -> 0 | G21: =G18*$D$21 -> 0 | H21: =H18*$D$21 -> 0 | I21: =I18*$D$21 -> 0 | K21: =SUM(E21:I21) -> 0
B23: Total Fee Splits | C23: SDK Independence LLC | E23: =E15+E20 -> 0 | F23: =F15+F20 -> 0 | G23: =G15+G20 -> 0 | H23: =H15+H20 -> 0 | I23: =I15+I20 -> 0 | K23: =SUM(E23:I23) -> 0
C24: New AHP LLC | E24: =E16+E21 -> 0 | F24: =F16+F21 -> 0 | G24: =G16+G21 -> 0 | H24: =H16+H21 -> 0 | I24: =I16+I21 -> 0 | K24: =SUM(E24:I24) -> 0
B26: * Development Fee is paid upon satisfaction of benchmarks as set out in the Limited Partnership Agreement and Development Services Agreement of Independence Heights Apartments II, Limited Partnership.
B27: Payment dates are estimated based on when we believe benchmarks will be met, but are subject to change. In addition, paid fee amounts are projected assuming a succesful project.
B28: The amount of paid fee could change depending on how successful the project is. | M28: Vic Loraso | N28: 500000 | O28: 0.25
M29: Robert Wolf | N29: 500000 | O29: 0.25
N30: 1000000 | O30: 0.5

Sheet 25% Test
C2: Uses from Development Budget:
C3: Aggregate Basis | D3: ='Development Budget'!J94 -> 0
D4: =SUM(D3:D3) -> 0 | E4: Max Bond Amt (50%): | F4: =D4*0.5 -> 0
E5: Min Bond Amt (25%): | F5: =D4*0.25 -> 0
C6: Total Bonds | D6: =F5 -> 0
C8: Total Bond Proceeds
C10: 25% Test | D10: =D6/D4 -> #DIV/0! | F10: Must exceed 25% per IRC §42(h)(4)

Sheet Income (2)
A2: Unit Mix Set-Asides, County AMI and Rent Limits, and Utility Allowances
M3: Average Income Targeting: | N3: 0.56507937 | Q3: Stabilized Net Operating Income
A4: AMI Set-Asides | B4: Targeted / | C4: Unit Style | F4: Number | G4: Net | H4: Total | I4: Max Net | J4: Net Rent | K4: Total | L4: Rent | M4: Min BR | N4: Hourly | V4: Rent
B5: Actual | C5: BR | D5: Type | E5: BA | F5: of Units | G5: Area | H5: SqFt | I5: Rent | J5: p/Unit | K5: Rent/Mo | L5: p/SqFt | M5: Income | N5: Wages | Q5: Rental Inc. | R5: 982800 | U5: Market | V5: Advantage | W5: % RA
B6: 0.36065574 | D6: A | H6: 0 | I6: 828 | K6: 4290 | L6: 0 | M6: 28600 | N6: 13.75 | O6: 0.93 | P6: 2813.1148 | Q6: Garage/Comm. | R6: 0 | V6: 604 | W6: 0.45792267
A7: LIHTC | D7: B | E7: 2 | H7: 0 | I7: 828 | K7: 6840 | L7: 0 | M7: 34200 | N7: 16.442308 | P7: 4485.2459 | Q7: Other Inc. | V7: 583 | W7: 0.4054242
A8: LIHTC | D8: C | E8: 2 | H8: 0 | I8: 828 | K8: 2925 | L8: 0 | M8: 39000 | N8: 18.75 | P8: 1918.0328 | Q8: Gross Potential | R8: 982800 | V8: 783 | W8: 0.44539249
A9: 0 | D9: D | E9: 2 | H9: 0 | I9: 828 | K9: 1075 | L9: 0 | M9: 43000 | N9: 20.673077 | P9: 704.91803 | Q9: Vacancy | R9: -68796 | V9: 794 | W9: 0.42482611
A10: 0.5 | D10: E | E10: 2 | H10: 0 | I10: 828 | K10: 1075 | L10: 0 | M10: 43000 | N10: 20.673077 | P10: 704.91803 | Q10: Effective Gross | R10: 914004 | V10: 794 | W10: 0.42482611
A11: LIHTC | D11: F | E11: 2 | H11: 0 | I11: 828 | K11: 975 | L11: 0 | M11: 39000 | N11: 18.75 | P11: 639.34426 | Q11: Net OpEx | R11: -477524 | V11: 783 | W11: 0.44539249
A12: LIHTC | D12: G | E12: 2 | H12: 0 | I12: 828 | K12: 855 | L12: 0 | M12: 34200 | N12: 16.442308 | P12: 560.65574 | R12: -67100 | V12: 583 | W12: 0.4054242
A13: LIHTC | D13: H | H13: 0 | I13: 828 | K13: 715 | L13: 0 | M13: 28600 | N13: 13.75 | P13: 468.85246 | Q13: Repl. Res. | R13: -18300 | V13: 604 | W13: 0.45792267
B14: 0.67213115 | D14: A | E14: 1 | H14: 0 | I14: 994 | K14: 10200 | L14: 0 | M14: 34000 | N14: 16.346154 | O14: 0.93 | P14: 6688.5246 | Q14: Total OpEx | R14: -562924 | V14: 469 | W14: 0.3555724
A15: LIHTC | D15: B | E15: 2 | H15: 0 | I15: 994 | K15: 16000 | L15: 0 | M15: 40000 | N15: 19.230769 | P15: 10491.803 | Q15: Net Oper. Inc. | R15: 351080 | V15: 438 | W15: 0.30458971
A16: LIHTC | D16: C | E16: 2 | H16: 0 | I16: 994 | K16: 8800 | L16: 0 | M16: 44000 | N16: 21.153846 | P16: 5770.4918 | R16: -10351.44 | V16: 658 | W16: 0.37428896
A17: LIHTC | D17: D | E17: 2 | H17: 0 | I17: 994 | K17: 6000 | L17: 0 | M17: 48000 | N17: 23.076923 | P17: 3934.4262 | V17: 669 | W17: 0.35794543
A18: 0.6 | D18: E | E18: 2 | H18: 0 | I18: 0 | Q18: Houston-The Woodlands-Sugar Land, TX HUD Metro FMR Area
A19: LIHTC | D19: F | E19: 2 | H19: 0 | I19: 0
A20: LIHTC | D20: G | E20: 2 | H20: 0 | I20: 0 | Q20: NNMMI
A21: LIHTC | D21: H | E21: 1 | H21: 0 | I21: 0 | Q21: Harris County
B22: 0.27868852 | D22: A | E22: 1 | H22: 0 | I22: 497 | K22: 5875 | L22: 0 | M22: 47000 | N22: 22.596154 | O22: 0.93 | P22: 3852.459 | V22: 144 | W22: 0.10917362
A23: 1 | D23: B | E23: 2 | H23: 0 | I23: 497 | K23: 8925 | L23: 0 | M23: 51000 | N23: 24.519231 | P23: 5852.459 | V23: 163 | W23: 0.11335188
A24: 1 | D24: C | E24: 2 | H24: 0 | I24: 497 | K24: 5800 | L24: 0 | M24: 58000 | N24: 27.884615 | P24: 3803.2787 | Q24: Per Unit Type Income Averaging | V24: 308 | W24: 0.17519909
A25: 1 | D25: D | E25: 2 | H25: 0 | I25: 497 | K25: 1550 | L25: 0 | M25: 62000 | N25: 29.807692 | P25: 1016.3934 | Q25: A | V25: 319 | W25: 0.17067951
A26: 1 | D26: E | E26: 2 | H26: 0 | I26: 497 | Q26: B
A27: 1 | D27: F | E27: 2 | H27: 0 | I27: 497 | Q27: C
A28: 1 | D28: G | E28: 2 | H28: 0 | I28: 497 | Q28: D
A29: 1 | D29: H | E29: 1 | H29: 0 | I29: 497 | Q29: E
E30: Totals | F30: 80 | H30: 0 | K30: 81900 | M30: 53704.918 | N30: Average Income | Q30: F
Q31: G
C32: 2 | D32: 3 | E32: 4 | F32: 5 | G32: 6 | K32: 0 | L32: 1 | M32: 2 | N32: 3 | O32: 4 | Q32: H
B33: 19890 | C33: 22710 | D33: 25560 | E33: 28380 | F33: 30660 | G33: 32940 | J33: Utilities | K33: 0 | L33: -210 | M33: -279 | N33: -349 | O33: 0
B34: 26520 | C34: 30280 | D34: 34080 | E34: 37840 | F34: 40880 | G34: 43920 | J34: 0.3 | K34: 497 | L34: 532 | M34: 428 | N34: 494 | O34: 823 | Q34: Per BR Type Income Averaging
J35: Max Rent | K35: 497 | L35: 322 | M35: 149 | N35: 145 | O35: 823
B36: 39780 | C36: 45420 | D36: 51120 | E36: 56760 | F36: 61320 | G36: 65880 | J36: 0.4 | K36: 663 | L36: 710 | M36: 852 | N36: 984 | O36: 1098
B37: 46410 | C37: 52990 | D37: 59640 | E37: 66220 | F37: 71540 | G37: 76860 | J37: Max Rent | K37: 663 | L37: 500 | M37: 573 | N37: 635 | O37: 1098
B38: 53040 | C38: 60560 | D38: 68160 | E38: 75680 | F38: 81760 | G38: 87840 | J38: 0.5 | K38: 828 | L38: 887 | M38: 1065 | N38: 1230 | O38: 1372
B39: 66300 | C39: 75700 | D39: 85200 | E39: 94600 | F39: 102200 | G39: 109800 | J39: Max Rent | K39: 828 | L39: 677 | M39: 786 | N39: 881 | O39: 1372
J40: 0.6 | K40: 994 | L40: 1065 | M40: 1278 | N40: 1476 | O40: 1647
G41: Building: | H41: LowRise | J41: Max Rent | K41: 994 | L41: 855 | M41: 999 | N41: 1127 | O41: 1647
A42: Utility Allowances | C42: Houston Housing Authority | G42: Effective: | J42: 0.7 | K42: 1160 | L42: 1242 | M42: 1491 | N42: 1722 | O42: 1921
A43: Use | C43: Tenant Pd? | F43: 2 | G43: 3 | H43: 4 | J43: Max Rent | K43: 1160 | L43: 1032 | M43: 1212 | N43: 1373 | O43: 1921
A44: Heating - Electric | C44: Y | J44: 0.8 | K44: 1326 | L44: 1420 | M44: 1704 | N44: 1968 | O44: 2196
A45: Cooking - Electric | C45: Y | J45: Max Rent | K45: 1326 | L45: 1210 | M45: 1425 | N45: 1619 | O45: 2196
A46: Other: | B46: Electric | C46: Y | J46: 1 | K46: 1657 | L46: 1775 | M46: 2130 | N46: 2460 | O46: 2745
A47: Other: | B47: A/C | C47: Y | J47: Max Rent | K47: 1657 | L47: 1565 | M47: 1851 | N47: 2111 | O47: 2745
A48: Hot Water - Electric | C48: Y | J48: FMR
A49: Water | C49: Y | J49: Max Rent
A50: Sewer | C50: Y | J50: Low HOME
A51: Trash Collection | C51: N | J51: Max Rent
A52: Other: | J52: High HOME
C53: Sum "Y" = | D53: 0 | E53: 210 | F53: 279 | G53: 349 | H53: 0 | J53: Max Rent

Sheet Income
A1: [Project Name]
A2: Unit Mix Set-Asides, County AMI and Rent Limits, and Utility Allowances
M3: Average Income Targeting: | N3: 0.56507937 | Q3: Stabilized Net Operating Income
A4: AMI Set-Asides | B4: Targeted / | C4: Unit Style | F4: Number | G4: Net | H4: Total | I4: Max Net | J4: Net Rent | K4: Total | L4: Rent | M4: Min BR | N4: Hourly | V4: Rent
B5: Actual | C5: BR | D5: Type | E5: BA | F5: of Units | G5: Area | H5: SqFt | I5: Rent | J5: p/Unit | K5: Rent/Mo | L5: p/SqFt | M5: Income | N5: Wages | Q5: Rental Inc. | R5: 999600 | U5: Market | V5: Advantage | W5: % RA
B6: 0.36065574 | D6: A | H6: 0 | I6: 662 | K6: 4290 | L6: 0 | M6: 37600 | N6: 18.076923 | O6: 0.93 | P6: 3698.3607 | Q6: Garage/Comm. | R6: 100 | V6: 604 | W6: 0.45792267
A7: LIHTC | D7: B | E7: 2 | H7: 0 | I7: 771 | K7: 6840 | L7: 0 | M7: 45960 | N7: 22.096154 | P7: 6027.541 | Q7: Other Inc. | R7: 13908 | V7: 583 | W7: 0.4054242
A8: LIHTC | D8: C | E8: 2 | H8: 0 | I8: 866 | K8: 2925 | L8: 0 | M8: 53560 | N8: 25.75 | P8: 2634.0984 | Q8: Gross Potential | R8: 1013608 | V8: 783 | W8: 0.44539249
A9: 0 | D9: D | E9: 2 | H9: 0 | I9: 1372 | K9: 1075 | L9: 0 | M9: 43000 | N9: 20.673077 | P9: 704.91803 | Q9: Vacancy | R9: -70952.56 | V9: 794 | W9: 0.42482611
A10: 0.5 | D10: E | E10: 2 | H10: 0 | I10: 1372 | K10: 1075 | L10: 0 | M10: 43000 | N10: 20.673077 | P10: 704.91803 | Q10: Effective Gross | R10: 942655.44 | V10: 794 | W10: 0.42482611
A11: LIHTC | D11: F | E11: 2 | H11: 0 | I11: 866 | K11: 975 | L11: 0 | M11: 53560 | N11: 25.75 | P11: 878.03279 | Q11: Net OpEx | R11: -562924 | V11: 783 | W11: 0.44539249
A12: LIHTC | D12: G | E12: 2 | H12: 0 | I12: 771 | K12: 855 | L12: 0 | M12: 45960 | N12: 22.096154 | P12: 753.44262 | V12: 583 | W12: 0.4054242
A13: LIHTC | D13: H | H13: 0 | I13: 662 | K13: 715 | L13: 0 | M13: 37600 | N13: 18.076923 | P13: 616.39344 | Q13: Repl. Res. | R13: -18300 | V13: 604 | W13: 0.45792267
B14: 0.67213115 | D14: A | E14: 1 | H14: 0 | I14: 840 | K14: 10200 | L14: 0 | M14: 43000 | N14: 20.673077 | O14: 0.93 | P14: 8459.0164 | Q14: Total OpEx | R14: -581224 | V14: 469 | W14: 0.3555724
A15: LIHTC | D15: B | E15: 2 | H15: 0 | I15: 984 | K15: 16000 | L15: 0 | M15: 51760 | N15: 24.884615 | P15: 13576.393 | Q15: Net Oper. Inc. | R15: 361431.44 | V15: 438 | W15: 0.30458971
A16: LIHTC | D16: C | E16: 2 | H16: 0 | I16: 1112 | K16: 8800 | L16: 0 | M16: 58560 | N16: 28.153846 | P16: 7680 | R16: 0 | V16: 658 | W16: 0.37428896
A17: LIHTC | D17: D | E17: 2 | H17: 0 | I17: 1647 | K17: 6000 | L17: 0 | M17: 48000 | N17: 23.076923 | P17: 3934.4262 | V17: 669 | W17: 0.35794543
A18: 0.6 | D18: E | E18: 2 | H18: 0 | I18: 0
A19: LIHTC | D19: F | E19: 2 | H19: 0 | I19: 0
A20: LIHTC | D20: G | E20: 2 | H20: 0 | I20: 0 | Q20: NNMMI
A21: LIHTC | D21: H | E21: 1 | H21: 0 | I21: 0 | Q21: Houston-The Woolands-Sugar Land
B22: 0.27868852 | D22: A | E22: 1 | H22: 0 | I22: 307 | K22: 5875 | L22: 0 | M22: 56000 | N22: 26.923077 | O22: 0.93 | P22: 4590.1639 | V22: 144 | W22: 0.10917362
A23: 1 | D23: B | E23: 2 | H23: 0 | I23: 134 | K23: 8925 | L23: 0 | M23: 62760 | N23: 30.173077 | P23: 7201.9672 | V23: 163 | W23: 0.11335188
A24: 1 | D24: C | E24: 2 | H24: 0 | I24: 130 | K24: 5800 | L24: 0 | M24: 72560 | N24: 34.884615 | P24: 4758.0328 | Q24: Per Unit Type Income Averaging | V24: 308 | W24: 0.17519909
A25: 1 | D25: D | E25: 2 | H25: 0 | I25: 823 | K25: 1550 | L25: 0 | M25: 62000 | N25: 29.807692 | P25: 1016.3934 | Q25: A | V25: 319 | W25: 0.17067951
A26: 1 | D26: E | E26: 2 | H26: 0 | I26: 823 | Q26: B
A27: 1 | D27: F | E27: 2 | H27: 0 | I27: 130 | Q27: C
A28: 1 | D28: G | E28: 2 | H28: 0 | I28: 134 | Q28: D
A29: 1 | D29: H | E29: 1 | H29: 0 | I29: 307 | Q29: E
E30: Totals | F30: 80 | H30: 0 | K30: 81900 | M30: 67234.098 | N30: Average Income | Q30: F
Q31: G
C32: 2 | D32: 3 | E32: 4 | F32: 5 | G32: 6 | K32: 0 | L32: 1 | M32: 2 | N32: 3 | O32: 4 | Q32: H
B33: 19890 | C33: 22710 | D33: 25560 | E33: 28380 | F33: 30660 | G33: 32940 | J33: Utilities | K33: 0 | L33: -225 | M33: -294 | N33: -364 | O33: 0
B34: 26520 | C34: 30280 | D34: 34080 | E34: 37840 | F34: 40880 | G34: 43920 | J34: 0.3 | K34: 497 | L34: 532 | M34: 428 | N34: 494 | O34: 823 | Q34: Per BR Type Income Averaging
J35: Max Rent | K35: 497 | L35: 307 | M35: 134 | N35: 130 | O35: 823 | R35: 0.56315789
B36: 39780 | C36: 45420 | D36: 51120 | E36: 56760 | F36: 61320 | G36: 65880 | J36: 0.4 | K36: 663 | L36: 710 | M36: 852 | N36: 984 | O36: 1098 | R36: 0.564
B37: 46410 | C37: 52990 | D37: 59640 | E37: 66220 | F37: 71540 | G37: 76860 | J37: Max Rent | K37: 663 | L37: 485 | M37: 558 | N37: 620 | O37: 1098 | R37: 0.56666667
B38: 53040 | C38: 60560 | D38: 68160 | E38: 75680 | F38: 81760 | G38: 87840 | J38: 0.5 | K38: 828 | L38: 887 | M38: 1065 | N38: 1230 | O38: 1372 | R38: 0.57142857
B39: 66300 | C39: 75700 | D39: 85200 | E39: 94600 | F39: 102200 | G39: 109800 | J39: Max Rent | K39: 828 | L39: 662 | M39: 771 | N39: 866 | O39: 1372
J40: 0.6 | K40: 994 | L40: 1065 | M40: 1278 | N40: 1476 | O40: 1647
G41: Building: | H41: LowRise | J41: Max Rent | K41: 994 | L41: 840 | M41: 984 | N41: 1112 | O41: 1647
A42: Utility Allowances | C42: HHA | G42: Effective: | J42: 0.7 | K42: 1160 | L42: 1242 | M42: 1491 | N42: 1722 | O42: 1921
A43: Use | C43: Tenant Pd? | F43: 2 | G43: 3 | H43: 4 | J43: Max Rent | K43: 1160 | L43: 1017 | M43: 1197 | N43: 1358 | O43: 1921
A44: Heating - Electric | C44: Y | J44: 0.8 | K44: 1326 | L44: 1420 | M44: 1704 | N44: 1968 | O44: 2196
A45: Cooking - Electric | C45: Y | J45: Max Rent | K45: 1326 | L45: 1195 | M45: 1410 | N45: 1604 | O45: 2196
A46: Other: | B46: Electric | C46: Y | J46: 1 | K46: 1657 | L46: 1775 | M46: 2130 | N46: 2460 | O46: 2745
A47: Other: | B47: A/C | C47: Y | J47: Max Rent | K47: 1657 | L47: 1550 | M47: 1836 | N47: 2096 | O47: 2745
A48: Hot Water - Electric | C48: Y | J48: FMR
A49: Water | C49: Y | J49: Max Rent
A50: Sewer | C50: Y | J50: Low HOME
A51: Trash Collection | C51: N | J51: Max Rent
A52: Other: | C52: Y | J52: High HOME
C53: Sum "Y" = | D53: 0 | E53: 225 | F53: 294 | G53: 364 | H53: 0 | J53: Max Rent

Sheet Construction Sources-Uses
A1: CONSTRUCTION SOURCES & USES — LIVE OAK MANOR PHASE 1 | P1: Financial Proforma Model 5.5
A2: 61 Homes | Tax-Exempt Bond / 4% LIHTC | Jefferson Parish, LA | P2: 44403
C4: Bond Proceeds | G4: Jefferson Parish | I4: FHLB Dallas | K4: LIHTC Equity | N4: Deferred Fee | P4: Total Funds | Q4: Total Funds
C5: Tax-Exempt | E5: Taxable | G5: (HOME Funds) | I5: (AHP Grant) | P5: (Construction)
A6: DEVELOPMENT SOURCES
A8: Tax-Exempt Bond Proceeds | P8: 10613079
P9: 0
A10: Jefferson Parish HOME Funds (2nd) | P10: 3660000
A11: LHC Soft Loan / Capital Magnet (3rd) | P11: 2877977
A12: FHLB of Dallas AHP | P12: 1830000
A13: LIHTC Equity (4% - at construction closing) | P13: 1101527
A14: Deferred Developer Fee | P14: 1374929 | S14: 34240984
A16: TOTAL CONSTRUCTION SOURCES | C16: 10613079 | E16: 0 | G16: 6537977 | I16: 1830000 | K16: 1101527 | N16: 0 | P16: 21457512 | Q16: 21457512 | R16: 20082583 | S16: 55698496
S17: 34240984
A18: DEVELOPMENT USES
A20: ACQUISITION
A21: Building | P21: 0 | Q21: 0 | R21: 0
A22: Land | B22: 4656689.8 | G22: 4656689.8 | P22: 4656689.8 | Q22: 0 | R22: 0
P23: 0 | Q23: 0 | R23: 0
A24: HARD COST CONSTRUCTION | P24: 0 | Q24: 0 | R24: 0
A25: Demo/Abatement Contract | B25: 3016378 | C25: 3016378 | P25: 3016378 | Q25: 0
A26: Demo/Abatement Contingency | B26: 326932.18 | G26: 76932.18 | P26: 326932.18 | Q26: 0
A27: Construction Hard Costs | B27: 29663009 | G27: 6772168.4 | P27: 29663009 | Q27: 0 | R27: 0 | S27: -7542929
A28: Sitework | B28: 1833281 | C28: 1833281 | P28: 1833281 | Q28: 0
A29: Contingency | B29: 1795459.6 | G29: 1795459.6 | P29: 1795459.6 | Q29: 0 | R29: 0
A30: GC Profit | B30: 662560 | C30: 662560 | P30: 662560 | Q30: 0 | R30: 0 | S30: 1659007
A31: GC Overhead | B31: 1875171 | C31: 1875171 | G31: 0 | P31: 1875171 | Q31: 0
A32: GC General Conditions | B32: 1875171 | C32: 1875171 | P32: 1875171 | Q32: 0 | R32: 0 | S32: 1548407
A33: P&P Bond | B33: 255000 | C33: 255000 | P33: 255000 | Q33: 0 | R33: 0
A34: Builders Risk Insurance | B34: 400000 | P34: 470000 | Q34: -70000 | R34: -70000 | S34: 38429652
A35: Demolition | P35: 0 | Q35: 0 | R35: 0
A36: Site Preparation | P36: 0 | Q36: 0 | R36: 0
A37: Site Utilities | P37: 0 | Q37: 0 | R37: 0
A38: Landscaping | P38: 0 | Q38: 0 | R38: 0
A39: Retaining walls | P39: 0 | Q39: 0 | R39: 0
A40: Fencing and Vehicle Gates | P40: 0 | Q40: 0 | R40: 0
A41: Roads | P41: 0 | Q41: 0 | R41: 0
A42: Sidewalks | P42: 0 | Q42: 0 | R42: 0
A43: Exterior Amenities | P43: 0 | Q43: 0 | R43: 0
P44: 0 | Q44: 0 | R44: 0
A45: DEVELOPMENT COSTS | P45: 0 | Q45: 0 | R45: 0
A46: Property Appraisal | B46: 20000 | K46: 20000 | P46: 20000 | Q46: 0 | R46: 0
A47: Market Study | B47: 20000 | K47: 20000 | P47: 20000 | Q47: 0 | R47: 0
A48: Environmental Report(s) | B48: 25000 | K48: 8792 | P48: 25000 | Q48: 0
A49: Soil Borings | B49: 80000 | K49: -5688 | P49: 80000 | Q49: 0
A50: Boundary and Topographical Survey | B50: 16000 | K50: 16000 | P50: 16000 | Q50: 0
A51: Zoning/Site Plan Fees | B51: 0 | K51: 0 | P51: 0 | Q51: 0
A52: Bond Issuer Closing Fee | B52: 320000 | K52: 320000 | P52: 320000 | Q52: 0
A53: Construction Loan fee | B53: 256000 | P53: 256000 | Q53: 0
A54: Construction Loan Interest | B54: 2925000 | I54: 1309196.3 | K54: 1010584.7 | P54: 2319781 | Q54: 605219 | R54: 605219
A55: Construction Legal Fees (Lender) | B55: 47500 | K55: 47500 | P55: 47500 | Q55: 0 | R55: 0
A56: Construction loan costs | B56: 9855 | K56: 9855 | P56: 9855 | Q56: 0 | R56: 0
A57: Construction Insurance | B57: 50000 | K57: -68183.36 | P57: 25000 | Q57: 25000 | R57: 25000
A58: Bond Issuer Legal | B58: 175000 | K58: 175000 | P58: 175000 | Q58: 0 | R58: 0
A59: Architectural Fee-all services and reimbursables | B59: 737600 | C59: 737600 | P59: 737600 | Q59: 0 | R59: 0
A60: Landscape Architect | B60: 20000 | C60: 20000 | P60: 20000 | Q60: -2.910383e-11 | R60: -2.910383e-11
A61: Engineering | B61: 275000 | P61: 275000 | Q61: 0 | R61: 0
A62: City of Houston Legal | B62: 40000 | P62: 30000 | Q62: 10000 | R62: 10000
A63: HHA Legal | B63: 150000 | P63: 140000 | Q63: 10000 | R63: 10000
A64: Partnership Legal | B64: 150000 | P64: 106200.03 | Q64: 43799.97 | R64: 43799.97
A65: Accounting | B65: 200000 | K65: 142500 | P65: 142500 | Q65: 57500 | R65: 57500
A66: Green Building Certification/Registration | B66: 50000 | I66: 12000 | P66: 35000 | Q66: 15000 | R66: 15000
A67: Construction Inspection Fees | B67: 47600 | G67: 47600 | P67: 47600 | Q67: 0 | R67: 0
A68: Accessibility Consulting | B68: 50000 | G68: 43800 | P68: 50000 | Q68: 0 | R68: 0
A69: Construction Materials Testing | B69: 0 | G69: 0 | P69: 0 | Q69: 0 | R69: 0
A70: Building Permits | B70: 57400 | P70: 57400 | Q70: 0 | R70: 0
A71: Impact Fees | B71: 152000 | K71: 152000 | P71: 152000 | Q71: 0 | R71: 0
A72: Plan Review | B72: 15250 | K72: 15250 | P72: 15250 | Q72: 0 | R72: 0
A73: Other Local fees | B73: 50000 | P73: 50000 | Q73: 0 | R73: 0
A74: Permanent Loan Fees | B74: 128700 | P74: 112000 | Q74: 16700 | R74: 16700
A75: Permanent Loan Legal Fees | B75: 50000 | P75: 30000 | Q75: 20000 | R75: 20000
A76: Title and Recording Fees | B76: 212056 | P76: 190492.4 | Q76: 21563.6 | R76: 21563.6
A77: As-Built Survey | B77: 5000 | P77: 0 | Q77: 5000
A78: Conversion Fee | B78: 10000 | P78: 10000 | Q78: 0 | R78: 0
A79: TDHCA Application Fees | B79: 5910 | K79: 5910 | P79: 5910 | Q79: 0 | R79: 0
A80: TDHCA Commitment Fee | B80: 77750 | K80: 77750 | P80: 77750 | Q80: 0 | R80: 0
A81: Bond Development Determination Fee | B81: 82974 | K81: 82974 | P81: 82974 | Q81: 0 | R81: 0
A82: LIHTC Allocation Processing Fee | B82: 50000 | K82: 50000 | P82: 50000 | Q82: 0 | R82: 0
A83: LIHTC Complaince Monitoring Fee | B83: 6360 | P83: 0 | Q83: 6360 | R83: 6360
A84: Partnership Organization Fees | B84: 0 | P84: 0 | Q84: 0 | R84: 0
A85: Tax Credit Legal Opinion | B85: 0 | P85: 0 | Q85: 0 | R85: 0
A86: Syndicator Legal Fees | B86: 0 | K86: 0 | P86: 0 | Q86: 0 | R86: 0
A87: Syndicator Due Diligence Fee | B87: 55000 | P87: 55000 | Q87: 0 | R87: 0
A88: Marketing | B88: 75000 | K88: 0 | P88: 0 | Q88: 75000 | R88: 75000
A89: Rent -Up Reserves (3mos exp) | B89: 565804 | P89: 198031 | Q89: 367773 | R89: 367773
A90: Operating Deficit Reserve | B90: 921000 | K90: 0 | P90: 0 | Q90: 921000 | R90: 921000
A91: Replacement Reserve | B91: 59100 | K91: 55000 | P91: 55000 | Q91: 4100 | R91: 4100
A92: Furniture, Fixtures and Equipment | B92: 500000 | G92: 492000 | P92: 500000 | Q92: 0
A93: Relocation | B93: 0 | P93: 0 | Q93: 0 | R93: 0
A94: Soft cost contingecy | B94: 97146 | P94: 75000 | Q94: 22146 | R94: 22146
A95: Developer Overhead | B95: 1360000 | G95: 130449.9 | P95: 1360000 | Q95: 0 | R95: 0
A96: Developer Fee | B96: 5440000 | G96: 1366215.6 | P96: 1366215.6 | Q96: 4073784.4 | R96: 4073784.4
Q97: 0
A98: TOTAL DEVELOPMENT USES | B98: 62000657 | C98: 31990000 | E98: 0 | G98: 15524499 | H98: 0 | I98: 5092079 | K98: 3164132.8 | L98: 0 | M98: 0 | N98: 0 | O98: 0 | P98: 55770711 | Q98: 6229946 | R98: 6224946
B99: -44083.33 | C99: -21376921 | D99: 0 | E99: 0 | F99: 0 | G99: -8986521.9 | H99: 0 | I99: -3262079 | K99: -2062605.8 | L99: 0 | M99: 0 | N99: 0 | O99: 0 | P99: -34313199
P100: Equity pays down TEBonds to TEL loan amount
A101: EQUITY PAY-IN SCHEDULE | B101: 62000657 | C101: AMOUNT | E101: DUE DATE
I102: 50% Test: | K102: 0.51596228
A103: Initial Cap contribution (Closing) | C103: 2846768
A104: 2nd cap contribution | C104: 9738021 | K104: meets 50% test
...
